Workbook

Sheet Performance
B2: SWITCH · CALLING PERFORMANCE
B4: Live totals across all area tabs — updates as you fill the call sheets
B6: TOTAL LEADS | D6: CONTACTED | F6: ORDERS
B7: =COUNTA('Udyog Vihar'!B5:B1666)+COUNTA('Galleria Market'!B5:B1266) | D7: =COUNTA('Udyog Vihar'!H5:H1666)+COUNTA('Galleria Market'!H5:H1266) | F7: =COUNTIF('Udyog Vihar'!J5:J1666,"Yes")+COUNTIF('Galleria Market'!J5:J1266,"Yes")
B9: INTERESTED | D9: CONVERSION | F9: HOURS BOOKED
B10: =COUNTIF('Udyog Vihar'!H5:H1666,"Yes")+COUNTIF('Galleria Market'!H5:H1266,"Yes") | D10: =IFERROR((COUNTIF('Udyog Vihar'!J5:J1666,"Yes")+COUNTIF('Galleria Market'!J5:J1266,"Yes"))/(COUNTA('Udyog Vihar'!H5:H1666)+COUNTA('Galleria Market'!H5:H1266)),0) | F10: =SUM('Udyog Vihar'!I5:I1666)+SUM('Galleria Market'!I5:I1266)
B12: Area | C12: Leads | D12: Contacted | E12: Interested | F12: Orders | G12: Hours
B13: Udyog Vihar | C13: =COUNTA('Udyog Vihar'!B5:B1666) | D13: =COUNTA('Udyog Vihar'!H5:H1666) | E13: =COUNTIF('Udyog Vihar'!H5:H1666,"Yes") | F13: =COUNTIF('Udyog Vihar'!J5:J1666,"Yes") | G13: =SUM('Udyog Vihar'!I5:I1666)
B14: Galleria Market | C14: =COUNTA('Galleria Market'!B5:B1266) | D14: =COUNTA('Galleria Market'!H5:H1266) | E14: =COUNTIF('Galleria Market'!H5:H1266,"Yes") | F14: =COUNTIF('Galleria Market'!J5:J1266,"Yes") | G14: =SUM('Galleria Market'!I5:I1266)
B15: TOTAL | C15: =COUNTA('Udyog Vihar'!B5:B1666)+COUNTA('Galleria Market'!B5:B1266) | D15: =COUNTA('Udyog Vihar'!H5:H1666)+COUNTA('Galleria Market'!H5:H1266) | E15: =COUNTIF('Udyog Vihar'!H5:H1666,"Yes")+COUNTIF('Galleria Market'!H5:H1266,"Yes") | F15: =COUNTIF('Udyog Vihar'!J5:J1666,"Yes")+COUNTIF('Galleria Market'!J5:J1266,"Yes") | G15: =SUM('Udyog Vihar'!I5:I1666)+SUM('Galleria Market'!I5:I1266)
B17: ↳ Fill the Interested? / Hours / Order Confirmed? columns on each area tab — these numbers move automatically.

Sheet Udyog Vihar
A1: SWITCH · UDYOG VIHAR · CALL SHEET
A2: Shifts of 1–12 hrs, billed per hour · pay after worker reports · instant replacement · 1662 leads with phone
A3: LEADS | B3: =COUNTA(B5:B1666) | C3: CONTACTED | D3: =COUNTA(H5:H1666) | E3: INTERESTED | F3: =COUNTIF(H5:H1666,"Yes") | G3: ORDERS | H3: =COUNTIF(J5:J1666,"Yes") | I3: HOURS BOOKED | J3: =SUM(I5:I1666)
A4: S.No | B4: Business Name | C4: Category | D4: Suggested Roles (per shift) | E4: Phone | F4: Rating | G4: Address | H4: Interested? | I4: Hours (1-12) | J4: Order Confirmed? | K4: Remarks | L4: Map
A5: 1 | B5: 3 Phase Ac Repair and Service | C5: service | D5: Helper, Housekeeping, Security, Office Boy | E5: 087969 88406 | F5: 5 | G5: Shop no.21, Phase IV, Udyog Vihar, Sector 18, Gurugram, Haryana 122001, India | L5: Map
A6: 2 | B6: A k led lights | C6: wholesaler | D6: Helper, Housekeeping, Security, Office Boy | E6: 098185 72482 | F6: 5 | G6: Metro Pillar Number 58, Sikanderpur, Navin tawar, Sector 24, Gurugram, Haryana 122002, India | L6: Map
A7: 3 | B7: A S Gurugram | C7: guest_house | D7: Housekeeping, Room Boy, Kitchen Helper, Front Desk | E7: 085869 62478 | F7: 5 | G7: T-15, 2, Moulsari Ave, T Block, DLF Phase 3, Sector 24, Gurugram, Haryana 122002, India | L7: Map
A8: 4 | B8: Aashish international packers and movers | C8: transportation_service | D8: Loader, Packer, Picker, Warehouse Helper, Delivery | E8: 087965 34461 | F8: 5 | G8: Office No 3, No 2, Maruti Gate, Maruti Udyog, Sector 18, Gurugram, Haryana 122015, India | L8: Map
A9: 5 | B9: AAVS | C9: business | D9: Helper, Housekeeping, Security, Office Boy | E9: 093508 74962 | F9: 5 | G9: V-11/37, DLF Phase 3, Sector 24, Gurugram, Haryana 122010, India | L9: Map
A10: 6 | B10: Abhishek Paper and Glassware | C10: manufacturer | D10: Machine Operator, Helper, Loader, Packer | E10: 079087 49091 | F10: 5 | G10: 28a, Road No. N-3, DLF Phase 2, Sector 25, Gurugram, Haryana 122002, India | L10: Map
A11: 7 | B11: Accrete solutions | C11: corporate_office | D11: Office Boy, Housekeeping, Security, Data Entry | E11: 087784 95838 | F11: 5 | G11: 204A, Tenon Ln, Electronic City, Phase IV, Udyog Vihar, Sector 18, Gurugram, Haryana 122015, India | L11: Map
A12: 8 | B12: Ace India Sourcing Pvt. Ltd. | C12: manufacturer | D12: Machine Operator, Helper, Loader, Packer | E12: 098996 88867 | F12: 5 | G12: 633 A, Udyog Vihar Phase V Rd, Phase V, Udyog Vihar, Sector 19, Gurugram, Haryana 122016, India | L12: Map
A13: 9 | B13: Acumen Overseas Pvt Ltd. | C13: corporate_office | D13: Office Boy, Housekeeping, Security, Data Entry | E13: 0124 667 4000 | F13: 5 | G13: 142, Phase IV, Udyog Vihar, Sector 18, Gurugram, Haryana 122015, India | L13: Map
A14: 10 | B14: Admush Network | C14: service | D14: Helper, Housekeeping, Security, Office Boy | E14: 070426 44199 | F14: 5 | G14: Udyog Vihar, Phase 4, Phase II, Udyog Vihar, Sector 20, Gurugram, Haryana 122016, India | L14: Map
A15: 11 | B15: Ads Media (powered by INTERCEDE MEDIA HOUSE), Digital Marketing Company | C15: service | D15: Store Helper, Housekeeping, Security, Sales Staff | E15: 099902 97717 | F15: 5 | G15: 310, Phase IV, Udyog Vihar, Sector 18, Gurugram, Haryana 122001, India | L15: Map
A16: 12 | B16: Adv Antriksh Bhaskar, Divorce, Bail, PMLA, Cheque Bounce, RERA, 138 NI Act NDPS POCSO. Criminal Best Lawyer in Gurugram | C16: consultant | D16: Office Boy, Housekeeping, Security, Data Entry | E16: 089240 43135 | F16: 5 | G16: 85, Moulsari Ave, DLF Phase 3, Sector 24, Gurugram, Haryana 122002, India | L16: Map
... A1309: 1305 | B1309: Vaishali Communication | C1309: service | D1309: Helper, Housekeeping, Security, Office Boy | E1309: 093117 43566 | F1309: 1 | G1309: 30, Gali No 12, Kapas Hera Extension, Kapas Hera, New Delhi, Delhi 110097, India | L1309: Map
A1310: 1306 | B1310: 24xliving 1119p | C1310: lodging | D1310: Housekeeping, Room Boy, Kitchen Helper, Front Desk | E1310: 092899 36080 | G1310: 1112 p, Sector 21, near huda market, Pocket C, Sector 21, Gurugram, Haryana 122016, India | L1310: Map
A1311: 1307 | B1311: A @ A Communication | C1311: service | D1311: Helper, Housekeeping, Security, Office Boy | E1311: 093103 29525 | G1311: House No. 1206, Gali No. 12, Matke Wali Gali, Kapas Hera Extension, Kapas Hera, New Delhi, Delhi 110097, India | L1311: Map
A1312: 1308 | B1312: A K Electrical | C1312: service | D1312: Helper, Housekeeping, Security, Office Boy | E1312: 095600 53383 | G1312: 45, near Govt School, Dundahera, Dundahera Village, Sector 21, Gurugram, Haryana 122016, India | L1312: Map
A1313: 1309 | B1313: A.R Bike Service Center | C1313: store | D1313: Store Helper, Housekeeping, Security, Sales Staff | E1313: 091259 29965 | G1313: 234 phase, 1, Udyog Vihar, Udyog Vihar Phase 1, Dundahera Village, Sector 20, Gurugram, Haryana 122016, India | L1313: Map
A1314: 1310 | B1314: Aarav travels | C1314: travel_agency | D1314: Helper, Housekeeping, Security, Office Boy | E1314: 086850 18042 | G1314: Sector 22 Rd, Sector 22A, Sector 22, Gurugram, Haryana 122015, India | L1314: Map
A1315: 1311 | B1315: Aarya IT Solutions | C1315: service | D1315: Helper, Housekeeping, Security, Office Boy | E1315: 083180 58211 | G1315: Radhe Krishna Tempal, IDPL Twp, Sector 22A, Sector 21, Gurugram, Haryana 122016, India | L1315: Map
A1316: 1312 | B1316: Aazad Texi Tour Package | C1316: travel_agency | D1316: Helper, Housekeeping, Security, Office Boy | E1316: 098123 92553 | G1316: Palam Vihar Extension, Gurugram, Haryana 122015, India | L1316: Map
A1317: 1313 | B1317: Ackerland capital | C1317: finance | D1317: Office Boy, Housekeeping, Security, Data Entry | E1317: 098990 80909 | G1317: Shiv Sagar Farmhouse, 25, Kapashera Estate Rd, D Block, Kapas Hera Estate, New Delhi, Delhi 110097, India | L1317: Map
A1318: 1314 | B1318: ACPL Transport UDYOG VIHAR | C1318: transportation_service | D1318: Loader, Packer, Picker, Warehouse Helper, Delivery | E1318: 074101 05079 | G1318: Plot, No 24, Old Dehi Road, near Sheetal Hotel, Noble Enclave, Sector 22, Palam Vihar Extension, Gurugram, Haryana 122015, India | L1318: Map
A1319: 1315 | B1319: Adarsh Chauhan | C1319: coffee_shop | D1319: Kitchen Helper, Cook, Dishwasher, Waiter | E1319: 082879 95588 | G1319: Adarsh Chauhan, Old Delhi Gurugram Rd, near by Infotech Center, Dundahera Village, Sector 20, Gurugram, Haryana 122016, India | L1319: Map
A1320: 1316 | B1320: adidas Outlet | C1320: sportswear_store | D1320: Store Helper, Housekeeping, Security, Sales Staff | E1320: 011 2694 4264 | G1320: Upper Ground Floor, Abul Fazal Part II, G-13A, Jasola, Sector 18, New Delhi, Gurugram, Delhi 110025, India | L1320: Map
A1321: 1317 | B1321: Aditya Health Care | C1321: medical_clinic | D1321: Ward Boy, Housekeeping, Attendant, Security | E1321: 095406 94511 | G1321: Hdhfhdjhdud, Dzrzrzriu, G474+X76, Rajokri Village, Rajokri, Gurugram, New Delhi, Delhi 110038, India | L1321: Map
... A1666: 1662 | B1666: Zipphatt | C1666: consultant | D1666: Office Boy, Housekeeping, Security, Data Entry | E1666: 070424 21241 | G1666: IDPL Twp, Udyog Vihar, Sector 19, Gurugram, Haryana 122016, India | L1666: Map

Sheet Galleria Market
A1: SWITCH · GALLERIA MARKET · CALL SHEET
A2: Shifts of 1–12 hrs, billed per hour · pay after worker reports · instant replacement · 1262 leads with phone
A3: LEADS | B3: =COUNTA(B5:B1266) | C3: CONTACTED | D3: =COUNTA(H5:H1266) | E3: INTERESTED | F3: =COUNTIF(H5:H1266,"Yes") | G3: ORDERS | H3: =COUNTIF(J5:J1266,"Yes") | I3: HOURS BOOKED | J3: =SUM(I5:I1266)
A4: S.No | B4: Business Name | C4: Category | D4: Suggested Roles (per shift) | E4: Phone | F4: Rating | G4: Address | H4: Interested? | I4: Hours (1-12) | J4: Order Confirmed? | K4: Remarks | L4: Map
A5: 1 | B5: 14 Star Interior | C5: furniture_store | D5: Store Helper, Housekeeping, Security, Sales Staff | E5: 098998 04177 | F5: 5 | G5: Near, Paras Hospital Rd, Block C, Sushant Lok Phase I, Sector 53, Gurugram, Haryana 122009, India | L5: Map
A6: 2 | B6: A m automobile | C6: parking_garage | D6: Mechanic Helper, Cleaner, Washer | E6: 075504 14934 | F6: 5 | G6: Paras Hospital Rd, Horizon Colony, DLF Phase 5, Sector 43, Gurugram, Haryana 122009, India | L6: Map
A7: 3 | B7: AACE Journeys PVT. LTD. | C7: business | D7: Helper, Housekeeping, Security, Office Boy | E7: 096259 71729 | F7: 5 | G7: G-316 3rd Floor, Sushant Shopping Arcade, near G-316, 3rd Floor, Sushant Lok Phase I, Kanahi, Gurugram, Haryana 122009, India | L7: Map
A8: 4 | B8: Aaman General Store | C8: general_store | D8: Store Helper, Housekeeping, Security, Sales Staff | E8: 097174 11809 | F8: 5 | G8: 814, Jaina Market, A Block, Chakkarpur, Gurugram, Haryana 122002, India | L8: Map
A9: 5 | B9: Aastha P.G | C9: condominium_complex | D9: Helper, Housekeeping, Security, Office Boy | E9: 099998 15252 | F9: 5 | G9: House no. 189, Sector 28, Chakkarpur, Gurugram, Haryana 122002, India | L9: Map
A10: 6 | B10: Aayush Enterprises | C10: courier_service | D10: Loader, Packer, Picker, Warehouse Helper, Delivery | E10: 085060 00504 | F10: 5 | G10: Shop No.1 Sector.29, Housing Board Colony, Sector 28, Chakkarpur, Sarswati Vihar, Gurugram, Haryana 122002, India | L10: Map
A11: 7 | B11: Ajanta Wrouht Iron And Metal Works | C11: manufacturer | D11: Machine Operator, Helper, Loader, Packer | E11: 098716 28801 | F11: 5 | G11: 139, Abc, Horizon Colony, Sector 43, Gurugram, Haryana 122009, India | L11: Map
A12: 8 | B12: Alaya Stays by ELIVAAS Liv Regalia Gurgaon Golf Course road | C12: service | D12: Helper, Housekeeping, Security, Office Boy | E12: 079 6931 6141 | F12: 5 | G12: C-1000, Block C, Sushant Lok Phase I, Sector 43, Gurugram, Haryana 122009, India | L12: Map
A13: 9 | B13: All Things Real Estate | C13: consultant | D13: Office Boy, Housekeeping, Security, Data Entry | E13: 086506 11000 | F13: 5 | G13: JMD Empire Square, Mehrauli-Gurgaon Rd, Sector 28, DLF Phase 1, Gurugram, Haryana 122002, India | L13: Map
A14: 10 | B14: Amara Design | C14: service | D14: Helper, Housekeeping, Security, Office Boy | E14: 099994 88442 | F14: 5 | G14: 1, J-9, DLF Phase 2, Sector 25, Gurugram, Haryana 122002, India | L14: Map
A15: 11 | B15: AnchorCSR | C15: association_or_organization | D15: Office Boy, Housekeeping, Security, Data Entry | E15: 083838 64288 | F15: 5 | G15: A1, 356, Sushant Lok 2, Sector 55, Gurugram, Haryana 122009, India | L15: Map
A16: 12 | B16: Anjali Cosmetic Shop | C16: cosmetics_store | D16: Store Helper, Housekeeping, Security, Sales Staff | E16: 099712 65506 | F16: 5 | G16: Shop No 1, Chakarpur, Sector 28, Gurugram, NCR, Sector 28, Chakkarpur, Region, Gurugram, Haryana 122002, India | L16: Map
... A1035: 1031 | B1035: WHATACART | C1035: corporate_office | D1035: Office Boy, Housekeeping, Security, Data Entry | E1035: 098104 08482 | F1035: 1 | G1035: A-8, Plot, GH-4, Block D, South City I, Sector 56, Gurugram, Haryana 122003, India | L1035: Map
A1036: 1032 | B1036: 99acres Sales Office Sec-27 Gurgaon | C1036: real_estate_agency | D1036: Office Boy, Housekeeping, Security, Data Entry | E1036: 1800 419 9099 | G1036: Bestech Chembers, B Block, Unit 515 to 517 5th Floor, Sector 27, Sushant Lok Phase I, Sector 43, Gurugram, Haryana 122009, India | L1036: Map
A1037: 1033 | B1037: A.R. Communication | C1037: business | D1037: Helper, Housekeeping, Security, Office Boy | E1037: 096503 13252 | G1037: Shop No 102, Horizon Colony, Sector 43, Gurugram, Haryana 122009, India | L1037: Map
A1038: 1034 | B1038: Ablers Group | C1038: corporate_office | D1038: Office Boy, Housekeeping, Security, Data Entry | E1038: 099725 98267 | G1038: D-805, Paras Towers, Sector – 30, Block B, Sector 26A, Faridabad, Gurugram, Haryana 122002, India | L1038: Map
A1039: 1035 | B1039: Access CFO Consultants | C1039: corporate_office | D1039: Office Boy, Housekeeping, Security, Data Entry | E1039: 098101 32858 | G1039: Tower-R, T-19B, DLF Phase IV, Sector 27, Gurugram, Haryana 122009, India | L1039: Map
A1040: 1036 | B1040: Adlytic Media Pvt Ltd | C1040: service | D1040: Helper, Housekeeping, Security, Office Boy | E1040: 093101 16465 | G1040: Adlytic, Media Pvt Ltd Truworx, Golf Course Rd, DLF Phase 1, Sector 26A, Gurugram, Haryana 122002, India | L1040: Map
A1041: 1037 | B1041: Ajay Shop | C1041: store | D1041: Store Helper, Housekeeping, Security, Sales Staff | E1041: 095603 18127 | G1041: Sikanderpur Market, DLF Cyber City, DLF Phase 2, Sector 24, Gurugram, Haryana 122002, India | L1041: Map
A1042: 1038 | B1042: Alliance Mantra | C1042: corporate_office | D1042: Office Boy, Housekeeping, Security, Data Entry | E1042: 070990 14413 | G1042: 45, Arjun Marg, Block E, DLF Phase 1, Sector 26A, Gurugram, Haryana 122002, India | L1042: Map
A1043: 1039 | B1043: AltUrban | C1043: service | D1043: Helper, Housekeeping, Security, Office Boy | E1043: 095408 71917 | G1043: House no 522, Sector 42, Gurugram, Haryana 122002, India | L1043: Map
A1044: 1040 | B1044: Am luxury filowar decoration | C1044: florist | D1044: Helper, Housekeeping, Security, Office Boy | E1044: 092179 17620 | G1044: shop no 10, 56, Sector Rd, Huda Market, Block D, South City I, Sector 41, Gurugram, Haryana 122003, India | L1044: Map
A1045: 1041 | B1045: Amabze Rentals Pvt Ltd | C1045: transportation_service | D1045: Loader, Packer, Picker, Warehouse Helper, Delivery | E1045: 088267 16382 | G1045: Leisure Valley Rd, Sector 29, Gurugram, Haryana 122009, India | L1045: Map
A1046: 1042 | B1046: Ambience Public School, Gurugram | C1046: school | D1046: Peon, Housekeeping, Security, Attendant | E1046: 0124 257 4627 | G1046: Ambience Public School, Plot 1, opp. Golf Course, near DLF Phase 5, Horizon Colony, Sector 43, Gurugram, Haryana 122009, India | L1046: Map
A1047: 1043 | B1047: AnamkaaRuh Therapy Care & Counselling | C1047: medical_clinic | D1047: Ward Boy, Housekeeping, Attendant, Security | E1047: 099998 63745 | G1047: 476B, Block C, Sushant Lok Phase I, Kanahi, Gurugram, Haryana 122002, India | L1047: Map
... A1266: 1262 | B1266: सुमित मेडिकल स्टोर | C1266: pharmacy | D1266: Ward Boy, Housekeeping, Attendant, Security | E1266: 080037 51745 | G1266: 758, Vijay Cinema Hall Rd, Jaina Market, A-46, Chakkarpur, Gurugram, Haryana 122002, India | L1266: Map

Sheet How to use
B1: SWITCH — CALLING SHEET · HOW TO USE
B3: THE OFFER (say this, every time)
B4: • Shifts of 1–12 hours, billed by the hour. NO monthly, NO weekly.
B5: • Pay only AFTER the worker reports — no advance.
B6: • Instant replacement if the worker doesn't show or isn't a fit.
B7: • Verified, local staff delivered in 24 hours.
B9: HOW TO WORK THE SHEET
B10: 1. Two tabs: 'Udyog Vihar' and 'Sector 52'. Work each top-down.
B11: 2. WhatsApp first, then call. After each contact, click the dropdowns:
B12: · Interested? → Yes / No / Maybe / Call back / No answer / Wrong number
B13: · Hours → 1 to 12 (what they want per shift)
B14: · Order Confirmed? → Yes once they agree to take staff
... B18: Only businesses with a phone number are included. Deduped by number.
