Workbook

Sheet Performance
B2: SWITCH · GOLF COURSE ROAD · CALLING PERFORMANCE
B4: Live totals across all sector tabs — updates as you fill the call sheets
B6: TOTAL LEADS | D6: MOBILES (OWNER/MGR) | F6: ORDERS
B7: =COUNTA('Sector 56'!B5:B184)+COUNTA('Sector 55'!B5:B80)+COUNTA('Sector 53'!B5:B166)+COUNTA('Sector 52A'!B5:B46)+COUNTA('Sector 42'!B5:B147)+COUNTA('Sector 27'!B5:B105)+COUNTA('Sector 28'!B5:B264)+COUNTA('Sector 26A'!B5:B170) | D7: =COUNTIF('Sector 56'!F5:F184,"Mobile*")+COUNTIF('Sector 55'!F5:F80,"Mobile*")+COUNTIF('Sector 53'!F5:F166,"Mobile*")+COUNTIF('Sector 52A'!F5:F46,"Mobile*")+COUNTIF('Sector 42'!F5:F147,"Mobile*")+COUNTIF('Sector 27'!F5:F105,"Mobile*")+COUNTIF('Sector 28'!F5:F264,"Mobile*")+COUNTIF('Sector 26A'!F5:F170,"Mobile*") | F7: =COUNTIF('Sector 56'!K5:K184,"Yes")+COUNTIF('Sector 55'!K5:K80,"Yes")+COUNTIF('Sector 53'!K5:K166,"Yes")+COUNTIF('Sector 52A'!K5:K46,"Yes")+COUNTIF('Sector 42'!K5:K147,"Yes")+COUNTIF('Sector 27'!K5:K105,"Yes")+COUNTIF('Sector 28'!K5:K264,"Yes")+COUNTIF('Sector 26A'!K5:K170,"Yes")
B9: CONTACTED | D9: INTERESTED | F9: CONVERSION | H9: HOURS
B10: =COUNTA('Sector 56'!I5:I184)+COUNTA('Sector 55'!I5:I80)+COUNTA('Sector 53'!I5:I166)+COUNTA('Sector 52A'!I5:I46)+COUNTA('Sector 42'!I5:I147)+COUNTA('Sector 27'!I5:I105)+COUNTA('Sector 28'!I5:I264)+COUNTA('Sector 26A'!I5:I170) | D10: =COUNTIF('Sector 56'!I5:I184,"Yes")+COUNTIF('Sector 55'!I5:I80,"Yes")+COUNTIF('Sector 53'!I5:I166,"Yes")+COUNTIF('Sector 52A'!I5:I46,"Yes")+COUNTIF('Sector 42'!I5:I147,"Yes")+COUNTIF('Sector 27'!I5:I105,"Yes")+COUNTIF('Sector 28'!I5:I264,"Yes")+COUNTIF('Sector 26A'!I5:I170,"Yes") | F10: =IFERROR((COUNTIF('Sector 56'!K5:K184,"Yes")+COUNTIF('Sector 55'!K5:K80,"Yes")+COUNTIF('Sector 53'!K5:K166,"Yes")+COUNTIF('Sector 52A'!K5:K46,"Yes")+COUNTIF('Sector 42'!K5:K147,"Yes")+COUNTIF('Sector 27'!K5:K105,"Yes")+COUNTIF('Sector 28'!K5:K264,"Yes")+COUNTIF('Sector 26A'!K5:K170,"Yes"))/(COUNTA('Sector 56'!I5:I184)+COUNTA('Sector 55'!I5:I80)+COUNTA('Sector 53'!I5:I166)+COUNTA('Sector 52A'!I5:I46)+COUNTA('Sector 42'!I5:I147)+COUNTA('Sector 27'!I5:I105)+COUNTA('Sector 28'!I5:I264)+COUNTA('Sector 26A'!I5:I170)),0) | H10: =SUM('Sector 56'!J5:J184)+SUM('Sector 55'!J5:J80)+SUM('Sector 53'!J5:J166)+SUM('Sector 52A'!J5:J46)+SUM('Sector 42'!J5:J147)+SUM('Sector 27'!J5:J105)+SUM('Sector 28'!J5:J264)+SUM('Sector 26A'!J5:J170)
B12: Sector | C12: Leads | D12: Mobiles | E12: Contacted | F12: Interested | G12: Orders | H12: Hours
B13: Sector 56 | C13: =COUNTA('Sector 56'!B5:B184) | D13: =COUNTIF('Sector 56'!F5:F184,"Mobile*") | E13: =COUNTA('Sector 56'!I5:I184) | F13: =COUNTIF('Sector 56'!I5:I184,"Yes") | G13: =COUNTIF('Sector 56'!K5:K184,"Yes") | H13: =SUM('Sector 56'!J5:J184)
B14: Sector 55 | C14: =COUNTA('Sector 55'!B5:B80) | D14: =COUNTIF('Sector 55'!F5:F80,"Mobile*") | E14: =COUNTA('Sector 55'!I5:I80) | F14: =COUNTIF('Sector 55'!I5:I80,"Yes") | G14: =COUNTIF('Sector 55'!K5:K80,"Yes") | H14: =SUM('Sector 55'!J5:J80)
B15: Sector 53 | C15: =COUNTA('Sector 53'!B5:B166) | D15: =COUNTIF('Sector 53'!F5:F166,"Mobile*") | E15: =COUNTA('Sector 53'!I5:I166) | F15: =COUNTIF('Sector 53'!I5:I166,"Yes") | G15: =COUNTIF('Sector 53'!K5:K166,"Yes") | H15: =SUM('Sector 53'!J5:J166)
B16: Sector 52A | C16: =COUNTA('Sector 52A'!B5:B46) | D16: =COUNTIF('Sector 52A'!F5:F46,"Mobile*") | E16: =COUNTA('Sector 52A'!I5:I46) | F16: =COUNTIF('Sector 52A'!I5:I46,"Yes") | G16: =COUNTIF('Sector 52A'!K5:K46,"Yes") | H16: =SUM('Sector 52A'!J5:J46)
B17: Sector 42 | C17: =COUNTA('Sector 42'!B5:B147) | D17: =COUNTIF('Sector 42'!F5:F147,"Mobile*") | E17: =COUNTA('Sector 42'!I5:I147) | F17: =COUNTIF('Sector 42'!I5:I147,"Yes") | G17: =COUNTIF('Sector 42'!K5:K147,"Yes") | H17: =SUM('Sector 42'!J5:J147)
B18: Sector 27 | C18: =COUNTA('Sector 27'!B5:B105) | D18: =COUNTIF('Sector 27'!F5:F105,"Mobile*") | E18: =COUNTA('Sector 27'!I5:I105) | F18: =COUNTIF('Sector 27'!I5:I105,"Yes") | G18: =COUNTIF('Sector 27'!K5:K105,"Yes") | H18: =SUM('Sector 27'!J5:J105)
B19: Sector 28 | C19: =COUNTA('Sector 28'!B5:B264) | D19: =COUNTIF('Sector 28'!F5:F264,"Mobile*") | E19: =COUNTA('Sector 28'!I5:I264) | F19: =COUNTIF('Sector 28'!I5:I264,"Yes") | G19: =COUNTIF('Sector 28'!K5:K264,"Yes") | H19: =SUM('Sector 28'!J5:J264)
B20: Sector 26A | C20: =COUNTA('Sector 26A'!B5:B170) | D20: =COUNTIF('Sector 26A'!F5:F170,"Mobile*") | E20: =COUNTA('Sector 26A'!I5:I170) | F20: =COUNTIF('Sector 26A'!I5:I170,"Yes") | G20: =COUNTIF('Sector 26A'!K5:K170,"Yes") | H20: =SUM('Sector 26A'!J5:J170)
B21: TOTAL | C21: =COUNTA('Sector 56'!B5:B184)+COUNTA('Sector 55'!B5:B80)+COUNTA('Sector 53'!B5:B166)+COUNTA('Sector 52A'!B5:B46)+COUNTA('Sector 42'!B5:B147)+COUNTA('Sector 27'!B5:B105)+COUNTA('Sector 28'!B5:B264)+COUNTA('Sector 26A'!B5:B170) | D21: =COUNTIF('Sector 56'!F5:F184,"Mobile*")+COUNTIF('Sector 55'!F5:F80,"Mobile*")+COUNTIF('Sector 53'!F5:F166,"Mobile*")+COUNTIF('Sector 52A'!F5:F46,"Mobile*")+COUNTIF('Sector 42'!F5:F147,"Mobile*")+COUNTIF('Sector 27'!F5:F105,"Mobile*")+COUNTIF('Sector 28'!F5:F264,"Mobile*")+COUNTIF('Sector 26A'!F5:F170,"Mobile*") | E21: =COUNTA('Sector 56'!I5:I184)+COUNTA('Sector 55'!I5:I80)+COUNTA('Sector 53'!I5:I166)+COUNTA('Sector 52A'!I5:I46)+COUNTA('Sector 42'!I5:I147)+COUNTA('Sector 27'!I5:I105)+COUNTA('Sector 28'!I5:I264)+COUNTA('Sector 26A'!I5:I170) | F21: =COUNTIF('Sector 56'!I5:I184,"Yes")+COUNTIF('Sector 55'!I5:I80,"Yes")+COUNTIF('Sector 53'!I5:I166,"Yes")+COUNTIF('Sector 52A'!I5:I46,"Yes")+COUNTIF('Sector 42'!I5:I147,"Yes")+COUNTIF('Sector 27'!I5:I105,"Yes")+COUNTIF('Sector 28'!I5:I264,"Yes")+COUNTIF('Sector 26A'!I5:I170,"Yes") | G21: =COUNTIF('Sector 56'!K5:K184,"Yes")+COUNTIF('Sector 55'!K5:K80,"Yes")+COUNTIF('Sector 53'!K5:K166,"Yes")+COUNTIF('Sector 52A'!K5:K46,"Yes")+COUNTIF('Sector 42'!K5:K147,"Yes")+COUNTIF('Sector 27'!K5:K105,"Yes")+COUNTIF('Sector 28'!K5:K264,"Yes")+COUNTIF('Sector 26A'!K5:K170,"Yes") | H21: =SUM('Sector 56'!J5:J184)+SUM('Sector 55'!J5:J80)+SUM('Sector 53'!J5:J166)+SUM('Sector 52A'!J5:J46)+SUM('Sector 42'!J5:J147)+SUM('Sector 27'!J5:J105)+SUM('Sector 28'!J5:J264)+SUM('Sector 26A'!J5:J170)
B23: ↳ Fill Interested? / Hours / Order Confirmed? on each sector tab — these numbers move automatically.

Sheet Sector 56
A1: SWITCH · SECTOR 56 · CALL SHEET
A2: Shifts 1–12 hrs, billed per hour · pay after worker reports · instant replacement | 180 leads · 166 mobiles (owner/mgr) at top
A3: LEADS | B3: =COUNTA(B5:B184) | C3: CONTACTED | D3: =COUNTA(I5:I184) | E3: INTERESTED | F3: =COUNTIF(I5:I184,"Yes") | G3: ORDERS | H3: =COUNTIF(K5:K184,"Yes") | I3: HOURS BOOKED | J3: =SUM(J5:J184)
A4: S.No | B4: Business Name | C4: Category | D4: Suggested Roles (per shift) | E4: Phone | F4: Number Type | G4: Rating | H4: Address | I4: Interested? | J4: Hours (1-12) | K4: Order Confirmed? | L4: Remarks | M4: Map
A5: 1 | B5: Aanurag Interiors & Developers | C5: corporate_office | D5: Office Boy, Housekeeping, Security, Data Entry | E5: 078270 90991 | F5: Mobile (owner/mgr) | G5: 5 | H5: 1st Floor, 55-56 metro station, Sector 56, Gurugram, Haryana 122011, India | M5: Map
A6: 2 | B6: Aatishbaazi Instant Prints Photo Booths | Event Photography | Prints and Party Supplies | C6: service | D6: Helper, Housekeeping, Security, Office Boy | E6: 099998 94294 | F6: Mobile (owner/mgr) | G6: 5 | H6: C 37, Sushant Lok 2, Sector 56, Gurugram, Haryana 122011, India | M6: Map
A7: 3 | B7: Abbas Furniture | C7: furniture_store | D7: Store Helper, Housekeeping, Security, Sales Staff | E7: 063960 77466 | F7: Mobile (owner/mgr) | G7: 5 | H7: Shushant Lok 2, Sector 56, Gurugram, Haryana 122011, India | M7: Map
A8: 4 | B8: Agarwal Packers And Movers Gurgaon Sector 56 | C8: transportation_service | D8: Loader, Packer, Picker, Warehouse Helper, Delivery | E8: 080580 17005 | F8: Mobile (owner/mgr) | G8: 5 | H8: Shop No, 28/14, Kendriya Vihar, Sector 56, Gurugram, Haryana 122011, India | M8: Map
A9: 5 | B9: Ahffi | C9: store | D9: Store Helper, Housekeeping, Security, Sales Staff | E9: 096541 93121 | F9: Mobile (owner/mgr) | G9: 5 | H9: Sector 56, Gurugram, Haryana 122011, India | M9: Map
A10: 6 | B10: Apollo 24|7 Lab Tests Near Me | Sector 56 | Home collection | Gurgaon | C10: medical_clinic | D10: Ward Boy, Housekeeping, Attendant, Security | E10: 080 4885 1037 | F10: Mobile (owner/mgr) | G10: 5 | H10: SCO. 68 and 69 Sector 55 & 56, Block B, Sector 56, Gurugram, Haryana 122011, India | M10: Map
A11: 7 | B11: ARCS Design Studio | C11: service | D11: Helper, Housekeeping, Security, Office Boy | E11: 088513 36569 | F11: Mobile (owner/mgr) | G11: 5 | H11: C 79, Kendriya Vihar, Sector 56, Gurugram, Haryana 122011, India | M11: Map
A12: 8 | B12: Bhagat ji general store | C12: general_store | D12: Store Helper, Housekeeping, Security, Sales Staff | E12: 070330 08800 | F12: Mobile (owner/mgr) | G12: 5 | H12: Olive Heights, Plot no.36 B, Sector 56, Gurugram, Haryana 122011, India | M12: Map
A13: 9 | B13: BOMBAY DRY CLEANERS | C13: service | D13: Helper, Housekeeping, Security, Office Boy | E13: 098913 29062 | F13: Mobile (owner/mgr) | G13: 5 | H13: Sagar Apartment, B-BLOCK, AIT Chowk, Block B, Sector 56, Gurugram, Haryana 122011, India | M13: Map
A14: 10 | B14: CMD Developers & Promoters Pvt. Ltd. | C14: real_estate_agency | D14: Office Boy, Housekeeping, Security, Data Entry | E14: 099112 10005 | F14: Mobile (owner/mgr) | G14: 5 | H14: 4th Floor, CMD Developers & Promoters, Plot No - D6, Golf Course Ext Rd, Sector 56, Gurugram, Ghata, Haryana 122011, India | M14: Map
A15: 11 | B15: Commerce Machine | C15: business | D15: Helper, Housekeeping, Security, Office Boy | E15: 098997 18786 | F15: Mobile (owner/mgr) | G15: 5 | H15: H.no 2579, Sec 57, opposite Devender Vihar Power House, Block G, Sushant Lok 2, Sector 56, Gurugram, Haryana 122011, India | M15: Map
A16: 12 | B16: Commerce Pathshaala | C16: business | D16: Helper, Housekeeping, Security, Office Boy | E16: 096502 96648 | F16: Mobile (owner/mgr) | G16: 5 | H16: A 303, JOY KUNJ, SOCIETY, Block B, Sector 56, Gurugram, Haryana 122011, India | M16: Map
... A134: 130 | B134: Usman tailor | C134: tailor | D134: Helper, Housekeeping, Security, Office Boy | E134: 099111 36076 | F134: Mobile (owner/mgr) | G134: 1 | H134: Huda Market Rd, opp. Harish Bakery, Block B, Sector 56, Gurugram, Haryana 122011, India | M134: Map
A135: 131 | B135: 101 Circle by SIPL | C135: association_or_organization | D135: Office Boy, Housekeeping, Security, Data Entry | E135: 088824 79009 | F135: Mobile (owner/mgr) | H135: 101 Circle, by SIPL, Block B, Sector 56, Gurugram, Haryana 122011, India | M135: Map
A136: 132 | B136: Amicable | C136: consultant | D136: Office Boy, Housekeeping, Security, Data Entry | E136: 084470 60168 | F136: Mobile (owner/mgr) | H136: Society, Rail Vihar, Sector 56, Gurugram, Haryana 122011, India | M136: Map
A137: 133 | B137: Bharti International Convent School Sector 56 | C137: school | D137: Peon, Housekeeping, Security, Attendant | E137: 098107 58205 | F137: Mobile (owner/mgr) | H137: C3GV+697, 60, Block A, Sector 56, Gurugram, Haryana 122011, India | M137: Map
A138: 134 | B138: BrewHill Coffee | C138: corporate_office | D138: Kitchen Helper, Cook, Dishwasher, Waiter | E138: 093543 33813 | F138: Mobile (owner/mgr) | H138: C4J2+5HV, Rail Vihar, Sector 56, Gurugram, Haryana 122011, India | M138: Map
A139: 135 | B139: clinical psychologist | C139: medical_clinic | D139: Ward Boy, Housekeeping, Attendant, Security | E139: 098703 63768 | F139: Mobile (owner/mgr) | H139: Flat no C160, Kendriya Vihar, Sector 56, Gurugram, Haryana 122011, India | M139: Map
A140: 136 | B140: CONSULTANT SOFT DRINKS AND WATER TREATMENT | C140: consultant | D140: Office Boy, Housekeeping, Security, Data Entry | E140: 098115 59818 | F140: Mobile (owner/mgr) | H140: 7-B, J N U Aravali, Apartments, Sector 56, Gurugram, Haryana 122011, India | M140: Map
A141: 137 | B141: Dudhbhate Fast Food | C141: food_court | D141: Kitchen Helper, Cook, Dishwasher, Waiter | E141: 099604 85261 | F141: Mobile (owner/mgr) | H141: Shop No.55, Huda Center, Sector 56, Gurugram, Haryana 122011, India | M141: Map
A142: 138 | B142: Educational institution | C142: business | D142: Peon, Housekeeping, Security, Attendant | E142: 093986 58096 | F142: Mobile (owner/mgr) | H142: D block vigyan vihar, gate no 5, beside shalom presidency school, Shushant Lok 2, Sushant Lok 2, Sector 56, Gurugram, Haryana 122011, India | M142: Map
A143: 139 | B143: Family Health Centre | C143: doctor | D143: Ward Boy, Housekeeping, Attendant, Security | E143: 097179 54290 | F143: Mobile (owner/mgr) | H143: C3JX+2C7, Jal Vayu Towers Rd, Sector 56, Gurugram, Haryana 122011, India | M143: Map
A144: 140 | B144: Gajna Overseas (OPC) Private Limited | C144: corporate_office | D144: Office Boy, Housekeeping, Security, Data Entry | E144: 098117 89665 | F144: Mobile (owner/mgr) | H144: 505, Park Royal Apartments, GH-80, Block E, Sector 56, Gurugram, Haryana 122011, India | M144: Map
A145: 141 | B145: HDFC ERGO Insurance Agent: Rajeev Goel | C145: insurance_agency | D145: Office Boy, Housekeeping, Security, Data Entry | E145: 080 4599 9684 | F145: Mobile (owner/mgr) | H145: No 17/2B, opposite Rapid Metro Depot, IILM Institute, Rail Vihar, Sector 56, Gurugram, Haryana 122011, India | M145: Map
A146: 142 | B146: Healthify Soul | C146: service | D146: Ward Boy, Housekeeping, Attendant, Security | E146: 088600 68314 | F146: Mobile (owner/mgr) | H146: 806, New Anand, GH 47, Block B, Sector 56, Gurugram, Haryana 122011, India | M146: Map
... A170: 166 | B170: urbn. Architects | C170: service | D170: Helper, Housekeeping, Security, Office Boy | E170: 096678 52454 | F170: Mobile (owner/mgr) | H170: C-153, Sushant Lok 2, Sector 56, Gurugram, Haiderpur, Haryana 122011, India | M170: Map
A171: 167 | B171: Foodaids | C171: manufacturer | D171: Kitchen Helper, Cook, Dishwasher, Waiter | E171: 011 4250 8333 | F171: Landline (reception) | G171: 5 | H171: Phase 4, HSIIDC, Plot No. 2, Sector 56, Kundli, kundli, Gurugram, Haryana 1310281, India | M171: Map
A172: 168 | B172: Sukriti Design Studio | C172: service | D172: Helper, Housekeeping, Security, Office Boy | E172: 0124 471 2342 | F172: Landline (reception) | G172: 4.8 | H172: 01, Hewo Rd, Block B, Sector 56, Gurugram, Haryana 122011, India | M172: Map
A173: 169 | B173: Artius Inc | C173: service | D173: Helper, Housekeeping, Security, Office Boy | E173: 0124 408 6109 | F173: Landline (reception) | G173: 4.6 | H173: E-189 Basement, Sushant Lok 2, Sector 56, Gurugram, Haryana 122011, India | M173: Map
A174: 170 | B174: NOI TRE Salon - Sector 56 | C174: hair_salon | D174: Beautician, Helper, Receptionist, Cleaner | E174: 0124 257 8400 | F174: Landline (reception) | G174: 4.6 | H174: SCO-67, GF, HUDA More Market, Block B, Sector 56, Gurugram, Haryana 122011, India | M174: Map
A175: 171 | B175: Mother Dairy Milk Shop - Sector 56, Gurugram | C175: food_store | D175: Kitchen Helper, Cook, Dishwasher, Waiter | E175: 1800 180 1018 | F175: Landline (helpline) | G175: 4.2 | H175: Booth No 15910, C Block Rd, nearby Durga Puja, Kendriya Vihar, Sector 56, Gurugram, Haryana 122011, India | M175: Map
A176: 172 | B176: Sidhartha CGHS Apartment | C176: apartment_complex | D176: Helper, Housekeeping, Security, Office Boy | E176: 0124 414 1405 | F176: Landline (reception) | G176: 4.2 | H176: Plot number 31, Block B, Sector 56, Gurugram, Haryana 122011, India | M176: Map
A177: 173 | B177: Kendriya Bhandar | C177: grocery_store | D177: Store Helper, Housekeeping, Security, Sales Staff | E177: 011 2905 1908 | F177: Landline (reception) | G177: 4.1 | H177: Kendriya Vihar, Sector 56, Gurugram, Haryana 122011, India | M177: Map
A178: 174 | B178: MG Motor Cargo Motors Showroom | C178: car_dealer | D178: Loader, Packer, Picker, Warehouse Helper, Delivery | E178: 011 4113 2664 | F178: Landline (reception) | G178: 4 | H178: Double Tree by Hilton, Golf Course Rd, Sector 56, Ghata, Gurugram, Haryana 122011, India | M178: Map
A179: 175 | B179: Royal Palm Apartments | C179: apartment_building | D179: Helper, Housekeeping, Security, Office Boy | E179: 0124 411 2708 | F179: Landline (reception) | G179: 3.8 | H179: Plot No: 6, Sector 56, Gurugram, Haryana 122011, India | M179: Map
A180: 176 | B180: Kotak Mahindra Bank | C180: bank | D180: Office Boy, Housekeeping, Security, Data Entry | E180: 1800 4100 | F180: Landline (helpline) | G180: 3.5 | H180: SCO 63, Huda Market Rd, Block B, Sector 56, Gurugram, Haryana 122001, India | M180: Map
A181: 177 | B181: Kendriya Vihar Office | C181: association_or_organization | D181: Office Boy, Housekeeping, Security, Data Entry | E181: 0124 257 2817 | F181: Landline (reception) | G181: 3.1 | H181: C3FV+64X, Kendriya Vihar, Sector 56, Gurugram, Haryana 122011, India | M181: Map
A182: 178 | B182: IndusInd Bank | C182: bank | D182: Office Boy, Housekeeping, Security, Data Entry | E182: 1860 267 7777 | F182: Landline (helpline) | G182: 2.4 | H182: SCO 61, DSC Huda Market, Sector 56, Block B, Sector 56, Gurugram, Haryana 122011, India | M182: Map
A183: 179 | B183: BNW and Associates | C183: corporate_office | D183: Office Boy, Housekeeping, Security, Data Entry | E183: 011 4153 6539 | F183: Landline (reception) | H183: MS-2/502, Kendriya Vihar, Sector 56, Gurugram, Haryana 122011, India | M183: Map
A184: 180 | B184: Elegant Technologies India | C184: corporate_office | D184: Office Boy, Housekeeping, Security, Data Entry | E184: 0124 405 5354 | F184: Landline (reception) | H184: SCO-100, 1st Floor, HUDA Market, Sector 10A, Block B, Sector 56, Gurugram, Haryana 122011, India | M184: Map

Sheet Sector 55
A1: SWITCH · SECTOR 55 · CALL SHEET
A2: Shifts 1–12 hrs, billed per hour · pay after worker reports · instant replacement | 76 leads · 68 mobiles (owner/mgr) at top
A3: LEADS | B3: =COUNTA(B5:B80) | C3: CONTACTED | D3: =COUNTA(I5:I80) | E3: INTERESTED | F3: =COUNTIF(I5:I80,"Yes") | G3: ORDERS | H3: =COUNTIF(K5:K80,"Yes") | I3: HOURS BOOKED | J3: =SUM(J5:J80)
A4: S.No | B4: Business Name | C4: Category | D4: Suggested Roles (per shift) | E4: Phone | F4: Number Type | G4: Rating | H4: Address | I4: Interested? | J4: Hours (1-12) | K4: Order Confirmed? | L4: Remarks | M4: Map
A5: 1 | B5: Aastha Sidana Makeup Artistry | C5: makeup_artist | D5: Helper, Housekeeping, Security, Office Boy | E5: 085879 51587 | F5: Mobile (owner/mgr) | G5: 5 | H5: Huda Sector, Sushant Lok 2, Sector 55, Gurugram, Ghata, Haryana 122011, India | M5: Map
A6: 2 | B6: AnchorCSR | C6: association_or_organization | D6: Office Boy, Housekeeping, Security, Data Entry | E6: 083838 64288 | F6: Mobile (owner/mgr) | G6: 5 | H6: A1, 356, Sushant Lok 2, Sector 55, Gurugram, Haryana 122009, India | M6: Map
A7: 3 | B7: Bani Dham Mandir | C7: hindu_temple | D7: Helper, Housekeeping, Security, Office Boy | E7: 098110 67177 | F7: Mobile (owner/mgr) | G7: 5 | H7: Ghatagaon Shiv Mandir Huda Sector Sushant Lok Do Gurugram, Pradip Kumar Shop Ghata Gaon Sabji Mandi, Huda Sector, Sushant Lok 2, Sector 55, Gurugram, Gurugram Division Delhi, Huda Sector, Sushant Lok 2, Sector 55, Gurugram, Haryana 122011, India | M7: Map
A8: 4 | B8: Banidham Mandir Gaushala | C8: hindu_temple | D8: Helper, Housekeeping, Security, Office Boy | E8: 098738 74414 | F8: Mobile (owner/mgr) | G8: 5 | H8: Banidham Mandir Gaushala, Shree Khatu Shyam Mandir, Ghatta Kanarpur, Sector 55, Ghata, Gurugram, Haryana 122011, India | M8: Map
A9: 5 | B9: Bold Mark Agency | C9: service | D9: Helper, Housekeeping, Security, Office Boy | E9: 092204 92929 | F9: Mobile (owner/mgr) | G9: 5 | H9: A12, Sector 55, Ghata, Gurugram, Haryana 122011, India | M9: Map
A10: 6 | B10: Dayma Tent House | C10: supplier | D10: Helper, Housekeeping, Security, Office Boy | E10: 070658 83501 | F10: Mobile (owner/mgr) | G10: 5 | H10: 203, near Metro Stations, Sushant Lok 2, Sector 55, Gurugram, Haryana 122002, India | M10: Map
A11: 7 | B11: Designer's Abode Interior Designers | C11: general_contractor | D11: Helper, Housekeeping, Security, Office Boy | E11: 093139 31313 | F11: Mobile (owner/mgr) | G11: 5 | H11: Sagavi Apartment, GH 85, Golf Crse Rd, Huda, Sushant Lok 2, Sector 55, Gurugram, Haryana 122011, India | M11: Map
A12: 8 | B12: Dev Infosol | C12: service | D12: Helper, Housekeeping, Security, Office Boy | E12: 081999 53209 | F12: Mobile (owner/mgr) | G12: 5 | H12: B1 A12, Sector 55, Gurugram, Haryana 122011, India | M12: Map
A13: 9 | B13: Dev Kirana Store | C13: general_store | D13: Store Helper, Housekeeping, Security, Sales Staff | E13: 063776 85984 | F13: Mobile (owner/mgr) | G13: 5 | H13: Dev Kirana Store, Ghatta Kanarpur, Sector 55, Gurugram, Haryana 122011, India | M13: Map
A14: 10 | B14: DLF Safe Shifting Expert | C14: manufacturer | D14: Machine Operator, Helper, Loader, Packer | E14: 093191 76856 | F14: Mobile (owner/mgr) | G14: 5 | H14: SCO 91, Huda Market Rd, Block B, Sector 55, Gurugram, Haryana 122011, India | M14: Map
A15: 11 | B15: FIVE ELEMENTS INTERIORS | C15: general_contractor | D15: Helper, Housekeeping, Security, Office Boy | E15: 088268 57030 | F15: Mobile (owner/mgr) | G15: 5 | H15: Huda Sector, Sushant Lok 2, Sector 55, Gurugram, Haryana 122011, India | M15: Map
A16: 12 | B16: Hair Cut Salon | C16: barber_shop | D16: Kitchen Helper, Cook, Dishwasher, Waiter | E16: 073031 95750 | F16: Mobile (owner/mgr) | G16: 5 | H16: Ghata Kanarpur Sector 55 Gurugram, C4C7+Fg6, Ghatta Kanarpur, Sector 55, Gurugram, Ghatta Kanarpur, Sector 58, Delhi NCR, Gurugram, Haryana 122011, India | M16: Map
... A52: 48 | B52: Biryani.com | C52: restaurant | D52: Kitchen Helper, Cook, Dishwasher, Waiter | E52: 098115 56705 | F52: Mobile (owner/mgr) | G52: 3 | H52: C4G4+74H, Golf Course Rd, Sushant Lok 2, Sector 55, Gurugram, Haryana 122011, India | M52: Map
A53: 49 | B53: Amway product distributor | C53: consultant | D53: Office Boy, Housekeeping, Security, Data Entry | E53: 093540 22182 | F53: Mobile (owner/mgr) | H53: 306 Surya Society, Huda Sector, Sushant Lok 2, Sector 55, Gurugram, Haryana 122011, India | M53: Map
A54: 50 | B54: Atson Medical Tourism | C54: corporate_office | D54: Ward Boy, Housekeeping, Attendant, Security | E54: 078275 66148 | F54: Mobile (owner/mgr) | H54: 901, Tower 4, Sagavi Apartment, Huda, Sushant Lok 2, Sector 55, Gurugram, Haryana 122011, India | M54: Map
A55: 51 | B55: Brijesh SinghFoods | C55: vegetarian_restaurant | D55: Kitchen Helper, Cook, Dishwasher, Waiter | E55: 096642 46878 | F55: Mobile (owner/mgr) | H55: Huda Sector, Sushant Lok 2, Sector 55, Ghata, Gurugram, Haryana 122001, India | M55: Map
A56: 52 | B56: CA RIDDHIMA MISHRA | C56: consultant | D56: Office Boy, Housekeeping, Security, Data Entry | E56: 072230 43741 | F56: Mobile (owner/mgr) | H56: GOLF COURSE ROAD, 2, SECTOR 55, Sushant Lok Phase I, Sector 43, Gurugram, Haryana 122009, India | M56: Map
A57: 53 | B57: Lalan plumbing work | C57: plumber | D57: Helper, Housekeeping, Security, Office Boy | E57: 076546 19798 | F57: Mobile (owner/mgr) | H57: Block B, Sector 55, Ghata, Gurugram, Haryana 122011, India | M57: Map
A58: 54 | B58: Me And Ing Lync | C58: educational_institution | D58: Peon, Housekeeping, Security, Attendant | E58: 098180 35044 | F58: Mobile (owner/mgr) | H58: me&ing lync, sector 55, Huda, Sushant Lok 2, Sector 55, Gurugram, Haryana 122011, India | M58: Map
A59: 55 | B59: Mks Elder Care | C59: health | D59: Ward Boy, Housekeeping, Attendant, Security | E59: 081031 86864 | F59: Mobile (owner/mgr) | H59: Huda Sector, Sushant Lok 2, Sector 55, Ghata, Gurugram, Haryana 122011, India | M59: Map
A60: 56 | B60: Musabbir Ali | C60: store | D60: Store Helper, Housekeeping, Security, Sales Staff | E60: 074285 17317 | F60: Mobile (owner/mgr) | H60: Shop No 1, Block B, Sector 55, Gurugram, Haryana 122011, India | M60: Map
A61: 57 | B61: MyTourBox Svcs Pvt Ltd | C61: travel_agency | D61: Helper, Housekeeping, Security, Office Boy | E61: 093199 30107 | F61: Mobile (owner/mgr) | H61: A1, 244-245, Golf Course Rd, Sector 55, Gurugram, Haryana 122011, India | M61: Map
A62: 58 | B62: National Pharmacy | C62: pharmacy | D62: Ward Boy, Housekeeping, Attendant, Security | E62: 096804 13532 | F62: Mobile (owner/mgr) | H62: 12, Ground Floor, Plot 304 B, Block - B, Shanti Kunj, Gurugram Delhi NCR, Sushant Lok 2, Sector 55, Gurugram, Haryana 122011, India | M62: Map
A63: 59 | B63: Pankaj laundry | C63: laundry | D63: Helper, Housekeeping, Security, Office Boy | E63: 070423 56120 | F63: Mobile (owner/mgr) | H63: Sector-55, Sushant Lok 2, A-30, Gurugram, Haryana 122011, India | M63: Map
A64: 60 | B64: Ravindar Bhai Fast Food | C64: food_court | D64: Kitchen Helper, Cook, Dishwasher, Waiter | E64: 092898 52946 | F64: Mobile (owner/mgr) | H64: Shop No, 15, near by Win Shop, Gaon, Sector 55, Ghata, Gurugram, Haryana 122011, India | M64: Map
... A72: 68 | B72: VIBRO SEPRO SYSTEMS - Khoya Making Machine, Vibro Sifter Machine, Screening Machine, Powder Sieving Machine Manufacturer | C72: manufacturer | D72: Machine Operator, Helper, Loader, Packer | E72: 078419 14279 | F72: Mobile (owner/mgr) | H72: Plot No.12 GC, Chana, Gurudwara, Bhatti Gail, near Sector 55, Huda, Sushant Lok 2, Sector 55, Faridabad, Gurugram, Haryana 122011, India | M72: Map
A73: 69 | B73: Insigne Carpets | C73: manufacturer | D73: Machine Operator, Helper, Loader, Packer | E73: 0124 401 2462 | F73: Landline (reception) | G73: 4.6 | H73: A-12, Sushant Lok 2, Sector 55, Gurugram, Haryana 122011, India | M73: Map
A74: 70 | B74: Fitso Sector 55 Unicosmos, Multi-Sports (Indoor-Heated Swimming pool, Badminton) Gurgaon | C74: swimming_pool | D74: Trainer, Housekeeping, Front Desk | E74: 011 6119 5846 | F74: Landline (reception) | G74: 4.4 | H74: UNICOSMOS School Rd, off Golf Course Rd, opposite Huda Market Road, Sushant Lok 2, Sector 55, Ghata, Gurugram, Haryana 122011, India | M74: Map
A75: 71 | B75: Sagavi CGHS LTD {Apartments} | C75: association_or_organization | D75: Office Boy, Housekeeping, Security, Data Entry | E75: 0124 423 7229 | F75: Landline (reception) | G75: 4.3 | H75: Sagavi CHGS, GH 85, Huda, Sushant Lok 2, Sector 55, Gurugram, Haryana 122011, India | M75: Map
A76: 72 | B76: Sushant School of Art and Architecture | C76: educational_institution | D76: Peon, Housekeeping, Security, Attendant | E76: 0124 475 0501 | F76: Landline (reception) | G76: 4.2 | H76: Block-A, Golf Course Rd, Huda, Sushant Lok 2, Sector 55, Gurugram, Haryana 122011, India | M76: Map
A77: 73 | B77: Sushant University | C77: university | D77: Peon, Housekeeping, Security, Attendant | E77: 1800 270 5520 | F77: Landline (helpline) | G77: 4 | H77: Golf Course Rd, Huda, Sushant Lok 2, Sector 55, Gurugram, Haryana 122011, India | M77: Map
A78: 74 | B78: In2sports | C78: sports_school | D78: Trainer, Housekeeping, Front Desk | E78: 011 4601 2522 | F78: Landline (reception) | H78: Sector 55, Ansal University, Huda, Sushant Lok 2, Sector 55, Gurugram, Haryana 122011, India | M78: Map
A79: 75 | B79: OYO Darksleep Near Bestech Central Square Mall | C79: hotel | D79: Housekeeping, Room Boy, Kitchen Helper, Front Desk | E79: 0124 620 1166 | F79: Landline (reception) | H79: H.No-167, A1, Block, Sector -55, Huda, Block A, Sushant Lok 2, Sector 57, Gurugram, Haryana 122011, India | M79: Map
A80: 76 | B80: Yes Bank ATM | C80: bank | D80: Office Boy, Housekeeping, Security, Data Entry | E80: 1800 1200 | F80: Landline (helpline) | H80: Ground Floor & Basement, S.C.O.-103, Sushant Lok 2, Sector 55, Gurugram, Haryana 122011, India | M80: Map

Sheet Sector 53
A1: SWITCH · SECTOR 53 · CALL SHEET
A2: Shifts 1–12 hrs, billed per hour · pay after worker reports · instant replacement | 162 leads · 144 mobiles (owner/mgr) at top
A3: LEADS | B3: =COUNTA(B5:B166) | C3: CONTACTED | D3: =COUNTA(I5:I166) | E3: INTERESTED | F3: =COUNTIF(I5:I166,"Yes") | G3: ORDERS | H3: =COUNTIF(K5:K166,"Yes") | I3: HOURS BOOKED | J3: =SUM(J5:J166)
A4: S.No | B4: Business Name | C4: Category | D4: Suggested Roles (per shift) | E4: Phone | F4: Number Type | G4: Rating | H4: Address | I4: Interested? | J4: Hours (1-12) | K4: Order Confirmed? | L4: Remarks | M4: Map
A5: 1 | B5: Agarwal Shifting Packers And Movers | C5: transportation_service | D5: Loader, Packer, Picker, Warehouse Helper, Delivery | E5: 091001 67870 | F5: Mobile (owner/mgr) | G5: 5 | H5: Shop No.92/2, Parsvnath Exotica, DLF Phase 5, Sector 53, Gurugram, Haryana 122011, India | M5: Map
A6: 2 | B6: Apna barph dipo | C6: manufacturer | D6: Kitchen Helper, Cook, Dishwasher, Waiter | E6: 070652 31220 | F6: Mobile (owner/mgr) | G6: 5 | H6: 142, St Thomas Marg, DLF Phase 5, Sector 53, Gurugram, Haryana 122009, India | M6: Map
A7: 3 | B7: APOLLO MRI HEALTHCARE NO.1 MRI SCAN / SECTOR 53-54 GOLF COURSE ROAD MRI KNEE / MRI LS SPINE /MRI BRAIN | C7: medical_clinic | D7: Ward Boy, Housekeeping, Attendant, Security | E7: 087000 03787 | F7: Mobile (owner/mgr) | G7: 5 | H7: Plots Number 1628 Ground floor sector 54 Near Sector 53-43, Rapid Metro, IILM Institute, Sector 53, Gurugram, Haryana 122011, India | M7: Map
A8: 4 | B8: Arthavat Law Offices | C8: corporate_office | D8: Office Boy, Housekeeping, Security, Data Entry | E8: 098314 15457 | F8: Mobile (owner/mgr) | G8: 5 | H8: Club Drive, WELLINGTON ESTATE, W2B - 155, Golf Course Rd, DLF Phase 5, Sector 53, Gurugram, Haryana 122009, India | M8: Map
A9: 5 | B9: Avni Logistic Door To Door Service Pvt.(Packers and Movers in Gurgaon packers and Movers sector 53 Gurgaon car transport | C9: moving_company | D9: Loader, Packer, Picker, Warehouse Helper, Delivery | E9: 089294 36492 | F9: Mobile (owner/mgr) | G9: 5 | H9: Packers and Movers in Gurgaon packers and Movers, Ground Floor, car transport services, TOWER-C, C 002, DLF Phase 5, Sector 53, Gurugram, Haryana 122009, India | M9: Map
A10: 6 | B10: Chauhan Building Material Supplier | C10: point_of_interest | D10: Helper, Housekeeping, Security, Office Boy | E10: 098118 37131 | F10: Mobile (owner/mgr) | G10: 5 | H10: C3VM+JG7, near Bharat Petroleum, Wazirabad, Sector 53, Gurugram, Haryana 122011, India | M10: Map
A11: 7 | B11: Crowd Internet Marketing | C11: service | D11: Store Helper, Housekeeping, Security, Sales Staff | E11: 099719 32934 | F11: Mobile (owner/mgr) | G11: 5 | H11: 607 saraswati kunj, second floor, Parsvnath Exotica, DLF Phase 5, Sector 53, Gurugram, Haryana 122011, India | M11: Map
A12: 8 | B12: Dilshad Mobile | C12: store | D12: Store Helper, Housekeeping, Security, Sales Staff | E12: 072503 33335 | F12: Mobile (owner/mgr) | G12: 5 | H12: near Jalvayu Tower, IILM Institute, Sector 53, Gurugram, Haryana 122011, India | M12: Map
A13: 9 | B13: Dlf Camellias golf Course Road sector 53 Gurugram Haryana 122001 | C13: general_contractor | D13: Helper, Housekeeping, Security, Office Boy | E13: 096504 20088 | F13: Mobile (owner/mgr) | G13: 5 | H13: Golf Course Rd, Parsvnath Exotica, DLF Phase 5, Sector 53, Gurugram, Haryana 122001, India | M13: Map
A14: 10 | B14: DLF Cargo Packers and Movers Gurgaon | C14: transportation_service | D14: Loader, Packer, Picker, Warehouse Helper, Delivery | E14: 088602 78889 | F14: Mobile (owner/mgr) | G14: 5 | H14: Shop No. 12/2, OURANIA APARTMENT, Parsvnath Exotica, DLF Phase 5, Sector 53, Gurugram, Haryana 122011, India | M14: Map
A15: 11 | B15: Door step girls pg | C15: private_guest_room | D15: Helper, Housekeeping, Security, Office Boy | E15: 092176 17960 | F15: Mobile (owner/mgr) | G15: 5 | H15: Saraswati Kunj, Plot 615, Golf Course Rd, Parsvnath Exotica, DLF Phase 5, Sector 53, Gurugram, Haryana 122002, India | M15: Map
A16: 12 | B16: Dr Neha PhysioCare | C16: physiotherapist | D16: Ward Boy, Housekeeping, Attendant, Security | E16: 098105 32668 | F16: Mobile (owner/mgr) | G16: 5 | H16: House no. 74, Saraswati Kunj, near Shoppers Stop, IILM Institute, Sector 53, Gurugram, Haryana 122011, India | M16: Map
... A122: 118 | B122: FreshMenu Gurgaon Sec 53 | C122: asian_restaurant | D122: Kitchen Helper, Cook, Dishwasher, Waiter | E122: 095134 20082 | F122: Mobile (owner/mgr) | G122: 1.7 | H122: Saraswati Kunj, Parsvnath Exotica, DLF Phase 5, Sector 53, Gurugram, Haryana 122011, India | M122: Map
A123: 119 | B123: Alam Clinic | C123: skin_care_clinic | D123: Ward Boy, Housekeeping, Attendant, Security | E123: 097613 35268 | F123: Mobile (owner/mgr) | H123: Sarswati Kunj II, Sector 53, Gurugram, Haryana 122011, India | M123: Map
A124: 120 | B124: Anil nanda techical consultants | C124: consultant | D124: Office Boy, Housekeeping, Security, Data Entry | E124: 098105 96932 | F124: Mobile (owner/mgr) | H124: DLF Exclusive Floors, D14/31 FF, DLF Phase 5, Sector 53, Gurugram, Haryana 122009, India | M124: Map
A125: 121 | B125: Antar Vikash | C125: place_of_worship | D125: Helper, Housekeeping, Security, Office Boy | E125: 072920 59157 | F125: Mobile (owner/mgr) | H125: 1, B 54, WELLINGTON ESTATE, Club Dr, Phase 5, Sector 53, Gurugram, Haryana 122009, India | M125: Map
A126: 122 | B126: Bhushan Yadav Paan Shop | C126: store | D126: Store Helper, Housekeeping, Security, Sales Staff | E126: 076317 71555 | F126: Mobile (owner/mgr) | H126: 44, opposite to Paras Hospital Road, DLF Phase 5, Sector 53, Gurugram, Haryana 122009, India | M126: Map
A127: 123 | B127: Bishnupriya Clinic | C127: doctor | D127: Ward Boy, Housekeeping, Attendant, Security | E127: 095605 21945 | F127: Mobile (owner/mgr) | H127: Bishnupriya Clinic Bangali Market, Wazirabad, Sector 53, Gurugram, Haryana 122011, India | M127: Map
A128: 124 | B128: Dawara Enterprises - Vectus Authorised Partner (Water Storage Tanks) | C128: hardware_store | D128: Loader, Packer, Picker, Warehouse Helper, Delivery | E128: 088518 82747 | F128: Mobile (owner/mgr) | H128: Plot No 754 Sector No 53, nearby Khatu Shyam Mandir, Parsvnath Exotica, DLF Phase 5, Sector 53, Gurugram, Haryana 122001, India | M128: Map
A129: 125 | B129: Entry DLF Exclusive Floors Phase-5 | C129: point_of_interest | D129: Helper, Housekeeping, Security, Office Boy | E129: 098120 21951 | F129: Mobile (owner/mgr) | H129: Main Entry, Phase- 5, DLF Exclusive Floors, Golf Crse Rd, opp. Horizon Centre, DLF Phase 5, Sector 53, Gurugram, Haryana 122009, India | M129: Map
A130: 126 | B130: Fitwib | C130: corporate_office | D130: Office Boy, Housekeeping, Security, Data Entry | E130: 096504 60024 | F130: Mobile (owner/mgr) | H130: 3rd Floor, Orchid Centre, near IILM Institute, IILM Institute, Sector 53, Gurugram, Haryana 122011, India | M130: Map
A131: 127 | B131: HDFC ERGO Insurance Agent: Chander Kanta Dhingra | C131: insurance_agency | D131: Office Boy, Housekeeping, Security, Data Entry | E131: 080 4594 8617 | F131: Mobile (owner/mgr) | H131: No 302, Tower B, 1, Parsvnath Exotica, DLF Phase 5, Sector 53, Gurugram, Haryana 122002, India | M131: Map
A132: 128 | B132: HDFC ERGO Insurance Agent: Rajan Wadhawan | C132: insurance_agency | D132: Office Boy, Housekeeping, Security, Data Entry | E132: 079 4746 1568 | F132: Mobile (owner/mgr) | H132: No D11/12, Gr Flr, DLF, Exclusive Floors, DLF Phase 5, Sector 53, Gurugram, Haryana 122011, India | M132: Map
A133: 129 | B133: Kabadi ki Dukan | C133: business | D133: Helper, Housekeeping, Security, Office Boy | E133: 097188 15877 | F133: Mobile (owner/mgr) | H133: DLF Phase 5, Sector 53, Ghata, Gurugram, Haryana 122002, India | M133: Map
A134: 130 | B134: KSC Techno | C134: corporate_office | D134: Office Boy, Housekeeping, Security, Data Entry | E134: 090391 95222 | F134: Mobile (owner/mgr) | H134: 3rd Floor, Orchid Centre, IILM Institute, Sector 53, Gurugram, Haryana 122011, India | M134: Map
... A148: 144 | B148: Valuekojen | C148: local_government_office | D148: Office Boy, Housekeeping, Security, Data Entry | E148: 093100 45469 | F148: Mobile (owner/mgr) | H148: PARK TOWERS, DLF PHASE-V, SECTOR 53, DLF Phase 5, Sector 53, Gurugram, Haryana 122009, India | M148: Map
A149: 145 | B149: Experion Developers Residential Project | C149: general_contractor | D149: Helper, Housekeeping, Security, Office Boy | E149: 0124 628 1630 | F149: Landline (reception) | G149: 5 | H149: Experion Developers Residential Project, opposite Jal Vayu Towers Road, IILM Institute, Sector 53, Gurugram, Haryana 122011, India | M149: Map
A150: 146 | B150: The Leaders | C150: employment_agency | D150: Helper, Housekeeping, Security, Office Boy | E150: 0124 495 1750 | F150: Landline (reception) | G150: 5 | H150: C3VW+GCV, Parsvnath Exotica, DLF Phase 5, Sector 53, Gurugram, Haryana 122011, India | M150: Map
A151: 147 | B151: Provee | C151: manufacturer | D151: Machine Operator, Helper, Loader, Packer | E151: 0124 465 3250 | F151: Landline (reception) | G151: 4.9 | H151: Hotel Complex, Office No. 101, 1st Floor, Pegasus One, Golf Course Rd, inside IBIS, Parsvnath Exotica, Sector 53, Gurugram, Haryana 122011, India | M151: Map
A152: 148 | B152: KOREA TOURISM ORGANIZATION | C152: tourist_information_center | D152: Helper, Housekeeping, Security, Office Boy | E152: 0124 464 9191 | F152: Landline (reception) | G152: 4.7 | H152: 303, Pegasus One, Golf Course Rd, Parsvnath Exotica, DLF Phase 5, Sector 53, Gurugram, Haryana 122011, India | M152: Map
A153: 149 | B153: ipsaa Preschool & Day-Care, DLF Phase V | C153: child_care_agency | D153: Peon, Housekeeping, Security, Attendant | E153: 1800 121 2467 | F153: Landline (helpline) | G153: 4.5 | H153: Site no. 6, DLF, Phase V, DLF Phase 5, Sector 53, Gurugram, Haryana 122009, India | M153: Map
A154: 150 | B154: Genpact India Private Limited | C154: business | D154: Helper, Housekeeping, Security, Office Boy | E154: 0124 402 2000 | F154: Landline (reception) | G154: 4.4 | H154: DLF Phase 5, Sector 53, Gurugram, Haryana 122011, India | M154: Map
A155: 151 | B155: Falken Tyre India | C155: tire_shop | D155: Store Helper, Housekeeping, Security, Sales Staff | E155: 0124 463 8989 | F155: Landline (reception) | G155: 4.1 | H155: Unit No. 402, 4th Floor, Sewa Corporate Park M.G. Road, IILM Institute, Sector 53, Gurugram, Haryana 122011, India | M155: Map
A156: 152 | B156: IILM School of Technology | C156: university | D156: Peon, Housekeeping, Security, Attendant | E156: 0124 277 5656 | F156: Landline (reception) | G156: 4 | H156: IILM University, Gurugram 1 Knowledge Center, Golf Course Rd, IILM Institute, Sector 53, Gurugram, Haryana 122011, India | M156: Map
A157: 153 | B157: Le Millennium Medicare | C157: drugstore | D157: Store Helper, Housekeeping, Security, Sales Staff | E157: 0124 436 7118 | F157: Landline (reception) | G157: 3.8 | H157: please club vita, 54 Park, DLF Phase 5, Sector 53, Gurugram, Haryana 122003, India | M157: Map
A158: 154 | B158: Needs Supermarket | C158: supermarket | D158: Store Helper, Housekeeping, Security, Sales Staff | E158: 0124 410 6423 | F158: Landline (reception) | G158: 3.8 | H158: WESTEND HEIGHTS, DLF Phase 5, Sector 53, Gurugram, Haryana 122009, India | M158: Map
A159: 155 | B159: Nirula's Sector 54 Suncity | C159: fast_food_restaurant | D159: Kitchen Helper, Cook, Dishwasher, Waiter | E159: 1800 102 5247 | F159: Landline (helpline) | G159: 3 | H159: SHOP NO.5, GROUND FLOOR, RAPID METRO STATION, Suncity, Sector 53, Gurugram, Haryana 122011, India | M159: Map
A160: 156 | B160: Basics Techno Services Pvt. Ltd. | C160: corporate_office | D160: Office Boy, Housekeeping, Security, Data Entry | E160: 03772 222 445 | F160: Landline (reception) | H160: Carlton Estate 1, c-144, DLF Phase 5, Sector 53, Gurugram, Haryana 122009, India | M160: Map
A161: 157 | B161: JinKorp International Travel Services Private Limited | C161: corporate_office | D161: Office Boy, Housekeeping, Security, Data Entry | E161: 0124 413 1915 | F161: Landline (reception) | H161: Unit No.406 A, 4th Floor, Centrum Plaza, Golf Course Road, Sector-53, Parsvnath Exotica, DLF Phase 5, Sector 53, Gurugram, Haryana 122011, India | M161: Map
A162: 158 | B162: Karo Hotels | C162: corporate_office | D162: Housekeeping, Room Boy, Kitchen Helper, Front Desk | E162: 0124 427 5302 | F162: Landline (reception) | H162: 1102, SL Towers, Ivory Court 1, M.G Road, Parsvnath Exotica, DLF Phase 5, Sector 53, Gurugram, Haryana 122011, India | M162: Map
A163: 159 | B163: Police Station Sector 53 | C163: police | D163: Helper, Housekeeping, Security, Office Boy | E163: 0124 257 6355 | F163: Landline (reception) | H163: C3WX+G79, DLF Phase 5, Sector 53, Gurugram, Haryana 122011, India | M163: Map
A164: 160 | B164: Primok Naturelle Care Pvt Ltd | C164: corporate_office | D164: Office Boy, Housekeeping, Security, Data Entry | E164: 0124 423 3347 | F164: Landline (reception) | H164: Centrum Plaza, Unit No Marriott Business Development Centre And CEC, near, IILM Institute, Sector 53, Gurugram, Haryana 122011, India | M164: Map
A165: 161 | B165: PropXIndia | C165: corporate_office | D165: Office Boy, Housekeeping, Security, Data Entry | E165: 0124 431 1109 | F165: Landline (reception) | H165: Realty Corporate Deals, 3rd Floor, B-Wing, Vatika Atrium, Golf Course Road, Sector-53, Parsvnath Exotica, DLF Phase 5, Sector 53, Gurugram, Haryana 122011, India | M165: Map
A166: 162 | B166: Punjab National Bank - ATM | C166: atm | D166: Office Boy, Housekeeping, Security, Data Entry | E166: 1800 1800 | F166: Landline (helpline) | H166: Shop No 1 to 3, Centrum Plaza, IILM Institute, Sector 53, Gurugram, Haryana 122011, India | M166: Map

Sheet Sector 52A
A1: SWITCH · SECTOR 52A · CALL SHEET
A2: Shifts 1–12 hrs, billed per hour · pay after worker reports · instant replacement | 42 leads · 38 mobiles (owner/mgr) at top
A3: LEADS | B3: =COUNTA(B5:B46) | C3: CONTACTED | D3: =COUNTA(I5:I46) | E3: INTERESTED | F3: =COUNTIF(I5:I46,"Yes") | G3: ORDERS | H3: =COUNTIF(K5:K46,"Yes") | I3: HOURS BOOKED | J3: =SUM(J5:J46)
A4: S.No | B4: Business Name | C4: Category | D4: Suggested Roles (per shift) | E4: Phone | F4: Number Type | G4: Rating | H4: Address | I4: Interested? | J4: Hours (1-12) | K4: Order Confirmed? | L4: Remarks | M4: Map
A5: 1 | B5: Airtel broadband xtream fiber | C5: service | D5: Helper, Housekeeping, Security, Office Boy | E5: 097170 41327 | F5: Mobile (owner/mgr) | G5: 5 | H5: Sushant lok, Phase -1, Block C, Sector 52A, Gurugram, Haryana 122011, India | M5: Map
A6: 2 | B6: Fit N Fast Runner | C6: health | D6: Ward Boy, Housekeeping, Attendant, Security | E6: 098689 36854 | F6: Mobile (owner/mgr) | G6: 5 | H6: Tau Devi Lal Biodiversity Park, Sector 52A, Gurugram, Haryana 122011, India | M6: Map
A7: 3 | B7: Girls PG accommodation | C7: service | D7: Helper, Housekeeping, Security, Office Boy | E7: 080765 48118 | F7: Mobile (owner/mgr) | G7: 5 | H7: E149sushant lok phase 1, Sector 52A, Gurugram, Haryana 122011, India | M7: Map
A8: 4 | B8: Herbal Medicines | C8: store | D8: Store Helper, Housekeeping, Security, Sales Staff | E8: 092115 77218 | F8: Mobile (owner/mgr) | G8: 5 | H8: C3WP+8CR, Ardee Mall Rd, Sector 52A, Gurugram, Haryana 122011, India | M8: Map
A9: 5 | B9: Kai Studio | C9: jewelry_store | D9: Store Helper, Housekeeping, Security, Sales Staff | E9: 079826 63475 | F9: Mobile (owner/mgr) | G9: 5 | H9: E - Block, Block E, DLF Phase 1, Sector 52A, Gurugram, Haryana 122002, India | M9: Map
A10: 6 | B10: KIRAN STEEL AND CEMENT | C10: wholesaler | D10: Helper, Housekeeping, Security, Office Boy | E10: 098217 03506 | F10: Mobile (owner/mgr) | G10: 5 | H10: Wazirabad Rd, behind WINE SHOP, DHANI, Sector 52A, Gurugram, Haryana 122011, India | M10: Map
A11: 7 | B11: Maheshwar Paan Bhandar | C11: store | D11: Store Helper, Housekeeping, Security, Sales Staff | E11: 087973 50646 | F11: Mobile (owner/mgr) | G11: 5 | H11: Shop No.8 Sector.52 Dhani Market, Wazirabad, Sector 52A, Gurugram, Haryana 122011, India | M11: Map
A12: 8 | B12: N K Evergreen Nursery | C12: farm | D12: Helper, Housekeeping, Security, Office Boy | E12: 099999 40408 | F12: Mobile (owner/mgr) | G12: 5 | H12: NK evergreen nursery, near Tau devilal biodiversity park, Sector 52A, Gurugram, Haryana 122011, India | M12: Map
A13: 9 | B13: Suraj Health Insurance Consulting | C13: insurance_agency | D13: Ward Boy, Housekeeping, Attendant, Security | E13: 088777 85869 | F13: Mobile (owner/mgr) | G13: 5 | H13: Gurgaon, Sector 52A, Delhi, Gurugram, Haryana 122001, India | M13: Map
A14: 10 | B14: Balaji Cleaning Company- Gurgaon | C14: service | D14: Helper, Housekeeping, Security, Office Boy | E14: 087440 00091 | F14: Mobile (owner/mgr) | G14: 4.8 | H14: House No - 953, Shop No - 1, Ground Floor, near Sai Ka Aangan, Saraswati Kunj, Sector 53A, Sector 52A, Gurugram, Haryana 122009, India | M14: Map
A15: 11 | B15: PROFESSIONAL HYUNDAI GURUGRAM | C15: car_repair | D15: Mechanic Helper, Cleaner, Washer | E15: 085271 97803 | F15: Mobile (owner/mgr) | G15: 4.8 | H15: near IOC Petrol Pump, Wazirabad, Sector 52A, Gurugram, Haryana 122003, India | M15: Map
A16: 12 | B16: Sai Ka Angan | C16: hindu_temple | D16: Helper, Housekeeping, Security, Office Boy | E16: 070115 20083 | F16: Mobile (owner/mgr) | G16: 4.8 | H16: BLOCK-E, opp. Paras Hospital Road, Sushant Lok Phase I, Sector 52A, Gurugram, Haryana 122009, India | M16: Map
... A35: 31 | B35: Sandeep Electrical and repairing center | C35: electronics_store | D35: Store Helper, Housekeeping, Security, Sales Staff | E35: 080841 54699 | F35: Mobile (owner/mgr) | G35: 1 | H35: Khatu Shyam Mandir Rd, Parsvnath Exotica, Sector 52A, Gurugram, Haryana 122011, India | M35: Map
A36: 32 | B36: Falak Battery | C36: wholesaler | D36: Helper, Housekeeping, Security, Office Boy | E36: 099111 33543 | F36: Mobile (owner/mgr) | H36: Shop 13, Wazirabad, Sector 52A, Gurugram, Haryana 122011, India | M36: Map
A37: 33 | B37: Gd goenka signature school | C37: school | D37: Peon, Housekeeping, Security, Attendant | E37: 098109 10000 | F37: Mobile (owner/mgr) | H37: 55, Sector 52A, Gurugram, Haryana 122009, India | M37: Map
A38: 34 | B38: HOLISTA CURE HOMEOPATHY | C38: health | D38: Ward Boy, Housekeeping, Attendant, Security | E38: 096505 10133 | F38: Mobile (owner/mgr) | H38: Third floor, D-311, Sushant Lok Phase I, Sector 52A, Gurugram, Haryana 122009, India | M38: Map
A39: 35 | B39: Mohd Noor Alam | C39: chauffeur_service | D39: Helper, Housekeeping, Security, Office Boy | E39: 087579 53213 | F39: Mobile (owner/mgr) | H39: CNG Pump Sec52 A, near CNG Pump, Sector 52A, Gurugram, Haryana 122011, India | M39: Map
A40: 36 | B40: Pk Sweets | C40: candy_store | D40: Kitchen Helper, Cook, Dishwasher, Waiter | E40: 097991 61561 | F40: Mobile (owner/mgr) | H40: plot number 929, Sarswati Kunj II, Sector 52A, Gurugram, Haryana 122011, India | M40: Map
A41: 37 | B41: Sai Clinic | C41: medical_clinic | D41: Ward Boy, Housekeeping, Attendant, Security | E41: 098117 53248 | F41: Mobile (owner/mgr) | H41: C3RQ+5XJ, Khatu Shyam Mandir Rd, Sector 52A, Gurugram, Haryana 122011, India | M41: Map
A42: 38 | B42: WEAVES & MORE | C42: clothing_store | D42: Store Helper, Housekeeping, Security, Sales Staff | E42: 098736 01069 | F42: Mobile (owner/mgr) | H42: Dhani Ram Complex, V.P.O. Wazirabad Main Market, Sector 52, Opp Tau Devi Lal Park, Sector 52A, Gurugram, Haryana 122011, India | M42: Map
A43: 39 | B43: Edupixels | C43: corporate_office | D43: Office Boy, Housekeeping, Security, Data Entry | E43: 0124 410 9454 | F43: Landline (reception) | G43: 5 | H43: 53, Sector 52A, Gurugram, Haryana 122009, India | M43: Map
A44: 40 | B44: Global Communication | C44: cell_phone_store | D44: Store Helper, Housekeeping, Security, Sales Staff | E44: 0124 257 7153 | F44: Landline (reception) | G44: 4.6 | H44: C3RR+736, HUDA Sector Rd, Sector 52A, Gurugram, Haryana 122011, India | M44: Map
A45: 41 | B45: SKN-HCG CNG Station | C45: gas_station | D45: Pump Attendant, Cleaner, Security | E45: 0124 427 2107 | F45: Landline (reception) | G45: 4 | H45: Sector 52A, Gurugram, Haryana 122011, India | M45: Map
A46: 42 | B46: IndianOil | C46: gas_station | D46: Helper, Housekeeping, Security, Office Boy | E46: 0124 234 0541 | F46: Landline (reception) | G46: 3.8 | H46: Ground Floor, Sector 52A, Gurugram, Haryana 122011, India | M46: Map

Sheet Sector 42
A1: SWITCH · SECTOR 42 · CALL SHEET
A2: Shifts 1–12 hrs, billed per hour · pay after worker reports · instant replacement | 143 leads · 129 mobiles (owner/mgr) at top
A3: LEADS | B3: =COUNTA(B5:B147) | C3: CONTACTED | D3: =COUNTA(I5:I147) | E3: INTERESTED | F3: =COUNTIF(I5:I147,"Yes") | G3: ORDERS | H3: =COUNTIF(K5:K147,"Yes") | I3: HOURS BOOKED | J3: =SUM(J5:J147)
A4: S.No | B4: Business Name | C4: Category | D4: Suggested Roles (per shift) | E4: Phone | F4: Number Type | G4: Rating | H4: Address | I4: Interested? | J4: Hours (1-12) | K4: Order Confirmed? | L4: Remarks | M4: Map
A5: 1 | B5: Agarwal Movers And Packers Gurgaon | C5: moving_company | D5: Loader, Packer, Picker, Warehouse Helper, Delivery | E5: 070561 66001 | F5: Mobile (owner/mgr) | G5: 5 | H5: Shop No. 16, DLF Golf Course, Sector 42, Gurugram, Haryana 122009, India | M5: Map
A6: 2 | B6: AmbassadorPerk: Web Development & Marketing Agency | C6: service | D6: Store Helper, Housekeeping, Security, Sales Staff | E6: 082879 38099 | F6: Mobile (owner/mgr) | G6: 5 | H6: Dlf The Camellias, Golf Course Rd, DLF Phase 5, Sector 42, Gurugram, Haryana 122009, India | M6: Map
A7: 3 | B7: Ankit car rental | C7: point_of_interest | D7: Helper, Housekeeping, Security, Office Boy | E7: 093513 04217 | F7: Mobile (owner/mgr) | G7: 5 | H7: House No, 285D, Sector 42, Gurugram, Haryana 122009, India | M7: Map
A8: 4 | B8: Antarang | C8: art_gallery | D8: Helper, Housekeeping, Security, Office Boy | E8: 085888 15322 | F8: Mobile (owner/mgr) | G8: 5 | H8: Antarang, Unit 3, Tower 8, Dlf The Camellias, DLF Golf Course, Sector 42, Gurugram, Haryana 122009, India | M8: Map
A9: 5 | B9: astitva - aestheticvision.yoga | C9: yoga_studio | D9: Trainer, Housekeeping, Front Desk | E9: 089299 66222 | F9: Mobile (owner/mgr) | G9: 5 | H9: Eternal Oasis, 591 A, opposite Shiv Nadar School, Sector 42, Gurugram, Haryana 122009, India | M9: Map
A10: 6 | B10: Avidion Softwares Pvt. Ltd | C10: business | D10: Helper, Housekeeping, Security, Office Boy | E10: 098965 84099 | F10: Mobile (owner/mgr) | G10: 5 | H10: 676, Sector 42 Main Rd, Sector 42, Gurugram, Haryana 122011, India | M10: Map
A11: 7 | B11: Bhagwati cab service - Taxi Service in Sector 42 Gurgaon | C11: taxi_service | D11: Helper, Housekeeping, Security, Office Boy | E11: 099101 70323 | F11: Mobile (owner/mgr) | G11: 5 | H11: 285D, Sector 42, Gurugram, Haryana 122009, India | M11: Map
A12: 8 | B12: Blinx India Pvt. Ltd. | C12: electronics_store | D12: Store Helper, Housekeeping, Security, Sales Staff | E12: 095606 84455 | F12: Mobile (owner/mgr) | G12: 5 | H12: Rehmat House, 46IP, Basement, Urban Estate, Sector 42, Gurugram, Haryana 122009, India | M12: Map
A13: 9 | B13: Bosch Washing Machine Customer Care . Gurugaon | C13: service | D13: Helper, Housekeeping, Security, Office Boy | E13: 092665 24045 | F13: Mobile (owner/mgr) | G13: 5 | H13: Shop No 45, Golf Course Rd, Sector 42, Gurugram, Haryana 122009, India | M13: Map
A14: 10 | B14: Buonai | C14: home_goods_store | D14: Store Helper, Housekeeping, Security, Sales Staff | E14: 099902 91448 | F14: Mobile (owner/mgr) | G14: 5 | H14: DLF Magnolias, near, Golf Course Rd, Sector 42, Gurugram, Haryana 122009, India | M14: Map
A15: 11 | B15: DLF The Camellias 2 | Sales Office | C15: corporate_office | D15: Office Boy, Housekeeping, Security, Data Entry | E15: 099532 40037 | F15: Mobile (owner/mgr) | G15: 5 | H15: Golf Course Road, DLF Golf Course, Sector 42, Gurugram, Haryana 122009, India | M15: Map
A16: 12 | B16: DLF The Dahlias Gurgaon Sales Gallery | C16: general_contractor | D16: Helper, Housekeeping, Security, Office Boy | E16: 093551 33342 | F16: Mobile (owner/mgr) | G16: 5 | H16: Plot No. 44, DLF Phase 5, Sector 42, Gurugram, Haryana 122009, India | M16: Map
... A119: 115 | B119: Signz | C119: manufacturer | D119: Machine Operator, Helper, Loader, Packer | E119: 092207 91840 | F119: Mobile (owner/mgr) | G119: 1 | H119: 765, Sector 42, Gurugram, Haryana 122009, India | M119: Map
A120: 116 | B120: Aarohana Consulting | C120: consultant | D120: Office Boy, Housekeeping, Security, Data Entry | E120: 099100 26255 | F120: Mobile (owner/mgr) | H120: D-1101 Central Park –I, Golf Course Rd, Sector 42, Gurugram, Haryana 122009, India | M120: Map
A121: 117 | B121: AltUrban | C121: service | D121: Helper, Housekeeping, Security, Office Boy | E121: 095408 71917 | F121: Mobile (owner/mgr) | H121: House no 522, Sector 42, Gurugram, Haryana 122002, India | M121: Map
A122: 118 | B122: CapBuild Clincial skills Pvt Ltd | C122: corporate_office | D122: Office Boy, Housekeeping, Security, Data Entry | E122: 098108 02817 | F122: Mobile (owner/mgr) | H122: A-254, Park Heights, Park Place, Golf Course Rd, DLF Phase 5, Sector 42, Gurugram, Haryana 122009, India | M122: Map
A123: 119 | B123: Corumm | C123: wellness_center | D123: Beautician, Helper, Receptionist, Cleaner | E123: 098716 14567 | F123: Mobile (owner/mgr) | H123: 3rd Floor, F-17/1, Golf Course Rd, DLF Phase 1, Sector 42, Gurugram, Haryana 122002, India | M123: Map
A124: 120 | B124: DLF | C124: corporate_office | D124: Office Boy, Housekeeping, Security, Data Entry | E124: 088820 12093 | F124: Mobile (owner/mgr) | H124: Block C, Sushant Lok Phase I, Sector 42, Gurugram, Haryana 122009, India | M124: Map
A125: 121 | B125: DLF Magnolias Gurgaon | C125: real_estate_agency | D125: Office Boy, Housekeeping, Security, Data Entry | E125: 096678 09619 | F125: Mobile (owner/mgr) | H125: F33, Office No-26, Plot No- 100, Sector 42 Main Rd, Sector 43, Gurugram, Haryana 122009, India | M125: Map
A126: 122 | B126: GrowYo | C126: educational_institution | D126: Peon, Housekeeping, Security, Attendant | E126: 093118 79331 | F126: Mobile (owner/mgr) | H126: 820, Golf Course Rd, Sector 42, Gurugram, Haryana 122009, India | M126: Map
A127: 123 | B127: Kalyra AI Labs | C127: service | D127: Helper, Housekeeping, Security, Office Boy | E127: 099533 60965 | F127: Mobile (owner/mgr) | H127: Fl 3, Shiv Nadar School, 525T, Landmark:, Sector 42, Gurugram, Haryana 122009, India | M127: Map
A128: 124 | B128: MEHRA BUILDTECH | C128: general_contractor | D128: Helper, Housekeeping, Security, Office Boy | E128: 076967 56458 | F128: Mobile (owner/mgr) | H128: 410, Basement, Golf Course Rd, Sector 42, Gurugram, Haryana 122009, India | M128: Map
A129: 125 | B129: Real Madrid Football Program - DLF Camellias | Delhi NCR’s Leading Football Development Program | C129: sports_club | D129: Trainer, Housekeeping, Front Desk | E129: 088600 07341 | F129: Mobile (owner/mgr) | H129: Golf Course Rd, DLF Golf Course, Sector 42, Gurugram, Haryana 122009, India | M129: Map
A130: 126 | B130: SAAB ENTERPRISES | C130: consultant | D130: Office Boy, Housekeeping, Security, Data Entry | E130: 097122 22897 | F130: Mobile (owner/mgr) | H130: PLOT NO. 372, Sector 42, Gurugram, Haryana 122009, India | M130: Map
A131: 127 | B131: Studio inside outside | C131: general_contractor | D131: Helper, Housekeeping, Security, Office Boy | E131: 098115 50606 | F131: Mobile (owner/mgr) | H131: 682P, Sector 42, Gurugram, Haryana 122009, India | M131: Map
... A133: 129 | B133: The Resolute Academy - Special Education Autism School in Gurgaon | Occupational & Speech Therapy in Gurgaon | C133: school | D133: Peon, Housekeeping, Security, Attendant | E133: 093197 15557 | F133: Mobile (owner/mgr) | H133: Plot no. 611, Sector 43, Golf course road, Gugaon, 43, near rapid metro station, Sector 42, Gurugram, Haryana 122009, India | M133: Map
A134: 130 | B134: Fabhotel Harnoor House | C134: hotel | D134: Housekeeping, Room Boy, Kitchen Helper, Front Desk | E134: 11246907102 | F134: Landline (reception) | G134: 5 | H134: No. 811, Sector 42, Gurugram, Haryana 122009, India | M134: Map
A135: 131 | B135: RehabMe. | C135: medical_clinic | D135: Ward Boy, Housekeeping, Attendant, Security | E135: 0124 414 1546 | F135: Landline (reception) | G135: 5 | H135: 1, Basement, Golf Avenue 42, F/17, Sunset Blvd, DLF Phase 1, Sector 42, Gurugram, Haryana 122002, India | M135: Map
A136: 132 | B136: UrbanShift Packers & Movers - Sector 42 Gurgaon | C136: moving_company | D136: Loader, Packer, Picker, Warehouse Helper, Delivery | E136: 1800 572 3936 | F136: Landline (helpline) | G136: 4.8 | H136: Shop No.5, The Aralias, Golf Course Rd, Sector 42, Gurugram, Haryana 122009, India | M136: Map
A137: 133 | B137: Golf Pavilion | C137: sports_club | D137: Trainer, Housekeeping, Front Desk | E137: 0124 452 5261 | F137: Landline (reception) | G137: 4.7 | H137: F444+G2Q, DLF Golf Course, Sector 42, Gurugram, Haryana 122009, India | M137: Map
A138: 134 | B138: DLF Golf and Country Club | C138: golf_course | D138: Helper, Housekeeping, Security, Office Boy | E138: 0124 452 5275 | F138: Landline (reception) | G138: 4.6 | H138: Golf Course Rd, opp. American Express, DLF Phase 5, Sector 42, Gurugram, Haryana 122009, India | M138: Map
A139: 135 | B139: One Up Library Gurugram | C139: library | D139: Helper, Housekeeping, Security, Office Boy | E139: 0124 428 7638 | F139: Landline (reception) | G139: 4.5 | H139: 682P, opposite Shiv Nadar School, next to Hotel Foxtrail, Sector 42, Gurugram, Haryana 122009, India | M139: Map
A140: 136 | B140: The Wellness Co. | C140: wellness_center | D140: Beautician, Helper, Receptionist, Cleaner | E140: 1800 121 2429 | F140: Landline (helpline) | G140: 4.4 | H140: First Floor, Ameya One, Golf Course Rd, Sector 42, Gurugram, Haryana 122009, India | M140: Map
A141: 137 | B141: AutoZone India Services LLP | C141: auto_parts_store | D141: Store Helper, Housekeeping, Security, Sales Staff | E141: 0124 447 0914 | F141: Landline (reception) | G141: 4.3 | H141: 7th floor, BLOCK - A, DLF CENTRE COURT, Golf Course Rd, Sector 42, Gurugram, Haryana 122003, India | M141: Map
A142: 138 | B142: American Express Global Business Travel | C142: travel_agency | D142: Helper, Housekeeping, Security, Office Boy | E142: 0124 628 4940 | F142: Landline (reception) | G142: 4.2 | H142: DLF Centre Court, Golf Course Rd, DLF Phase 5, Sector 42, Gurugram, Haryana 122009, India | M142: Map
A143: 139 | B143: Ameya Group Gurgaon | C143: general_contractor | D143: Helper, Housekeeping, Security, Office Boy | E143: 0124 257 1477 | F143: Landline (reception) | G143: 3.7 | H143: Ameya One, Sector 42, Gurugram, Haryana 122009, India | M143: Map
A144: 140 | B144: Key Management Group | C144: business | D144: Helper, Housekeeping, Security, Office Boy | E144: 0124 473 5555 | F144: Landline (reception) | G144: 3.7 | H144: Tower B, Golf View Towers, Golf Course Rd, Sector 42, Gurugram, Haryana 122009, India | M144: Map
A145: 141 | B145: Global Healthcare And Medical Services | C145: consultant | D145: Ward Boy, Housekeeping, Attendant, Security | E145: 0124 403 8181 | F145: Landline (reception) | H145: 108, Centrum Plaza Golf Course Road, Sector 42, Gurugram, Haryana 122009, India | M145: Map
A146: 142 | B146: ICICI BANK ATM | C146: bank | D146: Office Boy, Housekeeping, Security, Data Entry | E146: 1800 1080 | F146: Landline (helpline) | H146: ICICI Bank ATM, Dlf The Camellias, Golf Course Rd, DLF Phase 5, Sector 42, Gurugram, Haryana 122009, India | M146: Map
A147: 143 | B147: IDFC FIRST Bank ATM | C147: atm | D147: Office Boy, Housekeeping, Security, Data Entry | E147: 1800 10888 | F147: Landline (helpline) | H147: P Hills, Condominium Association, NH 48, SPR Road, near Kherki Daula Toll Plaza, Palam Hills, Sec 77, Sector 42, Gurugram, Haryana 122009, India | M147: Map

Sheet Sector 27
A1: SWITCH · SECTOR 27 · CALL SHEET
A2: Shifts 1–12 hrs, billed per hour · pay after worker reports · instant replacement | 101 leads · 89 mobiles (owner/mgr) at top
A3: LEADS | B3: =COUNTA(B5:B105) | C3: CONTACTED | D3: =COUNTA(I5:I105) | E3: INTERESTED | F3: =COUNTIF(I5:I105,"Yes") | G3: ORDERS | H3: =COUNTIF(K5:K105,"Yes") | I3: HOURS BOOKED | J3: =SUM(J5:J105)
A4: S.No | B4: Business Name | C4: Category | D4: Suggested Roles (per shift) | E4: Phone | F4: Number Type | G4: Rating | H4: Address | I4: Interested? | J4: Hours (1-12) | K4: Order Confirmed? | L4: Remarks | M4: Map
A5: 1 | B5: Aarvines Jewells | C5: jewelry_store | D5: Store Helper, Housekeeping, Security, Sales Staff | E5: 096673 30138 | F5: Mobile (owner/mgr) | G5: 5 | H5: 2nd floor, 573, Sector 27, Gurugram, Haryana 122002, India | M5: Map
A6: 2 | B6: Ashram श्रीगौडपाद मठ | C6: educational_institution | D6: Peon, Housekeeping, Security, Attendant | E6: 098181 86089 | F6: Mobile (owner/mgr) | G6: 5 | H6: 165, Sector 27, Gurugram, Haryana 122009, India | M6: Map
A7: 3 | B7: Balaji Daily Needs | C7: point_of_interest | D7: Helper, Housekeeping, Security, Office Boy | E7: 097183 70601 | F7: Mobile (owner/mgr) | G7: 5 | H7: Sector 27, Gurugram, Haryana 122009, India | M7: Map
A8: 4 | B8: Cluster 27 Classroom, Mission Learning Foundation | C8: school | D8: Peon, Housekeeping, Security, Attendant | E8: 098185 41729 | F8: Mobile (owner/mgr) | G8: 5 | H8: F38Q+5P4, Sector 27, Gurugram, Haryana 122009, India | M8: Map
A9: 5 | B9: Dental Pod - A Multispeciality Clinic | C9: dental_clinic | D9: Ward Boy, Housekeeping, Attendant, Security | E9: 088105 61282 | F9: Mobile (owner/mgr) | G9: 5 | H9: F37R+FFR, 493, behind Golf Course Road, Sector 27, Gurugram, Haryana 122009, India | M9: Map
A10: 6 | B10: Dr Meenu Duggal Chopra | C10: health | D10: Ward Boy, Housekeeping, Attendant, Security | E10: 098104 54839 | F10: Mobile (owner/mgr) | G10: 5 | H10: 486, DLF Phase IV, Sector 27, Gurugram, Haryana 122009, India | M10: Map
A11: 7 | B11: Dr. Rashmi Agrawal | C11: doctor | D11: Ward Boy, Housekeeping, Attendant, Security | E11: 098117 75369 | F11: Mobile (owner/mgr) | G11: 5 | H11: NOVA IVF, Plot No 522, Sector 27, Gurugram, Haryana 122009, India | M11: Map
A12: 8 | B12: Easydose Pharmacy | C12: pharmacy | D12: Ward Boy, Housekeeping, Attendant, Security | E12: 092665 32929 | F12: Mobile (owner/mgr) | G12: 5 | H12: 2, Regency Park Road, DLF Phase IV, Sector 27, Gurugram, Haryana 122009, India | M12: Map
A13: 9 | B13: Gulshan Hydraulic & hydra crane service | C13: service | D13: Helper, Housekeeping, Security, Office Boy | E13: 080767 88126 | F13: Mobile (owner/mgr) | G13: 5 | H13: phase 1, Sector 27, Sushant Lok Rd, Block D, Gurugram, Haryana 122002, India | M13: Map
A14: 10 | B14: House of Satva | C14: clothing_store | D14: Store Helper, Housekeeping, Security, Sales Staff | E14: 095604 28403 | F14: Mobile (owner/mgr) | G14: 5 | H14: Santosh Plaza, Plot No 728, B Block Dr, Sushant Lok Phase I, Sector 27, Gurugram, Haryana 122009, India | M14: Map
A15: 11 | B15: JBS Adventures LLP | C15: taxi_service | D15: Helper, Housekeeping, Security, Office Boy | E15: 090402 87000 | F15: Mobile (owner/mgr) | G15: 5 | H15: building no. 660, WeWork,HQ27, Sushant Lok Phase I, Sector 27, Gurugram, Haryana 122009, India | M15: Map
A16: 12 | B16: KSH544 | C16: service | D16: Helper, Housekeeping, Security, Office Boy | E16: 097111 98717 | F16: Mobile (owner/mgr) | G16: 5 | H16: Houe 544, Sector 27, Gurugram, Haryana 122009, India | M16: Map
... A71: 67 | B71: Orthosport.In | C71: medical_clinic | D71: Ward Boy, Housekeeping, Attendant, Security | E71: 080 6510 5052 | F71: Mobile (owner/mgr) | G71: 2.5 | H71: Ground, Floor, F, 10, 4, Golf Course Rd, DLF Phase 1, Sector 27, Gurugram, Haryana 122001, India | M71: Map
A72: 68 | B72: Aakaar Holistic Home Care | C72: health | D72: Ward Boy, Housekeeping, Attendant, Security | E72: 079887 47886 | F72: Mobile (owner/mgr) | H72: SCO. 400, Sector 27, Gurugram, Haryana 122009, India | M72: Map
A73: 69 | B73: Abhay Khurana - Growth Architect | C73: consultant | D73: Office Boy, Housekeeping, Security, Data Entry | E73: 099994 40880 | F73: Mobile (owner/mgr) | H73: 573, Sector 27, Gurugram, Haryana 122001, India | M73: Map
A74: 70 | B74: Agilus Diagnostics (formerly SRL) - Sector 27, Gurugram | Blood Test | Full Body Checkup | Pathology Lab | C74: medical_clinic | D74: Ward Boy, Housekeeping, Attendant, Security | E74: 077038 04202 | F74: Mobile (owner/mgr) | H74: Plot No 9, Hamilton Court Road, Sector 27, Gurugram Haryana - 122009, Sector 27, Gurugram, Haryana 122022, India | M74: Map
A75: 71 | B75: Autoknox | C75: car_dealer | D75: Helper, Housekeeping, Security, Office Boy | E75: 098733 30036 | F75: Mobile (owner/mgr) | H75: opp. Arjun Marg, near Jalsa resturant, DLF Phase 1, Sector 27, Gurugram, Haryana 122009, India | M75: Map
A76: 72 | B76: Blink eye care | C76: medical_clinic | D76: Ward Boy, Housekeeping, Attendant, Security | E76: 083839 41792 | F76: Mobile (owner/mgr) | H76: SCO 180, Jharsa Rd, Friends Colony, Sector 27, Gurugram, Haryana 122009, India | M76: Map
A77: 73 | B77: Coordinates | C77: consultant | D77: Office Boy, Housekeeping, Security, Data Entry | E77: 072047 26525 | F77: Mobile (owner/mgr) | H77: 7th floor, B-660, Sushant Lok Phase I, Sector 27, Gurugram, Haryana 122009, India | M77: Map
A78: 74 | B78: Delhi Public School Sushant Lok| Best School in Gurugram | C78: school | D78: Peon, Housekeeping, Security, Attendant | E78: 096433 08832 | F78: Mobile (owner/mgr) | H78: B-Block, behind Max Hospital, Block B, Sushant Lok Phase I, Sector 27, Gurugram, Haryana 122009, India | M78: Map
A79: 75 | B79: Dr. Vandana Datta | V-Medica Gurgaon | Psychology | C79: doctor | D79: Ward Boy, Housekeeping, Attendant, Security | E79: 098212 06779 | F79: Mobile (owner/mgr) | H79: 6303, DLF Phase IV, Sector 27, Gurugram, Haryana 122009, India | M79: Map
A80: 76 | B80: Euna | C80: jewelry_store | D80: Store Helper, Housekeeping, Security, Sales Staff | E80: 074649 44944 | F80: Mobile (owner/mgr) | H80: 249, Sector 27, Gurugram, Haryana 122009, India | M80: Map
A81: 77 | B81: Harsh kaushik & Associates | C81: consultant | D81: Office Boy, Housekeeping, Security, Data Entry | E81: 095608 80827 | F81: Mobile (owner/mgr) | H81: 363, Sector 27, Gurugram, Haryana 122009, India | M81: Map
A82: 78 | B82: Integrity Education India - Gurgaon | C82: business | D82: Helper, Housekeeping, Security, Office Boy | E82: 070116 05618 | F82: Mobile (owner/mgr) | H82: C-579, Block C, Sushant Lok Phase I, Sector 27, Gurugram, Haryana 122009, India | M82: Map
A83: 79 | B83: Karmic Blessings | C83: supplier | D83: Helper, Housekeeping, Security, Office Boy | E83: 093543 17743 | F83: Mobile (owner/mgr) | H83: 182P 3rd floor, near Hamilton Court Road, Sector 27, Gurugram, Haryana 122009, India | M83: Map
... A93: 89 | B93: Xiphi Insights | C93: service | D93: Helper, Housekeeping, Security, Office Boy | E93: 098705 03997 | F93: Mobile (owner/mgr) | H93: 302, 3rd floor, Tower B, MILLENNIUM PLAZA, Sector 27, Gurugram, Haryana 122002, India | M93: Map
A94: 90 | B94: MInArch Studio | C94: service | D94: Helper, Housekeeping, Security, Office Boy | E94: 0124 419 2766 | F94: Landline (reception) | G94: 5 | H94: B-438A, Sushant Lok Phase I, Sector 27, Gurugram, Haryana 122009, India | M94: Map
A95: 91 | B95: Mehta & Mehta Associates | C95: consultant | D95: Office Boy, Housekeeping, Security, Data Entry | E95: 0124 410 8474 | F95: Landline (reception) | G95: 4.9 | H95: B-474, Sushant Lok Phase I, Sector 27, Gurugram, Haryana 122009, India | M95: Map
A96: 92 | B96: Dr Mueller's AktivHealth | C96: medical_clinic | D96: Ward Boy, Housekeeping, Attendant, Security | E96: 011 7136 6777 | F96: Landline (reception) | G96: 4.8 | H96: 4, 2nd Floor, F-10, Golf Course Rd, DLF Phase 1, Sector 27, Gurugram, Haryana 122009, India | M96: Map
A97: 93 | B97: Dr. Deepika's Wellness Clinic | C97: consultant | D97: Ward Boy, Housekeeping, Attendant, Security | E97: 0124 238 5270 | F97: Landline (reception) | G97: 4.8 | H97: 133, Galleria Boulevard, DLF Phase IV, Sector 27, Gurugram, Haryana 122009, India | M97: Map
A98: 94 | B98: Vmedica Physiotherapy | C98: medical_clinic | D98: Ward Boy, Housekeeping, Attendant, Security | E98: 0124 429 6877 | F98: Landline (reception) | G98: 4.8 | H98: 6303, DLF Phase IV, Sector 27, Gurugram, Haryana 122009, India | M98: Map
A99: 95 | B99: NIDO Inn | C99: guest_house | D99: Housekeeping, Room Boy, Kitchen Helper, Front Desk | E99: 902902304 | F99: Landline (reception) | G99: 4.5 | H99: F-13/13, Golf Course Rd, CRSINDIA Sector 27, DLF Phase IV, Sector 27, Gurugram, Haryana 122009, India | M99: Map
A100: 96 | B100: Jalsa Restaurant | C100: tibetan_restaurant | D100: Kitchen Helper, Cook, Dishwasher, Waiter | E100: 0124 425 7952 | F100: Landline (reception) | G100: 4.1 | H100: F-11/9, Golf Course Road, गोल्फ कोर्स मार्ग, opp. Arjun Marg, DLF Phase 1, Sector 27, Gurugram, Haryana 122009, India | M100: Map
A101: 97 | B101: Bharat Gas | C101: service | D101: Helper, Housekeeping, Security, Office Boy | E101: 1800 22 2725 | F101: Landline (helpline) | G101: 3.7 | H101: Sector 27, Gurugram, Haryana 122009, India | M101: Map
A102: 98 | B102: Ayushakti Ayurved Center | C102: doctor | D102: Ward Boy, Housekeeping, Attendant, Security | E102: 0124 401 9008 | F102: Landline (reception) | G102: 2.3 | H102: F16/10, Golf Course Road, Phase -1, Sector 27, Sector 27, Gurugram, Haryana 122009, India | M102: Map
A103: 99 | B103: Collection O Daffodils | C103: hotel | D103: Housekeeping, Room Boy, Kitchen Helper, Front Desk | E103: 0124 433 0575 | F103: Landline (reception) | G103: 1.8 | H103: HOUSE No 1526, Sector 46, Near A M I T Y International School Sector 46 MarketO.823,SEC-57, INDIAnull, Sector 27, Gurugram, Haryana 122009, India | M103: Map
A104: 100 | B104: 99acres Sales Office Sec-27 Gurgaon | C104: real_estate_agency | D104: Office Boy, Housekeeping, Security, Data Entry | E104: 1800 419 9099 | F104: Landline (helpline) | H104: Bestech Chembers, B Block, Unit 515 to 517 5th Floor, Sector 27, Sushant Lok Phase I, Sector 43, Gurugram, Haryana 122009, India | M104: Map
A105: 101 | B105: Dr. Nitisha Goyal - Best Neurologist | Medanta Mediclinic - Golf Course , Gurugram | C105: doctor | D105: Ward Boy, Housekeeping, Attendant, Security | E105: 0124 483 4574 | F105: Landline (reception) | H105: Plot No. 562SP, Golf Course Rd, Sector 27, Gurugram, Haryana 122009, India | M105: Map

Sheet Sector 28
A1: SWITCH · SECTOR 28 · CALL SHEET
A2: Shifts 1–12 hrs, billed per hour · pay after worker reports · instant replacement | 260 leads · 230 mobiles (owner/mgr) at top
A3: LEADS | B3: =COUNTA(B5:B264) | C3: CONTACTED | D3: =COUNTA(I5:I264) | E3: INTERESTED | F3: =COUNTIF(I5:I264,"Yes") | G3: ORDERS | H3: =COUNTIF(K5:K264,"Yes") | I3: HOURS BOOKED | J3: =SUM(J5:J264)
A4: S.No | B4: Business Name | C4: Category | D4: Suggested Roles (per shift) | E4: Phone | F4: Number Type | G4: Rating | H4: Address | I4: Interested? | J4: Hours (1-12) | K4: Order Confirmed? | L4: Remarks | M4: Map
A5: 1 | B5: Aastha P.G | C5: condominium_complex | D5: Helper, Housekeeping, Security, Office Boy | E5: 099998 15252 | F5: Mobile (owner/mgr) | G5: 5 | H5: House no. 189, Sector 28, Chakkarpur, Gurugram, Haryana 122002, India | M5: Map
A6: 2 | B6: Aayush Enterprises | C6: courier_service | D6: Loader, Packer, Picker, Warehouse Helper, Delivery | E6: 085060 00504 | F6: Mobile (owner/mgr) | G6: 5 | H6: Shop No.1 Sector.29, Housing Board Colony, Sector 28, Chakkarpur, Sarswati Vihar, Gurugram, Haryana 122002, India | M6: Map
A7: 3 | B7: Aggarwal Cement Sales | C7: building_materials_store | D7: Store Helper, Housekeeping, Security, Sales Staff | E7: 097117 70796 | F7: Mobile (owner/mgr) | G7: 5 | H7: Shop No.-2, Housing Board, near Sector 28, Housing Board Colony, Saraswati Vihar, Maruti Housing Colony, Gurugram, Haryana 122002, India | M7: Map
A8: 4 | B8: Akash Fast Food Store | C8: food_court | D8: Kitchen Helper, Cook, Dishwasher, Waiter | E8: 099901 81605 | F8: Mobile (owner/mgr) | G8: 5 | H8: Shop No, 16 Area, Sector 28, Nathupur Dlf, Gurugram, Haryana 122009, India | M8: Map
A9: 5 | B9: All Things Real Estate | C9: consultant | D9: Office Boy, Housekeeping, Security, Data Entry | E9: 086506 11000 | F9: Mobile (owner/mgr) | G9: 5 | H9: JMD Empire Square, Mehrauli-Gurgaon Rd, Sector 28, DLF Phase 1, Gurugram, Haryana 122002, India | M9: Map
A10: 6 | B10: Anand Estates | C10: private_guest_room | D10: Helper, Housekeeping, Security, Office Boy | E10: 095601 90017 | F10: Mobile (owner/mgr) | G10: 5 | H10: A-134, Sector 28, Sushant Lok Phase I, Gurugram, Haryana 122009, India | M10: Map
A11: 7 | B11: Anjali Cosmetic Shop | C11: cosmetics_store | D11: Store Helper, Housekeeping, Security, Sales Staff | E11: 099712 65506 | F11: Mobile (owner/mgr) | G11: 5 | H11: Shop No 1, Chakarpur, Sector 28, Gurugram, NCR, Sector 28, Chakkarpur, Region, Gurugram, Haryana 122002, India | M11: Map
A12: 8 | B12: Arjun Tea Stall | C12: tea_store | D12: Store Helper, Housekeeping, Security, Sales Staff | E12: 062818 23006 | F12: Mobile (owner/mgr) | G12: 5 | H12: Shop No 155, Mehrauli-Gurgaon Rd, near MGF Metropolitan Mall, Sector 28, Maruti Housing Colony, Gurugram, Haryana 122009, India | M12: Map
A13: 9 | B13: Arogyam Spa MG Road-Massage Spa Center in MG Road Gurgaon | Spa in MG Road Gurgaon | Luxury Spa in MG Road | C13: spa | D13: Beautician, Helper, Receptionist, Cleaner | E13: 079826 57810 | F13: Mobile (owner/mgr) | G13: 5 | H13: Shop No 5, Ground Floor, Arcade Mall, Mehrauli-Gurgaon Rd, Sector 28, DLF Phase 1, Gurugram, Haryana 122001, India | M13: Map
A14: 10 | B14: Arun Pan Shope | C14: store | D14: Store Helper, Housekeeping, Security, Sales Staff | E14: 091627 43412 | F14: Mobile (owner/mgr) | G14: 5 | H14: Shop No.10, Metro Station, Mehrauli-Gurgaon Rd, Sector 28, DLF Phase 2, Sector 25, Gurugram, Haryana 122002, India | M14: Map
A15: 11 | B15: Blue heaven therapy at Homes | C15: massage | D15: Beautician, Helper, Receptionist, Cleaner | E15: 093829 89566 | F15: Mobile (owner/mgr) | G15: 5 | H15: Sector 28, Chakkarpur, Sector 43, Gurugram, Haryana 122009, India | M15: Map
A16: 12 | B16: BNGIN ONLINE | C16: hypermarket | D16: Store Helper, Housekeeping, Security, Sales Staff | E16: 098214 94061 | F16: Mobile (owner/mgr) | G16: 5 | H16: F 12/1, DLF PHASE 1, Golf Course Road, Sector 28, DLF Phase 1, Gurugram, Haryana 122002, India | M16: Map
... A187: 183 | B187: S R Ledis Tailor | C187: clothing_store | D187: Store Helper, Housekeeping, Security, Sales Staff | E187: 088604 29799 | F187: Mobile (owner/mgr) | G187: 1 | H187: Shop No.4, Market, Jaina Market, Sector 28, Chakkarpur, Gurugram, Haryana 122002, India | M187: Map
A188: 184 | B188: Ambay Car Shingar | C188: chauffeur_service | D188: Helper, Housekeeping, Security, Office Boy | E188: 097115 97170 | F188: Mobile (owner/mgr) | H188: Shop Number 1, Old, Delhi Road, opp. Punjab National Bank, Sector 28, Sushant Lok Phase I, Gurugram, Haryana 122009, India | M188: Map
A189: 185 | B189: Anarul Dyeing | C189: laundry | D189: Helper, Housekeeping, Security, Office Boy | E189: 085958 76392 | F189: Mobile (owner/mgr) | H189: near Ascent Public School, Nathuram Market, Sector 28, Chakkarpur, Gurugram, Haryana 122002, India | M189: Map
A190: 186 | B190: Anita Devi | C190: store | D190: Store Helper, Housekeeping, Security, Sales Staff | E190: 096937 19840 | F190: Mobile (owner/mgr) | H190: Sector 28, Gurugram, Haryana 122002, India | M190: Map
A191: 187 | B191: Architecture & Interior Design | C191: service | D191: Helper, Housekeeping, Security, Office Boy | E191: 098105 54829 | F191: Mobile (owner/mgr) | H191: A/4, Mehrauli-Gurgaon Rd, nr. Sahara Mall, Sector 28, Sushant Lok Phase I, Gurugram, Haryana 122002, India | M191: Map
A192: 188 | B192: Breast Cancer Treatment in Gurgaon | Mastectomy Surgery | Breast Reconstruction Surgery | Max Healthcare, Gurugram | C192: doctor | D192: Ward Boy, Housekeeping, Attendant, Security | E192: 092688 80303 | F192: Mobile (owner/mgr) | H192: 1st Floor, B Block, Max Hospital, MF Hussain Marg, near Huda City Centre, Phase 1, Sector 28, Sushant Lok Phase I, Sector 43, Gurugram, Haryana 122001, India | M192: Map
A193: 189 | B193: ChildrenPlus | C193: medical_clinic | D193: Ward Boy, Housekeeping, Attendant, Security | E193: 084474 49331 | F193: Mobile (owner/mgr) | H193: Aartas Clinishare, Metro Station, 10-P, Golf Course Rd, near DLF Phase 1, Sector 28, Gurugram, Haryana 122009, India | M193: Map
A194: 190 | B194: CloudInfinity Technolgies | C194: business | D194: Helper, Housekeeping, Security, Office Boy | E194: 076657 52485 | F194: Mobile (owner/mgr) | H194: 2nd Floor, 142, Sector 28, Chakkarpur, Gurugram, Haryana 122009, India | M194: Map
A195: 191 | B195: Coal depo | C195: corporate_office | D195: Office Boy, Housekeeping, Security, Data Entry | E195: 088160 50777 | F195: Mobile (owner/mgr) | H195: shop no. 1, A Block, Mehrauli-Gurgaon Rd, Sector 28, DLF Phase 1, Sarhol, Gurugram, Haryana 122002, India | M195: Map
A196: 192 | B196: Crazy Trader | C196: store | D196: Store Helper, Housekeeping, Security, Sales Staff | E196: 095822 41693 | F196: Mobile (owner/mgr) | H196: 79, Mehrauli-Gurgaon Rd, Sector 28, Maruti Housing Colony, Sector 25, Gurugram, Haryana 122009, India | M196: Map
A197: 193 | B197: Deluxe Cargo Packers And Movers | C197: transportation_service | D197: Loader, Packer, Picker, Warehouse Helper, Delivery | E197: 087969 01998 | F197: Mobile (owner/mgr) | H197: Shop No, 433, Phase 1, Sector 28, Sushant Lok Phase I, Sector 43, Gurugram, Haryana 122009, India | M197: Map
A198: 194 | B198: Dev Health Care | C198: medical_clinic | D198: Ward Boy, Housekeeping, Attendant, Security | E198: 098718 58300 | F198: Mobile (owner/mgr) | H198: 159, Near Dayal Public School, Chakkarpur, Gurgaon, NCR, Sector 28, Chakkarpur, Region, Gurugram, Haryana 122002, India | M198: Map
A199: 195 | B199: Dev Shakya Tea Shop | C199: store | D199: Store Helper, Housekeeping, Security, Sales Staff | E199: 095288 35702 | F199: Mobile (owner/mgr) | H199: 57, Mg Metro, Sector 28, DLF Phase 2, Sector 25, Gurugram, Haryana 122009, India | M199: Map
... A234: 230 | B234: Yadav Fast Food | C234: restaurant | D234: Kitchen Helper, Cook, Dishwasher, Waiter | E234: 077390 25853 | F234: Mobile (owner/mgr) | H234: Chakkarpur Village Rd, near by Radha Krishna Mandir, Sector 28, Chakkarpur, Gurugram, Haryana 122002, India | M234: Map
A235: 231 | B235: CISO Cybersecurity Private Limited | C235: corporate_office | D235: Office Boy, Housekeeping, Security, Data Entry | E235: 0124 423 8697 | F235: Landline (reception) | G235: 5 | H235: A-29/6, Sector 28, Maruti Housing Colony, Gurugram, Haryana 122002, India | M235: Map
A236: 232 | B236: KP Actuaries and Consultants LLP (KPAC) | C236: consultant | D236: Office Boy, Housekeeping, Security, Data Entry | E236: 011 4701 2603 | F236: Landline (reception) | G236: 5 | H236: 2nd Floor, JMD Empire Square, Metro Station, Unit No. 202, Mehrauli-Gurgaon Rd, near Sikanderpur, Sector 28, DLF Phase 1, Gurugram, Haryana 122002, India | M236: Map
A237: 233 | B237: Precious Pearl Play School | C237: child_care_agency | D237: Peon, Housekeeping, Security, Attendant | E237: 0124 257 4300 | F237: Landline (reception) | G237: 5 | H237: 2002, DLF Phase IV,, Hamilton Ct Rd, Sector 28, DLF City IV, Gurugram, Haryana 122009, India | M237: Map
A238: 234 | B238: Transform Plus Pvt. Ltd. | C238: corporate_office | D238: Office Boy, Housekeeping, Security, Data Entry | E238: 0124 406 8726 | F238: Landline (reception) | G238: 5 | H238: C-1867, Sushant Lok 1, Phase 1, Sector 28, Sushant Lok Phase I, Gurugram, Haryana 122009, India | M238: Map
A239: 235 | B239: DPDO Gurgaon Gurgaon Haryana Plot | C239: point_of_interest | D239: Helper, Housekeeping, Security, Office Boy | E239: 0124 238 5579 | F239: Landline (reception) | G239: 4.8 | H239: F3FR+JGR, Street Number 53, Sector 28, DLF Phase 1, Gurugram, Haryana 122002, India | M239: Map
A240: 236 | B240: Amaha Mental Health Centre, DLF Phase 1, Gurugram | C240: medical_clinic | D240: Ward Boy, Housekeeping, Attendant, Security | E240: 020 7117 1501 | F240: Landline (reception) | G240: 4.7 | H240: B 18/9, Golf Crse Rd, Sector 28, DLF Phase 1, Sector 26A, Gurugram, Haryana 122002, India | M240: Map
A241: 237 | B241: Brown Forman Worldwide LLC - Branch Office India | C241: corporate_office | D241: Office Boy, Housekeeping, Security, Data Entry | E241: 0124 667 2222 | F241: Landline (reception) | G241: 4.7 | H241: 7th Floor, Time Tower, 701-702, MG Road, Sector - 28, Sushant Lok Phase I, Gurugram, Haryana 122009, India | M241: Map
A242: 238 | B242: Greenworld Contrakts Pvt. Ltd. | C242: business | D242: Helper, Housekeeping, Security, Office Boy | E242: 0124 421 0271 | F242: Landline (reception) | G242: 4.7 | H242: 31/9, Sector 28, DLF Phase 1, Gurugram, Haryana 122002, India | M242: Map
A243: 239 | B243: UAS International A Unit of United Accrual Services Pvt. Ltd. | C243: finance | D243: Office Boy, Housekeeping, Security, Data Entry | E243: 0124 428 5911 | F243: Landline (reception) | G243: 4.7 | H243: unit number, Vipul agora mall, 121, Mehrauli-Gurgaon Rd, Sector 28, Gurugram, Haryana 122002, India | M243: Map
A244: 240 | B244: VIJAY SALES - MEHRAULI | C244: electronics_store | D244: Store Helper, Housekeeping, Security, Sales Staff | E244: 0124 460 6930 | F244: Landline (reception) | G244: 4.7 | H244: Lower Ground Floor, The Plaza Mall, Mehrauli-Gurgaon Rd, near Fabindia, Sector 28, Sushant Lok Phase I, Gurugram, Haryana 122002, India | M244: Map
A245: 241 | B245: Work, Prescient Healthcare Group - India | C245: consultant | D245: Ward Boy, Housekeeping, Attendant, Security | E245: 011 7127 9170 | F245: Landline (reception) | G245: 4.6 | H245: 105-106 MG Road, Time Tower, Sector 28, Sushant Lok Phase I, Gurugram, Haryana 122009, India | M245: Map
A246: 242 | B246: EAZY ERP Technologies Private Limited | C246: business | D246: Helper, Housekeeping, Security, Office Boy | E246: 0124 479 4479 | F246: Landline (reception) | G246: 4.5 | H246: 2nd Floor, Vipul Agora Building, 201, Mehrauli-Gurgaon Rd, Sector 28, Gurugram, Haryana 122002, India | M246: Map
... A261: 257 | B261: Boosting Station | C261: government_office | D261: Office Boy, Housekeeping, Security, Data Entry | E261: 1800 180 1817 | F261: Landline (helpline) | G261: 1 | H261: Ward No 33, Near Power House, Chakkarpur, Sector 28, Sector 28, Chakkarpur, Gurugram, Haryana 122002, India | M261: Map
A262: 258 | B262: Gridlogic | C262: business | D262: Helper, Housekeeping, Security, Office Boy | E262: 0124 669 5847 | F262: Landline (reception) | H262: 3rd Floor, JMD Empire Square, Mehrauli-Gurgaon Rd, near Sikanderpur Ghosi, Sector 28, Gurugram, Haryana 122002, India | M262: Map
A263: 259 | B263: My Sky Hopper (AVV SkyShuttle Pvt. Ltd.) | C263: corporate_office | D263: Office Boy, Housekeeping, Security, Data Entry | E263: 0124 421 5251 | F263: Landline (reception) | H263: LCG-304A, Laburnum, B Block, Sushant Lok-1, Sector 28, Sector 28, DLF Phase IV, Gurugram, Haryana 122009, India | M263: Map
A264: 260 | B264: Samudrika Beverages Private Limited | C264: corporate_office | D264: Office Boy, Housekeeping, Security, Data Entry | E264: 0124 406 0598 | F264: Landline (reception) | H264: E-5/5, DLF Phase 1, Near Shopping Mall, Sector 28, DLF Phase 1, Gurugram, Haryana 122002, India | M264: Map

Sheet Sector 26A
A1: SWITCH · SECTOR 26A · CALL SHEET
A2: Shifts 1–12 hrs, billed per hour · pay after worker reports · instant replacement | 166 leads · 140 mobiles (owner/mgr) at top
A3: LEADS | B3: =COUNTA(B5:B170) | C3: CONTACTED | D3: =COUNTA(I5:I170) | E3: INTERESTED | F3: =COUNTIF(I5:I170,"Yes") | G3: ORDERS | H3: =COUNTIF(K5:K170,"Yes") | I3: HOURS BOOKED | J3: =SUM(J5:J170)
A4: S.No | B4: Business Name | C4: Category | D4: Suggested Roles (per shift) | E4: Phone | F4: Number Type | G4: Rating | H4: Address | I4: Interested? | J4: Hours (1-12) | K4: Order Confirmed? | L4: Remarks | M4: Map
A5: 1 | B5: Ace Consulting | C5: service | D5: Helper, Housekeeping, Security, Office Boy | E5: 091150 90909 | F5: Mobile (owner/mgr) | G5: 5 | H5: 3rd Floor, 49, Arjun Marg, Block E, DLF Phase 1, Sector 26A, Gurugram, Haryana 122002, India | M5: Map
A6: 2 | B6: Acharya Monica - Best Vastu Consultant in Gurgaon | C6: consultant | D6: Office Boy, Housekeeping, Security, Data Entry | E6: 098182 45656 | F6: Mobile (owner/mgr) | G6: 5 | H6: B 13/7, DLF Phase 1, Sector 26A, Gurugram, Haryana 122002, India | M6: Map
A7: 3 | B7: ASTP Personal Training Fitness Studio | C7: fitness_center | D7: Trainer, Housekeeping, Front Desk | E7: 099992 69996 | F7: Mobile (owner/mgr) | G7: 5 | H7: B11, 1, Ashoka Cresent Marg, DLF Phase 1, Sector 26A, Gurugram, Haryana 122002, India | M7: Map
A8: 4 | B8: Be Home Realty | C8: consultant | D8: Office Boy, Housekeeping, Security, Data Entry | E8: 078381 07333 | F8: Mobile (owner/mgr) | G8: 5 | H8: B 14/30, Paschim Marg, DLF Phase 1, Sector 26A, Gurugram, Haryana 122022, Block C, Sector 26A, Gurugram, Haryana 122002, India | M8: Map
A9: 5 | B9: Casamed | C9: medical_clinic | D9: Ward Boy, Housekeeping, Attendant, Security | E9: 082358 58626 | F9: Mobile (owner/mgr) | G9: 5 | H9: 42 Ashoka Crescent Marg, Golf Crse Rd, DLF Phase 1, Sector 26A, New Delhi, Gurugram, Haryana 122002, India | M9: Map
A10: 6 | B10: Chrono Seconds | C10: store | D10: Store Helper, Housekeeping, Security, Sales Staff | E10: 098156 42918 | F10: Mobile (owner/mgr) | G10: 5 | H10: 80, Arjun Marg, Block E, DLF Phase 1, Sector 26A, Gurugram, Haryana 122002, India | M10: Map
A11: 7 | B11: Click Moments Photography In Gurgaon - Photographers in Gurugram | best Wedding Photographers in Gurugram & Ncr | C11: service | D11: Helper, Housekeeping, Security, Office Boy | E11: 078384 85239 | F11: Mobile (owner/mgr) | G11: 5 | H11: B4/8, Block B, Sector 26A, Gurugram, Haryana 122002, India | M11: Map
A12: 8 | B12: CSC CENTRE | C12: service | D12: Helper, Housekeeping, Security, Office Boy | E12: 085889 71717 | F12: Mobile (owner/mgr) | G12: 5 | H12: Badsha, Block D, Sector 26A, Gurugram, Haryana 122002, India | M12: Map
A13: 9 | B13: Deluxe Cargo Packers And Movers | C13: transportation_service | D13: Loader, Packer, Picker, Warehouse Helper, Delivery | E13: 095885 70502 | F13: Mobile (owner/mgr) | G13: 5 | H13: E6/40, Block E, DLF Phase 1, Sector 26A, Gurugram, Haryana 122002, India | M13: Map
A14: 10 | B14: Dr Tushant Physiotherapy & Sports Injury Clinic | DLF Phase 1 Gurgaon | C14: physiotherapist | D14: Ward Boy, Housekeeping, Attendant, Security | E14: 085953 77104 | F14: Mobile (owner/mgr) | G14: 5 | H14: Landmark Cafe By Soul, The Basement of B11, 1, Ashoka Cresent Marg, Block B, Sector 26A, Gurugram, Haryana 122003, India | M14: Map
A15: 11 | B15: Dr. Mansi Bhayana - Homoeopathic physician | C15: health | D15: Ward Boy, Housekeeping, Attendant, Security | E15: 097111 91728 | F15: Mobile (owner/mgr) | G15: 5 | H15: 14, Paschim Marg, DLF Phase 1, Sector 26A, Gurugram, Haryana 122002, India | M15: Map
A16: 12 | B16: Dr.simran Certified Manual Physiotherapist in Gurugram | C16: physiotherapist | D16: Ward Boy, Housekeeping, Attendant, Security | E16: 089507 12281 | F16: Mobile (owner/mgr) | G16: 5 | H16: Landmark Cafe By Soul, The Basement of B11, Café by soul basement, 1, Ashoka Cresent Marg, Block B, Sector 26A, Gurugram, Haryana 122002, India | M16: Map
... A125: 121 | B125: VenueMonk | C125: corporate_office | D125: Office Boy, Housekeeping, Security, Data Entry | E125: 082792 20676 | F125: Mobile (owner/mgr) | G125: 2 | H125: PurplePatch Online Services Pvt. Ltd. 412, DLF Qutub Plaza, DLF Phase 1, Sector 26A, Gurugram, Haryana 122002, India | M125: Map
A126: 122 | B126: Ablers Group | C126: corporate_office | D126: Office Boy, Housekeeping, Security, Data Entry | E126: 099725 98267 | F126: Mobile (owner/mgr) | H126: D-805, Paras Towers, Sector – 30, Block B, Sector 26A, Faridabad, Gurugram, Haryana 122002, India | M126: Map
A127: 123 | B127: Adlytic Media Pvt Ltd | C127: service | D127: Helper, Housekeeping, Security, Office Boy | E127: 093101 16465 | F127: Mobile (owner/mgr) | H127: Adlytic, Media Pvt Ltd Truworx, Golf Course Rd, DLF Phase 1, Sector 26A, Gurugram, Haryana 122002, India | M127: Map
A128: 124 | B128: Ciel D' Art | C128: manufacturer | D128: Machine Operator, Helper, Loader, Packer | E128: 098101 84613 | F128: Mobile (owner/mgr) | H128: F-2/33, Block F, DLF Phase 1, Sector 26A, Gurugram, Haryana 122002, India | M128: Map
A129: 125 | B129: Complete Bathing Solution | C129: market | D129: Store Helper, Housekeeping, Security, Sales Staff | E129: 092112 30134 | F129: Mobile (owner/mgr) | H129: A27/62, DLF Phase 1, Sector 26A, Gurugram, Haryana 122002, India | M129: Map
A130: 126 | B130: Diwani ji all India ambulance service | C130: health | D130: Ward Boy, Housekeeping, Attendant, Security | E130: 093505 92527 | F130: Mobile (owner/mgr) | H130: Block C, Sector 26A, Gurugram, Haryana 122002, India | M130: Map
A131: 127 | B131: Dr Vani Wasir | C131: doctor | D131: Ward Boy, Housekeeping, Attendant, Security | E131: 098112 52189 | F131: Mobile (owner/mgr) | H131: C-10/8, DLF Phase 1, Sector 26A, Gurugram, Haryana 122002, India | M131: Map
A132: 128 | B132: Kohler | C132: building_materials_store | D132: Store Helper, Housekeeping, Security, Sales Staff | E132: 098108 22617 | F132: Mobile (owner/mgr) | H132: 51, Ashoka Cresent Marg, DLF Phase 1, Sector 26A, Gurugram, Haryana 122002, India | M132: Map
A133: 129 | B133: Lasso Design Studio | C133: business | D133: Helper, Housekeeping, Security, Office Boy | E133: 088604 13555 | F133: Mobile (owner/mgr) | H133: 21, Basement, Block A, DLF Phase 1, Sector 26A, Gurugram, Haryana 122002, India | M133: Map
A134: 130 | B134: Md Rafique Auto Mobile Service | C134: chauffeur_service | D134: Helper, Housekeeping, Security, Office Boy | E134: 098702 05277 | F134: Mobile (owner/mgr) | H134: U10/1, DLF, Block D, Sector 26A, Gurugram, Haryana 122002, India | M134: Map
A135: 131 | B135: Mediworld publications Gurgaon | C135: consultant | D135: Office Boy, Housekeeping, Security, Data Entry | E135: 098100 26796 | F135: Mobile (owner/mgr) | H135: A- 3/18, A-13 St, Block A, Sector 26A, Gurugram, Haryana 122002, India | M135: Map
A136: 132 | B136: Moving Box Packers And Movers Gurgaon | C136: moving_company | D136: Loader, Packer, Picker, Warehouse Helper, Delivery | E136: 087969 95430 | F136: Mobile (owner/mgr) | H136: Shop No 17, Arjun Marg, Block E, DLF Phase 1, Sector 26A, Gurugram, Haryana 122002, India | M136: Map
A137: 133 | B137: NKPRealtors | C137: service | D137: Helper, Housekeeping, Security, Office Boy | E137: 078360 08900 | F137: Mobile (owner/mgr) | H137: Paschim Marg, DLF Phase 1, Sector 26A, Gurugram, Haryana 122002, India | M137: Map
... A144: 140 | B144: Wadhwa residency | C144: hotel | D144: Housekeeping, Room Boy, Kitchen Helper, Front Desk | E144: 099101 79479 | F144: Mobile (owner/mgr) | H144: E 2/12, Bodhi Marg, Block F, DLF Phase 1, Sector 26A, Gurugram, Haryana 122002, India | M144: Map
A145: 141 | B145: Bidada Foods Pvt Ltd | C145: corporate_office | D145: Kitchen Helper, Cook, Dishwasher, Waiter | E145: 0124 404 8477 | F145: Landline (reception) | G145: 5 | H145: 77, Arjun Marg, Block E, DLF Phase 1, Sector 26A, Gurugram, Haryana 122002, India | M145: Map
A146: 142 | B146: Laxmi Estate Agency | C146: real_estate_agency | D146: Office Boy, Housekeeping, Security, Data Entry | E146: 0124 405 9070 | F146: Landline (reception) | G146: 5 | H146: 29, 2, Shahtoot Marg, Block D, Sector 26A, Gurugram, Haryana 122002, India | M146: Map
A147: 143 | B147: Pratap Technocrats private limited | C147: corporate_office | D147: Office Boy, Housekeeping, Security, Data Entry | E147: 0141 403 2156 | F147: Landline (reception) | G147: 5 | H147: B20, 1, Paschim Marg, Block B, Sector 26A, Gurugram, Haryana 122002, India | M147: Map
A148: 144 | B148: Anand Preschool | C148: preschool | D148: Peon, Housekeeping, Security, Attendant | E148: 0124 438 1799 | F148: Landline (reception) | G148: 4.9 | H148: E5, Arjun Marg, Block E, DLF Phase 1, Sector 26A, Gurugram, Haryana 122002, India | M148: Map
A149: 145 | B149: Maheshwari Residence | C149: condominium_complex | D149: Helper, Housekeeping, Security, Office Boy | E149: 0124 405 2318 | F149: Landline (reception) | G149: 4.9 | H149: A - 13/11, Block A, Sector 26A, Gurugram, Haryana 122002, India | M149: Map
A150: 146 | B150: QEC Constructions Pvt. Ltd. | C150: general_contractor | D150: Helper, Housekeeping, Security, Office Boy | E150: 0124 238 8301 | F150: Landline (reception) | G150: 4.9 | H150: House No.49, Arjun Marg, DLF Phase 1, Sector 26A, Gurugram, Haryana 122002, India | M150: Map
A151: 147 | B151: CareMS India (Gurgaon Haryana) | C151: service | D151: Helper, Housekeeping, Security, Office Boy | E151: 011 4100 1188 | F151: Landline (reception) | G151: 4.8 | H151: A-55, 8, DLF Phase 1, Sector 26A, Gurugram, Haryana 122002, India | M151: Map
A152: 148 | B152: GreatCircle Infotech LLP | C152: corporate_office | D152: Office Boy, Housekeeping, Security, Data Entry | E152: 0124 410 8955 | F152: Landline (reception) | G152: 4.7 | H152: 33, Arjun Marg, Block E, DLF Phase 1, Sector 26A, Gurugram, Haryana 122002, India | M152: Map
A153: 149 | B153: INNERQUEST | C153: health | D153: Ward Boy, Housekeeping, Attendant, Security | E153: 0124 430 1900 | F153: Landline (reception) | G153: 4.7 | H153: B 2/ 18, DLF Phase 1, Sector 26A, Gurugram, Haryana 122002, India | M153: Map
A154: 150 | B154: Axis Bank Branch | C154: bank | D154: Office Boy, Housekeeping, Security, Data Entry | E154: 1860 500 5555 | F154: Landline (helpline) | G154: 4.4 | H154: Ground Floor, Basement & Mezzanine, Shop No 3, Shopping Mall, Arjun Marg, Block E, DLF Phase 1, Sector 26A, Gurugram, Haryana 122002, India | M154: Map
A155: 151 | B155: Boutique Hotel By One Tee Stays ,Building No 18, Arjun Marg | C155: hotel | D155: Housekeeping, Room Boy, Kitchen Helper, Front Desk | E155: 011 4314 6978 | F155: Landline (reception) | G155: 4.4 | H155: Building no - 18, Arjun Marg, DLF Phase 1, Sector 26A, Gurugram, Haryana 122002, India | M155: Map
A156: 152 | B156: Felix Advisory Private Limited | C156: corporate_office | D156: Office Boy, Housekeeping, Security, Data Entry | E156: 0124 425 2720 | F156: Landline (reception) | G156: 4.4 | H156: 45, Arjun Marg, Block E, Block D, Sector 26A, Gurugram, Haryana 122002, India | M156: Map
... A165: 161 | B165: Bank Of Baroda | C165: bank | D165: Kitchen Helper, Cook, Dishwasher, Waiter | E165: 1800 5700 | F165: Landline (helpline) | G165: 3.2 | H165: Shop No 19-20, Shopping Mall, Arjun Marg, DLF Phase 1, Sector 26A, Gurugram, Haryana 122002, India | M165: Map
A166: 162 | B166: Homeopathic Physician | C166: health | D166: Ward Boy, Housekeeping, Attendant, Security | E166: 0124 405 3983 | F166: Landline (reception) | H166: E-8/17, Dlf, Arjun Marg, Phase-i, Block E, Dlf, Sector 26A, Gurugram, Haryana 122001, India | M166: Map
A167: 163 | B167: Japan International Academy | C167: school | D167: Peon, Housekeeping, Security, Attendant | E167: 0124 401 6000 | F167: Landline (reception) | H167: 11, Club Marg, DLF Phase 1, Sector 26A, Gurugram, Haryana 122002, India | M167: Map
A168: 164 | B168: Propenza Technologies | C168: corporate_office | D168: Office Boy, Housekeeping, Security, Data Entry | E168: 0124 410 4805 | F168: Landline (reception) | H168: D4, A/8, Shahtoot Marg, DLF Phase 1, Sector 26A, Gurugram, Haryana 122002, India | M168: Map
A169: 165 | B169: Sethi Varun Mbbs | C169: doctor | D169: Ward Boy, Housekeeping, Attendant, Security | E169: 0124 235 2022 | F169: Landline (reception) | H169: A-27/19, Dlf City I, Sadar Bazar, Block B, Sector 26A, Gurugram, Haryana 122002, India | M169: Map
A170: 166 | B170: Shiv Nadar School, Gurgaon | C170: school | D170: Peon, Housekeeping, Security, Attendant | E170: 0124 454 9200 | F170: Landline (reception) | H170: Pahari Road, Block E, DLF Phase 1, Sector 26A, Gurugram, Haryana 122002, India | M170: Map

Sheet How to use
B1: SWITCH — GOLF COURSE ROAD CALLING SHEET · HOW TO USE
B3: THE OFFER (say this, every time)
B4: • Shifts of 1–12 hours, billed by the hour. NO monthly, NO weekly.
B5: • Pay only AFTER the worker reports — no advance.
B6: • Instant replacement if the worker doesn't show or isn't a fit.
B7: • Verified, local staff delivered in 24 hours.
B9: ABOUT THE NUMBERS
B10: • 'Number Type' = Mobile (owner/mgr) → a personal mobile; usually the owner or manager. Call these FIRST.
B11: • 'Number Type' = Landline (reception) → front desk; ask for the owner/manager by name.
B12: • Mobiles are already sorted to the top of every sector tab.
B14: HOW TO WORK THE SHEET
B15: 1. One tab per sector: 56, 55, 53, 52A, 42, 27, 28, 26A. Work each top-down.
... B23: Only businesses with a phone number are included. Deduped by number across all sectors.
