Workbook

Sheet Performance
B2: SWITCH · GOLF COURSE ROAD · MOBILE CALLING PERFORMANCE
B4: Live totals across every sector tab — updates as you fill the sheets
B6: TOTAL MOBILE LEADS | D6: CONTACTED | F6: ORDERS
B7: =COUNTA('Sector 26'!B5:B151)+COUNTA('Sector 27'!B5:B46)+COUNTA('Sector 28'!B5:B145)+COUNTA('Sector 42'!B5:B66)+COUNTA('Sector 43'!B5:B145)+COUNTA('Sector 44'!B5:B27)+COUNTA('Sector 45'!B5:B18)+COUNTA('Sector 50'!B5:B24)+COUNTA('Sector 52'!B5:B164)+COUNTA('Sector 53'!B5:B77)+COUNTA('Sector 54'!B5:B45)+COUNTA('Sector 55'!B5:B40)+COUNTA('Sector 56'!B5:B109)+COUNTA('Sector 57'!B5:B88)+COUNTA('Sector 58'!B5:B46)+COUNTA('Sector 59'!B5:B22)+COUNTA('Sector 60'!B5:B15)+COUNTA('Sector 61'!B5:B38)+COUNTA('Sector 62'!B5:B92)+COUNTA('Sector 63'!B5:B21)+COUNTA('Sector 64'!B5:B56)+COUNTA('Sector 65'!B5:B128)+COUNTA('Sector 66'!B5:B94)+COUNTA('Sector 67'!B5:B66)+COUNTA('GCR — Other'!B5:B22) | D7: =COUNTA('Sector 26'!I5:I151)+COUNTA('Sector 27'!I5:I46)+COUNTA('Sector 28'!I5:I145)+COUNTA('Sector 42'!I5:I66)+COUNTA('Sector 43'!I5:I145)+COUNTA('Sector 44'!I5:I27)+COUNTA('Sector 45'!I5:I18)+COUNTA('Sector 50'!I5:I24)+COUNTA('Sector 52'!I5:I164)+COUNTA('Sector 53'!I5:I77)+COUNTA('Sector 54'!I5:I45)+COUNTA('Sector 55'!I5:I40)+COUNTA('Sector 56'!I5:I109)+COUNTA('Sector 57'!I5:I88)+COUNTA('Sector 58'!I5:I46)+COUNTA('Sector 59'!I5:I22)+COUNTA('Sector 60'!I5:I15)+COUNTA('Sector 61'!I5:I38)+COUNTA('Sector 62'!I5:I92)+COUNTA('Sector 63'!I5:I21)+COUNTA('Sector 64'!I5:I56)+COUNTA('Sector 65'!I5:I128)+COUNTA('Sector 66'!I5:I94)+COUNTA('Sector 67'!I5:I66)+COUNTA('GCR — Other'!I5:I22) | F7: =COUNTIF('Sector 26'!K5:K151,"Yes")+COUNTIF('Sector 27'!K5:K46,"Yes")+COUNTIF('Sector 28'!K5:K145,"Yes")+COUNTIF('Sector 42'!K5:K66,"Yes")+COUNTIF('Sector 43'!K5:K145,"Yes")+COUNTIF('Sector 44'!K5:K27,"Yes")+COUNTIF('Sector 45'!K5:K18,"Yes")+COUNTIF('Sector 50'!K5:K24,"Yes")+COUNTIF('Sector 52'!K5:K164,"Yes")+COUNTIF('Sector 53'!K5:K77,"Yes")+COUNTIF('Sector 54'!K5:K45,"Yes")+COUNTIF('Sector 55'!K5:K40,"Yes")+COUNTIF('Sector 56'!K5:K109,"Yes")+COUNTIF('Sector 57'!K5:K88,"Yes")+COUNTIF('Sector 58'!K5:K46,"Yes")+COUNTIF('Sector 59'!K5:K22,"Yes")+COUNTIF('Sector 60'!K5:K15,"Yes")+COUNTIF('Sector 61'!K5:K38,"Yes")+COUNTIF('Sector 62'!K5:K92,"Yes")+COUNTIF('Sector 63'!K5:K21,"Yes")+COUNTIF('Sector 64'!K5:K56,"Yes")+COUNTIF('Sector 65'!K5:K128,"Yes")+COUNTIF('Sector 66'!K5:K94,"Yes")+COUNTIF('Sector 67'!K5:K66,"Yes")+COUNTIF('GCR — Other'!K5:K22,"Yes")
B9: INTERESTED | D9: CONVERSION | F9: HOURS BOOKED
B10: =COUNTIF('Sector 26'!I5:I151,"Yes")+COUNTIF('Sector 27'!I5:I46,"Yes")+COUNTIF('Sector 28'!I5:I145,"Yes")+COUNTIF('Sector 42'!I5:I66,"Yes")+COUNTIF('Sector 43'!I5:I145,"Yes")+COUNTIF('Sector 44'!I5:I27,"Yes")+COUNTIF('Sector 45'!I5:I18,"Yes")+COUNTIF('Sector 50'!I5:I24,"Yes")+COUNTIF('Sector 52'!I5:I164,"Yes")+COUNTIF('Sector 53'!I5:I77,"Yes")+COUNTIF('Sector 54'!I5:I45,"Yes")+COUNTIF('Sector 55'!I5:I40,"Yes")+COUNTIF('Sector 56'!I5:I109,"Yes")+COUNTIF('Sector 57'!I5:I88,"Yes")+COUNTIF('Sector 58'!I5:I46,"Yes")+COUNTIF('Sector 59'!I5:I22,"Yes")+COUNTIF('Sector 60'!I5:I15,"Yes")+COUNTIF('Sector 61'!I5:I38,"Yes")+COUNTIF('Sector 62'!I5:I92,"Yes")+COUNTIF('Sector 63'!I5:I21,"Yes")+COUNTIF('Sector 64'!I5:I56,"Yes")+COUNTIF('Sector 65'!I5:I128,"Yes")+COUNTIF('Sector 66'!I5:I94,"Yes")+COUNTIF('Sector 67'!I5:I66,"Yes")+COUNTIF('GCR — Other'!I5:I22,"Yes") | D10: =IFERROR((COUNTIF('Sector 26'!K5:K151,"Yes")+COUNTIF('Sector 27'!K5:K46,"Yes")+COUNTIF('Sector 28'!K5:K145,"Yes")+COUNTIF('Sector 42'!K5:K66,"Yes")+COUNTIF('Sector 43'!K5:K145,"Yes")+COUNTIF('Sector 44'!K5:K27,"Yes")+COUNTIF('Sector 45'!K5:K18,"Yes")+COUNTIF('Sector 50'!K5:K24,"Yes")+COUNTIF('Sector 52'!K5:K164,"Yes")+COUNTIF('Sector 53'!K5:K77,"Yes")+COUNTIF('Sector 54'!K5:K45,"Yes")+COUNTIF('Sector 55'!K5:K40,"Yes")+COUNTIF('Sector 56'!K5:K109,"Yes")+COUNTIF('Sector 57'!K5:K88,"Yes")+COUNTIF('Sector 58'!K5:K46,"Yes")+COUNTIF('Sector 59'!K5:K22,"Yes")+COUNTIF('Sector 60'!K5:K15,"Yes")+COUNTIF('Sector 61'!K5:K38,"Yes")+COUNTIF('Sector 62'!K5:K92,"Yes")+COUNTIF('Sector 63'!K5:K21,"Yes")+COUNTIF('Sector 64'!K5:K56,"Yes")+COUNTIF('Sector 65'!K5:K128,"Yes")+COUNTIF('Sector 66'!K5:K94,"Yes")+COUNTIF('Sector 67'!K5:K66,"Yes")+COUNTIF('GCR — Other'!K5:K22,"Yes"))/(COUNTA('Sector 26'!I5:I151)+COUNTA('Sector 27'!I5:I46)+COUNTA('Sector 28'!I5:I145)+COUNTA('Sector 42'!I5:I66)+COUNTA('Sector 43'!I5:I145)+COUNTA('Sector 44'!I5:I27)+COUNTA('Sector 45'!I5:I18)+COUNTA('Sector 50'!I5:I24)+COUNTA('Sector 52'!I5:I164)+COUNTA('Sector 53'!I5:I77)+COUNTA('Sector 54'!I5:I45)+COUNTA('Sector 55'!I5:I40)+COUNTA('Sector 56'!I5:I109)+COUNTA('Sector 57'!I5:I88)+COUNTA('Sector 58'!I5:I46)+COUNTA('Sector 59'!I5:I22)+COUNTA('Sector 60'!I5:I15)+COUNTA('Sector 61'!I5:I38)+COUNTA('Sector 62'!I5:I92)+COUNTA('Sector 63'!I5:I21)+COUNTA('Sector 64'!I5:I56)+COUNTA('Sector 65'!I5:I128)+COUNTA('Sector 66'!I5:I94)+COUNTA('Sector 67'!I5:I66)+COUNTA('GCR — Other'!I5:I22)),0) | F10: =SUM('Sector 26'!J5:J151)+SUM('Sector 27'!J5:J46)+SUM('Sector 28'!J5:J145)+SUM('Sector 42'!J5:J66)+SUM('Sector 43'!J5:J145)+SUM('Sector 44'!J5:J27)+SUM('Sector 45'!J5:J18)+SUM('Sector 50'!J5:J24)+SUM('Sector 52'!J5:J164)+SUM('Sector 53'!J5:J77)+SUM('Sector 54'!J5:J45)+SUM('Sector 55'!J5:J40)+SUM('Sector 56'!J5:J109)+SUM('Sector 57'!J5:J88)+SUM('Sector 58'!J5:J46)+SUM('Sector 59'!J5:J22)+SUM('Sector 60'!J5:J15)+SUM('Sector 61'!J5:J38)+SUM('Sector 62'!J5:J92)+SUM('Sector 63'!J5:J21)+SUM('Sector 64'!J5:J56)+SUM('Sector 65'!J5:J128)+SUM('Sector 66'!J5:J94)+SUM('Sector 67'!J5:J66)+SUM('GCR — Other'!J5:J22)
B12: Sector | C12: Leads | D12: Contacted | E12: Interested | F12: Orders | G12: Hours
B13: Sector 26 | C13: =COUNTA('Sector 26'!B5:B151) | D13: =COUNTA('Sector 26'!I5:I151) | E13: =COUNTIF('Sector 26'!I5:I151,"Yes") | F13: =COUNTIF('Sector 26'!K5:K151,"Yes") | G13: =SUM('Sector 26'!J5:J151)
B14: Sector 27 | C14: =COUNTA('Sector 27'!B5:B46) | D14: =COUNTA('Sector 27'!I5:I46) | E14: =COUNTIF('Sector 27'!I5:I46,"Yes") | F14: =COUNTIF('Sector 27'!K5:K46,"Yes") | G14: =SUM('Sector 27'!J5:J46)
B15: Sector 28 | C15: =COUNTA('Sector 28'!B5:B145) | D15: =COUNTA('Sector 28'!I5:I145) | E15: =COUNTIF('Sector 28'!I5:I145,"Yes") | F15: =COUNTIF('Sector 28'!K5:K145,"Yes") | G15: =SUM('Sector 28'!J5:J145)
B16: Sector 42 | C16: =COUNTA('Sector 42'!B5:B66) | D16: =COUNTA('Sector 42'!I5:I66) | E16: =COUNTIF('Sector 42'!I5:I66,"Yes") | F16: =COUNTIF('Sector 42'!K5:K66,"Yes") | G16: =SUM('Sector 42'!J5:J66)
B17: Sector 43 | C17: =COUNTA('Sector 43'!B5:B145) | D17: =COUNTA('Sector 43'!I5:I145) | E17: =COUNTIF('Sector 43'!I5:I145,"Yes") | F17: =COUNTIF('Sector 43'!K5:K145,"Yes") | G17: =SUM('Sector 43'!J5:J145)
B18: Sector 44 | C18: =COUNTA('Sector 44'!B5:B27) | D18: =COUNTA('Sector 44'!I5:I27) | E18: =COUNTIF('Sector 44'!I5:I27,"Yes") | F18: =COUNTIF('Sector 44'!K5:K27,"Yes") | G18: =SUM('Sector 44'!J5:J27)
B19: Sector 45 | C19: =COUNTA('Sector 45'!B5:B18) | D19: =COUNTA('Sector 45'!I5:I18) | E19: =COUNTIF('Sector 45'!I5:I18,"Yes") | F19: =COUNTIF('Sector 45'!K5:K18,"Yes") | G19: =SUM('Sector 45'!J5:J18)
B20: Sector 50 | C20: =COUNTA('Sector 50'!B5:B24) | D20: =COUNTA('Sector 50'!I5:I24) | E20: =COUNTIF('Sector 50'!I5:I24,"Yes") | F20: =COUNTIF('Sector 50'!K5:K24,"Yes") | G20: =SUM('Sector 50'!J5:J24)
B21: Sector 52 | C21: =COUNTA('Sector 52'!B5:B164) | D21: =COUNTA('Sector 52'!I5:I164) | E21: =COUNTIF('Sector 52'!I5:I164,"Yes") | F21: =COUNTIF('Sector 52'!K5:K164,"Yes") | G21: =SUM('Sector 52'!J5:J164)
B22: Sector 53 | C22: =COUNTA('Sector 53'!B5:B77) | D22: =COUNTA('Sector 53'!I5:I77) | E22: =COUNTIF('Sector 53'!I5:I77,"Yes") | F22: =COUNTIF('Sector 53'!K5:K77,"Yes") | G22: =SUM('Sector 53'!J5:J77)
B23: Sector 54 | C23: =COUNTA('Sector 54'!B5:B45) | D23: =COUNTA('Sector 54'!I5:I45) | E23: =COUNTIF('Sector 54'!I5:I45,"Yes") | F23: =COUNTIF('Sector 54'!K5:K45,"Yes") | G23: =SUM('Sector 54'!J5:J45)
B24: Sector 55 | C24: =COUNTA('Sector 55'!B5:B40) | D24: =COUNTA('Sector 55'!I5:I40) | E24: =COUNTIF('Sector 55'!I5:I40,"Yes") | F24: =COUNTIF('Sector 55'!K5:K40,"Yes") | G24: =SUM('Sector 55'!J5:J40)
B25: Sector 56 | C25: =COUNTA('Sector 56'!B5:B109) | D25: =COUNTA('Sector 56'!I5:I109) | E25: =COUNTIF('Sector 56'!I5:I109,"Yes") | F25: =COUNTIF('Sector 56'!K5:K109,"Yes") | G25: =SUM('Sector 56'!J5:J109)
B26: Sector 57 | C26: =COUNTA('Sector 57'!B5:B88) | D26: =COUNTA('Sector 57'!I5:I88) | E26: =COUNTIF('Sector 57'!I5:I88,"Yes") | F26: =COUNTIF('Sector 57'!K5:K88,"Yes") | G26: =SUM('Sector 57'!J5:J88)
B27: Sector 58 | C27: =COUNTA('Sector 58'!B5:B46) | D27: =COUNTA('Sector 58'!I5:I46) | E27: =COUNTIF('Sector 58'!I5:I46,"Yes") | F27: =COUNTIF('Sector 58'!K5:K46,"Yes") | G27: =SUM('Sector 58'!J5:J46)
B28: Sector 59 | C28: =COUNTA('Sector 59'!B5:B22) | D28: =COUNTA('Sector 59'!I5:I22) | E28: =COUNTIF('Sector 59'!I5:I22,"Yes") | F28: =COUNTIF('Sector 59'!K5:K22,"Yes") | G28: =SUM('Sector 59'!J5:J22)
B29: Sector 60 | C29: =COUNTA('Sector 60'!B5:B15) | D29: =COUNTA('Sector 60'!I5:I15) | E29: =COUNTIF('Sector 60'!I5:I15,"Yes") | F29: =COUNTIF('Sector 60'!K5:K15,"Yes") | G29: =SUM('Sector 60'!J5:J15)
B30: Sector 61 | C30: =COUNTA('Sector 61'!B5:B38) | D30: =COUNTA('Sector 61'!I5:I38) | E30: =COUNTIF('Sector 61'!I5:I38,"Yes") | F30: =COUNTIF('Sector 61'!K5:K38,"Yes") | G30: =SUM('Sector 61'!J5:J38)
B31: Sector 62 | C31: =COUNTA('Sector 62'!B5:B92) | D31: =COUNTA('Sector 62'!I5:I92) | E31: =COUNTIF('Sector 62'!I5:I92,"Yes") | F31: =COUNTIF('Sector 62'!K5:K92,"Yes") | G31: =SUM('Sector 62'!J5:J92)
B32: Sector 63 | C32: =COUNTA('Sector 63'!B5:B21) | D32: =COUNTA('Sector 63'!I5:I21) | E32: =COUNTIF('Sector 63'!I5:I21,"Yes") | F32: =COUNTIF('Sector 63'!K5:K21,"Yes") | G32: =SUM('Sector 63'!J5:J21)
B33: Sector 64 | C33: =COUNTA('Sector 64'!B5:B56) | D33: =COUNTA('Sector 64'!I5:I56) | E33: =COUNTIF('Sector 64'!I5:I56,"Yes") | F33: =COUNTIF('Sector 64'!K5:K56,"Yes") | G33: =SUM('Sector 64'!J5:J56)
B34: Sector 65 | C34: =COUNTA('Sector 65'!B5:B128) | D34: =COUNTA('Sector 65'!I5:I128) | E34: =COUNTIF('Sector 65'!I5:I128,"Yes") | F34: =COUNTIF('Sector 65'!K5:K128,"Yes") | G34: =SUM('Sector 65'!J5:J128)
B35: Sector 66 | C35: =COUNTA('Sector 66'!B5:B94) | D35: =COUNTA('Sector 66'!I5:I94) | E35: =COUNTIF('Sector 66'!I5:I94,"Yes") | F35: =COUNTIF('Sector 66'!K5:K94,"Yes") | G35: =SUM('Sector 66'!J5:J94)
B36: Sector 67 | C36: =COUNTA('Sector 67'!B5:B66) | D36: =COUNTA('Sector 67'!I5:I66) | E36: =COUNTIF('Sector 67'!I5:I66,"Yes") | F36: =COUNTIF('Sector 67'!K5:K66,"Yes") | G36: =SUM('Sector 67'!J5:J66)
B37: GCR — Other | C37: =COUNTA('GCR — Other'!B5:B22) | D37: =COUNTA('GCR — Other'!I5:I22) | E37: =COUNTIF('GCR — Other'!I5:I22,"Yes") | F37: =COUNTIF('GCR — Other'!K5:K22,"Yes") | G37: =SUM('GCR — Other'!J5:J22)
B38: TOTAL | C38: =COUNTA('Sector 26'!B5:B151)+COUNTA('Sector 27'!B5:B46)+COUNTA('Sector 28'!B5:B145)+COUNTA('Sector 42'!B5:B66)+COUNTA('Sector 43'!B5:B145)+COUNTA('Sector 44'!B5:B27)+COUNTA('Sector 45'!B5:B18)+COUNTA('Sector 50'!B5:B24)+COUNTA('Sector 52'!B5:B164)+COUNTA('Sector 53'!B5:B77)+COUNTA('Sector 54'!B5:B45)+COUNTA('Sector 55'!B5:B40)+COUNTA('Sector 56'!B5:B109)+COUNTA('Sector 57'!B5:B88)+COUNTA('Sector 58'!B5:B46)+COUNTA('Sector 59'!B5:B22)+COUNTA('Sector 60'!B5:B15)+COUNTA('Sector 61'!B5:B38)+COUNTA('Sector 62'!B5:B92)+COUNTA('Sector 63'!B5:B21)+COUNTA('Sector 64'!B5:B56)+COUNTA('Sector 65'!B5:B128)+COUNTA('Sector 66'!B5:B94)+COUNTA('Sector 67'!B5:B66)+COUNTA('GCR — Other'!B5:B22) | D38: =COUNTA('Sector 26'!I5:I151)+COUNTA('Sector 27'!I5:I46)+COUNTA('Sector 28'!I5:I145)+COUNTA('Sector 42'!I5:I66)+COUNTA('Sector 43'!I5:I145)+COUNTA('Sector 44'!I5:I27)+COUNTA('Sector 45'!I5:I18)+COUNTA('Sector 50'!I5:I24)+COUNTA('Sector 52'!I5:I164)+COUNTA('Sector 53'!I5:I77)+COUNTA('Sector 54'!I5:I45)+COUNTA('Sector 55'!I5:I40)+COUNTA('Sector 56'!I5:I109)+COUNTA('Sector 57'!I5:I88)+COUNTA('Sector 58'!I5:I46)+COUNTA('Sector 59'!I5:I22)+COUNTA('Sector 60'!I5:I15)+COUNTA('Sector 61'!I5:I38)+COUNTA('Sector 62'!I5:I92)+COUNTA('Sector 63'!I5:I21)+COUNTA('Sector 64'!I5:I56)+COUNTA('Sector 65'!I5:I128)+COUNTA('Sector 66'!I5:I94)+COUNTA('Sector 67'!I5:I66)+COUNTA('GCR — Other'!I5:I22) | E38: =COUNTIF('Sector 26'!I5:I151,"Yes")+COUNTIF('Sector 27'!I5:I46,"Yes")+COUNTIF('Sector 28'!I5:I145,"Yes")+COUNTIF('Sector 42'!I5:I66,"Yes")+COUNTIF('Sector 43'!I5:I145,"Yes")+COUNTIF('Sector 44'!I5:I27,"Yes")+COUNTIF('Sector 45'!I5:I18,"Yes")+COUNTIF('Sector 50'!I5:I24,"Yes")+COUNTIF('Sector 52'!I5:I164,"Yes")+COUNTIF('Sector 53'!I5:I77,"Yes")+COUNTIF('Sector 54'!I5:I45,"Yes")+COUNTIF('Sector 55'!I5:I40,"Yes")+COUNTIF('Sector 56'!I5:I109,"Yes")+COUNTIF('Sector 57'!I5:I88,"Yes")+COUNTIF('Sector 58'!I5:I46,"Yes")+COUNTIF('Sector 59'!I5:I22,"Yes")+COUNTIF('Sector 60'!I5:I15,"Yes")+COUNTIF('Sector 61'!I5:I38,"Yes")+COUNTIF('Sector 62'!I5:I92,"Yes")+COUNTIF('Sector 63'!I5:I21,"Yes")+COUNTIF('Sector 64'!I5:I56,"Yes")+COUNTIF('Sector 65'!I5:I128,"Yes")+COUNTIF('Sector 66'!I5:I94,"Yes")+COUNTIF('Sector 67'!I5:I66,"Yes")+COUNTIF('GCR — Other'!I5:I22,"Yes") | F38: =COUNTIF('Sector 26'!K5:K151,"Yes")+COUNTIF('Sector 27'!K5:K46,"Yes")+COUNTIF('Sector 28'!K5:K145,"Yes")+COUNTIF('Sector 42'!K5:K66,"Yes")+COUNTIF('Sector 43'!K5:K145,"Yes")+COUNTIF('Sector 44'!K5:K27,"Yes")+COUNTIF('Sector 45'!K5:K18,"Yes")+COUNTIF('Sector 50'!K5:K24,"Yes")+COUNTIF('Sector 52'!K5:K164,"Yes")+COUNTIF('Sector 53'!K5:K77,"Yes")+COUNTIF('Sector 54'!K5:K45,"Yes")+COUNTIF('Sector 55'!K5:K40,"Yes")+COUNTIF('Sector 56'!K5:K109,"Yes")+COUNTIF('Sector 57'!K5:K88,"Yes")+COUNTIF('Sector 58'!K5:K46,"Yes")+COUNTIF('Sector 59'!K5:K22,"Yes")+COUNTIF('Sector 60'!K5:K15,"Yes")+COUNTIF('Sector 61'!K5:K38,"Yes")+COUNTIF('Sector 62'!K5:K92,"Yes")+COUNTIF('Sector 63'!K5:K21,"Yes")+COUNTIF('Sector 64'!K5:K56,"Yes")+COUNTIF('Sector 65'!K5:K128,"Yes")+COUNTIF('Sector 66'!K5:K94,"Yes")+COUNTIF('Sector 67'!K5:K66,"Yes")+COUNTIF('GCR — Other'!K5:K22,"Yes") | G38: =SUM('Sector 26'!J5:J151)+SUM('Sector 27'!J5:J46)+SUM('Sector 28'!J5:J145)+SUM('Sector 42'!J5:J66)+SUM('Sector 43'!J5:J145)+SUM('Sector 44'!J5:J27)+SUM('Sector 45'!J5:J18)+SUM('Sector 50'!J5:J24)+SUM('Sector 52'!J5:J164)+SUM('Sector 53'!J5:J77)+SUM('Sector 54'!J5:J45)+SUM('Sector 55'!J5:J40)+SUM('Sector 56'!J5:J109)+SUM('Sector 57'!J5:J88)+SUM('Sector 58'!J5:J46)+SUM('Sector 59'!J5:J22)+SUM('Sector 60'!J5:J15)+SUM('Sector 61'!J5:J38)+SUM('Sector 62'!J5:J92)+SUM('Sector 63'!J5:J21)+SUM('Sector 64'!J5:J56)+SUM('Sector 65'!J5:J128)+SUM('Sector 66'!J5:J94)+SUM('Sector 67'!J5:J66)+SUM('GCR — Other'!J5:J22)
B40: ↳ Fill Interested? / Hours / Order Confirmed? on each sector tab — these totals move automatically.

Sheet Cloud Kitchen Ops
A1: SWITCH · CLOUD KITCHEN OPERATORS · GO DIRECT (BULK STAFFING)
A2: Cloud kitchens barely list on Google — chase the OPERATORS instead. One facility runs 8–10 brands, so one contact = staff for many kitchens. Find their Gurgaon commissary (Sohna Rd / Udyog Vihar) and ask for the ops / kitchen manager.
A3: S.No | B3: Operator / Business | C3: Brands / what they run | D3: Suggested Roles (per shift) | E3: Where in Gurgaon | F3: Manager Mobile | G3: Interested? | H3: Hours (1-12) | I3: Order Confirmed? | J3: Remarks
A4: 1 | B4: Rebel Foods | C4: Faasos, Behrouz Biryani, Oven Story, Mojo Pizza, LunchBox, Sweet Truth | D4: Kitchen Helper, Cook, Packer, Delivery Rider, Dishwasher | E4: Sohna Rd / Udyog Vihar hubs | J4: 🔍 Research Gurgaon facility → ask for ops/kitchen manager
A5: 2 | B5: Kitchens@ (Swiggy) | C5: Swiggy's own multi-brand cloud-kitchen network | D5: Kitchen Helper, Cook, Packer, Dishwasher | E5: Multiple Gurgaon hubs | J5: 🔍 Research Gurgaon facility → ask for ops/kitchen manager
A6: 3 | B6: EatClub / Box8 | C6: Box8, MOJO Pizza, Itminaan Biryani, LEATS | D6: Kitchen Helper, Cook, Packer, Rider | E6: Sohna Rd / Sector 37 | J6: 🔍 Research Gurgaon facility → ask for ops/kitchen manager
A7: 4 | B7: Curefoods | C7: EatFit, CakeZone, Nomad Pizza, Sharief Bhai, Great Indian Khichdi | D7: Kitchen Helper, Cook, Packer, Dishwasher | E7: Gurgaon cloud hubs | J7: 🔍 Research Gurgaon facility → ask for ops/kitchen manager
A8: 5 | B8: Ghost Kitchens India | C8: Multi-brand ghost-kitchen facilities | D8: Kitchen Helper, Cook, Packer, Rider | E8: Gurgaon facilities | J8: 🔍 Research Gurgaon facility → ask for ops/kitchen manager
A9: 6 | B9: Loyal Hospitality | C9: Multi-brand cloud kitchens (Awadhi, Chinese, Punjabi...) | D9: Kitchen Helper, Cook, Packer | E9: Gurgaon hubs | J9: 🔍 Research Gurgaon facility → ask for ops/kitchen manager
A10: 7 | B10: Biryani By Kilo (BBK) | C10: BBK, Goila Butter Chicken, Ammi's Biryani | D10: Kitchen Helper, Cook, Packer, Rider | E10: Sohna Rd / Sector 39 | J10: 🔍 Research Gurgaon facility → ask for ops/kitchen manager
A11: 8 | B11: Wow! Momo Foods | C11: Wow! Momo, Wow! China, Wow! Chicken | D11: Kitchen Helper, Cook, Packer | E11: Gurgaon kitchen units | J11: 🔍 Research Gurgaon facility → ask for ops/kitchen manager
A12: 9 | B12: Chinese Wok | C12: Chinese Wok cloud outlets | D12: Kitchen Helper, Cook, Packer, Rider | E12: Multiple Gurgaon units | J12: 🔍 Research Gurgaon facility → ask for ops/kitchen manager
A13: 10 | B13: The Bowl Company / Bercos | C13: Bowl Co., Bercos cloud units | D13: Kitchen Helper, Cook, Dishwasher | E13: Gurgaon units | J13: 🔍 Research Gurgaon facility → ask for ops/kitchen manager
A14: ↓ Callable cloud kitchens found in the scrape (real mobiles) — call these now
A15: 1 | B15: Goila Butter Chicken | C15: north_indian_restaurant | D15: Kitchen Helper, Cook, Packer, Delivery Rider, Dishwasher | E15: H16/6, near Gurudwara, Block H, DLF Phase 1, Sector 26, Gurugram, Haryana 122002, India | F15: 8588887718 | J15: From Google scrape
A16: 2 | B16: Biryani Blues | C16: restaurant | D16: Kitchen Helper, Cook, Packer, Delivery Rider, Dishwasher | E16: Shop No A6, 3rd Floor, Mall, Ardee City, Sector 52, Gurugram, Haryana 122003, India | F16: 8010801000 | J16: From Google scrape
A17: 3 | B17: FreshMenu Gurgaon Sec 53 | C17: asian_restaurant | D17: Kitchen Helper, Cook, Packer, Delivery Rider, Dishwasher | E17: Saraswati Kunj, Parsvnath Exotica, DLF Phase 5, Sector 53, Gurugram, Haryana 122011, India | F17: 9513420082 | J17: From Google scrape
A18: 4 | B18: Mukku's Kitchen – Cloud Kitchen & Tiffin Service | C18: restaurant | D18: Kitchen Helper, Cook, Packer, Delivery Rider, Dishwasher | E18: F Block, Suncity, Sector 54, Gurugram, Haryana 122011, India | F18: 9584550787 | J18: From Google scrape
A19: 5 | B19: Charcoal Eats - Ramji Market | C19: restaurant | D19: Kitchen Helper, Cook, Packer, Delivery Rider, Dishwasher | E19: Triumph Hyundai Showroom Golf, Shop No. 17 On First Floor, Ramji Market Gramin Bank, Ullahawas, Sector 61, Gurugram, Haryana 122101, India | F19: 9022500500 | J19: From Google scrape

Sheet Sector 26
A1: SWITCH · SECTOR 26 · MOBILE CALL SHEET
A2: Owner/manager mobiles · shifts 1–12 hrs, pay after worker reports · instant replacement | 147 leads · 133 in priority industries (top)
A3: LEADS | B3: =COUNTA(B5:B151) | C3: CONTACTED | D3: =COUNTA(I5:I151) | E3: INTERESTED | F3: =COUNTIF(I5:I151,"Yes") | G3: ORDERS | H3: =COUNTIF(K5:K151,"Yes") | I3: HOURS BOOKED | J3: =SUM(J5:J151)
A4: S.No | B4: Business Name | C4: Target Industry | D4: Suggested Roles (per shift) | E4: Manager Mobile | F4: Rating | G4: Reviews | H4: Address | I4: Interested? | J4: Hours (1-12) | K4: Order Confirmed? | L4: Remarks | M4: Map
A5: 1 | B5: Sikandarpur Metro | C5: Warehouse / Logistics | D5: Loader, Packer, Picker, Warehouse Helper, Delivery | E5: 8510098048 | F5: 4.3 | G5: 2615 | H5: Metro Gaet, F3JV+3PX, Sikanderpur, DLF Phase 1, Sector 26, Gurugram, Haryana 122002, India | M5: Map
A6: 2 | B6: Cafe By Soul | Best Outdoor Cafe | C6: Restaurant / Food | D6: Kitchen Helper, Cook, Dishwasher, Waiter | E6: 8826856001 | F6: 4.2 | G6: 1283 | H6: B-11/1, Ashoka Cresent Marg, DLF Phase 1, Sector 26A, Gurugram, Haryana 122002, India | M6: Map
A7: 3 | B7: Truefitt & Hill - DLF Phase-1, Gurugram | C7: Restaurant / Food | D7: Kitchen Helper, Cook, Dishwasher, Waiter | E7: 9899694034 | F7: 4.8 | G7: 996 | H7: A-14/15, Golf Course Rd, DLF Phase 1, Sector 26A, Gurugram, Haryana 122002, India | M7: Map
A8: 4 | B8: RAASA Awadh, to your plate | C8: Restaurant / Food | D8: Kitchen Helper, Cook, Dishwasher, Waiter | E8: 8800791005 | F8: 4.7 | G8: 421 | H8: The shopping mall, C-117, Arjun Marg, Block E, DLF Phase 1, Sector 26A, Gurugram, Haryana 122002, India | M8: Map
A9: 5 | B9: Kith And Kin | C9: Shop / Retail | D9: Store Helper, Housekeeping, Security, Sales Staff | E9: 9599808613 | F9: 4.2 | G9: 402 | H9: Shopping Mall, Arjun Marg, Block E, DLF Phase 1, Sector 26, Gurugram, Haryana 122002, India | M9: Map
A10: 6 | B10: The Woodbury | C10: Hotel / OYO | D10: Housekeeping, Room Boy, Kitchen Helper, Front Desk | E10: 9999071320 | F10: 4.5 | G10: 308 | H10: 1, Kusum Marg, G Block, DLF Phase 1, Sector 26, Gurugram, Haryana 122002, India | M10: Map
A11: 7 | B11: Fabuliv Experience Centre | C11: Shop / Retail | D11: Store Helper, Housekeeping, Security, Sales Staff | E11: 7827133144 | F11: 4.3 | G11: 306 | H11: 3rd, Floor, A-14, 15, Golf Course Rd, DLF Phase 1, Sector 26A, Gurugram, Haryana 122002, India | M11: Map
A12: 8 | B12: Mughal Sarai | C12: Restaurant / Food | D12: Kitchen Helper, Cook, Dishwasher, Waiter | E12: 9710260786 | F12: 4 | G12: 206 | H12: Shopping Mall, D-144, Arjun Marg, DLF Phase 1, Sector 26A, Gurugram, Haryana 122002, India | M12: Map
A13: 9 | B13: Fun Station golf course road | C13: Restaurant / Food | D13: Kitchen Helper, Cook, Dishwasher, Waiter | E13: 9871864446 | F13: 3.9 | G13: 194 | H13: Golf Course Road, Block F4, 1, Block F, DLF Phase 1, Sector 26A, Gurugram, Haryana 122002, India | M13: Map
A14: 10 | B14: Dr Anuj Gaba - GABA HEALTH & WELLNESS | C14: Salon / Spa | D14: Ward Boy, Housekeeping, Attendant, Security | E14: 8287517670 | F14: 5 | G14: 165 | H14: Silver Oaks Apartments, 113-4C3, G Block, DLF Phase 1, Sector 26, Gurugram, Haryana 122002, India | M14: Map
A15: 11 | B15: Sailors Home - Gurgaon | C15: Hotel / OYO | D15: Housekeeping, Room Boy, Kitchen Helper, Front Desk | E15: 9711337992 | F15: 4.1 | G15: 165 | H15: 10/13, Block H, DLF Phase 1, Sector 26, Gurugram, Haryana 122002, India | M15: Map
A16: 12 | B16: Bed & Oats | C16: Hotel / OYO | D16: Office Boy, Housekeeping, Security, Helper | E16: 9773770290 | F16: 4.4 | G16: 153 | H16: 34, G - 19 Rd, G Block, DLF Phase 1, Sector 26, Gurugram, Haryana 122002, India | M16: Map
... A113: 109 | B113: New Laxmi Jewlers | C113: Shop / Retail | D113: Store Helper, Housekeeping, Security, Sales Staff | E113: 9268713758 | F113: 3 | G113: 1 | H113: Sikenderpur, Nambardar Market, Mehrauli-Gurgaon Rd, Block H, DLF Phase 1, Sector 26, Gurugram, Haryana 122002, India | M113: Map
A114: 110 | B114: Chamakandcharms | C114: Shop / Retail | D114: Store Helper, Housekeeping, Security, Sales Staff | E114: 8800381888 | H114: 19/2, G Block, DLF Phase 1, Sector 26, Gurugram, Haryana 122002, India | M114: Map
A115: 111 | B115: Complete Bathing Solution | C115: Shop / Retail | D115: Store Helper, Housekeeping, Security, Sales Staff | E115: 9211230134 | H115: A27/62, DLF Phase 1, Sector 26A, Gurugram, Haryana 122002, India | M115: Map
A116: 112 | B116: HealthnWellness by Dietician Rashmi | C116: Salon / Spa | D116: Ward Boy, Housekeeping, Attendant, Security | E116: 9811699251 | H116: Flat No. 002, Tower 2 The palms, South city, H-1 Rd, Block H, DLF Phase 1, Sector 26, Gurugram, Haryana 122009, India | M116: Map
A117: 113 | B117: Jabbar Steel Works | C117: Restaurant / Food | D117: Kitchen Helper, Cook, Dishwasher, Waiter | E117: 9810727485 | H117: Block H, DLF Phase 1, Sector 26, Gurugram, Haryana 122002, India | M117: Map
A118: 114 | B118: Jitendar Food | C118: Supermarket / Grocery | D118: Kitchen Helper, Cook, Dishwasher, Waiter | E118: 9599170373 | H118: 12, Jitendar Secator 29, DLF Phase 1, Sector 26, Gurugram, Haryana 122002, India | M118: Map
A119: 115 | B119: Kohler | C119: Shop / Retail | D119: Store Helper, Housekeeping, Security, Sales Staff | E119: 9810822617 | H119: 51, Ashoka Cresent Marg, DLF Phase 1, Sector 26A, Gurugram, Haryana 122002, India | M119: Map
A120: 116 | B120: Md Rafique Auto Mobile Service | C120: Warehouse / Logistics | D120: Office Boy, Housekeeping, Security, Helper | E120: 9870205277 | H120: U10/1, DLF, Block D, Sector 26A, Gurugram, Haryana 122002, India | M120: Map
A121: 117 | B121: Moving Box Packers And Movers Gurgaon | C121: Warehouse / Logistics | D121: Loader, Packer, Picker, Warehouse Helper, Delivery | E121: 8796995430 | H121: Shop No 17, Arjun Marg, Block E, DLF Phase 1, Sector 26A, Gurugram, Haryana 122002, India | M121: Map
A122: 118 | B122: NOONOO | C122: Shop / Retail | D122: Store Helper, Housekeeping, Security, Sales Staff | E122: 7678328764 | H122: M Square, 1, A-14 Ln, DLF Phase 1, Sector 26, Gurugram, Haryana 122002, India | M122: Map
A123: 119 | B123: Primary eye care | C123: Shop / Retail | D123: Store Helper, Housekeeping, Security, Sales Staff | E123: 9015812518 | H123: E4, QUTUB PLAZA, market, DLF Phase 1, Sector 26A, Gurugram, Haryana 122002, India | M123: Map
A124: 120 | B124: Purple Inn | C124: Hotel / OYO | D124: Housekeeping, Room Boy, Kitchen Helper, Front Desk | E124: 8088988711 | H124: F4H4+44X, Sikanderpur, Sector 26, Gurugram, Haryana 122002, India | M124: Map
A125: 121 | B125: Raunak Fast Food | C125: Restaurant / Food | D125: Kitchen Helper, Cook, Dishwasher, Waiter | E125: 7982786111 | H125: 5, DLF Phase 1, Sector 26, Gurugram, Haryana 122002, India | M125: Map
... A137: 133 | B137: Zain Chairs | C137: Shop / Retail | D137: Store Helper, Housekeeping, Security, Sales Staff | E137: 9873953786 | H137: 1, Kachnar Marg, Block H, DLF Phase 1, Sector 26, Haryana, Gurugram, Haryana 122002, India | M137: Map
A138: 134 | B138: Toothsi by MakeO | Invisible Braces & Aligners | DLF Phase 1 | C138: Other | D138: Ward Boy, Housekeeping, Attendant, Security | E138: 8451849771 | F138: 4.6 | G138: 294 | H138: No A, 14/1, Golf Course Rd, DLF Phase 1, Sector 26, Gurugram, Haryana 122002, India | M138: Map
A139: 135 | B139: Malik Tyre World | C139: Other | D139: Store Helper, Housekeeping, Security, Sales Staff | E139: 9278085708 | F139: 3.9 | G139: 252 | H139: Shop No. 1 & 2 Sikandarpur Rapid Metro Station, Opposite Metro Pillar No. 11, DLF Phase-1 Road, Block H, DLF Phase 1, Sector 26, Gurugram, Haryana 122002, India | M139: Map
A140: 136 | B140: Korec Physiocare - Dr. Debanjan Mondal and Dr. Soumyadip Bose | C140: Other | D140: Ward Boy, Housekeeping, Attendant, Security | E140: 9971806365 | F140: 5 | G140: 206 | H140: F 2/33A, DLF Phase:-1, DLF Phase 1, Sector 26A, Gurugram, Haryana 122021, India | M140: Map
A141: 137 | B141: Dr Lohiya Fracture Clinic | C141: Other | D141: Ward Boy, Housekeeping, Attendant, Security | E141: 9891054136 | F141: 4.7 | G141: 137 | H141: Opposite Govt middle school, sikanderpur ghosi, Mehrauli-Gurgaon Rd, Sikanderpur, Sector 26, Gurugram, Haryana 122002, India | M141: Map
A142: 138 | B142: Vaastu Sanjivanii | C142: Other | D142: Office Boy, Housekeeping, Security, Helper | E142: 9910558589 | F142: 4.9 | G142: 125 | H142: Block E, DLF Phase 1, Sector 26A, Gurugram, Haryana 122002, India | M142: Map
A143: 139 | B143: Balance pilates India | C143: Other | D143: Trainer, Housekeeping, Front Desk | E143: 9810105546 | F143: 4.8 | G143: 119 | H143: House No, 10, Ashoka Cresent Marg, DLF Phase 1, Sector 26A, Gurugram, Haryana 122002, India | M143: Map
A144: 140 | B144: Sachin Kakkar | C144: Other | D144: Trainer, Housekeeping, Front Desk | E144: 8586002020 | F144: 4.9 | G144: 109 | H144: B 1 /15, DLF Phase 1, Sector 26A, Gurugram, Haryana 122002, India | M144: Map
A145: 141 | B145: Dr. Mansi Bhayana - Homoeopathic physician | C145: Other | D145: Ward Boy, Housekeeping, Attendant, Security | E145: 9711191728 | F145: 5 | G145: 97 | H145: 14, Paschim Marg, DLF Phase 1, Sector 26A, Gurugram, Haryana 122002, India | M145: Map
A146: 142 | B146: 6/6 Eye Centre | Dr. Ashwani Aggarwal (MS - Ophthalmology, MBBS - Ophthalmologist/ Eye Surgeon) | Delhi Gurgaon | C146: Other | D146: Ward Boy, Housekeeping, Attendant, Security | E146: 9650286258 | F146: 4.4 | G146: 92 | H146: 74, Arjun Marg, Block E, DLF Phase 1, Sector 26A, Gurugram, Haryana 122002, India | M146: Map
A147: 143 | B147: Dr Sunil Marwah Clinic | C147: Other | D147: Ward Boy, Housekeeping, Attendant, Security | E147: 9810153207 | F147: 2.9 | G147: 80 | H147: F-1/9, DLF Phase-1, Block F, DLF Phase 1, Sector 26A, Gurugram, Haryana 122002, India | M147: Map
A148: 144 | B148: RARITY DENTAL | C148: Other | D148: Ward Boy, Housekeeping, Attendant, Security | E148: 7899418483 | F148: 4.9 | G148: 78 | H148: 42, Ashoka Crescent Marg, Golf Crse Rd, DLF Phase 1, Sector 26A, Gurugram, Haryana 122002, India | M148: Map
A149: 145 | B149: Dr.simran Certified Manual Physiotherapist in Gurugram | C149: Other | D149: Ward Boy, Housekeeping, Attendant, Security | E149: 8950712281 | F149: 5 | G149: 75 | H149: Landmark Cafe By Soul, The Basement of B11, Café by soul basement, 1, Ashoka Cresent Marg, Block B, Sector 26A, Gurugram, Haryana 122002, India | M149: Map
... A151: 147 | B151: Proveda Herbal Pvt. Ltd | C151: Other | D151: Machine Operator, Helper, Loader, Packer | E151: 9818403953 | F151: 3.8 | G151: 70 | H151: A 42, First Floor, DLF Phase -1, Ashoka Crescent Road, Sector 26A, Gurugram, Haryana 122002, India | M151: Map

Sheet Sector 27
A1: SWITCH · SECTOR 27 · MOBILE CALL SHEET
A2: Owner/manager mobiles · shifts 1–12 hrs, pay after worker reports · instant replacement | 42 leads · 38 in priority industries (top)
A3: LEADS | B3: =COUNTA(B5:B46) | C3: CONTACTED | D3: =COUNTA(I5:I46) | E3: INTERESTED | F3: =COUNTIF(I5:I46,"Yes") | G3: ORDERS | H3: =COUNTIF(K5:K46,"Yes") | I3: HOURS BOOKED | J3: =SUM(J5:J46)
A4: S.No | B4: Business Name | C4: Target Industry | D4: Suggested Roles (per shift) | E4: Manager Mobile | F4: Rating | G4: Reviews | H4: Address | I4: Interested? | J4: Hours (1-12) | K4: Order Confirmed? | L4: Remarks | M4: Map
A5: 1 | B5: Karim's Sushant Lok - Original From Delhi 6 | C5: Restaurant / Food | D5: Kitchen Helper, Cook, Dishwasher, Waiter | E5: 9654902020 | F5: 4.8 | G5: 1222 | H5: B728, Santosh Plaza, Sushant Lok Phase I, Sector 27, Gurugram, Haryana 122002, India | M5: Map
A6: 2 | B6: PEHLE CHAI | C6: Restaurant / Food | D6: Kitchen Helper, Cook, Dishwasher, Waiter | E6: 7428908282 | F6: 4.3 | G6: 1100 | H6: PLOT NO 728, SHOP NO 1, GROUND FLOOR, SANTOSH PLAZA, 2 & 3, Sushant Lok Phase I, Sector 27, Gurugram, Haryana 122001, India | M6: Map
A7: 3 | B7: STEPiNN Ess Kay Ess Villa | C7: Hotel / OYO | D7: Housekeeping, Room Boy, Kitchen Helper, Front Desk | E7: 9971823335 | F7: 4.4 | G7: 440 | H7: F-13/13, DLF Phase 1, Sector 27, Gurugram, Haryana 122002, India | M7: Map
A8: 4 | B8: AKU'S - The Burger Co. | HQ27, Gurugram | C8: Restaurant / Food | D8: Kitchen Helper, Cook, Dishwasher, Waiter | E8: 9667519279 | F8: 4.8 | G8: 324 | H8: Showroom No 10, HQ27 - The Headquarters, B - 660, Sushant Lok Phase I, Sector 27, Gurugram, Haryana 122009, India | M8: Map
A9: 5 | B9: Varun Attri | Hair | Beauty | Unisex Salon in Gurugram | C9: Salon / Spa | D9: Beautician, Helper, Receptionist, Cleaner | E9: 8588857572 | F9: 4.6 | G9: 307 | H9: F-10/4, Golf Course Rd, DLF Phase 1, Sector 27, Gurugram, Haryana 122009, India | M9: Map
A10: 6 | B10: Dr Amit Bhasin | C10: Salon / Spa | D10: Office Boy, Housekeeping, Security, Helper | E10: 8527336665 | F10: 4.7 | G10: 254 | H10: Prive Skin Clinic, 6101, near Super Mart 1, DLF Phase IV, Sector 27, Gurugram, Haryana 122009, India | M10: Map
A11: 7 | B11: NOVY | C11: Restaurant / Food | D11: Kitchen Helper, Cook, Dishwasher, Waiter | E11: 9599711003 | F11: 4.6 | G11: 232 | H11: 8, HQ27 The Headquarters, Sector 27, Sector 43, Gurugram, Haryana 122009, India | M11: Map
A12: 8 | B12: Threads Physio | Best Physiotherapist in Gurgaon | Sports Physio & Rehab | ACL Surgery Specialist | C12: Salon / Spa | D12: Ward Boy, Housekeeping, Attendant, Security | E12: 9310138022 | F12: 4.8 | G12: 224 | H12: F, 10/4, Golf Course Rd, DLF Phase 1, Sector 27, Gurugram, Haryana 122001, India | M12: Map
A13: 9 | B13: PopnCrunch | C13: Restaurant / Food | D13: Kitchen Helper, Cook, Dishwasher, Waiter | E13: 9818050442 | F13: 4.9 | G13: 131 | H13: B 357A, Sushant Lok Rd, Sushant Lok Phase I, Sector 27, Gurugram, Haryana 122009, India | M13: Map
A14: 10 | B14: B One Premium Thai Spa Sector 27 DLF Phase 1 Gurugram | C14: Salon / Spa | D14: Beautician, Helper, Receptionist, Cleaner | E14: 8826788480 | F14: 4.8 | G14: 106 | H14: 2nd Floor, Rao Mohar Singh Complex, Golf Course Rd, DLF Phase 1, Sector 27, Gurugram, Haryana 122009, India | M14: Map
A15: 11 | B15: Plan B Luxe Spa | C15: Salon / Spa | D15: Beautician, Helper, Receptionist, Cleaner | E15: 9958043330 | F15: 4.7 | G15: 104 | H15: 1st Floor, Golf Course Rd, above 3M Care Servies On, DLF Phase 1, Sector 27, Gurugram, Haryana 122009, India | M15: Map
A16: 12 | B16: Say PC Enterprises | C16: Shop / Retail | D16: Store Helper, Housekeeping, Security, Sales Staff | E16: 9711111454 | F16: 4.9 | G16: 97 | H16: 121, near Community Centre DLF City Phase I., Sector 27, Gurugram, Haryana 122009, India | M16: Map
... A37: 33 | B37: Swaad Mahal Restaurant | C37: Restaurant / Food | D37: Kitchen Helper, Cook, Dishwasher, Waiter | E37: 8447038625 | F37: 5 | G37: 1 | H37: Block B, DLF Phase 1, Sector 27, Gurugram, Haryana 122009, India | M37: Map
A38: 34 | B38: Autoknox | C38: Shop / Retail | D38: Mechanic Helper, Cleaner, Washer | E38: 9873330036 | H38: opp. Arjun Marg, near Jalsa resturant, DLF Phase 1, Sector 27, Gurugram, Haryana 122009, India | M38: Map
A39: 35 | B39: Euna | C39: Shop / Retail | D39: Store Helper, Housekeeping, Security, Sales Staff | E39: 7464944944 | H39: 249, Sector 27, Gurugram, Haryana 122009, India | M39: Map
A40: 36 | B40: KOFFEE AND BEVV | C40: Restaurant / Food | D40: Kitchen Helper, Cook, Dishwasher, Waiter | E40: 9971870603 | H40: 6716, DLF Phase IV, Sector 27, Gurugram, Haryana 122009, India | M40: Map
A41: 37 | B41: Sri Bala Ji Gurgaon Taxi Services | C41: Warehouse / Logistics | D41: Office Boy, Housekeeping, Security, Helper | E41: 9660181898 | H41: 248, Sector 27, Gurugram, Haryana 122009, India | M41: Map
A42: 38 | B42: Unique Home Massage Spa | C42: Salon / Spa | D42: Beautician, Helper, Receptionist, Cleaner | E42: 7982517232 | H42: office no.1, A-92, Golf Course Rd, Sector 27, Gurugram, Haryana 122009, India | M42: Map
A43: 39 | B43: Nova IVF Fertility Center Gurugram - Best IVF Centre in Gurgaon, Haryana | C43: Other | D43: Office Boy, Housekeeping, Security, Helper | E43: 8044474652 | F43: 4.9 | G43: 213 | H43: Plot No 522, near Supermarket, Sector 27, Gurugram, Haryana 122009, India | M43: Map
A44: 40 | B44: Dr. Rashmi Agrawal | C44: Other | D44: Office Boy, Housekeeping, Security, Helper | E44: 9811775369 | F44: 5 | G44: 207 | H44: NOVA IVF, Plot No 522, Sector 27, Gurugram, Haryana 122009, India | M44: Map
A45: 41 | B45: eFiling Portal | C45: Other | D45: Office Boy, Housekeeping, Security, Helper | E45: 9555247000 | F45: 4.2 | G45: 125 | H45: 509 Sector 27, Sector 27, Gurugram, Haryana 122009, India | M45: Map
A46: 42 | B46: Sadhyog - Isha Hatha Yoga Center Gurgaon | C46: Other | D46: Trainer, Housekeeping, Front Desk | E46: 8178748463 | F46: 4.9 | G46: 93 | H46: Plot No. 489, Sector 27, Gurugram, Haryana 122009, India | M46: Map

Sheet Sector 28
A1: SWITCH · SECTOR 28 · MOBILE CALL SHEET
A2: Owner/manager mobiles · shifts 1–12 hrs, pay after worker reports · instant replacement | 141 leads · 127 in priority industries (top)
A3: LEADS | B3: =COUNTA(B5:B145) | C3: CONTACTED | D3: =COUNTA(I5:I145) | E3: INTERESTED | F3: =COUNTIF(I5:I145,"Yes") | G3: ORDERS | H3: =COUNTIF(K5:K145,"Yes") | I3: HOURS BOOKED | J3: =SUM(J5:J145)
A4: S.No | B4: Business Name | C4: Target Industry | D4: Suggested Roles (per shift) | E4: Manager Mobile | F4: Rating | G4: Reviews | H4: Address | I4: Interested? | J4: Hours (1-12) | K4: Order Confirmed? | L4: Remarks | M4: Map
A5: 1 | B5: Meena Bazaar | C5: Shop / Retail | D5: Store Helper, Housekeeping, Security, Sales Staff | E5: 7303888625 | F5: 4.9 | G5: 6996 | H5: A-1, Mehrauli-Gurgaon Rd, Sector 28, Sushant Lok Phase I, Gurugram, Haryana 122002, India | M5: Map
A6: 2 | B6: Haute24 | C6: Shop / Retail | D6: Store Helper, Housekeeping, Security, Sales Staff | E6: 9561794706 | F6: 4.2 | G6: 1670 | H6: 1314, 13th Ave Rd, near Galleria Market, Sector 28, DLF Phase IV, Gurugram, Haryana 122009, India | M6: Map
A7: 3 | B7: Hyundai Showroom, Dee Emm Hyundai - Sikanderpur, Near Sahara Mall, MG Road, Gurgaon | C7: Shop / Retail | D7: Store Helper, Housekeeping, Security, Sales Staff | E7: 9773647900 | F7: 4.9 | G7: 1373 | H7: Plot No. 90, Mehrauli-Gurgaon Rd, near Sahara Mall, Sector 28, DLF Phase 1, Gurugram, Haryana 122001, India | M7: Map
A8: 4 | B8: SURYANSH FAB GURUGRAM | C8: Shop / Retail | D8: Store Helper, Housekeeping, Security, Sales Staff | E8: 9810682621 | F8: 4.9 | G8: 1336 | H8: 103, 3/1, near GRAND MALL, Sector 28, DLF Phase 1, Gurugram, Haryana 122002, India | M8: Map
A9: 5 | B9: Floor & Furnishings, DLF | FF | C9: Shop / Retail | D9: Store Helper, Housekeeping, Security, Sales Staff | E9: 9643403802 | F9: 4.8 | G9: 1247 | H9: A-5, Mehrauli-Gurgaon Road, Mall Road, near Metro Pillar Number 94, Sector 28, DLF Phase 1, Gurugram, Haryana 122002, India | M9: Map
A10: 6 | B10: The Atara | C10: Hotel / OYO | D10: Housekeeping, Room Boy, Kitchen Helper, Front Desk | E10: 8527575333 | F10: 4.1 | G10: 628 | H10: A-29/10, behind Dt Mega Mall, Sector 28, DLF Phase 1, Gurugram, Haryana 122002, India | M10: Map
A11: 7 | B11: Jawa Yezdi BSA Motorcycles - Siddhanth Automobiles, MG Road, Gurugram | C11: Shop / Retail | D11: Store Helper, Housekeeping, Security, Sales Staff | E11: 8037537489 | F11: 4.8 | G11: 534 | H11: Metro Pillar 82 And 83, MG Road DLF Phase 1, nearby Jmd Regent Square, Sector 28, Arcade, Gurugram, Haryana 122002, India | M11: Map
A12: 8 | B12: Blue heaven therapy at Homes | C12: Salon / Spa | D12: Beautician, Helper, Receptionist, Cleaner | E12: 9382989566 | F12: 5 | G12: 470 | H12: Sector 28, Chakkarpur, Sector 43, Gurugram, Haryana 122009, India | M12: Map
A13: 9 | B13: ElectricOne Gurgaon DLF - Electric Vehicle Showroom | C13: Shop / Retail | D13: Office Boy, Housekeeping, Security, Helper | E13: 9811312988 | F13: 4.9 | G13: 450 | H13: Shop No 2, Mehrauli-Gurgaon Rd, opposite Pillar No P81, adjacent to Sahara Mall, Sector 28, DLF Phase 1, Gurugram, Haryana 122002, India | M13: Map
A14: 10 | B14: Barman Eye Care Center - Eye Specialist in Gurgaon | Cataract Specialist in Gurgaon | Ophthalmologist in Gurugram | C14: Restaurant / Food | D14: Kitchen Helper, Cook, Dishwasher, Waiter | E14: 9667888433 | F14: 4.8 | G14: 387 | H14: 4307, besides, Galleria Market, Sector 28, DLF Phase IV, Gurugram, Haryana 122009, India | M14: Map
A15: 11 | B15: Stately Suites MG Road | C15: Hotel / OYO | D15: Housekeeping, Room Boy, Kitchen Helper, Front Desk | E15: 9560078177 | F15: 4.1 | G15: 352 | H15: A151/A, Road, Sector 28, Sushant Lok Phase I, Gurugram, Haryana 122009, India | M15: Map
A16: 12 | B16: The Pink Falcon | C16: Restaurant / Food | D16: Office Boy, Housekeeping, Security, Helper | E16: 9315988586 | F16: 4.4 | G16: 328 | H16: Lower ground Floor, JMD Empire Square, Mehrauli-Gurgaon Rd, Sector 28, DLF Phase 1, Gurugram, Sikanderpur Ghosi, Haryana 122002, India | M16: Map
... A109: 105 | B109: S R Ledis Tailor | C109: Shop / Retail | D109: Store Helper, Housekeeping, Security, Sales Staff | E109: 8860429799 | F109: 1 | G109: 1 | H109: Shop No.4, Market, Jaina Market, Sector 28, Chakkarpur, Gurugram, Haryana 122002, India | M109: Map
A110: 106 | B110: Ambay Car Shingar | C110: Warehouse / Logistics | D110: Office Boy, Housekeeping, Security, Helper | E110: 9711597170 | H110: Shop Number 1, Old, Delhi Road, opp. Punjab National Bank, Sector 28, Sushant Lok Phase I, Gurugram, Haryana 122009, India | M110: Map
A111: 107 | B111: Anita Devi | C111: Shop / Retail | D111: Store Helper, Housekeeping, Security, Sales Staff | E111: 9693719840 | H111: Sector 28, Gurugram, Haryana 122002, India | M111: Map
A112: 108 | B112: Crazy Trader | C112: Shop / Retail | D112: Store Helper, Housekeeping, Security, Sales Staff | E112: 9582241693 | H112: 79, Mehrauli-Gurgaon Rd, Sector 28, Maruti Housing Colony, Sector 25, Gurugram, Haryana 122009, India | M112: Map
A113: 109 | B113: Deluxe Cargo Packers And Movers | C113: Warehouse / Logistics | D113: Loader, Packer, Picker, Warehouse Helper, Delivery | E113: 8796901998 | H113: Shop No, 433, Phase 1, Sector 28, Sushant Lok Phase I, Sector 43, Gurugram, Haryana 122009, India | M113: Map
A114: 110 | B114: Dev Shakya Tea Shop | C114: Shop / Retail | D114: Store Helper, Housekeeping, Security, Sales Staff | E114: 9528835702 | H114: 57, Mg Metro, Sector 28, DLF Phase 2, Sector 25, Gurugram, Haryana 122009, India | M114: Map
A115: 111 | B115: Devendra Kirana Store | C115: Supermarket / Grocery | D115: Store Helper, Housekeeping, Security, Sales Staff | E115: 7880214756 | H115: Devendra Aana Store, Sector 28, DLF City IV, Tikamgarh, Gurugram, Madhya Pradesh 122002, India | M115: Map
A116: 112 | B116: Gulab Footwear | C116: Shop / Retail | D116: Store Helper, Housekeeping, Security, Sales Staff | E116: 9958778828 | H116: A-46, 756, Vijay Cinema Hall Rd, Jaina Market, Sector 28, Chakkarpur, Gurugram, Haryana 122002, India | M116: Map
A117: 113 | B117: Himanshu General Store | C117: Restaurant / Food | D117: Store Helper, Housekeeping, Security, Sales Staff | E117: 9953077258 | H117: Himanshu General Store, near Dayal Public School, Sector 28, Chakkarpur, Gurugram, Haryana 122002, India | M117: Map
A118: 114 | B118: Jai Beauty Parlour | C118: Salon / Spa | D118: Beautician, Helper, Receptionist, Cleaner | E118: 8383051858 | H118: House No-16, 11A. Blocka, Balakishan Tower, Mg Road, Chakkarpur, Behind Sahara Mall, Gurugram, NCR, Sector 28, Chakkarpur, Region, Gurugram, Haryana 122002, India | M118: Map
A119: 115 | B119: Jai Krishan Fruits Shop | C119: Restaurant / Food | D119: Kitchen Helper, Cook, Dishwasher, Waiter | E119: 9289371197 | H119: Jaina Market, Sector 28, Chakkarpur, Gurugram, Haryana 122002, India | M119: Map
A120: 116 | B120: Laxman Readymade Garments | C120: Shop / Retail | D120: Store Helper, Housekeeping, Security, Sales Staff | E120: 8588888638 | H120: 761, near Jaina Mandir, Jaina Market, Sector 28, Chakkarpur, Gurugram, Haryana 122002, India | M120: Map
A121: 117 | B121: Leelsdhar Shop | C121: Shop / Retail | D121: Store Helper, Housekeeping, Security, Sales Staff | E121: 9024120859 | H121: 7, Sector 28, DLF Phase 2, Sector 24, Gurugram, Haryana 122009, India | M121: Map
... A131: 127 | B131: Yadav Fast Food | C131: Restaurant / Food | D131: Kitchen Helper, Cook, Dishwasher, Waiter | E131: 7739025853 | H131: Chakkarpur Village Rd, near by Radha Krishna Mandir, Sector 28, Chakkarpur, Gurugram, Haryana 122002, India | M131: Map
A132: 128 | B132: Universal Gym - Available on Cult.fit | Best gym in MG Road, Gurugram | C132: Other | D132: Trainer, Housekeeping, Front Desk | E132: 9911113032 | F132: 4.2 | G132: 319 | H132: Grace Rd 798 Saraswati Vihar, behind Sahara Mall, Sector 28, Chakkarpur, Gurugram, Haryana 122009, India | M132: Map
A133: 129 | B133: IB Global Academy - Best IB, IGCSE & SAT Tutor in Gurgaon | C133: Other | D133: Office Boy, Housekeeping, Security, Helper | E133: 9312411928 | F133: 4.9 | G133: 211 | H133: House No - 4315, 2nd Floor, near Galleria Market, Galleria Market, Sector 28, DLF Phase IV, Gurugram, Haryana 122009, India | M133: Map
A134: 130 | B134: DLF Heart Care Clinic | C134: Other | D134: Ward Boy, Housekeeping, Attendant, Security | E134: 9873214382 | F134: 4.3 | G134: 190 | H134: A- 41/27, DLF Phase 1, Sector 28, Chakkarpur, Gurugram, Haryana 122002, India | M134: Map
A135: 131 | B135: The Platform | C135: Other | D135: Trainer, Housekeeping, Front Desk | E135: 6371220920 | F135: 5 | G135: 136 | H135: V, 799, Grace Rd, Sector 28, Chakkarpur, Gurugram, Haryana 122009, India | M135: Map
A136: 132 | B136: astrology Vastu Numerology | C136: Other | D136: Office Boy, Housekeeping, Security, Helper | E136: 9653561556 | F136: 4.9 | G136: 121 | H136: 196 P, near Jan Pratinidhi Apartments, Sector 28, Chakkarpur, Gurugram, Haryana 122002, India | M136: Map
A137: 133 | B137: Dr. Dipika Thakur Physiotherapist - Physiotherapy Clinic Near Sector 42 & Sector 43 Gurgaon | C137: Other | D137: Ward Boy, Housekeeping, Attendant, Security | E137: 8800818568 | F137: 5 | G137: 97 | H137: Near, Supermart-1, Sector 28, DLF Phase IV, Gurugram, Haryana 122001, India | M137: Map
A138: 134 | B138: HW Infotech – Website & Mobile App Development | AI, Blockchain & SaaS Company | C138: Other | D138: Office Boy, Housekeeping, Security, Helper | E138: 7678430274 | F138: 5 | G138: 88 | H138: Cospaces Cowork Plot No 360, Golf Course Rd, Sector 28, Chakkarpur, Gurugram, Haryana 122002, India | M138: Map
A139: 135 | B139: Children First Mental Health Institute, Gurugram | C139: Other | D139: Ward Boy, Housekeeping, Attendant, Security | E139: 9650844774 | F139: 4.7 | G139: 78 | H139: B 18/9, Golf Course Rd, Sector 28, DLF Phase 1, Sector 26A, Gurugram, Haryana 122002, India | M139: Map
A140: 136 | B140: The Lifestyle Clinic: By Dr Jateen Ukrani & Dr Varsha Mahadik | C140: Other | D140: Ward Boy, Housekeeping, Attendant, Security | E140: 8368845563 | F140: 4.8 | G140: 76 | H140: H 1234 GF, sector 28, Maruti Vihar, Maruti Housing Colony, Gurgaonr, Gurugram, Haryana 122002, India | M140: Map
A141: 137 | B141: Dr. Ahtasham | C141: Other | D141: Ward Boy, Housekeeping, Attendant, Security | E141: 9205736607 | F141: 5 | G141: 62 | H141: 3410, near IVY APARTMENT, Sector 28, Sushant Lok Phase I, Sector 43, Gurugram, Haryana 122009, India | M141: Map
A142: 138 | B142: Dr Ankesh Singh | COGNIZEN HEALTHCARE | Best Psychiatrist in Gurgaon | Psychiatrist Near Me in Gurgaon | C142: Other | D142: Ward Boy, Housekeeping, Attendant, Security | E142: 9599595489 | F142: 4.9 | G142: 51 | H142: 5th Floor, Crosspoint Mall, GL-506, Sector 28, DLF Phase IV, Gurugram, Haryana 122002, India | M142: Map
A143: 139 | B143: Jivem Pilates & Yoga Studio | C143: Other | D143: Trainer, Housekeeping, Front Desk | E143: 9643658631 | F143: 5 | G143: 47 | H143: Hamilton Ct Rd, Sector 28, Chakkarpur, Gurugram, Haryana 122002, India | M143: Map
... A145: 141 | B145: Manoj carpenter wooden works | C145: Other | D145: Machine Operator, Helper, Loader, Packer | E145: 9650743241 | F145: 4.7 | G145: 47 | H145: Sector 28, Chakarpur House no 345 second floor Gali no 11, near Atal seva Kendra, Sector 28, Chakkarpur, Gurugram, Haryana 122002, India | M145: Map

Sheet Sector 42
A1: SWITCH · SECTOR 42 · MOBILE CALL SHEET
A2: Owner/manager mobiles · shifts 1–12 hrs, pay after worker reports · instant replacement | 62 leads · 56 in priority industries (top)
A3: LEADS | B3: =COUNTA(B5:B66) | C3: CONTACTED | D3: =COUNTA(I5:I66) | E3: INTERESTED | F3: =COUNTIF(I5:I66,"Yes") | G3: ORDERS | H3: =COUNTIF(K5:K66,"Yes") | I3: HOURS BOOKED | J3: =SUM(J5:J66)
A4: S.No | B4: Business Name | C4: Target Industry | D4: Suggested Roles (per shift) | E4: Manager Mobile | F4: Rating | G4: Reviews | H4: Address | I4: Interested? | J4: Hours (1-12) | K4: Order Confirmed? | L4: Remarks | M4: Map
A5: 1 | B5: Mental Wellness Centre | C5: Salon / Spa | D5: Ward Boy, Housekeeping, Attendant, Security | E5: 9588392566 | F5: 4.8 | G5: 1047 | H5: First Floor, Plot No. 595, Golf Course Road, near Shiv Nadar Public School, Sector 42, Gurugram, Haryana 122009, India | M5: Map
A6: 2 | B6: Saltstayz Premier Sector 42 - Golf Course Road | C6: Hotel / OYO | D6: Housekeeping, Room Boy, Kitchen Helper, Front Desk | E6: 8800012701 | F6: 4.7 | G6: 951 | H6: Plot No. 780, Golf Crse Rd, Sector 42, Gurugram, Haryana 122009, India | M6: Map
A7: 3 | B7: Alaya Stays by ELIVAAS Eternal Oasis | C7: Hotel / OYO | D7: Office Boy, Housekeeping, Security, Helper | E7: 7969316141 | F7: 4.9 | G7: 425 | H7: Plot no. 591A, Sector 42, Gurugram, Haryana 122009, India | M7: Map
A8: 4 | B8: KOCA | C8: Restaurant / Food | D8: Kitchen Helper, Cook, Dishwasher, Waiter | E8: 8448184111 | F8: 4.4 | G8: 416 | H8: SCO4-7, Golf Avenue 42, Golf Course Rd, Sector 42, Gurugram, Haryana 122009, India | M8: Map
A9: 5 | B9: Effingut Brewpub Gurugram - India's most loved craft brew pub | C9: Restaurant / Food | D9: Office Boy, Housekeeping, Security, Helper | E9: 9211455592 | F9: 4.3 | G9: 403 | H9: 2nd Floor, Golf Avenue 42, Golf Course Rd, Sector 42, Gurugram, Haryana 122009, India | M9: Map
A10: 6 | B10: Eternal Oasis Gurugram | C10: Restaurant / Food | D10: Office Boy, Housekeeping, Security, Helper | E10: 7982883571 | F10: 4.5 | G10: 215 | H10: Landmark, Eternal Oasis, 591A, Sector 42 Main Rd, opposite Shiv Nadar School, Sector 42, Gurugram, Haryana 122002, India | M10: Map
A11: 7 | B11: Vaibhav Garg - Sports Performance Nutritionist & Metabolic Disorders Expert | C11: Salon / Spa | D11: Trainer, Housekeeping, Front Desk | E11: 9818467654 | F11: 4.9 | G11: 204 | H11: 697-P, Golf Course Rd, Sector 42, Gurugram, Haryana 122009, India | M11: Map
A12: 8 | B12: Diwan Saheb Gurugram | C12: Shop / Retail | D12: Store Helper, Housekeeping, Security, Sales Staff | E12: 8048070463 | F12: 4.2 | G12: 191 | H12: G 5-10, Ameya One Building Golf Course Road, Facing Rapid Metro Pillar No 91 Phase V, DLF Colony, Sector 42, Gurugram, Haryana 122011, India | M12: Map
A13: 9 | B13: Truefitt & Hill Ameya One | C13: Restaurant / Food | D13: Kitchen Helper, Cook, Dishwasher, Waiter | E13: 8527437773 | F13: 5 | G13: 158 | H13: Ameya One, Ground floor, Phase-5, Golf Course Rd, Sector 42, Gurugram, Haryana 122009, India | M13: Map
A14: 10 | B14: Cozy Stay (Co-living) Pg | C14: PG / Hostel | D14: Housekeeping, Cook, Caretaker, Security | E14: 9711181185 | F14: 4.7 | G14: 118 | H14: H.No 46C, near Cybercity and Ambience Mall, Sector 42, Gurugram, Haryana 122002, India | M14: Map
A15: 11 | B15: The Audio Co. | C15: Shop / Retail | D15: Store Helper, Housekeeping, Security, Sales Staff | E15: 9810502023 | F15: 5 | G15: 110 | H15: Plot 41, Sector 42, Gurugram, Haryana 122009, India | M15: Map
A16: 12 | B16: Needs Supermarket | C16: Supermarket / Grocery | D16: Store Helper, Housekeeping, Security, Sales Staff | E16: 9871211355 | F16: 4.1 | G16: 103 | H16: Tower 4, Magnolias Rd, Sector 42, Gurugram, Haryana 122009, India | M16: Map
... A58: 54 | B58: S K MOTERS | C58: Shop / Retail | D58: Mechanic Helper, Cleaner, Washer | E58: 6202881788 | F58: 4 | G58: 1 | H58: 371p, Sector 42, Gurugram, Haryana 122009, India | M58: Map
A59: 55 | B59: BMW Destination Charging Station | C59: Warehouse / Logistics | D59: Office Boy, Housekeeping, Security, Helper | E59: 8070743743 | H59: Magnolias Rd, Sector 42, Gurugram, Haryana 122009, India | M59: Map
A60: 56 | B60: Corumm | C60: Salon / Spa | D60: Beautician, Helper, Receptionist, Cleaner | E60: 9871614567 | H60: 3rd Floor, F-17/1, Golf Course Rd, DLF Phase 1, Sector 42, Gurugram, Haryana 122002, India | M60: Map
A61: 57 | B61: Preface Institute | C61: Other | D61: Peon, Housekeeping, Security, Attendant | E61: 9999488897 | F61: 5 | G61: 172 | H61: 525, J Near Camellias Apartments, Sector 42, Gurugram, Haryana 122002, India | M61: Map
A62: 58 | B62: Timeless Aesthetics | C62: Other | D62: Ward Boy, Housekeeping, Attendant, Security | E62: 9654009966 | F62: 4.8 | G62: 172 | H62: Ameya One, Sector 42, Gurugram, Haryana 122009, India | M62: Map
A63: 59 | B63: T and T Realty Services Pvt Ltd | C63: Other | D63: Office Boy, Housekeeping, Security, Helper | E63: 9873092255 | F63: 4.4 | G63: 154 | H63: second floor, Ameya One, Sector 42, Gurugram, Haryana 122009, India | M63: Map
A64: 60 | B64: Dr Guddi Kumari- best physiotherapist in gurgaon, cupping therapist, physiotherapy for home/neck pain/back pain/stroke/sports | C64: Other | D64: Ward Boy, Housekeeping, Attendant, Security | E64: 9818822205 | F64: 5 | G64: 114 | H64: White coat clinic, Plot no 372, off Golf Course Road, Sector 42, Gurugram, Haryana 122009, India | M64: Map
A65: 61 | B65: Mom's Preg-Ladder- Pregnancy, Birth & Beyond | C65: Other | D65: Office Boy, Housekeeping, Security, Helper | E65: 9711493909 | F65: 4.9 | G65: 104 | H65: Ground Floor, 697-P, Golf Crse Rd, Sector 42, Gurugram, Haryana 122009, India | M65: Map
A66: 62 | B66: Jagruti Rehab - Best Rehabilitation Centre & Mental Hospital in Gurgaon | Drug & Alcohol De-addiction Treatment | C66: Other | D66: Ward Boy, Housekeeping, Attendant, Security | E66: 9822207761 | F66: 4.4 | G66: 90 | H66: Plot no 596, Sector 42, Gurugram, Haryana 122009, India | M66: Map

Sheet Sector 43
A1: SWITCH · SECTOR 43 · MOBILE CALL SHEET
A2: Owner/manager mobiles · shifts 1–12 hrs, pay after worker reports · instant replacement | 141 leads · 127 in priority industries (top)
A3: LEADS | B3: =COUNTA(B5:B145) | C3: CONTACTED | D3: =COUNTA(I5:I145) | E3: INTERESTED | F3: =COUNTIF(I5:I145,"Yes") | G3: ORDERS | H3: =COUNTIF(K5:K145,"Yes") | I3: HOURS BOOKED | J3: =SUM(J5:J145)
A4: S.No | B4: Business Name | C4: Target Industry | D4: Suggested Roles (per shift) | E4: Manager Mobile | F4: Rating | G4: Reviews | H4: Address | I4: Interested? | J4: Hours (1-12) | K4: Order Confirmed? | L4: Remarks | M4: Map
A5: 1 | B5: Manhattan Bar & Brewery | C5: Restaurant / Food | D5: Kitchen Helper, Cook, Dishwasher, Waiter | E5: 8800697549 | F5: 4.4 | G5: 11223 | H5: 1st Floor Global Foyer Mall Unit 001, Golf Course Rd, Sector 43, Gurugram, Haryana 122009, India | M5: Map
A6: 2 | B6: Parul Garg | C6: Salon / Spa | D6: Office Boy, Housekeeping, Security, Helper | E6: 9599588312 | F6: 4.3 | G6: 1518 | H6: POWERGRID TOWNSHIP, D231, Gate, Sector 43, Gurugram, Haryana 122009, India | M6: Map
A7: 3 | B7: La La Land Brew Pub, Gurgaon | C7: Restaurant / Food | D7: Office Boy, Housekeeping, Security, Helper | E7: 8010950000 | F7: 4.3 | G7: 1484 | H7: 1st Floor, Global Foyer Mall, Golf Course Rd, Sector 43, Gurugram, Haryana 122009, India | M7: Map
A8: 4 | B8: ROF PORTICO | C8: Restaurant / Food | D8: Store Helper, Housekeeping, Security, Sales Staff | E8: 9999036154 | F8: 4.3 | G8: 859 | H8: I, Vyapar Kendra Rd, Sushant Lok, Block C, Sushant Lok Phase I, Sector 43, Gurugram, Haryana 122009, India | M8: Map
A9: 5 | B9: Limewood Signature - Huda City Centre | C9: Hotel / OYO | D9: Housekeeping, Room Boy, Kitchen Helper, Front Desk | E9: 9266591900 | F9: 4.9 | G9: 688 | H9: D-201 B, Sushant Lok Phase I, Sector 43, Gurugram, Haryana 122001, India | M9: Map
A10: 6 | B10: Quinnn Harper Unisex & Kids Salon | C10: Hotel / OYO | D10: Housekeeping, Room Boy, Kitchen Helper, Front Desk | E10: 8065076243 | F10: 4.8 | G10: 583 | H10: no 2, Market Gate, C 1001, near Vyapar Kendra Road, Block C, Sushant Lok Phase I, Sector 43, Gurugram, Haryana 122009, India | M10: Map
A11: 7 | B11: Cafe Dakia | C11: Restaurant / Food | D11: Kitchen Helper, Cook, Dishwasher, Waiter | E11: 8882006127 | F11: 4.5 | G11: 411 | H11: ROF PORTICO I, Vyapar Kendra Rd, Block C, Sushant Lok Phase I, Sector 43, Gurugram, Haryana 122009, India | M11: Map
A12: 8 | B12: Stretch Yog – Therapy & Wellness Center | C12: Salon / Spa | D12: Beautician, Helper, Receptionist, Cleaner | E12: 9529369361 | F12: 5 | G12: 323 | H12: Plot number 1183, near lord Krishna appartment, Block C, Sushant Lok Phase I, Sector 43, Gurugram, Haryana 122009, India | M12: Map
A13: 9 | B13: Golf Course Road Service Apartments | C13: Hotel / OYO | D13: Housekeeping, Room Boy, Kitchen Helper, Front Desk | E13: 7838881000 | F13: 4.7 | G13: 301 | H13: 1120, Golf Crse Rd, DLF Phase 5, Sector 43, Gurugram, Haryana 122009, India | M13: Map
A14: 10 | B14: Hotel B Stays | C14: Hotel / OYO | D14: Housekeeping, Room Boy, Kitchen Helper, Front Desk | E14: 9711721184 | F14: 4.8 | G14: 282 | H14: A-586, Block A, Sushant Lok Phase I, Sector 43, Gurugram, Haryana 122009, India | M14: Map
A15: 11 | B15: Shree Shyam Packers and Movers | Best Packers and Movers in Gurgaon | Packers and Movers Gurugram | C15: Warehouse / Logistics | D15: Loader, Packer, Picker, Warehouse Helper, Delivery | E15: 8708197926 | F15: 4.8 | G15: 256 | H15: Building Number - 680, C-BLOCK, Sector 43 Rd, Sushant Lok Phase I, Block C, Block B, Kanahi, Gurugram, Haryana 122009, India | M15: Map
A16: 12 | B16: Kiros Unisex Salon | C16: Salon / Spa | D16: Beautician, Helper, Receptionist, Cleaner | E16: 9899920150 | F16: 4.6 | G16: 251 | H16: Rof portico, Block C, Sushant Lok Phase I, Sector 43, Gurugram, Haryana 122009, India | M16: Map
... A121: 117 | B121: Sushiya Gurugram DLF 4 | C121: Restaurant / Food | D121: Kitchen Helper, Cook, Dishwasher, Waiter | E121: 9312444086 | F121: 1 | G121: 1 | H121: Shop 6, Khasra 505, Yadhuvanshi Market, Supermart 2, near DLF, Block C2, DLF Phase IV, Sector 43, Gurugram, Haryana 122002, India | M121: Map
A122: 118 | B122: ANNAPURNA RETAIL | C122: Supermarket / Grocery | D122: Store Helper, Housekeeping, Security, Sales Staff | E122: 8826282121 | H122: D 255, Sushant Lok Phase I, Sector 43, Gurugram, Haryana 122009, India | M122: Map
A123: 119 | B123: Bhaseer Ul Shop h | C123: Shop / Retail | D123: Store Helper, Housekeeping, Security, Sales Staff | E123: 8178985183 | H123: Shop Number 37, Horizon Colony, Sector 43, Gurugram, Haryana 122009, India | M123: Map
A124: 120 | B124: Dhaba Mithla Bhojan | C124: Restaurant / Food | D124: Kitchen Helper, Cook, Dishwasher, Waiter | E124: 9971606174 | H124: shop no . 3, plot, 7sp, Golf Course Rd, Sector 43, Gurugram, Haryana 122009, India | M124: Map
A125: 121 | B125: ElectricPe Charging Station | C125: Warehouse / Logistics | D125: Office Boy, Housekeeping, Security, Helper | E125: 8147060222 | H125: Sector43, Sector 41, Gurugram, Haryana 122015, India | M125: Map
A126: 122 | B126: Infinity Marketing Corporation | C126: Warehouse / Logistics | D126: Store Helper, Housekeeping, Security, Sales Staff | E126: 9899850105 | H126: House No.2962 First Floor, Block C, Sushant Lok Phase I, Sector 43, Gurugram, Haryana 122009, India | M126: Map
A127: 123 | B127: Mamajoyoga | C127: Hotel / OYO | D127: Beautician, Helper, Receptionist, Cleaner | E127: 9810766775 | H127: THE PINNACLE, Golf Course Rd, Horizon Colony, DLF Phase 5, Sector 43, Gurugram, Haryana 122009, India | M127: Map
A128: 124 | B128: Manoj Kumar | C128: Shop / Retail | D128: Store Helper, Housekeeping, Security, Sales Staff | E128: 7383679351 | H128: Olive Studio 1120, Golf Crse Rd, Sector 43, Gurugram, Haryana 122009, India | M128: Map
A129: 125 | B129: Speedex Packers And Movers Gurgaon | C129: Warehouse / Logistics | D129: Loader, Packer, Picker, Warehouse Helper, Delivery | E129: 8796965701 | H129: Shop No 16/D, Sector 43, Gurugram, Haryana 122009, India | M129: Map
A130: 126 | B130: Wheels of Freedom - Buy,Sell,Finance second hand bikes in Gurgaon | C130: Shop / Retail | D130: Store Helper, Housekeeping, Security, Sales Staff | E130: 7985611859 | H130: Opposite, Vyapar Kendra Rd, next to Indian oil petrol pump, Sushant Lok Phase I, Sector 43, Gurugram, Haryana 122009, India | M130: Map
A131: 127 | B131: Zee Jewels | C131: Shop / Retail | D131: Store Helper, Housekeeping, Security, Sales Staff | E131: 9599297140 | H131: Apartment, Sec-43, Hextax Commune, A 904, Sector 43, Gurugram, Haryana 122009, India | M131: Map
A132: 128 | B132: Super77 | C132: Other | D132: Office Boy, Housekeeping, Security, Helper | E132: 9557180240 | F132: 4.7 | G132: 1081 | H132: Human Charging India Pvt. Ltd, UTSAV-100, DLF Phase 5, Sector 43, Gurugram, Haryana 122009, India | M132: Map
A133: 129 | B133: OTWOGYMS | C133: Other | D133: Trainer, Housekeeping, Front Desk | E133: 9911243344 | F133: 4.3 | G133: 376 | H133: Shri Ram Complex, Block C, Sushant Lok Phase I, Sector 43, Gurugram, Haryana 122009, India | M133: Map
A134: 130 | B134: DOULA CLINIC - Best Lactation Consultant In Sector-43, Gurgaon | C134: Other | D134: Ward Boy, Housekeeping, Attendant, Security | E134: 7703969530 | F134: 4.9 | G134: 314 | H134: B-598 Ground Floor, Sushant Lok Phase I, Sector 43, Gurugram, Haryana 122009, India | M134: Map
A135: 131 | B135: Dietician Archana Batra's Clinic | C135: Other | D135: Ward Boy, Housekeeping, Attendant, Security | E135: 9971886474 | F135: 4.9 | G135: 300 | H135: House No. 97 (Lower Ground Floor, Power Grid Township Block-C2, Block C2, Sushant Lok Phase I, Sector 43, Gurugram, Haryana 122009, India | M135: Map
A136: 132 | B136: Grace IVF By Dr. Reubina Singh - IUI, ICSI, IVF Center In Gurgaon | Needle Free IVF In Gurgaon | C136: Other | D136: Ward Boy, Housekeeping, Attendant, Security | E136: 7558095116 | F136: 4.8 | G136: 224 | H136: 1327, Sector 43 Service Rd, Block C, PWO Appartments, Sector 43, Gurugram, Haryana 122009, India | M136: Map
A137: 133 | B137: EduGyani (Institutes and Home Tutors) | C137: Other | D137: Peon, Housekeeping, Security, Attendant | E137: 9315912518 | F137: 4.9 | G137: 221 | H137: C 359, Sushant Lok Phase I, Sector 43, Gurugram, Haryana 122002, India | M137: Map
A138: 134 | B138: Modenta Dental Clinic | C138: Other | D138: Ward Boy, Housekeeping, Attendant, Security | E138: 7837674763 | F138: 5 | G138: 220 | H138: 2772, St Thomas Marg, Block C, Sushant Lok Phase I, Sector 43, Gurugram, Haryana 122009, India | M138: Map
A139: 135 | B139: 𝐒𝐚𝐦𝐩𝐮𝐫𝐧 𝐕𝐚𝐬𝐭𝐮 | The Best Vastu Consultant in Gurgaon, India | C139: Other | D139: Office Boy, Housekeeping, Security, Helper | E139: 9625775679 | F139: 5 | G139: 210 | H139: Ground Floor, 567, Golf Course Rd, Sector 43, Gurugram, Haryana 122009, India | M139: Map
A140: 136 | B140: ErgoAlign Physiotherapy and Chiropractic Clinic - A Unit of Ergowork Healthcare | Sector 43 | Golf Course Road | Gurugram | C140: Other | D140: Ward Boy, Housekeeping, Attendant, Security | E140: 9999802613 | F140: 4.9 | G140: 183 | H140: House no 190 Basement Floor, DLF Phase 5, Sector 43, Gurugram, Haryana 122002, India | M140: Map
A141: 137 | B141: Dr Shiba Kalyan Biswal | Chest Specialist & Pulmonologist in Gurgaon | C141: Other | D141: Office Boy, Housekeeping, Security, Helper | E141: 8826914102 | F141: 4.9 | G141: 168 | H141: Ground Floor, C853, Vyapar Kendra Rd, Block C, Sushant Lok Phase I, Sector 43, Gurugram, Haryana 122009, India | M141: Map
A142: 138 | B142: Studio 694 | C142: Other | D142: Peon, Housekeeping, Security, Attendant | E142: 9811224217 | F142: 4.9 | G142: 162 | H142: 694, Block A, Sushant Lok Phase I, Sector 43, Gurugram, Haryana 122009, India | M142: Map
A143: 139 | B143: Mezzopiano School of Music | C143: Other | D143: Peon, Housekeeping, Security, Attendant | E143: 9810528509 | F143: 4.9 | G143: 145 | H143: 900, Horizon Colony, Sector 43, Gurugram, Haryana 122002, India | M143: Map
... A145: 141 | B145: KLAY DLF Phase 4 - Preschools and Daycare | C145: Other | D145: Peon, Housekeeping, Security, Attendant | E145: 7676708888 | F145: 4.8 | G145: 108 | H145: Nursery Site, 4106, Ashoka Marg, near Galleria Market, DLF Phase IV, Sector 43, Gurugram, Haryana 122009, India | M145: Map

Sheet Sector 44
A1: SWITCH · SECTOR 44 · MOBILE CALL SHEET
A2: Owner/manager mobiles · shifts 1–12 hrs, pay after worker reports · instant replacement | 23 leads · 20 in priority industries (top)
A3: LEADS | B3: =COUNTA(B5:B27) | C3: CONTACTED | D3: =COUNTA(I5:I27) | E3: INTERESTED | F3: =COUNTIF(I5:I27,"Yes") | G3: ORDERS | H3: =COUNTIF(K5:K27,"Yes") | I3: HOURS BOOKED | J3: =SUM(J5:J27)
A4: S.No | B4: Business Name | C4: Target Industry | D4: Suggested Roles (per shift) | E4: Manager Mobile | F4: Rating | G4: Reviews | H4: Address | I4: Interested? | J4: Hours (1-12) | K4: Order Confirmed? | L4: Remarks | M4: Map
A5: 1 | B5: Bamboo chick maker Gurgaon | C5: Shop / Retail | D5: Store Helper, Housekeeping, Security, Sales Staff | E5: 9670812019 | F5: 4.9 | G5: 72 | H5: Shop number 24, Ravidass mandir, Kanhai Colony, Sector 44, Gurugram, Haryana 122003, India | M5: Map
A6: 2 | B6: Nitya tiffin service gurgaon | C6: Restaurant / Food | D6: Kitchen Helper, Cook, Dishwasher, Waiter | E6: 9910292871 | F6: 4.9 | G6: 15 | H6: near Ambedkar cahupal, Kanhai Colony, Sector 44, Gurugram, Haryana 122003, India | M6: Map
A7: 3 | B7: Tattva Wellness Spa Corporate Office | C7: Salon / Spa | D7: Beautician, Helper, Receptionist, Cleaner | E7: 9999120413 | F7: 4.4 | G7: 13 | H7: CLC Tower, Plot 146, Sector 44, Gurugram, Haryana 122003, India | M7: Map
A8: 4 | B8: Soda Shop | C8: Restaurant / Food | D8: Store Helper, Housekeeping, Security, Sales Staff | E8: 9711730015 | F8: 4.4 | G8: 10 | H8: Sec-44, Bhagwan Mahaveer Marg, Kanhai, Sector 44, Gurugram, Haryana 122003, India | M8: Map
A9: 5 | B9: CHAI COTTAGE | C9: Restaurant / Food | D9: Kitchen Helper, Cook, Dishwasher, Waiter | E9: 9871874715 | F9: 4.8 | G9: 6 | H9: 142, Sector 44 Rd, Sector 44, Gurugram, Haryana 122003, India | M9: Map
A10: 6 | B10: Trisu | C10: Salon / Spa | D10: Beautician, Helper, Receptionist, Cleaner | E10: 9351323151 | F10: 2.3 | G10: 3 | H10: 4th Floor, Plot 146, CLC Tower, 146, Sector 44, Gurugram, Haryana 122003, India | M10: Map
A11: 7 | B11: 9 Dragon Chinese Food | C11: Restaurant / Food | D11: Kitchen Helper, Cook, Dishwasher, Waiter | E11: 9990003052 | F11: 5 | G11: 1 | H11: C3XG+PRC, Kanhai, Kanhai Colony, Sector 44, Gurugram, Haryana 122003, India | M11: Map
A12: 8 | B12: Chicken Biryani | C12: Restaurant / Food | D12: Kitchen Helper, Cook, Dishwasher, Waiter | E12: 8171830708 | F12: 5 | G12: 1 | H12: Main Market, Sector 44 Rd, Kanahi, Gurugram, Haryana 122003, India | M12: Map
A13: 9 | B13: Jitnedra Choudhari Shop | C13: Restaurant / Food | D13: Kitchen Helper, Cook, Dishwasher, Waiter | E13: 7011713132 | F13: 5 | G13: 1 | H13: Shop No 1, Sector 44, Gurugram, Haryana 122003, India | M13: Map
A14: 10 | B14: Saksham Enterprises | C14: Shop / Retail | D14: Store Helper, Housekeeping, Security, Sales Staff | E14: 9289971309 | F14: 5 | G14: 1 | H14: Shop No 55, Huda City Center, Metro Station, Sector 44, Gurugram, Haryana 122009, India | M14: Map
A15: 11 | B15: Devender Garments | C15: Shop / Retail | D15: Store Helper, Housekeeping, Security, Sales Staff | E15: 8368670083 | F15: 4 | G15: 1 | H15: Devender Garments, Metro, near Huda, Sector 44, Gurugram, Haryana 122009, India | M15: Map
A16: 12 | B16: Pooja Khera Shop | C16: Shop / Retail | D16: Store Helper, Housekeeping, Security, Sales Staff | E16: 7053602318 | F16: 1 | G16: 1 | H16: Shop No 90, Sector 44, Gurugram, Haryana 122003, India | M16: Map
A17: 13 | B17: Anuj Shop | C17: Restaurant / Food | D17: Store Helper, Housekeeping, Security, Sales Staff | E17: 8595274954 | H17: 18, Huda Metro, near Shiv Mandir, Sector 44, Gurugram, Haryana 122003, India | M17: Map
A18: 14 | B18: Efrail Qureshi Halal Meat Shop | C18: Restaurant / Food | D18: Kitchen Helper, Cook, Dishwasher, Waiter | E18: 8397011787 | H18: Shop No,4, near government school, Kanhai Colony, Sector 44, Gurugram, Haryana 122003, India | M18: Map
A19: 15 | B19: Manish | C19: Restaurant / Food | D19: Store Helper, Housekeeping, Security, Sales Staff | E19: 8222820179 | H19: Cng, Sector 44, Gurugram, Haryana 122009, India | M19: Map
A20: 16 | B20: Narendra pal | C20: Warehouse / Logistics | D20: Office Boy, Housekeeping, Security, Helper | E20: 8445779879 | H20: Kanhai, Sector 44, Gurugram, Haryana 122003, India | M20: Map
A21: 17 | B21: Nawab Fast Food | C21: Restaurant / Food | D21: Kitchen Helper, Cook, Dishwasher, Waiter | E21: 9896810063 | H21: Shop No, 5, Sector 44 Rd, Kanhai, Sector 45, Gurugram, Haryana 122003, India | M21: Map
A22: 18 | B22: Prem Shankar Shop | C22: Shop / Retail | D22: Store Helper, Housekeeping, Security, Sales Staff | E22: 8750450012 | H22: Shop No 45, near Gtown Wine House, Sector 44, Gurugram, Haryana 122003, India | M22: Map
A23: 19 | B23: Rajnesh Shop | C23: Shop / Retail | D23: Store Helper, Housekeeping, Security, Sales Staff | E23: 8130809370 | H23: Petrol Pump, 55, Sector 44 Rd, Sector 44, Gurugram, Haryana 122003, India | M23: Map
A24: 20 | B24: Ransingh | C24: Restaurant / Food | D24: Kitchen Helper, Cook, Dishwasher, Waiter | E24: 7253094827 | H24: Kanhai, Sector 44, Gurugram, Haryana 122009, India | M24: Map
A25: 21 | B25: Kaizen Training Solutions Pvt. Ltd. | C25: Other | D25: Peon, Housekeeping, Security, Attendant | E25: 9899462534 | F25: 4.9 | G25: 771 | H25: 4th floor, CLC Tower, Plot 146, Sector 44, Gurugram, Haryana 122003, India | M25: Map
A26: 22 | B26: Jaro Education | C26: Other | D26: Office Boy, Housekeeping, Security, Helper | E26: 8976850300 | F26: 4.1 | G26: 314 | H26: Ground Floor, CLC Tower, Plot no 146, Sector 44, Gurugram, Haryana 122003, India | M26: Map
A27: 23 | B27: Peacock Solar | C27: Other | D27: Office Boy, Housekeeping, Security, Helper | E27: 8739938888 | F27: 4.8 | G27: 140 | H27: 146, Sector 44, Gurugram, Haryana 122003, India | M27: Map

Sheet Sector 45
A1: SWITCH · SECTOR 45 · MOBILE CALL SHEET
A2: Owner/manager mobiles · shifts 1–12 hrs, pay after worker reports · instant replacement | 14 leads · 11 in priority industries (top)
A3: LEADS | B3: =COUNTA(B5:B18) | C3: CONTACTED | D3: =COUNTA(I5:I18) | E3: INTERESTED | F3: =COUNTIF(I5:I18,"Yes") | G3: ORDERS | H3: =COUNTIF(K5:K18,"Yes") | I3: HOURS BOOKED | J3: =SUM(J5:J18)
A4: S.No | B4: Business Name | C4: Target Industry | D4: Suggested Roles (per shift) | E4: Manager Mobile | F4: Rating | G4: Reviews | H4: Address | I4: Interested? | J4: Hours (1-12) | K4: Order Confirmed? | L4: Remarks | M4: Map
A5: 1 | B5: Flora Residency | C5: PG / Hostel | D5: Housekeeping, Cook, Caretaker, Security | E5: 9311266960 | F5: 4.8 | G5: 2117 | H5: Plot No. 682P, Captain Ganpat Ram Yadav Marg, Sector 45, Gurugram, Haryana 122003, India | M5: Map
A6: 2 | B6: Patanjali Ayurvedic | C6: Supermarket / Grocery | D6: Store Helper, Housekeeping, Security, Sales Staff | E6: 8287909445 | F6: 4.7 | G6: 53 | H6: 44, Bhagwan Mahaveer Marg, Kanhai, Sector D, Sector 45, Gurugram, Haryana 122003, India | M6: Map
A7: 3 | B7: Dayaram Halwai | C7: Restaurant / Food | D7: Office Boy, Housekeeping, Security, Helper | E7: 9718678076 | F7: 4 | G7: 4 | H7: Shop No 6, Kanhai Village, Near Shiv Mandir, Gurugram, NCR, Sector 45, Region, Gurugram, Haryana 122003, India | M7: Map
A8: 4 | B8: Shri Shyam Atta Chakki | C8: Restaurant / Food | D8: Machine Operator, Helper, Loader, Packer | E8: 9818542735 | F8: 5 | G8: 2 | H8: Shop No 84, Huda Market Rd, Block B, Sector 45, Gurugram, Haryana 122003, India | M8: Map
A9: 5 | B9: Tripti Beauty parlour | C9: Salon / Spa | D9: Beautician, Helper, Receptionist, Cleaner | E9: 8319755288 | F9: 5 | G9: 2 | H9: Kanhai sec 45, house no.322, bikaner hotal, vinod medical 44, Bhagwan Mahaveer Marg, near ramleela ground, Sector 45, Gurugram, Haryana 122003, India | M9: Map
A10: 6 | B10: JBMR FASHION ZONE | C10: Shop / Retail | D10: Store Helper, Housekeeping, Security, Sales Staff | E10: 7207827304 | F10: 5 | G10: 1 | H10: Shop no-07, ramleela ground, Bhagwan Mahaveer Marg, Kanhai, ghav, Sector 45, Gurugram, Haryana 122003, India | M10: Map
A11: 7 | B11: Bhullar Car place | C11: Shop / Retail | D11: Mechanic Helper, Cleaner, Washer | E11: 9813659400 | H11: 673P, Vikas Marg, near Vetic Clinic, Sector 45, Gurugram, Haryana 122003, India | M11: Map
A12: 8 | B12: Gaurav Paint & Hardware | C12: Shop / Retail | D12: Store Helper, Housekeeping, Security, Sales Staff | E12: 9910932552 | H12: Shop No. 8, Kanhai Market Sector 45, Shiv Mandir, Village, near Govt. High Schooll, Kanhal, Gurugram, Haryana 122003, India | M12: Map
A13: 9 | B13: Nandani popcorne center | C13: Restaurant / Food | D13: Kitchen Helper, Cook, Dishwasher, Waiter | E13: 8923191321 | H13: near by shiv mandir, Kanhai, Sector 45, Gurugram, Haryana 122003, India | M13: Map
A14: 10 | B14: Shree Shyam Juice and Shake Corner | C14: Restaurant / Food | D14: Store Helper, Housekeeping, Security, Sales Staff | E14: 9289807750 | H14: opposite Shiv Mandir, near Ramlila Ground, Kanhai, Sector 45, Gurugram, Haryana 122003, India | M14: Map
A15: 11 | B15: Surjeet Kumar Shop | C15: Restaurant / Food | D15: Store Helper, Housekeeping, Security, Sales Staff | E15: 8318754227 | H15: 11 Sec 43, Kanhai, Sector 45, Gurugram, Haryana 122003, India | M15: Map
A16: 12 | B16: Vetic Pet Clinic Sec-45 Gurgaon | C16: Other | D16: Ward Boy, Housekeeping, Attendant, Security | E16: 8750033894 | F16: 4.5 | G16: 1092 | H16: Plot No. - 675/778, Captain Ganpat Ram Yadav Marg, near Arihant Hospital, Sector 45, Gurugram, Haryana 122003, India | M16: Map
A17: 13 | B17: TIME INFRA | C17: Other | D17: Office Boy, Housekeeping, Security, Helper | E17: 9811000556 | F17: 4.4 | G17: 9 | H17: 677, Sector 45, Gurugram, Haryana 122003, India | M17: Map
A18: 14 | B18: Kumaar Properties | C18: Other | D18: Office Boy, Housekeeping, Security, Helper | E18: 9718865156 | F18: 5 | G18: 8 | H18: Plot no. 676, Sector 45, Gurugram, Haryana 122003, India | M18: Map

Sheet Sector 50
A1: SWITCH · SECTOR 50 · MOBILE CALL SHEET
A2: Owner/manager mobiles · shifts 1–12 hrs, pay after worker reports · instant replacement | 20 leads · 17 in priority industries (top)
A3: LEADS | B3: =COUNTA(B5:B24) | C3: CONTACTED | D3: =COUNTA(I5:I24) | E3: INTERESTED | F3: =COUNTIF(I5:I24,"Yes") | G3: ORDERS | H3: =COUNTIF(K5:K24,"Yes") | I3: HOURS BOOKED | J3: =SUM(J5:J24)
A4: S.No | B4: Business Name | C4: Target Industry | D4: Suggested Roles (per shift) | E4: Manager Mobile | F4: Rating | G4: Reviews | H4: Address | I4: Interested? | J4: Hours (1-12) | K4: Order Confirmed? | L4: Remarks | M4: Map
A5: 1 | B5: Wood Factory | C5: Shop / Retail | D5: Machine Operator, Helper, Loader, Packer | E5: 8130971530 | F5: 4.8 | G5: 79 | H5: LOTUS VALLEY SCHOOL, Tigra Rd, Nirvana Country, Sector 50, Gurugram, Haryana 122001, India | M5: Map
A6: 2 | B6: APNA KITCHEN | C6: Restaurant / Food | D6: Kitchen Helper, Cook, Dishwasher, Waiter | E6: 8178827380 | F6: 4.8 | G6: 24 | H6: D18 ,FF, Extn, D Block Rd, near Lotus Valley International School, Spring Floors, Mayfield Garden, Sector 50, Gurugram, Haryana 122018, India | M6: Map
A7: 3 | B7: National Generator Works | C7: Shop / Retail | D7: Store Helper, Housekeeping, Security, Sales Staff | E7: 9810537518 | F7: 4.9 | G7: 21 | H7: 1st floor, 110, woodstock floors, Nirvana Country, Sector 50, Gurugram, Haryana 122018, India | M7: Map
A8: 4 | B8: Resonate Psychological And wellness Services | C8: Salon / Spa | D8: Ward Boy, Housekeeping, Attendant, Security | E8: 8810280142 | F8: 4.8 | G8: 19 | H8: first floor, 205, Deerwood Chase, Nirvana Country, Sector 50, Gurugram, Haryana 122018, India | M8: Map
A9: 5 | B9: Epicura Culinary | C9: Restaurant / Food | D9: Kitchen Helper, Cook, Dishwasher, Waiter | E9: 9999942995 | F9: 5 | G9: 11 | H9: Deerwood Chase, Nirvana Country, Sector 50, Gurugram, Haryana 122018, India | M9: Map
A10: 6 | B10: Janta dhaba | C10: Restaurant / Food | D10: Kitchen Helper, Cook, Dishwasher, Waiter | E10: 9650309832 | F10: 4.3 | G10: 11 | H10: C37C+84P Janta dhaba, The Cl N Ave, Nirvana Country, Sector 50, Gurugram, Haryana 122018, India | M10: Map
A11: 7 | B11: ALL Car CSD & CPC | C11: Shop / Retail | D11: Mechanic Helper, Cleaner, Washer | E11: 9810659058 | F11: 4.9 | G11: 8 | H11: Silverton Towers, Golf Course Ext Rd, Nirvana Country, Sector 50, Gurugram, Haryana 122018, India | M11: Map
A12: 8 | B12: Dtdc courier- international Domestic | C12: Warehouse / Logistics | D12: Loader, Packer, Picker, Warehouse Helper, Delivery | E12: 7982862885 | F12: 5 | G12: 7 | H12: SHOP. NO. 4. 1RD FLOOR, BHARDWAJ MARKET NORTH AND, GATE NO, SECTOR - 50 ROAD, opposite TAGORE PUBLIC SCHOOL, The Close South, Sector 57, Gurugram, Haryana 122001, India | M12: Map
A13: 9 | B13: Pixel Prints | C13: Shop / Retail | D13: Machine Operator, Helper, Loader, Packer | E13: 9560952153 | F13: 4.9 | G13: 7 | H13: Tower-7, 1503, sec-50, Escape, Nirvana Country, Sector 50, Gurugram, Haryana 122018, India | M13: Map
A14: 10 | B14: DTDC MOVERS AND PACKERS | C14: Warehouse / Logistics | D14: Loader, Packer, Picker, Warehouse Helper, Delivery | E14: 9654911811 | F14: 4.8 | G14: 4 | H14: Deerwood Chase, Nirvana Country, Sector 50, Gurugram, Haryana 122018, India | M14: Map
A15: 11 | B15: Somveer Special Chaat Bhandar | C15: Restaurant / Food | D15: Kitchen Helper, Cook, Dishwasher, Waiter | E15: 9456860716 | F15: 5 | G15: 3 | H15: C345+QMQ, Sector 50, Gurugram, Haryana 122018, India | M15: Map
A16: 12 | B16: Hans Tour And Travels | C16: Warehouse / Logistics | D16: Office Boy, Housekeeping, Security, Helper | E16: 9871029498 | F16: 1 | G16: 2 | H16: Opposite The Close, Near Lotus Valley School, Nirvana Country, South City II, Sector 50, Gurugram, Haryana 122011, India | M16: Map
... A18: 14 | B18: PUSHPENDRA KUMAR | C18: Restaurant / Food | D18: Kitchen Helper, Cook, Dishwasher, Waiter | E18: 9758250739 | F18: 5 | G18: 1 | H18: C379+6MG, Main Rd, Nirvana Country, Sector 50, Gurugram, Haryana 122018, India | M18: Map
A19: 15 | B19: ELACHI STORE | C19: Supermarket / Grocery | D19: Store Helper, Housekeeping, Security, Sales Staff | E19: 8918949680 | H19: Tigra Vlg Rd, Block D, Sector 50, Gurugram, Haryana 122011, India | M19: Map
A20: 16 | B20: Gati Courier Bike And Car Transport Service Gati Movers And Packers Gurgaon | C20: Warehouse / Logistics | D20: Loader, Packer, Picker, Warehouse Helper, Delivery | E20: 9518423953 | H20: Unitech Business Zone, 345, Golf Course Ext Rd, Nirvana Country, Sector 50, Gurugram, Haryana 122018, India | M20: Map
A21: 17 | B21: Nariyal Shop | C21: Shop / Retail | D21: Store Helper, Housekeeping, Security, Sales Staff | E21: 7983454751 | H21: Nirvana Rd, Nirvana Country, Sector 50, Gurugram, Haryana 122011, India | M21: Map
A22: 18 | B22: Ritzart Art and Craft classes | C22: Other | D22: Peon, Housekeeping, Security, Attendant | E22: 9884925016 | F22: 4.9 | G22: 143 | H22: UNITECH ESCAPE, Sector 50, Gurugram, Haryana 122018, India | M22: Map
A23: 19 | B23: Bella Mente Preschool Sector 50 | Preschool & Daycare - Nirvana Country | C23: Other | D23: Peon, Housekeeping, Security, Attendant | E23: 8586000196 | F23: 4.8 | G23: 124 | H23: NS4, Deerwood, Espace, Nirvana Country, Sector 50, Gurugram, Haryana 122018, India | M23: Map
A24: 20 | B24: Rewire Music Academy | C24: Other | D24: Peon, Housekeeping, Security, Attendant | E24: 9773725122 | F24: 5 | G24: 119 | H24: E-27, Rosewood City Rd, Sector 50, Gurugram, Haryana 122018, India | M24: Map

Sheet Sector 52
A1: SWITCH · SECTOR 52 · MOBILE CALL SHEET
A2: Owner/manager mobiles · shifts 1–12 hrs, pay after worker reports · instant replacement | 160 leads · 144 in priority industries (top)
A3: LEADS | B3: =COUNTA(B5:B164) | C3: CONTACTED | D3: =COUNTA(I5:I164) | E3: INTERESTED | F3: =COUNTIF(I5:I164,"Yes") | G3: ORDERS | H3: =COUNTIF(K5:K164,"Yes") | I3: HOURS BOOKED | J3: =SUM(J5:J164)
A4: S.No | B4: Business Name | C4: Target Industry | D4: Suggested Roles (per shift) | E4: Manager Mobile | F4: Rating | G4: Reviews | H4: Address | I4: Interested? | J4: Hours (1-12) | K4: Order Confirmed? | L4: Remarks | M4: Map
A5: 1 | B5: KARTIK DRIVER SERVICES | C5: Warehouse / Logistics | D5: Office Boy, Housekeeping, Security, Helper | E5: 9990385588 | F5: 4.7 | G5: 2186 | H5: Shop No.- 3, Dhani Market(Near Indian Overseas Bank), Sec.-52 A, 122003, Sarswati Kunj II, Wazirabad, Sector 52, Gurugram, Haryana 122003, India | M5: Map
A6: 2 | B6: iVenus - Apple Authorised Reseller, Ardee Mall, Gurugram | C6: Shop / Retail | D6: Store Helper, Housekeeping, Security, Sales Staff | E6: 8419002400 | F6: 4.9 | G6: 2122 | H6: A-10 Lower Ground Floor, Ardee Mall, Ardee City, Sector 52, Gurugram, Haryana 122003, India | M6: Map
A7: 3 | B7: Geetanjali Salon - Ardee City Mall, Gurugram | C7: Salon / Spa | D7: Store Helper, Housekeeping, Security, Sales Staff | E7: 8448120310 | F7: 4.4 | G7: 1274 | H7: No A-7/8, Second Floor, Ardee City Mall, nearby Crocs Footwear, Ardee City, Sector 52, Gurugram, Haryana 122003, India | M7: Map
A8: 4 | B8: Blackberrys | C8: Shop / Retail | D8: Store Helper, Housekeeping, Security, Sales Staff | E8: 9619048930 | F8: 4.9 | G8: 974 | H8: Shop No A9, Ardee Mall, Wazirabad, Sector 52, Gurugram, Haryana 122003, India | M8: Map
A9: 5 | B9: A.S. Spare Parts & Bike accessories | C9: Salon / Spa | D9: Store Helper, Housekeeping, Security, Sales Staff | E9: 8882239879 | F9: 4.9 | G9: 696 | H9: Shop no 5, opp. Lakshay tent house, Wazirabad, Sector 52, Gurugram, Haryana 122003, India | M9: Map
A10: 6 | B10: Taco Bell | C10: Restaurant / Food | D10: Kitchen Helper, Cook, Dishwasher, Waiter | E10: 8448992835 | F10: 3.8 | G10: 688 | H10: Shop No. A-18, 3rd Floor, Ardee Mall, Block B, Ardee City, Sector 52, Gurugram, Haryana 122003, India | M10: Map
A11: 7 | B11: Sahil Sofa Repair(Recliner Sofa Repair, Sofa Cover, Sofa Upholstery Shop, Gurugram | C11: Shop / Retail | D11: Store Helper, Housekeeping, Security, Sales Staff | E11: 9899362008 | F11: 4.8 | G11: 654 | H11: Shop No 1, near Sultan Singh Complex, Wazirabad, Sector 52, Gurugram, Haryana 122003, India | M11: Map
A12: 8 | B12: Dr Pragya Punj | MBBS, MD Dermatology | ECFMG (USA) | Skin, Hair, Laser and Aesthetics Specialist | Skin Surgeon | C12: Salon / Spa | D12: Office Boy, Housekeeping, Security, Helper | E12: 9693874176 | F12: 4.8 | G12: 377 | H12: Villa no. 9, near Ardee mart, Block C, Ardee City, Sector 52, Gurugram, Haryana 122003, India | M12: Map
A13: 9 | B13: Royal Ac Services | C13: Shop / Retail | D13: Office Boy, Housekeeping, Security, Helper | E13: 8800180664 | F13: 4.7 | G13: 366 | H13: Shop 16, near Sultan Singh complex, Wazirabad, Sector 52, Gurugram, Haryana 122003, India | M13: Map
A14: 10 | B14: Frontier Auto World Pvt. Ltd. (Workshop) | C14: Shop / Retail | D14: Store Helper, Housekeeping, Security, Sales Staff | E14: 7290015735 | F14: 4.4 | G14: 353 | H14: Wazirabad, sector -52 Khasra No. 2482-84 Nr. Aardee City Mall Sector- 52 Gurgaon Haryana IN 122002, 2482, 84, Ardee City Rd, Block B, Ardee City, Sector 52, Gurugram, Haryana 122011, India | M14: Map
A15: 11 | B15: Hotel Comfy Cottage | C15: Hotel / OYO | D15: Housekeeping, Room Boy, Kitchen Helper, Front Desk | E15: 9220395676 | F15: 4.9 | G15: 307 | H15: H no 510, near Artemis hospital, Koyal Vihar, Sector 52, Gurugram, Haryana 122003, India | M15: Map
A16: 12 | B16: Zolo Artemis - PG in Sector 52 Gurgaon | C16: PG / Hostel | D16: Housekeeping, Cook, Caretaker, Security | E16: 8884518010 | F16: 3.8 | G16: 291 | H16: Plot No. 181, Lane Number D2, near Ardee School, Block D, Indira Colony 2, Sector 52, Gurugram, Haryana 122003, India | M16: Map
... A114: 110 | B114: Sandeep Electrical and repairing center | C114: Shop / Retail | D114: Store Helper, Housekeeping, Security, Sales Staff | E114: 8084154699 | F114: 1 | G114: 1 | H114: Khatu Shyam Mandir Rd, Parsvnath Exotica, Sector 52A, Gurugram, Haryana 122011, India | M114: Map
A115: 111 | B115: 1RK Room available | C115: Hotel / OYO | D115: Housekeeping, Room Boy, Kitchen Helper, Front Desk | E115: 8802327906 | H115: 1, Koyal Vihar, Sector 52, Gurugram, Haryana 122003, India | M115: Map
A116: 112 | B116: AJAY SALOON SHOP | C116: Salon / Spa | D116: Store Helper, Housekeeping, Security, Sales Staff | E116: 7428430879 | H116: Shop No. 4, Manohara Marg, near Union Bank Of India, Wazirabad, Sector 52, Gurugram, Haryana 122003, India | M116: Map
A117: 113 | B117: Apnaghar whitewash | C117: Hotel / OYO | D117: Housekeeping, Room Boy, Kitchen Helper, Front Desk | E117: 9999727653 | H117: 639 block, A/1/B, Sarswati Kunj II, Wazirabad, Sector 52, Gurugram, Haryana 122003, India | M117: Map
A118: 114 | B118: Blue House India | C118: Restaurant / Food | D118: Kitchen Helper, Cook, Dishwasher, Waiter | E118: 8852002222 | H118: E - 11, Ardee City Gate Number 2 Rd, Sarswati Kunj II, Wazirabad, Sector 52, Gurugram, Haryana 122003, India | M118: Map
A119: 115 | B119: Cut & Looks Men Salon | C119: Restaurant / Food | D119: Kitchen Helper, Cook, Dishwasher, Waiter | E119: 9891865232 | H119: 439, Wazirabad, Manohara Marg, Gurugram, NCR, Wazirabad, Sector 52, Region, Gurugram, Haryana 122003, India | M119: Map
A120: 116 | B120: Glam Beauty At Home | C120: Salon / Spa | D120: Beautician, Helper, Receptionist, Cleaner | E120: 9310746669 | H120: 902, Saraswati Kunj Rd, near yadav complex, Parsvnath Exotica, Wazirabad, Sector 52, Gurugram, Haryana 122003, India | M120: Map
A121: 117 | B121: indian hardware | C121: Shop / Retail | D121: Store Helper, Housekeeping, Security, Sales Staff | E121: 9971585201 | H121: C3JP+FC4, Wazirabad Rd, Wazirabad, Sector 52, Gurugram, Haryana 122003, India | M121: Map
A122: 118 | B122: JP Carrier Building Material Supplier | C122: Shop / Retail | D122: Store Helper, Housekeeping, Security, Sales Staff | E122: 9811186084 | H122: Sector-52 Side By Atcost Kisan Mandi, near Artemis Hospital, Wazirabad, Sector 52, Gurugram, Haryana 122003, India | M122: Map
A123: 119 | B123: ME LIKE SAGUN BEAUTY PARLOUR | C123: Salon / Spa | D123: Beautician, Helper, Receptionist, Cleaner | E123: 9811180041 | H123: Shop No-1, near Pracheen Shiv Mandir, Wazirabad, Sector 52, Gurugram, Haryana 122003, India | M123: Map
A124: 120 | B124: Meena enterprises | C124: Shop / Retail | D124: Store Helper, Housekeeping, Security, Sales Staff | E124: 7827345757 | H124: Wazirabad, Sector 52, Gurugram, Haryana 122003, India | M124: Map
A125: 121 | B125: Mohd Noor Alam | C125: Warehouse / Logistics | D125: Office Boy, Housekeeping, Security, Helper | E125: 8757953213 | H125: CNG Pump Sec52 A, near CNG Pump, Sector 52A, Gurugram, Haryana 122011, India | M125: Map
A126: 122 | B126: Mosharem Dafadar Fresh Fruit Shop | C126: Supermarket / Grocery | D126: Store Helper, Housekeeping, Security, Sales Staff | E126: 9990858476 | H126: DLF Phase 5, Sector 52, Gurugram, Haryana 122011, India | M126: Map
... A148: 144 | B148: सुमन वस्त्रालय एण्ड कोस्मैटिक सेन्टर | C148: Shop / Retail | D148: Store Helper, Housekeeping, Security, Sales Staff | E148: 9971401515 | H148: Sarswati Kunj II, Wazirabad, Sector 52, Gurugram, Haryana 122003, India | M148: Map
A149: 145 | B149: PROFESSIONAL HYUNDAI GURUGRAM | C149: Other | D149: Mechanic Helper, Cleaner, Washer | E149: 8527197803 | F149: 4.8 | G149: 5063 | H149: near IOC Petrol Pump, Wazirabad, Sector 52A, Gurugram, Haryana 122003, India | M149: Map
A150: 146 | B150: Volkswagen Gurgaon | C150: Other | D150: Mechanic Helper, Cleaner, Washer | E150: 9540019795 | F150: 4.7 | G150: 2938 | H150: Khasra Nos. 2482-2484 Mall, Dhani, Wazirabad Rd, near Ardee City, Sector 52A, Gurugram, Haryana 122011, India | M150: Map
A151: 147 | B151: Trinetra Vision Caare || Dr ( Major) Shuchi Verma best eye specialist best cataract and lasik,eye surgeon specialist doctor | C151: Other | D151: Ward Boy, Housekeeping, Attendant, Security | E151: 9871909266 | F151: 4.9 | G151: 827 | H151: TRINETRA VISION CAARE Villa B1/01, Palm Grv Hts Dr Dr, no 1, Ardee mall, 1 Road, near Ardee Mall Road, Block C, Ardee City, Sector 52, Gurugram, Haryana 122011, India | M151: Map
A152: 148 | B152: KALRA MOTORS-CAR AUTO PARTS-CAR WORKSHOP 🚗 | C152: Other | D152: Store Helper, Housekeeping, Security, Sales Staff | E152: 9910561996 | F152: 4.2 | G152: 556 | H152: Near wazirabad subzi mandi, Wazirabad, Sector 52, Gurugram, Haryana 122003, India | M152: Map
A153: 149 | B153: 𝗠 𝐍 𝗛𝗢𝐌𝐄 𝐂𝐀𝐑𝐄 𝐏𝐕𝐓 𝐋𝐓𝐃 | C153: Other | D153: Ward Boy, Housekeeping, Attendant, Security | E153: 8512067764 | F153: 5 | G153: 433 | H153: H No 360, near by prachin Shiv mandir, Sarswati Kunj II, Wazirabad, Sector 52, Gurugram, Haryana 122003, India | M153: Map
A154: 150 | B154: Maruti Suzuki Service (Rohan Motors) | C154: Other | D154: Mechanic Helper, Cleaner, Washer | E154: 8071649094 | F154: 4.1 | G154: 400 | H154: 2482/84 Sector-52a, Wazirabad Village Rd, opp. Aardi City, Mall, Gurugram, Haryana 122011, India | M154: Map
A155: 151 | B155: Gym armour | C155: Other | D155: Trainer, Housekeeping, Front Desk | E155: 7011331866 | F155: 4.8 | G155: 385 | H155: Sadwa Ram Marg, Sarswati Kunj II, Wazirabad, Sector 52, Gurugram, Haryana 122003, India | M155: Map
A156: 152 | B156: Wheels World, Gurgaon | C156: Other | D156: Store Helper, Housekeeping, Security, Sales Staff | E156: 7949290983 | F156: 4.7 | G156: 298 | H156: Indian oil petrol pump sec-52, near Hyundai work shop, Sector 52A, Gurugram, Haryana 122011, India | M156: Map
A157: 153 | B157: Mamta Healthcare | C157: Other | D157: Ward Boy, Housekeeping, Attendant, Security | E157: 9990456804 | F157: 4.9 | G157: 292 | H157: Wazirabad Rd, Wazirabad, Sector 52, Gurugram, Haryana 122003, India | M157: Map
A158: 154 | B158: Gym 52 By The Workout Factory | C158: Other | D158: Trainer, Housekeeping, Front Desk | E158: 9810004191 | F158: 5 | G158: 275 | H158: 1867p, opposite Hcc Cng Pump, near Ardee City Gate Number 2 Road, Sarswati Kunj II, Wazirabad, Sector 52, Gurugram, Haryana 122003, India | M158: Map
A159: 155 | B159: GoFitz Dance & Fitness Academy | C159: Other | D159: Trainer, Housekeeping, Front Desk | E159: 6264246995 | F159: 4.9 | G159: 239 | H159: C10/1, near gate no.3, Block D, Ardee City, Sector 52, Gurugram, Haryana 122003, India | M159: Map
A160: 156 | B160: Star Gymnastics Academy | C160: Other | D160: Trainer, Housekeeping, Front Desk | E160: 9560544604 | F160: 4.8 | G160: 200 | H160: Plot 524, Bhohra Niwash, sec 52, Sector 52, Gurugram, Haryana 122003, India | M160: Map
... A164: 160 | B164: Robins Physiocare , Best Stroke Rehab in gurugram , Best Neuro rehab , pain management | C164: Other | D164: Ward Boy, Housekeeping, Attendant, Security | E164: 8586854043 | F164: 5 | G164: 131 | H164: B1/01, near Ardee Mart, Block B, Block C, Ardee City, Sector 52, Gurugram, Haryana 122011, India | M164: Map

Sheet Sector 53
A1: SWITCH · SECTOR 53 · MOBILE CALL SHEET
A2: Owner/manager mobiles · shifts 1–12 hrs, pay after worker reports · instant replacement | 73 leads · 66 in priority industries (top)
A3: LEADS | B3: =COUNTA(B5:B77) | C3: CONTACTED | D3: =COUNTA(I5:I77) | E3: INTERESTED | F3: =COUNTIF(I5:I77,"Yes") | G3: ORDERS | H3: =COUNTIF(K5:K77,"Yes") | I3: HOURS BOOKED | J3: =SUM(J5:J77)
A4: S.No | B4: Business Name | C4: Target Industry | D4: Suggested Roles (per shift) | E4: Manager Mobile | F4: Rating | G4: Reviews | H4: Address | I4: Interested? | J4: Hours (1-12) | K4: Order Confirmed? | L4: Remarks | M4: Map
A5: 1 | B5: Tipsyy inn Suites 007 | C5: Hotel / OYO | D5: Housekeeping, Room Boy, Kitchen Helper, Front Desk | E5: 8810592147 | F5: 4.3 | G5: 309 | H5: plot no. 64A, saraswati kunj, Golf Course Rd, IILM Institute, Sector 53, Gurugram, Haryana 122011, India | M5: Map
A6: 2 | B6: LEVO – Dermatology | Salon | Spa | C6: Salon / Spa | D6: Beautician, Helper, Receptionist, Cleaner | E6: 8800544600 | F6: 4.4 | G6: 282 | H6: Entry From IBIS Hotel Entry Gate, Pegasus One, Golf Course Rd, Parsvnath Exotica, Sector 53, Gurugram, Haryana 122011, India | M6: Map
A7: 3 | B7: AH SO YUM | C7: Restaurant / Food | D7: Kitchen Helper, Cook, Dishwasher, Waiter | E7: 7303200824 | F7: 4.2 | G7: 264 | H7: C3RV+JRW, Parsvnath Exotica, DLF Phase 5, Sector 53, Gurugram, Haryana 122011, India | M7: Map
A8: 4 | B8: GIVA Silver & Gold Jewellery | Central Plaza Sector 53, Gurugram | C8: Shop / Retail | D8: Store Helper, Housekeeping, Security, Sales Staff | E8: 9035854969 | F8: 4.9 | G8: 247 | H8: G-16, Central Plaza Mall, Golf Course Rd, Parsvnath Exotica, DLF Phase 5, Sector 53, Gurugram, Haryana 122011, India | M8: Map
A9: 5 | B9: Tawa & Tadka Caterers | C9: Restaurant / Food | D9: Kitchen Helper, Cook, Dishwasher, Waiter | E9: 9650106661 | F9: 4.9 | G9: 118 | H9: 55,Saraswati Kunj, Golf Course Rd, IILM Institute, Sector 53, Gurugram, Haryana 122011, India | M9: Map
A10: 6 | B10: Sai tour and travels | C10: Warehouse / Logistics | D10: Office Boy, Housekeeping, Security, Helper | E10: 8744048888 | F10: 4.8 | G10: 112 | H10: Plot no. 1095, Saraswati Kunj Rd, opp. Paras Hospital, Parsvnath Exotica, DLF Phase 5, Sector 53, Gurugram, Haryana 122003, India | M10: Map
A11: 7 | B11: Dwellr Luxury Stays | C11: Hotel / OYO | D11: Housekeeping, Room Boy, Kitchen Helper, Front Desk | E11: 9911708119 | F11: 4.9 | G11: 60 | H11: 1612, Saraswati Kunj Rd, IILM Institute, Sector 53, Gurugram, Haryana 122011, India | M11: Map
A12: 8 | B12: Swear By Biryani | C12: Restaurant / Food | D12: Kitchen Helper, Cook, Dishwasher, Waiter | E12: 8800876886 | F12: 4.3 | G12: 58 | H12: Parsvnath Exotica, DLF Phase 5, Sector 53, Gurugram, Haryana 122011, India | M12: Map
A13: 9 | B13: Avni Logistic Door To Door Service Pvt.(Packers and Movers in Gurgaon packers and Movers sector 53 Gurgaon car transport | C13: Warehouse / Logistics | D13: Loader, Packer, Picker, Warehouse Helper, Delivery | E13: 8929436492 | F13: 5 | G13: 54 | H13: Packers and Movers in Gurgaon packers and Movers, Ground Floor, car transport services, TOWER-C, C 002, DLF Phase 5, Sector 53, Gurugram, Haryana 122009, India | M13: Map
A14: 10 | B14: Urbanroomz Coliving PG | C14: PG / Hostel | D14: Housekeeping, Cook, Caretaker, Security | E14: 7678336489 | F14: 2.8 | G14: 48 | H14: Plot No.138 E, Saraswati kunj, Golf Course Rd, Parsvnath Exotica, DLF Phase 5, Sector 53, Gurugram, Haryana 122011, India | M14: Map
A15: 11 | B15: Meals & Memories | C15: Restaurant / Food | D15: Kitchen Helper, Cook, Dishwasher, Waiter | E15: 9717071985 | F15: 3.8 | G15: 44 | H15: Khatu Shyam Mandir Rd, Parsvnath Exotica, DLF Phase 5, Sector 53, Gurugram, Haryana 122011, India | M15: Map
A16: 12 | B16: OM SAI TOUR & TRAVELS | C16: Warehouse / Logistics | D16: Office Boy, Housekeeping, Security, Helper | E16: 9810460500 | F16: 4.9 | G16: 36 | H16: Office No-1126, Saraswati Kunj Rd, opposite Paras Hospital, IILM Institute, Sector 53, Gurugram, Haryana 122011, India | M16: Map
... A64: 60 | B64: Dragonfly - Apparels & Gadgets. | C64: Shop / Retail | D64: Store Helper, Housekeeping, Security, Sales Staff | E64: 8524526969 | F64: 2 | G64: 1 | H64: The Outback, C4J3+JPM, AIT Chowk, IILM Institute, Sector 53, Gurugram, Haryana 122011, India | M64: Map
A65: 61 | B65: Bhushan Yadav Paan Shop | C65: Shop / Retail | D65: Store Helper, Housekeeping, Security, Sales Staff | E65: 7631771555 | H65: 44, opposite to Paras Hospital Road, DLF Phase 5, Sector 53, Gurugram, Haryana 122009, India | M65: Map
A66: 62 | B66: Dawara Enterprises - Vectus Authorised Partner (Water Storage Tanks) | C66: Warehouse / Logistics | D66: Loader, Packer, Picker, Warehouse Helper, Delivery | E66: 8851882747 | H66: Plot No 754 Sector No 53, nearby Khatu Shyam Mandir, Parsvnath Exotica, DLF Phase 5, Sector 53, Gurugram, Haryana 122001, India | M66: Map
A67: 63 | B67: Rahul Car Rental | C67: Warehouse / Logistics | D67: Office Boy, Housekeeping, Security, Helper | E67: 9694838281 | H67: 970, Saraswati Kunj, society, Sector 53, Gurugram, Haryana 122011, India | M67: Map
A68: 64 | B68: Sajan Ali Meat Shop | C68: Restaurant / Food | D68: Kitchen Helper, Cook, Dishwasher, Waiter | E68: 7029603105 | H68: IILM Institute, Sector 53, Gurugram, Haryana 122011, India | M68: Map
A69: 65 | B69: Specail Mohidul Chichken Shop | C69: Restaurant / Food | D69: Kitchen Helper, Cook, Dishwasher, Waiter | E69: 8810687366 | H69: Shop No 04, Saraswati Kunj Rd, IILM Institute, Sector 53, Gurugram, Haryana 122011, India | M69: Map
A70: 66 | B70: Uvion | C70: Restaurant / Food | D70: Kitchen Helper, Cook, Dishwasher, Waiter | E70: 9306000644 | H70: Plot No.1502, Khatu Shyam Road, Parsvnath Exotica, DLF Phase 5, Sector 53, Gurugram, Haryana 122011, India | M70: Map
A71: 67 | B71: MobiKwik HQ | C71: Other | D71: Office Boy, Housekeeping, Security, Helper | E71: 8069808320 | F71: 3.1 | G71: 694 | H71: Unit No. 102, 1st Floor, Block-B, Pegasus One, Golf Course Rd, Parsvnath Exotica, Sector 53, Gurugram, Haryana 122003, India | M71: Map
A72: 68 | B72: Zavya Jewellery | C72: Other | D72: Office Boy, Housekeeping, Security, Helper | E72: 9810814945 | F72: 4.1 | G72: 262 | H72: 4B, Ground, CENTRUM PLAZA, Golf Course Rd, IILM Institute, Sector 53, Gurugram, Haryana 122011, India | M72: Map
A73: 69 | B73: Advocate ANSHUL YADAV | 15+ years Experience| Corporate | Divorce | RERA | Cyber crime | Civil | IPR | C73: Other | D73: Office Boy, Housekeeping, Security, Helper | E73: 8373932995 | F73: 4.8 | G73: 71 | H73: Saraswati Kunj, 318, Golf Course Rd, Parsvnath Exotica, Sarswati Kunj II, DLF Phase 5, Sector 53, Gurugram, Haryana 122011, India | M73: Map
A74: 70 | B74: AV SPORTS ACADEMY | C74: Other | D74: Trainer, Housekeeping, Front Desk | E74: 9311028822 | F74: 4.1 | G74: 62 | H74: BLOCK-D, WESTEND HEIGHTS, St Thomas Marg, DLF Phase 5, Sector 53, Gurugram, Haryana 122009, India | M74: Map
A75: 71 | B75: Finmart Realty Dlf Phase 5 : Property Dealer | Plots | Dlf Phase 5 | C75: Other | D75: Office Boy, Housekeeping, Security, Helper | E75: 9319008431 | F75: 5 | G75: 59 | H75: shop no 882, DLF Phase 5, Sector 53, Gurugram, Haryana 122011, India | M75: Map
A76: 72 | B76: TOTAL FIT GYM | C76: Other | D76: Trainer, Housekeeping, Front Desk | E76: 9891773500 | F76: 4.8 | G76: 38 | H76: 92, Saraswati Kunj Rd, Parsvnath Exotica, DLF Phase 5, Sector 53, Gurugram, Haryana 122011, India | M76: Map
A77: 73 | B77: MP Fitness Personal Training | C77: Other | D77: Ward Boy, Housekeeping, Attendant, Security | E77: 9911659057 | F77: 4.8 | G77: 30 | H77: Golf Course Rd, DLF Phase 5, Sector 53, Gurugram, Haryana 122011, India | M77: Map

Sheet Sector 54
A1: SWITCH · SECTOR 54 · MOBILE CALL SHEET
A2: Owner/manager mobiles · shifts 1–12 hrs, pay after worker reports · instant replacement | 41 leads · 37 in priority industries (top)
A3: LEADS | B3: =COUNTA(B5:B45) | C3: CONTACTED | D3: =COUNTA(I5:I45) | E3: INTERESTED | F3: =COUNTIF(I5:I45,"Yes") | G3: ORDERS | H3: =COUNTIF(K5:K45,"Yes") | I3: HOURS BOOKED | J3: =SUM(J5:J45)
A4: S.No | B4: Business Name | C4: Target Industry | D4: Suggested Roles (per shift) | E4: Manager Mobile | F4: Rating | G4: Reviews | H4: Address | I4: Interested? | J4: Hours (1-12) | K4: Order Confirmed? | L4: Remarks | M4: Map
A5: 1 | B5: The Forestta - Best Cafe in Gurgaon | C5: Restaurant / Food | D5: Kitchen Helper, Cook, Dishwasher, Waiter | E5: 8988282828 | F5: 4.1 | G5: 6126 | H5: sarsawti kunj, Plot No 27, Golf Course Rd, opposite Alchemist Hospital, Suncity, Sector 54, Gurugram, Haryana 122003, India | M5: Map
A6: 2 | B6: Third Wave Coffee | C6: Restaurant / Food | D6: Kitchen Helper, Cook, Dishwasher, Waiter | E6: 8050003488 | F6: 4.6 | G6: 1485 | H6: G1, Ground Floor, Golf Course Rd, Suncity, Sector 54, Gurugram, Haryana 122011, India | M6: Map
A7: 3 | B7: Hi! Market | C7: Restaurant / Food | D7: Kitchen Helper, Cook, Dishwasher, Waiter | E7: 9896961330 | F7: 5 | G7: 931 | H7: 938, Park Dr, DLF Phase 5, Sector 54, Gurugram, Haryana 122009, India | M7: Map
A8: 4 | B8: Nona's Kitchen | C8: Restaurant / Food | D8: Kitchen Helper, Cook, Dishwasher, Waiter | E8: 8287543191 | F8: 4.5 | G8: 516 | H8: DLF, Park Dr, DLF Phase 5, Sector 54, Gurugram, Haryana 122002, India | M8: Map
A9: 5 | B9: Cafe Tuya Te | C9: Restaurant / Food | D9: Kitchen Helper, Cook, Dishwasher, Waiter | E9: 9220771119 | F9: 4.6 | G9: 169 | H9: 31, Golf Crse Rd, Suncity, Sector 54, Gurugram, Haryana 122011, India | M9: Map
A10: 6 | B10: Indyverse | C10: Shop / Retail | D10: Store Helper, Housekeeping, Security, Sales Staff | E10: 9205991345 | F10: 4.9 | G10: 129 | H10: Indyverse 311, Suncity Business Tower Rapid Metro Station Sector 54 Chowk, Tower, Golf Course Rd, Suncity, Sector 54, Gurugram, Haryana 122011, India | M10: Map
A11: 7 | B11: Leens Nestling Preschool Gurgaon | C11: PG / Hostel | D11: Housekeeping, Cook, Caretaker, Security | E11: 9818908571 | F11: 4.9 | G11: 102 | H11: Site IV, Gate no 16, B-Block, Suncity, Sector 54, Gurugram, Haryana 122011, India | M11: Map
A12: 8 | B12: FamilyPhysio The Wellness Hub | C12: Salon / Spa | D12: Ward Boy, Housekeeping, Attendant, Security | E12: 7669852298 | F12: 5 | G12: 77 | H12: Basement of Firstcry Intellitots Pre School, NS2, C-BLOCK, Golf Course Rd, near La Laguna, Suncity, Sector 54, Gurugram, Haryana 122011, India | M12: Map
A13: 9 | B13: Sheikh Chang Singh | C13: Restaurant / Food | D13: Kitchen Helper, Cook, Dishwasher, Waiter | E13: 7222077796 | F13: 4.2 | G13: 74 | H13: Shop No. - 7, LA LAGUNE, Golf Crse Rd, Suncity, Sector 54, Gurugram, Haryana 122011, India | M13: Map
A14: 10 | B14: The Gr8 Taste Of India | C14: Restaurant / Food | D14: Kitchen Helper, Cook, Dishwasher, Waiter | E14: 9999973392 | F14: 3.9 | G14: 60 | H14: Plot No, 26, Sarswati Kunj II, Golf Course Rd, opposite Alchemist Hospital, Suncity, Sector 54, Gurugram, Haryana 122011, India | M14: Map
A15: 11 | B15: Musical Bazaar - Harmonium House - A Unit of Tabla Sitar Musicals | C15: Shop / Retail | D15: Store Helper, Housekeeping, Security, Sales Staff | E15: 8130455825 | F15: 4.8 | G15: 56 | H15: F, 50, F Block, Suncity, Sector 54, Gurugram, Haryana 122011, India | M15: Map
A16: 12 | B16: Travert Apartment | C16: Hotel / OYO | D16: Housekeeping, Room Boy, Kitchen Helper, Front Desk | E16: 9220444624 | F16: 4.8 | G16: 53 | H16: Travert Apartment, B 3/3, Park Dr, DLF Phase 5, Sector 54, Gurugram, Haryana 122011, India | M16: Map
... A35: 31 | B35: 수게스트하우스 | C35: Hotel / OYO | D35: Housekeeping, Room Boy, Kitchen Helper, Front Desk | E35: 9910615022 | F35: 4 | G35: 1 | H35: India, Haryana, Gurugram, Sector 54, DLF Phase 5, The Crest | M35: Map
A36: 32 | B36: Agarwal Packers And Movers Gurgaon | C36: Warehouse / Logistics | D36: Loader, Packer, Picker, Warehouse Helper, Delivery | E36: 9817707828 | H36: C-42, Suncity, Sector 54, Gurugram, Haryana 122011, India | M36: Map
A37: 33 | B37: Hindustani Classical Music Training by Bhanu Roy | C37: Shop / Retail | D37: Store Helper, Housekeeping, Security, Sales Staff | E37: 9830122944 | H37: New IFS Ridgeview Apartments, B-401, opposite Sushant University Road, Huda, Sushant Lok 2, Sector 54, Gurugram, Haryana 122011, India | M37: Map
A38: 34 | B38: Kitchen Appliances | C38: Restaurant / Food | D38: Kitchen Helper, Cook, Dishwasher, Waiter | E38: 8882686815 | H38: G-847, Suncity, Sector 54, Gurugram, Haryana 122011, India | M38: Map
A39: 35 | B39: Mirasa Heritage | C39: Shop / Retail | D39: Store Helper, Housekeeping, Security, Sales Staff | E39: 9810022778 | H39: The Palm Springs, Golf Course Rd, DLF Phase 5, Sector 54, Gurugram, Haryana 122009, India | M39: Map
A40: 36 | B40: Ravangi Candles | C40: Shop / Retail | D40: Store Helper, Housekeeping, Security, Sales Staff | E40: 9911755588 | H40: 3 Floor, C-36, Suncity, Sector 54, Gurugram, Haryana 122011, India | M40: Map
A41: 37 | B41: Yamini Lal Makeovers - Best Makeup Artist in Gurugram, Bridal Makeup, Party Makeup, Engagement Makeup | C41: Salon / Spa | D41: Office Boy, Housekeeping, Security, Helper | E41: 8743927596 | H41: DLF PARK PLACE, Park Dr, DLF Phase 5, Sector 54, Gurugram, Haryana 122009, India | M41: Map
A42: 38 | B42: Music Soul | C42: Other | D42: Peon, Housekeeping, Security, Attendant | E42: 8963043909 | F42: 4.9 | G42: 248 | H42: B2/3, Park Drive, Golf Course Rd, DLF Phase 5, Sector 54, Gurugram, Haryana 122009, India | M42: Map
A43: 39 | B43: Emoha Elder care & Medical Centre | C43: Other | D43: Ward Boy, Housekeeping, Attendant, Security | E43: 8103099928 | F43: 4.9 | G43: 93 | H43: DLF Crest Park Drive, Golf Course, Extension Road, DLF Phase 5, Sector 54, Gurugram, Haryana 122009, India | M43: Map
A44: 40 | B44: FirstCry Intellitots Preschool & Daycare - Suncity, Gurugram | C44: Other | D44: Peon, Housekeeping, Security, Attendant | E44: 7042191288 | F44: 4.8 | G44: 92 | H44: C Block, NS-2, Suncity, Sector 54, Gurugram, Haryana 122002, India | M44: Map
A45: 41 | B45: OkayGo | C45: Other | D45: Office Boy, Housekeeping, Security, Helper | E45: 8882866060 | F45: 4.1 | G45: 41 | H45: 12th Floor, VATIKA TOWER, B Golf Course Rd, Suncity, Sector 54, Gurugram, Haryana 122011, India | M45: Map

Sheet Sector 55
A1: SWITCH · SECTOR 55 · MOBILE CALL SHEET
A2: Owner/manager mobiles · shifts 1–12 hrs, pay after worker reports · instant replacement | 36 leads · 33 in priority industries (top)
A3: LEADS | B3: =COUNTA(B5:B40) | C3: CONTACTED | D3: =COUNTA(I5:I40) | E3: INTERESTED | F3: =COUNTIF(I5:I40,"Yes") | G3: ORDERS | H3: =COUNTIF(K5:K40,"Yes") | I3: HOURS BOOKED | J3: =SUM(J5:J40)
A4: S.No | B4: Business Name | C4: Target Industry | D4: Suggested Roles (per shift) | E4: Manager Mobile | F4: Rating | G4: Reviews | H4: Address | I4: Interested? | J4: Hours (1-12) | K4: Order Confirmed? | L4: Remarks | M4: Map
A5: 1 | B5: Ombre By Charu | C5: Shop / Retail | D5: Store Helper, Housekeeping, Security, Sales Staff | E5: 9810408028 | F5: 4.9 | G5: 96 | H5: house number 5, Sector 55, Gurugram, Haryana 122011, India | M5: Map
A6: 2 | B6: Sportsun sports wear | C6: Shop / Retail | D6: Store Helper, Housekeeping, Security, Sales Staff | E6: 9911858512 | F6: 4.7 | G6: 51 | H6: Sector 55-56 Road, Nai wali Dhani Chowk, Sector 52A, Gurugram, Haryana 122011, India | M6: Map
A7: 3 | B7: Blue Sea PG | Girls Pg in Sector 55 Gurgaon | C7: PG / Hostel | D7: Housekeeping, Cook, Caretaker, Security | E7: 8010188010 | F7: 4.4 | G7: 42 | H7: Plot no 200, Sushant Lok 2, Sector 55, Gurugram, Haryana 122011, India | M7: Map
A8: 4 | B8: Yashvi collection | C8: Shop / Retail | D8: Store Helper, Housekeeping, Security, Sales Staff | E8: 9999919909 | F8: 4.9 | G8: 39 | H8: 251 City cooperative housing society Plot no.-73, Huda Sector, Sushant Lok 2, Sector 55, Gurugram, Haryana 122011, India | M8: Map
A9: 5 | B9: Haryana Paneer Bhandar | C9: Restaurant / Food | D9: Kitchen Helper, Cook, Dishwasher, Waiter | E9: 9015727004 | F9: 4.3 | G9: 31 | H9: Rajesh Pilot Rd, near Radha Krishna Mandir, Ghata Gao, Ghatta Kanarpur, Sector 55, Ghata, Gurugram, Haryana 122011, India | M9: Map
A10: 6 | B10: Meenu’s Studio the boutique | C10: Shop / Retail | D10: Store Helper, Housekeeping, Security, Sales Staff | E10: 9911324415 | F10: 4.8 | G10: 27 | H10: Near rapid metro station, 55-56, Golf Course Rd, opposite double tree hotel, Huda Sector, Sushant Lok 2, Sector 55, Gurugram, Haryana 122011, India | M10: Map
A11: 7 | B11: GM Stays 2 | C11: Hotel / OYO | D11: Office Boy, Housekeeping, Security, Helper | E11: 8126186294 | F11: 4 | G11: 23 | H11: House number 3, GM stays 2, Sushant Lok 2, Sector 55, Gurugram, Haryana 122011, India | M11: Map
A12: 8 | B12: Safe Stay homes & Serviced Apartment | C12: Hotel / OYO | D12: Housekeeping, Room Boy, Kitchen Helper, Front Desk | E12: 9810204470 | F12: 4.8 | G12: 20 | H12: A1- 132, Huda, Sushant Lok 2, Sector 55, Gurugram, Haryana 122011, India | M12: Map
A13: 9 | B13: Dayma Tent House | C13: Shop / Retail | D13: Office Boy, Housekeeping, Security, Helper | E13: 7065883501 | F13: 5 | G13: 12 | H13: 203, near Metro Stations, Sushant Lok 2, Sector 55, Gurugram, Haryana 122002, India | M13: Map
A14: 10 | B14: D STOCK Fashion | C14: Shop / Retail | D14: Store Helper, Housekeeping, Security, Sales Staff | E14: 9103732027 | F14: 4.9 | G14: 11 | H14: Ghata Gao, Ghatta Kanarpur, Sector 55, Ghata, Gurugram, Haryana 122011, India | M14: Map
A15: 11 | B15: Designer's Abode Interior Designers | C15: Shop / Retail | D15: Office Boy, Housekeeping, Security, Helper | E15: 9313931313 | F15: 5 | G15: 6 | H15: Sagavi Apartment, GH 85, Golf Crse Rd, Huda, Sushant Lok 2, Sector 55, Gurugram, Haryana 122011, India | M15: Map
A16: 12 | B16: Pine Valley Holidays | C16: Warehouse / Logistics | D16: Office Boy, Housekeeping, Security, Helper | E16: 8295704996 | F16: 5 | G16: 6 | H16: A 326, Sushant Lok 2, Sector 55, Gurugram, Haryana 122011, India | M16: Map
... A28: 24 | B28: Alok Gupta | C28: Shop / Retail | D28: Store Helper, Housekeeping, Security, Sales Staff | E28: 8287663612 | F28: 1 | G28: 1 | H28: Shop No 2, Sector 55.56, Sector 56, Gurugram, Haryana 122011, India | M28: Map
A29: 25 | B29: Bolt.Earth EV Charging Station | C29: Warehouse / Logistics | D29: Office Boy, Housekeeping, Security, Helper | E29: 8447746385 | H29: Gurgaon Division, Huda Sector, Sushant Lok 2, Sector 55, DELHI, NCR, Haryana 122003, India | M29: Map
A30: 26 | B30: Brijesh SinghFoods | C30: Restaurant / Food | D30: Kitchen Helper, Cook, Dishwasher, Waiter | E30: 9664246878 | H30: Huda Sector, Sushant Lok 2, Sector 55, Ghata, Gurugram, Haryana 122001, India | M30: Map
A31: 27 | B31: Musabbir Ali | C31: Shop / Retail | D31: Store Helper, Housekeeping, Security, Sales Staff | E31: 7428517317 | H31: Shop No 1, Block B, Sector 55, Gurugram, Haryana 122011, India | M31: Map
A32: 28 | B32: Pritam Boot House | C32: Shop / Retail | D32: Store Helper, Housekeeping, Security, Sales Staff | E32: 6201361114 | H32: Shop No 8 Sector.55 Ghata, Gaon Market, Huda Sector, Sushant Lok 2, Sector 55, Gurugram, Haryana 122011, India | M32: Map
A33: 29 | B33: Ravindar Bhai Fast Food | C33: Restaurant / Food | D33: Kitchen Helper, Cook, Dishwasher, Waiter | E33: 9289852946 | H33: Shop No, 15, near by Win Shop, Gaon, Sector 55, Ghata, Gurugram, Haryana 122011, India | M33: Map
A34: 30 | B34: Sanjeev General Store | C34: Restaurant / Food | D34: Store Helper, Housekeeping, Security, Sales Staff | E34: 9650935107 | H34: 1, Ghatta Kanarpur, Sector 55, Ghata, Gurugram, Haryana 122011, India | M34: Map
A35: 31 | B35: Shanti Travels | C35: Warehouse / Logistics | D35: Office Boy, Housekeeping, Security, Helper | E35: 9540732024 | H35: Sector 55, Gurugram, Haryana 122011, India | M35: Map
A36: 32 | B36: Shivani the nail artist | C36: Salon / Spa | D36: Beautician, Helper, Receptionist, Cleaner | E36: 9354817249 | H36: Sushant Lok 2, Sector 55, Gurugram, Haryana 122011, India | M36: Map
A37: 33 | B37: Subhash Turi Pan Shop | C37: Restaurant / Food | D37: Store Helper, Housekeeping, Security, Sales Staff | E37: 8252241559 | H37: Metro Station Sector 55 56, Sector 56, Gurugram, Haryana 122011, India | M37: Map
A38: 34 | B38: MAHESH DAYMA CORPORATOR WARD 30 Gurugram | C38: Other | D38: Office Boy, Housekeeping, Security, Helper | E38: 9810228194 | F38: 4.7 | G38: 452 | H38: 241 Ground Floor, Main, Golf Course Rd, opposite CLOUDNINE HOSPITAL, Sector 55, Gurugram, Haryana 122011, India | M38: Map
A39: 35 | B39: S Home Physiotherapy/Dr Vikram Singh/Sports Physiotherapy/Geriatric Physiotherapy/Stroke Physiotherapy/Physiotherapy Near Me | C39: Other | D39: Ward Boy, Housekeeping, Attendant, Security | E39: 9818002398 | F39: 5 | G39: 98 | H39: A1-97, Sushant Lok 2, Sector 55, Gurugram, Haryana 122011, India | M39: Map
A40: 36 | B40: MaxPetZ Gurgaon | C40: Other | D40: Office Boy, Housekeeping, Security, Helper | E40: 9810393915 | F40: 4.5 | G40: 75 | H40: A1/218, Sushant Lok 2, Sector 55, Gurugram, Haryana 122011, India | M40: Map

Sheet Sector 56
A1: SWITCH · SECTOR 56 · MOBILE CALL SHEET
A2: Owner/manager mobiles · shifts 1–12 hrs, pay after worker reports · instant replacement | 105 leads · 95 in priority industries (top)
A3: LEADS | B3: =COUNTA(B5:B109) | C3: CONTACTED | D3: =COUNTA(I5:I109) | E3: INTERESTED | F3: =COUNTIF(I5:I109,"Yes") | G3: ORDERS | H3: =COUNTIF(K5:K109,"Yes") | I3: HOURS BOOKED | J3: =SUM(J5:J109)
A4: S.No | B4: Business Name | C4: Target Industry | D4: Suggested Roles (per shift) | E4: Manager Mobile | F4: Rating | G4: Reviews | H4: Address | I4: Interested? | J4: Hours (1-12) | K4: Order Confirmed? | L4: Remarks | M4: Map
A5: 1 | B5: Harish Bakery | C5: Restaurant / Food | D5: Kitchen Helper, Cook, Dishwasher, Waiter | E5: 9560608422 | F5: 4.1 | G5: 3882 | H5: 33, Block B, Sector 56, Gurugram, Haryana 122011, India | M5: Map
A6: 2 | B6: Vamsor Heights | C6: Hotel / OYO | D6: Housekeeping, Room Boy, Kitchen Helper, Front Desk | E6: 9891989810 | F6: 4.8 | G6: 1226 | H6: 26, Block A, Sector 56, Gurugram, Haryana 122011, India | M6: Map
A7: 3 | B7: Firstcry Store Gurgaon Sector 56 | C7: Shop / Retail | D7: Store Helper, Housekeeping, Security, Sales Staff | E7: 9996354433 | F7: 4.6 | G7: 761 | H7: First Floor, HUDA Market, S.C.O # 20, near Harish Bakery, Block B, Sector 56, Gurugram, Haryana 122011, India | M7: Map
A8: 4 | B8: Redbrick Villa | C8: Hotel / OYO | D8: Housekeeping, Room Boy, Kitchen Helper, Front Desk | E8: 9210038150 | F8: 4.3 | G8: 580 | H8: Plot no. 575-P, Opposite Sushant Tower, D-BLOCK, adjacent C-Dot Apartment, Shushant Lok 2, Sushant Lok 2, Sector 56, Gurugram, Haryana 122011, India | M8: Map
A9: 5 | B9: Kashish Beauty Salon | C9: Salon / Spa | D9: Beautician, Helper, Receptionist, Cleaner | E9: 9810592988 | F9: 4.7 | G9: 460 | H9: E-175 A, Basement, Gate No 2, Kendriya Vihar, Sector 56, Beaide, Gurugram, Haryana 122002, India | M9: Map
A10: 6 | B10: CP Vet Sector 56 | C10: Shop / Retail | D10: Office Boy, Housekeeping, Security, Helper | E10: 9560952323 | F10: 4.1 | G10: 459 | H10: GF & Basement, SCO-65, Huda Market Rd, behind Jalvayu Tower, Block B, Sector 56, Gurugram, Haryana 122011, India | M10: Map
A11: 7 | B11: Ivory Room Salon Sec56 | C11: Salon / Spa | D11: Beautician, Helper, Receptionist, Cleaner | E11: 9625028724 | F11: 4.6 | G11: 322 | H11: SCO 19 , Ground Floor, Huda Market, near Harish Bakery, Block B, Sector 56, Gurugram, Haryana 122011, India | M11: Map
A12: 8 | B12: Subway Sector 56 Gurgaon | C12: Restaurant / Food | D12: Kitchen Helper, Cook, Dishwasher, Waiter | E12: 9971813195 | F12: 4.1 | G12: 322 | H12: District commercial centre, Sco 18, Huda Market Rd, near Harish Bakery, Block B, Sector 56, Gurugram, Haryana 122011, India | M12: Map
A13: 9 | B13: VZaara Salons and Academy Pvt Ltd | C13: Salon / Spa | D13: Beautician, Helper, Receptionist, Cleaner | E13: 8527056159 | F13: 4.8 | G13: 278 | H13: Golf Course Rd, Sector 56, Gurugram, Haryana 122011, India | M13: Map
A14: 10 | B14: GOLDEN CREATION | C14: Shop / Retail | D14: Office Boy, Housekeeping, Security, Helper | E14: 8745935729 | F14: 4.9 | G14: 167 | H14: G38, BAANI ADDRESS ONE SHOPPING ARCADE, RAPID METRO STATION, 55-56, Golf Course Rd, Sector 56, Gurugram, Haryana 122011, India | M14: Map
A15: 11 | B15: New AGE APPARELS | C15: Shop / Retail | D15: Store Helper, Housekeeping, Security, Sales Staff | E15: 9319855773 | F15: 4.9 | G15: 167 | H15: Ground Floor , First Floor & Basement, SCO-32, Huda Market Rd, Block B, Sector 56, Gurugram, Haryana 122011, India | M15: Map
A16: 12 | B16: The Ananda Cafe(Sector 56) | C16: Restaurant / Food | D16: Kitchen Helper, Cook, Dishwasher, Waiter | E16: 9002288021 | F16: 4.7 | G16: 161 | H16: Shop Number 87, Huda Market Rd, Block B, Sector 56, Gurugram, Haryana 122011, India | M16: Map
... A84: 80 | B84: Myra Boutique | C84: Shop / Retail | D84: Store Helper, Housekeeping, Security, Sales Staff | E84: 9990110810 | F84: 1 | G84: 1 | H84: Shop No 1, Rail Vihar, Sector 56, Gurugram, Haryana 122011, India | M84: Map
A85: 81 | B85: Anmol Reet | C85: Shop / Retail | D85: Store Helper, Housekeeping, Security, Sales Staff | E85: 8285581414 | H85: C-224, Kendriya Vihar, Sector 56, Gurugram, Haryana 122011, India | M85: Map
A86: 82 | B86: Bhoj | C86: Restaurant / Food | D86: Kitchen Helper, Cook, Dishwasher, Waiter | E86: 9821854571 | H86: C3FW+GMP, Kendriya Vihar, Sector 56, Gurugram, Haryana 122011, India | M86: Map
A87: 83 | B87: BrewHill Coffee | C87: Restaurant / Food | D87: Kitchen Helper, Cook, Dishwasher, Waiter | E87: 9354333813 | H87: C4J2+5HV, Rail Vihar, Sector 56, Gurugram, Haryana 122011, India | M87: Map
A88: 84 | B88: Dev Bhushan Fast Food | C88: Restaurant / Food | D88: Kitchen Helper, Cook, Dishwasher, Waiter | E88: 9118651809 | H88: Huda Market Rd, Sector 56, Gurugram, Haryana 122011, India | M88: Map
A89: 85 | B89: Dudhbhate Fast Food | C89: Restaurant / Food | D89: Kitchen Helper, Cook, Dishwasher, Waiter | E89: 9960485261 | H89: Shop No.55, Huda Center, Sector 56, Gurugram, Haryana 122011, India | M89: Map
A90: 86 | B90: Gharr Kii Mathi | C90: Restaurant / Food | D90: Machine Operator, Helper, Loader, Packer | E90: 9958297433 | H90: First Floor, D 263, Shushant Lok 2, Sushant Lok 2, Sector 56, Gurugram, Haryana 122011, India | M90: Map
A91: 87 | B91: KRISHAN KIRANA STORE | C91: Supermarket / Grocery | D91: Store Helper, Housekeeping, Security, Sales Staff | E91: 9560423747 | H91: 134, Rajesh Pilot Rd, nearby D Block Ramesh, Sector 56, Gurugram, Haryana 122011, India | M91: Map
A92: 88 | B92: Mental Health Wellness Center, Counseling and psychology services | C92: Salon / Spa | D92: Ward Boy, Housekeeping, Attendant, Security | E92: 9625776990 | H92: J-513, Jalvayu Towers, Sector 56, Gurugram, Haryana 122011, India | M92: Map
A93: 89 | B93: My Creative Club | Robotics & STEM Learning | Coding | Electronics | IoT | AI | Art n Craft | C93: Shop / Retail | D93: Store Helper, Housekeeping, Security, Sales Staff | E93: 7999820633 | H93: A51, Technical Paradise, CGHS, Sector 56, Gurugram, Haryana 122011, India | M93: Map
A94: 90 | B94: Noore Jewels | C94: Shop / Retail | D94: Store Helper, Housekeeping, Security, Sales Staff | E94: 9217945235 | H94: House No 505, GANPATI APARTMENT, Block B, Sector 56, Gurugram, Haryana 122011, India | M94: Map
A95: 91 | B95: SARIFUL SK MEAT SHOP | C95: Restaurant / Food | D95: Kitchen Helper, Cook, Dishwasher, Waiter | E95: 8527155430 | H95: 1 Bengali Market, IILM Institute, Sector 56, Gurugram, Haryana 122011, India | M95: Map
A96: 92 | B96: Shyam Kirana Store | C96: Supermarket / Grocery | D96: Store Helper, Housekeeping, Security, Sales Staff | E96: 8930695241 | H96: Shyam Kirana Store, Nangal Choudhary, Nangal Dargu, Sector 56, Gurugram, Haryana 122011, India | M96: Map
... A99: 95 | B99: Vinay | C99: Shop / Retail | D99: Store Helper, Housekeeping, Security, Sales Staff | E99: 8757870194 | H99: SCO18, Huda Market Rd, Block B, Sector 56, Gurugram, Haryana 122011, India | M99: Map
A100: 96 | B100: Miracles Mediclinic Sec 56, Gurugram | C100: Other | D100: Ward Boy, Housekeeping, Attendant, Security | E100: 9069068800 | F100: 4.6 | G100: 1979 | H100: SCO-68-69, More Market, 69, Block B, Sector 56, Gurugram, Haryana 122011, India | M100: Map
A101: 97 | B101: Muskaan Dentals | C101: Other | D101: Ward Boy, Housekeeping, Attendant, Security | E101: 9494947304 | F101: 4.8 | G101: 741 | H101: 1st Floor, 167-P, near Kendriya Vihar, Block B, Sector 56, Gurugram, Haryana 122011, India | M101: Map
A102: 98 | B102: TAEDAS ACADEMY PVT. LTD. | C102: Other | D102: Trainer, Housekeeping, Front Desk | E102: 8860553257 | F102: 4.9 | G102: 479 | H102: 107, C Block Road, GAIL Society, Sector 56, Gurugram, Haryana 122011, India | M102: Map
A103: 99 | B103: StockDaddy - Best Stock Market Institute, Gurgaon | C103: Other | D103: Store Helper, Housekeeping, Security, Sales Staff | E103: 7838756756 | F103: 4.6 | G103: 464 | H103: D-323, Golf Course Ext Rd, Shushant Lok 2, Sushant Lok 2, Sector 56, Gurugram, Ghata, Haryana 122011, India | M103: Map
A104: 100 | B104: Sukoon Psychiatry Centre - Gurugram, Mental Health Hospital | C104: Other | D104: Ward Boy, Housekeeping, Attendant, Security | E104: 8448156500 | F104: 4.6 | G104: 416 | H104: Plot 4P, Sector 56, Gurugram, Haryana 122011, India | M104: Map
A105: 101 | B105: APOLLO MRI MEDICAL CENTRE / 2D ECHO/ ULTRASOUND/ECG/ CT-SCAN IN SECTOR 55-56 GURGAON | C105: Other | D105: Ward Boy, Housekeeping, Attendant, Security | E105: 8700812392 | F105: 4.7 | G105: 355 | H105: House no, Ground Floor, 176, Sector 56, Gurugram, Haryana 122011, India | M105: Map
A106: 102 | B106: Svasthify Yoga | C106: Other | D106: Trainer, Housekeeping, Front Desk | E106: 8700745048 | F106: 4.9 | G106: 337 | H106: 417, near More market, Block B, Sector 56, Gurugram, Haryana 122011, India | M106: Map
A107: 103 | B107: The Tooth Care Dental Clinic | C107: Other | D107: Ward Boy, Housekeeping, Attendant, Security | E107: 9991112687 | F107: 4.8 | G107: 319 | H107: 9P, Sector 56, Gurugram, Haryana 122011, India | M107: Map
A108: 104 | B108: Curl Fitness Gym | C108: Other | D108: Trainer, Housekeeping, Front Desk | E108: 9953559947 | F108: 4.6 | G108: 287 | H108: SCO 18-19, 1st & 2nd Floor, near Harish Bakery, Block B, Sector 56, Gurugram, Haryana 122011, India | M108: Map
A109: 105 | B109: Oberst Strength- Sector 56 Gurugram | C109: Other | D109: Trainer, Housekeeping, Front Desk | E109: 9205460889 | F109: 4.9 | G109: 168 | H109: 1st & 2nd Floor, SCO 18-19, near Harish Bakery, Block B, Sector 56, Gurugram, Haryana 122011, India | M109: Map

Sheet Sector 57
A1: SWITCH · SECTOR 57 · MOBILE CALL SHEET
A2: Owner/manager mobiles · shifts 1–12 hrs, pay after worker reports · instant replacement | 84 leads · 76 in priority industries (top)
A3: LEADS | B3: =COUNTA(B5:B88) | C3: CONTACTED | D3: =COUNTA(I5:I88) | E3: INTERESTED | F3: =COUNTIF(I5:I88,"Yes") | G3: ORDERS | H3: =COUNTIF(K5:K88,"Yes") | I3: HOURS BOOKED | J3: =SUM(J5:J88)
A4: S.No | B4: Business Name | C4: Target Industry | D4: Suggested Roles (per shift) | E4: Manager Mobile | F4: Rating | G4: Reviews | H4: Address | I4: Interested? | J4: Hours (1-12) | K4: Order Confirmed? | L4: Remarks | M4: Map
A5: 1 | B5: The Lodgers Luxury Hotel Near Golf Course Road Gurgaon | C5: Hotel / OYO | D5: Housekeeping, Room Boy, Kitchen Helper, Front Desk | E5: 8800947663 | F5: 4.8 | G5: 507 | H5: 1287XP Near, Artemis Hospital Rd, Block H, Sector 57, Gurugram, Haryana 122011, India | M5: Map
A6: 2 | B6: Peteazy | C6: Shop / Retail | D6: Office Boy, Housekeeping, Security, Helper | E6: 8901509125 | F6: 4.8 | G6: 444 | H6: 2913, Ashiyana Floors Basement, Sushant Lok Phase 3, Sushant Lok 2, Sector 57, Gurugram, Haryana 122011, India | M6: Map
A7: 3 | B7: Lime Tree Hotel Golf Course Ext. Gurgaon | C7: Hotel / OYO | D7: Housekeeping, Room Boy, Kitchen Helper, Front Desk | E7: 7479000111 | F7: 4.7 | G7: 335 | H7: Plot No- 2731, near Bikaner Wala, Block A, Sushant Lok III, Sector 57, Gurugram, Haryana 122011, India | M7: Map
A8: 4 | B8: Tattoos For Life | C8: Shop / Retail | D8: Store Helper, Housekeeping, Security, Sales Staff | E8: 7669959859 | F8: 5 | G8: 215 | H8: 1064, Ground Floor, near Boom Plaza, Sushant Lok III, Sector 57, Gurugram, Haryana 122003, India | M8: Map
A9: 5 | B9: FreQuip - Rent Furniture & Appliances Online in Gurgaon | C9: Shop / Retail | D9: Store Helper, Housekeeping, Security, Sales Staff | E9: 9311709584 | F9: 4.6 | G9: 176 | H9: 2360, near SCOTTISH HIGH INTERNATIONAL SCHOOL, Block G, Sushant Lok 2, Sector 57, Gurugram, Haryana 122011, India | M9: Map
A10: 6 | B10: Cloud Residency | C10: PG / Hostel | D10: Housekeeping, Cook, Caretaker, Security | E10: 8860935909 | F10: 4.5 | G10: 161 | H10: F - 188, Block F, Sushant Lok 2, Sector 57, Gurugram, Haryana 122011, India | M10: Map
A11: 7 | B11: The Altruist Business Hotels | C11: Hotel / OYO | D11: Housekeeping, Room Boy, Kitchen Helper, Front Desk | E11: 9056060812 | F11: 4.8 | G11: 159 | H11: The Altruist Business Hotel, A-Block, 142 b, Block A, Sushant Lok III, Sector 57, Gurugram, Haryana 122003, India | M11: Map
A12: 8 | B12: FT GYM | C12: Salon / Spa | D12: Trainer, Housekeeping, Front Desk | E12: 9355178785 | F12: 5 | G12: 145 | H12: 3rd Floor, F-56, above XO Salon, Block G, Sushant Lok 2, Sector 57, Gurugram, Haryana 122001, India | M12: Map
A13: 9 | B13: Girls Pg Asma apartments | C13: PG / Hostel | D13: Housekeeping, Cook, Caretaker, Security | E13: 7289000199 | F13: 4.3 | G13: 144 | H13: Girls PG Asma Apartment house no 2955 near hong kong Bazaar, Sushant Lok Phase 3, Sushant Lok 2, Sector 57, Gurugram, Haryana 122011, India | M13: Map
A14: 10 | B14: Stanza Living Tortosa House - PG in Sec 57 Gurgaon | Coliving PG | Unisex PG | C14: PG / Hostel | D14: Housekeeping, Cook, Caretaker, Security | E14: 8047622222 | F14: 4.5 | G14: 119 | H14: Oyo Collection Hongkong Bazar, Golf Course Ext Rd, G-15, Sushant Lok 2, Sector 57, Gurugram, Haryana 122002, India | M14: Map
A15: 11 | B15: Lifespan Diabetes Clinics, Gurgaon | C15: Salon / Spa | D15: Ward Boy, Housekeeping, Attendant, Security | E15: 9289834394 | F15: 4.8 | G15: 115 | H15: 1814P, Block B1, Sector 57, Gurugram, Haryana 122011, India | M15: Map
A16: 12 | B16: Sharik Sofa Repair | C16: Shop / Retail | D16: Office Boy, Housekeeping, Security, Helper | E16: 7011018425 | F16: 4.7 | G16: 83 | H16: Wazirabad, market, Rod, near, Sector 57 Rd, Wazirabad, Sector 52, Gurugram, Haryana 122003, India | M16: Map
... A64: 60 | B64: Stone Metal Scissors | C64: Shop / Retail | D64: Store Helper, Housekeeping, Security, Sales Staff | E64: 9555063500 | F64: 4 | G64: 1 | H64: Basement Floor, 2096, near MKM Market Road, Block G, Sushant Lok 2, Sector 57, Gurugram, Haryana 122003, India | M64: Map
A65: 61 | B65: Bheru panipuri | C65: Restaurant / Food | D65: Kitchen Helper, Cook, Dishwasher, Waiter | E65: 8207452804 | H65: 2096, Block G, Sushant Lok 2, Sector 57, Gurugram, Haryana 122011, India | M65: Map
A66: 62 | B66: FORGIVING ROADS LLP | C66: Warehouse / Logistics | D66: Office Boy, Housekeeping, Security, Helper | E66: 9818073509 | H66: Plot No. 3141, near Rail Vihar, Basement, Rail Vihar, Sector 57, Gurugram, Haryana 122011, India | M66: Map
A67: 63 | B67: hellostayz | C67: Restaurant / Food | D67: Kitchen Helper, Cook, Dishwasher, Waiter | E67: 9211894338 | H67: hellostayz hotel, 1580p, Sector 57 Rd, B1 Block, Block G, Sushant Lok 2, Sector 57, Gurugram, Haryana 122011, India | M67: Map
A68: 64 | B68: K D Super Mart | C68: Supermarket / Grocery | D68: Store Helper, Housekeeping, Security, Sales Staff | E68: 8426842001 | H68: near Harmony Chowk, Block B, Sushant Lok III, Sector 57, Gurugram, Haryana 122011, India | M68: Map
A69: 65 | B69: Krit Lal Mandal Paan Shop | C69: Shop / Retail | D69: Store Helper, Housekeeping, Security, Sales Staff | E69: 9599109256 | H69: Shop No. 13, Sector 57, Tigra, Mandi, Gurugram, Haryana 122011, India | M69: Map
A70: 66 | B70: Mulla ji Chicken Shop | C70: Restaurant / Food | D70: Kitchen Helper, Cook, Dishwasher, Waiter | E70: 9991911148 | H70: Shop No.5, 550, Main Rd, Richpal Colony, Tigra, Sector 57 Manesar, Gurugram, Haryana 122011, India | M70: Map
A71: 67 | B71: Pradeep Fast Food | C71: Restaurant / Food | D71: Kitchen Helper, Cook, Dishwasher, Waiter | E71: 7983638108 | H71: near Wine Shop, Tigra, Sector 57, Gurugram, Haryana 122011, India | M71: Map
A72: 68 | B72: Pulao Korma Kebabs | C72: Restaurant / Food | D72: Office Boy, Housekeeping, Security, Helper | E72: 9899402328 | H72: C-1204, Rail Vihar, Sector 57, Gurugram, Haryana 122011, India | M72: Map
A73: 69 | B73: Rashid Scap Dealer | C73: Shop / Retail | D73: Store Helper, Housekeeping, Security, Sales Staff | E73: 6296497276 | H73: opp. LOTUS VALLEY SCHOOL, Tigra, Sector 57, Gurugram, Haryana 122011, India | M73: Map
A74: 70 | B74: Sahjad Vegitables | C74: Restaurant / Food | D74: Kitchen Helper, Cook, Dishwasher, Waiter | E74: 9984092577 | H74: near BPTP, Tigra, Sector 57, Gurugram, Haryana 122011, India | M74: Map
A75: 71 | B75: Saifur Tea Shop | C75: Supermarket / Grocery | D75: Store Helper, Housekeeping, Security, Sales Staff | E75: 7428525077 | H75: Saifur Tea Shop, Sabji Mandi, Tigra, Sector 57, Gurugram, Haryana 122011, India | M75: Map
A76: 72 | B76: Sanjeev Kumar Bamboo Chik Maker | C76: Shop / Retail | D76: Store Helper, Housekeeping, Security, Sales Staff | E76: 9871039894 | H76: 2D, Tigra, Sector 57, Mayfield Garden, LOTUS VALLEY SCHOOL, Nirvana Country, Sector 57, Gurugram, Haryana 122011, India | M76: Map
... A80: 76 | B80: Zaika Chicken Biryani | C80: Restaurant / Food | D80: Kitchen Helper, Cook, Dishwasher, Waiter | E80: 9758018424 | H80: Tigra, Sector 57, Gurugram, Haryana 122011, India | M80: Map
A81: 77 | B81: DR ANISH GUPTA | C81: Other | D81: Office Boy, Housekeeping, Security, Helper | E81: 9899334733 | F81: 4.9 | G81: 824 | H81: Hong Kong Bazaar, G- 240, Phase 2, Sushant Lok 2, Sector 57, Gurugram, Haryana 122006, India | M81: Map
A82: 78 | B82: Pain Free Dental | C82: Other | D82: Ward Boy, Housekeeping, Attendant, Security | E82: 9717300288 | F82: 4.7 | G82: 423 | H82: G 21, near Hong Kong Bazaar, Phase 2, Sushant Lok 2, Sector 57, Gurugram, Haryana 122011, India | M82: Map
A83: 79 | B83: 3m car workshop - Car Workshop in Sector 50 gurgaon | C83: Other | D83: Store Helper, Housekeeping, Security, Sales Staff | E83: 7840009030 | F83: 4.9 | G83: 408 | H83: gaon, near business zone, opp. LOTUS VALLEY SCHOOL, Tigra, Sector 57, Gurugram, Haryana 122001, India | M83: Map
A84: 80 | B84: All Time Fitness Gurugram - Available on cult.fit | Best gym in Sector 57, Gurugram | C84: Other | D84: Trainer, Housekeeping, Front Desk | E84: 8360025621 | F84: 4.9 | G84: 317 | H84: 4th & 5th floor, C-22, opposite The legend apartments, Block C, Sushant Lok III, Sector 57, Gurugram, Haryana 122003, India | M84: Map
A85: 81 | B85: AI HEALTHCARE (AUTHENTIC & INSIGHTFUL HEALTHCARE PVT. LTD.) | ECG AT HOME, TMT , PATHOLOGY TESTS | (Powered by BeLife) | C85: Other | D85: Ward Boy, Housekeeping, Attendant, Security | E85: 9667899166 | F85: 4.9 | G85: 238 | H85: 2578 , BASEMENT, MKM Market Rd, opposite ELECTRIC SUBSTATION, Block G, Sushant Lok 2, Sector 57, Gurugram, Haryana 122011, India | M85: Map
A86: 82 | B86: The India physio | C86: Other | D86: Ward Boy, Housekeeping, Attendant, Security | E86: 9467412464 | F86: 5 | G86: 208 | H86: Plot No. 2073, Near, MKM Market Rd, Block G, Sushant Lok 2, Sector 57, Gurugram, Haryana 122011, India | M86: Map
A87: 83 | B87: Omama - Women's Physiotherapy Clinic | C87: Other | D87: Ward Boy, Housekeeping, Attendant, Security | E87: 9967996740 | F87: 5 | G87: 207 | H87: 1st floor, C-22, Sector 57, Block C, Sushant Lok III Extension, Sector 57, Gurugram, Haryana 122011, India | M87: Map
A88: 84 | B88: NK FITNESS | C88: Other | D88: Trainer, Housekeeping, Front Desk | E88: 9266952797 | F88: 5 | G88: 201 | H88: G-506, near RYDERS SPORTS ACADEMY, Block G, Sushant Lok 2, Sector 57, Gurugram, Haryana 122011, India | M88: Map

Sheet Sector 58
A1: SWITCH · SECTOR 58 · MOBILE CALL SHEET
A2: Owner/manager mobiles · shifts 1–12 hrs, pay after worker reports · instant replacement | 42 leads · 38 in priority industries (top)
A3: LEADS | B3: =COUNTA(B5:B46) | C3: CONTACTED | D3: =COUNTA(I5:I46) | E3: INTERESTED | F3: =COUNTIF(I5:I46,"Yes") | G3: ORDERS | H3: =COUNTIF(K5:K46,"Yes") | I3: HOURS BOOKED | J3: =SUM(J5:J46)
A4: S.No | B4: Business Name | C4: Target Industry | D4: Suggested Roles (per shift) | E4: Manager Mobile | F4: Rating | G4: Reviews | H4: Address | I4: Interested? | J4: Hours (1-12) | K4: Order Confirmed? | L4: Remarks | M4: Map
A5: 1 | B5: Banjara Market Gurugram | C5: Shop / Retail | D5: Store Helper, Housekeeping, Security, Sales Staff | E5: 8000060380 | F5: 4.7 | G5: 7759 | H5: Ho No 51, behind Bani Mandir Gaushala Road, Ghatta Kanarpur, Sector 58, Ghata, Gurugram, Haryana 122011, India | M5: Map
A6: 2 | B6: Where Else BYOB & Cafe | C6: Restaurant / Food | D6: Kitchen Helper, Cook, Dishwasher, Waiter | E6: 8287082434 | F6: 3.8 | G6: 3282 | H6: Plot Number 1, Rajesh Pilot Marg, Golf Course Ext Rd, Sector 58, Gurugram, Haryana 122011, India | M6: Map
A7: 3 | B7: Banjara Market | C7: Shop / Retail | D7: Store Helper, Housekeeping, Security, Sales Staff | E7: 8826335048 | F7: 4.6 | G7: 3167 | H7: Bani Mandir Gaushala Rd, Karanpur, Sector 58, Ghata, Gurugram, Haryana 122102, India | M7: Map
A8: 4 | B8: Qube BYOB and Lounge | C8: Restaurant / Food | D8: Kitchen Helper, Cook, Dishwasher, Waiter | E8: 9711033333 | F8: 4 | G8: 440 | H8: C494+XJ, Sector 58, Gurugram, Haryana 122011, India | M8: Map
A9: 5 | B9: Cena Pranzo | C9: Restaurant / Food | D9: Kitchen Helper, Cook, Dishwasher, Waiter | E9: 8800021048 | F9: 4.7 | G9: 334 | H9: Cena Pranzo, Grand Hyatt, Golf Course Rd, Sector 58, Gurugram, Haryana 122098, India | M9: Map
A10: 6 | B10: Parisian Cafe | C10: Restaurant / Food | D10: Kitchen Helper, Cook, Dishwasher, Waiter | E10: 8929800085 | F10: 4.4 | G10: 216 | H10: shop 18A, ground floor, ireo grand view, high street, near grand hyatt hotel, Sector 58, Gurugram, Haryana 122098, India | M10: Map
A11: 7 | B11: Maison Maiya | C11: Restaurant / Food | D11: Kitchen Helper, Cook, Dishwasher, Waiter | E11: 9205780935 | F11: 4.4 | G11: 133 | H11: C473+R3 Maison Maiya, Sector 58, Gurugram, Haryana 122098, India | M11: Map
A12: 8 | B12: New Banjara Market Gurgaon | C12: Shop / Retail | D12: Store Helper, Housekeeping, Security, Sales Staff | E12: 8744888866 | F12: 4.6 | G12: 127 | H12: Bani Mandir Gaushala Rd, Ghatta Kanarpur, Sector 58, Gurugram, Ghata, Haryana 122011, India | M12: Map
A13: 9 | B13: Urban Furniture Home Renew & Repairs - Paint, Fabrications | C13: Shop / Retail | D13: Store Helper, Housekeeping, Security, Sales Staff | E13: 9718700734 | F13: 4.9 | G13: 122 | H13: Shop No.4, Banjara Mkt Rd, near Power House, Ghatta Kanarpur, Sector 58, Gurugram, Haryana 122098, India | M13: Map
A14: 10 | B14: Remy's | C14: Restaurant / Food | D14: Kitchen Helper, Cook, Dishwasher, Waiter | E14: 9473384149 | F14: 4.8 | G14: 109 | H14: Magnum Global Park, 1701A, Sector 58, Gurugram, Haryana 122098, India | M14: Map
A15: 11 | B15: SI | C15: Shop / Retail | D15: Store Helper, Housekeeping, Security, Sales Staff | E15: 9084006427 | F15: 4.5 | G15: 108 | H15: Buddha Market, Plot number 7, opposite Ireo ascot, Sector 58, Gurugram, Ghata, Haryana 122151, India | M15: Map
A16: 12 | B16: Gonzo - Asian Tapas Bar | C16: Restaurant / Food | D16: Kitchen Helper, Cook, Dishwasher, Waiter | E16: 9811926307 | F16: 4.1 | G16: 103 | H16: Shop no 5A,5B,5C, The Boulevard Magnum Global Park, Golf Course Ext Rd, Sector 58, Gurugram, Haryana 122098, India | M16: Map
... A36: 32 | B36: R.S Jewellers | C36: Shop / Retail | D36: Store Helper, Housekeeping, Security, Sales Staff | E36: 9654570423 | F36: 1 | G36: 1 | H36: Ghatta Kanarpur, Sector 58, Gurugram, Haryana 122011, India | M36: Map
A37: 33 | B37: 1C Charging Station | C37: Warehouse / Logistics | D37: Office Boy, Housekeeping, Security, Helper | E37: 9599443291 | H37: MAGNUM GLOBAL PARK, Golf Course Ext Rd, Sector 58, Gurugram, Haryana 122098, India | M37: Map
A38: 34 | B38: Customized Promotional & Corporate Gifts - Manufacturer and Wholesaler | C38: Shop / Retail | D38: Machine Operator, Helper, Loader, Packer | E38: 9560592143 | H38: Golf Course Ext Rd, Sector 58, Gurugram, Haryana 122001, India | M38: Map
A39: 35 | B39: EKA IREO | C39: Shop / Retail | D39: Store Helper, Housekeeping, Security, Sales Staff | E39: 7428821296 | H39: Ground Floor, Unit 17A & 17B, Ireo Grand View High Street, Golf Course Ext Rd, Sector 58, Gurugram, Haryana 122098, India | M39: Map
A40: 36 | B40: Gift Gallery | C40: Shop / Retail | D40: Store Helper, Housekeeping, Security, Sales Staff | E40: 7042403282 | H40: Banjara Mkt Rd, Sector 58, Gurugram, Haryana 122011, India | M40: Map
A41: 37 | B41: Rakshita BEAUTY PARLOUR | C41: Salon / Spa | D41: Beautician, Helper, Receptionist, Cleaner | E41: 9899242832 | H41: Ghatta Kanarpur, Sector 58, Gurugram, Haryana 122011, India | M41: Map
A42: 38 | B42: Ramjivan Chicken | C42: Restaurant / Food | D42: Kitchen Helper, Cook, Dishwasher, Waiter | E42: 9958180246 | H42: Shop no.12 Sector. 55 Ghata, Gaon, Ghatta Kanarpur, Sector 58, Gurugram, Haryana 122011, India | M42: Map
A43: 39 | B43: Lifelong Online | C43: Other | D43: Office Boy, Housekeeping, Security, Helper | E43: 9711558877 | F43: 4.3 | G43: 661 | H43: C475+39G Good Earth Business Bay II, Sector 58, Gurugram, Haryana 122098, India | M43: Map
A44: 40 | B44: Good Earth Business Bay II | C44: Other | D44: Office Boy, Housekeeping, Security, Helper | E44: 8527907829 | F44: 4.8 | G44: 139 | H44: Ground Floor, Good Earth Business Bay II, Sector 58, Gurugram, Haryana 122098, India | M44: Map
A45: 41 | B45: BIM Americas | C45: Other | D45: Office Boy, Housekeeping, Security, Helper | E45: 9999216000 | F45: 5 | G45: 83 | H45: 17th Floor, Magnum Global Park, Unit Number: 1714 B, Golf Course Ext Rd, Sector 58, Gurugram, Haryana 122098, India | M45: Map
A46: 42 | B46: 7 Estates India | C46: Other | D46: Office Boy, Housekeeping, Security, Helper | E46: 7877775772 | F46: 4.9 | G46: 57 | H46: Magnum Global Park, 715 B & C, Golf Course Ext Rd, Sector 58, Gurugram, Haryana 122011, India | M46: Map

Sheet Sector 59
A1: SWITCH · SECTOR 59 · MOBILE CALL SHEET
A2: Owner/manager mobiles · shifts 1–12 hrs, pay after worker reports · instant replacement | 18 leads · 16 in priority industries (top)
A3: LEADS | B3: =COUNTA(B5:B22) | C3: CONTACTED | D3: =COUNTA(I5:I22) | E3: INTERESTED | F3: =COUNTIF(I5:I22,"Yes") | G3: ORDERS | H3: =COUNTIF(K5:K22,"Yes") | I3: HOURS BOOKED | J3: =SUM(J5:J22)
A4: S.No | B4: Business Name | C4: Target Industry | D4: Suggested Roles (per shift) | E4: Manager Mobile | F4: Rating | G4: Reviews | H4: Address | I4: Interested? | J4: Hours (1-12) | K4: Order Confirmed? | L4: Remarks | M4: Map
A5: 1 | B5: Cafe Soul Garden | C5: Restaurant / Food | D5: Kitchen Helper, Cook, Dishwasher, Waiter | E5: 7701907883 | F5: 4.2 | G5: 4632 | H5: Ug 11-12, Ascott Ireo City Central, Alahawas, Sector 59, Gurugram, Haryana 122011, India | M5: Map
A6: 2 | B6: ate | altogether experimental | Omakase | C6: Restaurant / Food | D6: Kitchen Helper, Cook, Dishwasher, Waiter | E6: 9311915510 | F6: 4.6 | G6: 545 | H6: 1st Floor, Ascott Ireo City Central, Alahawas, Sector 59, Gurugram, Haryana 122098, India | M6: Map
A7: 3 | B7: Dana Choga Reserve | C7: Restaurant / Food | D7: Kitchen Helper, Cook, Dishwasher, Waiter | E7: 9213777111 | F7: 4.4 | G7: 411 | H7: Shop Number -FF-5,6,7, 1st Floor, Ascott Ireo City Central, 7A,8, Alahawas, Sector 59, Gurugram, Haryana 122098, India | M7: Map
A8: 4 | B8: Toni & Guy Hairdressing, Beauty, Make-up, Nail Bar | C8: Restaurant / Food | D8: Kitchen Helper, Cook, Dishwasher, Waiter | E8: 7303880494 | F8: 4.6 | G8: 341 | H8: UG 5,6,7, TONI AND GUY, Ascott Ireo City Central, Alahawas, Sector 59, Gurugram, Haryana 122098, India | M8: Map
A9: 5 | B9: JUJUBE - Asian Experience | C9: Restaurant / Food | D9: Kitchen Helper, Cook, Dishwasher, Waiter | E9: 9773662059 | F9: 4.6 | G9: 251 | H9: Shop 25, Ascott Ireo City Central, Alahawas, Sector 59, Gurugram, Haryana 122098, India | M9: Map
A10: 6 | B10: CUT&STYLE Salon - Sector-59, Gurugram | C10: Salon / Spa | D10: Beautician, Helper, Receptionist, Cleaner | E10: 7825893516 | F10: 4.7 | G10: 123 | H10: UG 68, Ascott Ireo City Central, Alahawas, Sector 59, Gurugram, Haryana 122001, India | M10: Map
A11: 7 | B11: Joaah Cafe | C11: Restaurant / Food | D11: Kitchen Helper, Cook, Dishwasher, Waiter | E11: 9650455005 | F11: 4.4 | G11: 120 | H11: Shop No. 18,19,28, Ascott Ireo City Central, behind Jagdish Store, Alahawas, Sector 59, Gurugram, Haryana 122011, India | M11: Map
A12: 8 | B12: KFC | C12: Restaurant / Food | D12: Kitchen Helper, Cook, Dishwasher, Waiter | E12: 8042754444 | F12: 4.6 | G12: 74 | H12: ground floor, Pink Floyd Blvd, Alahawas, Sector 59, Gurugram, Haryana 122098, India | M12: Map
A13: 9 | B13: K R Sofa Repairing | C13: Shop / Retail | D13: Store Helper, Housekeeping, Security, Sales Staff | E13: 9015555717 | F13: 5 | G13: 63 | H13: Shop No 313, Revenue Road, Dayma Rd, Alahawas, Sector 59, Gurugram, Haryana 122098, India | M13: Map
A14: 10 | B14: Jagdish Store Gurgaon - Home Furnishings & Linen Store | C14: Shop / Retail | D14: Store Helper, Housekeeping, Security, Sales Staff | E14: 9810012660 | F14: 4.6 | G14: 35 | H14: Shop No- 22, Ascott Ireo City Central, Alahawas, Sector 59, Gurugram, Haryana 122101, India | M14: Map
A15: 11 | B15: Emric salon 59 | C15: Salon / Spa | D15: Beautician, Helper, Receptionist, Cleaner | E15: 9319806566 | F15: 5 | G15: 25 | H15: Tower c, Tower c_altaris, MAHINDRA LIFESPACES LUMINARE, Alahawas, Sector 59, Gurugram, Haryana 122098, India | M15: Map
A16: 12 | B16: Food 59 Grill | C16: Restaurant / Food | D16: Kitchen Helper, Cook, Dishwasher, Waiter | E16: 9891211139 | F16: 5 | G16: 13 | H16: Alahawas, Sector 59, Gurugram, Haryana 122098, India | M16: Map
... A18: 14 | B18: Monsoon Salon Gurgaon -59 | C18: Salon / Spa | D18: Beautician, Helper, Receptionist, Cleaner | E18: 9821818420 | F18: 3.8 | G18: 10 | H18: Shop No-9, Ireo Icc, Alahawas, Sector 59, Gurugram, Haryana 122098, India | M18: Map
A19: 15 | B19: Hamad Aluminum | C19: Shop / Retail | D19: Store Helper, Housekeeping, Security, Sales Staff | E19: 9259622145 | H19: Sector 59, Dayma Rd, Alahawas, Sector 59, Gurugram, Haryana 122011, India | M19: Map
A20: 16 | B20: King Koil Mattress Store - F Decor | C20: Shop / Retail | D20: Store Helper, Housekeeping, Security, Sales Staff | E20: 9810483123 | H20: UG O9, Ascott Ireo City Central, Alahawas, Sector 59, Gurugram, Haryana 122011, India | M20: Map
A21: 17 | B21: Himanshi Clinic | C21: Other | D21: Ward Boy, Housekeeping, Attendant, Security | E21: 9634390209 | F21: 5 | G21: 1 | H21: C465+6R2, near Ayur Company, Behrampur Village, Sector 59, Gurugram, Haryana 122098, India | M21: Map
A22: 18 | B22: PVE Home Elevators - Delhi | C22: Other | D22: Machine Operator, Helper, Loader, Packer | E22: 8925845464 | F22: 5 | G22: 1 | H22: UG71-A, Ground Floor, Ascott Ireo City Central, Alahawas, Sector 59, Gurugram, Haryana 122098, India | M22: Map

Sheet Sector 60
A1: SWITCH · SECTOR 60 · MOBILE CALL SHEET
A2: Owner/manager mobiles · shifts 1–12 hrs, pay after worker reports · instant replacement | 11 leads · 8 in priority industries (top)
A3: LEADS | B3: =COUNTA(B5:B15) | C3: CONTACTED | D3: =COUNTA(I5:I15) | E3: INTERESTED | F3: =COUNTIF(I5:I15,"Yes") | G3: ORDERS | H3: =COUNTIF(K5:K15,"Yes") | I3: HOURS BOOKED | J3: =SUM(J5:J15)
A4: S.No | B4: Business Name | C4: Target Industry | D4: Suggested Roles (per shift) | E4: Manager Mobile | F4: Rating | G4: Reviews | H4: Address | I4: Interested? | J4: Hours (1-12) | K4: Order Confirmed? | L4: Remarks | M4: Map
A5: 1 | B5: Foxtrail Sector 60 - AM Hotel Kollection | C5: Hotel / OYO | D5: Housekeeping, Room Boy, Kitchen Helper, Front Desk | E5: 9217101072 | F5: 4.8 | G5: 172 | H5: ICP-D, Ascott Ireo City Central, D14-01, Sector 60, Gurugram, Haryana 122098, India | M5: Map
A6: 2 | B6: Adrita Menopause Wellness | C6: Salon / Spa | D6: Beautician, Helper, Receptionist, Cleaner | E6: 9560905470 | F6: 5 | G6: 92 | H6: Second Floor, Adrita Menopause Wellness, Miracle Mile, SF- 64, Sector 60, Gurugram, Haryana 122098, India | M6: Map
A7: 3 | B7: Glitz Salon, Sector 60, Miracle Mile Mall | C7: Salon / Spa | D7: Store Helper, Housekeeping, Security, Sales Staff | E7: 7303468816 | F7: 4.9 | G7: 60 | H7: Shop No, 64, Ground Floor, Miracle mile Mall, Sector 60, Gurugram, Haryana 122002, India | M7: Map
A8: 4 | B8: ADORNE by ADITI - Jewellery Store in Sector - 60 Gurgaon | C8: Shop / Retail | D8: Store Helper, Housekeeping, Security, Sales Staff | E8: 9870186408 | F8: 4.9 | G8: 30 | H8: GF 70, ADANI MIRACLE MILE, Sector 60, Gurugram, Haryana 122011, India | M8: Map
A9: 5 | B9: Chick Blinds Shop | Chick Maker In Gurgaon | Bamboo Blinds Maker In Gurgaon | pigeon net | C9: Shop / Retail | D9: Store Helper, Housekeeping, Security, Sales Staff | E9: 7982283142 | F9: 5 | G9: 4 | H9: Shop No- 21, Gate Adani, opposite DLF Park Place M Block, Sector 60, Samsara, Gurugram, Haryana 122009, India | M9: Map
A10: 6 | B10: Scapes Co-Work | C10: Salon / Spa | D10: Beautician, Helper, Receptionist, Cleaner | E10: 7042222715 | F10: 3.3 | G10: 3 | H10: Unit No. 5D, Block A, 5th Floor, Convention Center Lemon Tree Corporate Park, Ullawas Dhani Rd, Sector 60, Gurugram, Haryana 122098, India | M10: Map
A11: 7 | B11: Dukhiram Jana | C11: Restaurant / Food | D11: Kitchen Helper, Cook, Dishwasher, Waiter | E11: 9599063474 | F11: 5 | G11: 2 | H11: Tower-2, Lemon Tree Hotel, Sector 60 Ullawas ,Sec 60, Sector 60, Gurugram, Haryana 122098, India | M11: Map
A12: 8 | B12: STAPES & BAUBLE PRIVATE LIMITED | C12: Shop / Retail | D12: Store Helper, Housekeeping, Security, Sales Staff | E12: 9810742364 | F12: 4.5 | G12: 2 | H12: SF 35, Miracle Mile, off Golf Course Extension Road, Pocket M, Sector 60, Gurugram, Haryana 122098, India | M12: Map
A13: 9 | B13: Star Dance Company 🇮🇳 | C13: Other | D13: Trainer, Housekeeping, Front Desk | E13: 9560632514 | F13: 5 | G13: 89 | H13: Ireo Nuresry school plot, opposite IREO SKYON, Sector 60, Gurugram, Haryana 122098, India | M13: Map
A14: 10 | B14: Car Electricals Automobile | C14: Other | D14: Mechanic Helper, Cleaner, Washer | E14: 9319850097 | F14: 4.9 | G14: 63 | H14: Ch.Nandaram Marg, near Lemon Tree Hotel, Sector 60, Gurugram, Haryana 122102, India | M14: Map
A15: 11 | B15: Adani Realty | C15: Other | D15: Office Boy, Housekeeping, Security, Helper | E15: 8071500129 | F15: 4.2 | G15: 59 | H15: First floor 38, GLOBAL APPAREL, A D, off Golf Course Extension Road, Sector 60, Gurugram, Haryana 122098, India | M15: Map

Sheet Sector 61
A1: SWITCH · SECTOR 61 · MOBILE CALL SHEET
A2: Owner/manager mobiles · shifts 1–12 hrs, pay after worker reports · instant replacement | 34 leads · 31 in priority industries (top)
A3: LEADS | B3: =COUNTA(B5:B38) | C3: CONTACTED | D3: =COUNTA(I5:I38) | E3: INTERESTED | F3: =COUNTIF(I5:I38,"Yes") | G3: ORDERS | H3: =COUNTIF(K5:K38,"Yes") | I3: HOURS BOOKED | J3: =SUM(J5:J38)
A4: S.No | B4: Business Name | C4: Target Industry | D4: Suggested Roles (per shift) | E4: Manager Mobile | F4: Rating | G4: Reviews | H4: Address | I4: Interested? | J4: Hours (1-12) | K4: Order Confirmed? | L4: Remarks | M4: Map
A5: 1 | B5: DONJON | C5: Restaurant / Food | D5: Kitchen Helper, Cook, Dishwasher, Waiter | E5: 8800082111 | F5: 3.9 | G5: 1920 | H5: Golf Course Ext Rd, opposite Grand View High Street, Baharampur Naya, Sector 61, Gurugram, Haryana 122098, India | M5: Map
A6: 2 | B6: Snyllo Éstetica | C6: Salon / Spa | D6: Ward Boy, Housekeeping, Attendant, Security | E6: 8795606009 | F6: 3.6 | G6: 186 | H6: 4th Floor, BPTP Centra One, Golf Course Ext Rd, Baharampur Naya, Sector 61, Gurugram, Haryana 122011, India | M6: Map
A7: 3 | B7: Makerman | C7: Shop / Retail | D7: Office Boy, Housekeeping, Security, Helper | E7: 6912345678 | F7: 4.7 | G7: 138 | H7: Unit no. 617, Emaar Digital Greens, Tower A, Golf Course Ext Rd, Baharampur Naya, Sector 61, Gurugram, Haryana 122098, India | M7: Map
A8: 4 | B8: GYAN AQUARIUM & PET SHOP | C8: Shop / Retail | D8: Store Helper, Housekeeping, Security, Sales Staff | E8: 9971763325 | F8: 4.8 | G8: 131 | H8: Shop no 15, 1st floor, Ram ji market, near Pioneer park ulawas, Baharampur Naya, Sector 61, Gurugram, Haryana 122011, India | M8: Map
A9: 5 | B9: Rama Palace | C9: Hotel / OYO | D9: Housekeeping, Room Boy, Kitchen Helper, Front Desk | E9: 9811007394 | F9: 4.3 | G9: 118 | H9: Sector-61, Haryana Road, Baharampur Naya, Sector 61, Gurugram, Haryana 122098, India | M9: Map
A10: 6 | B10: Jaquar Authorised Dealer - Design & Style - MYK Laticrete & Wallpaper | C10: Shop / Retail | D10: Store Helper, Housekeeping, Security, Sales Staff | E10: 9313266928 | F10: 4.9 | G10: 47 | H10: Shop No. 25, Ullahawas, Baharampur Naya, Sector 61, Gurugram, Haryana 122001, India | M10: Map
A11: 7 | B11: Chick maker in gurgaon ad blinds Shop | C11: Shop / Retail | D11: Store Helper, Housekeeping, Security, Sales Staff | E11: 8279541079 | F11: 5 | G11: 28 | H11: shop no.4, Plot no 7, near Trinity mall, Ullahawas, Baharampur Naya, Sector 61, Gurugram, Haryana 122098, India | M11: Map
A12: 8 | B12: Mrs Bectors Food Specialities Ltd. | C12: Restaurant / Food | D12: Kitchen Helper, Cook, Dishwasher, Waiter | E12: 9826543746 | F12: 4.2 | G12: 23 | H12: Emaar Digital Greens Tower-A, First Floor, C37W+Q5P, Baharampur Naya, Sector 61, Gurugram, Haryana 122098, India | M12: Map
A13: 9 | B13: Parvanii | C13: Restaurant / Food | D13: Kitchen Helper, Cook, Dishwasher, Waiter | E13: 9583513344 | F13: 3.8 | G13: 17 | H13: Shop No 14, 15, 1st Floor, Ullawas Ramji Market, Baharampur Naya, Sector 61, Gurugram, Haryana 122101, India | M13: Map
A14: 10 | B14: SNYLLO INNOVATIONS PVT. LTD | SnylloAir | C14: Hotel / OYO | D14: Housekeeping, Room Boy, Kitchen Helper, Front Desk | E14: 8070067000 | F14: 3.3 | G14: 14 | H14: 3rd Floor, BPTP Centra, One, Golf Course Ext Rd, Baharampur Naya, Sector 61, Gurugram, Haryana 122098, India | M14: Map
A15: 11 | B15: Himanshu Prints And Design | C15: Shop / Retail | D15: Machine Operator, Helper, Loader, Packer | E15: 8468847888 | F15: 5 | G15: 12 | H15: Shop No. B-1, HBR Market, CRPF Rd, HBR Chowk, Ullawas, Sector 61, Gurugram, Haryana 122098, India | M15: Map
A16: 12 | B16: AS BALAJI CYBER CAFE & COMPUTER CENTER | C16: Restaurant / Food | D16: Kitchen Helper, Cook, Dishwasher, Waiter | E16: 8910605188 | F16: 4.5 | G16: 10 | H16: SHOP NO 2 CRPF ROAD HBR MARKET ULLAWAS, near HBR 1 RESIDENCY, HBR CHAWK, Sector 61, Gurugram, Haryana 122098, India | M16: Map
... A32: 28 | B32: Charcoal Eats - Ramji Market | C32: Cloud Kitchen | D32: Kitchen Helper, Cook, Packer, Delivery Rider, Dishwasher | E32: 9022500500 | F32: 1 | G32: 1 | H32: Triumph Hyundai Showroom Golf, Shop No. 17 On First Floor, Ramji Market Gramin Bank, Ullahawas, Sector 61, Gurugram, Haryana 122101, India | M32: Map
A33: 29 | B33: Kurban Ali rashan Shop | C33: Restaurant / Food | D33: Kitchen Helper, Cook, Dishwasher, Waiter | E33: 8447089695 | H33: Dayma Rd, near Hyatt hotel, Baharampur Naya, Sector 61, Gurugram, Haryana 122098, India | M33: Map
A34: 30 | B34: Muhjair Cycles | C34: Shop / Retail | D34: Store Helper, Housekeeping, Security, Sales Staff | E34: 9006931159 | H34: Shop No 12, Hbr Market, Baharampur Naya, Sector 61, Gurugram, Haryana 122098, India | M34: Map
A35: 31 | B35: Sunil Hair Cutting Saloon | C35: Salon / Spa | D35: Beautician, Helper, Receptionist, Cleaner | E35: 7041548234 | H35: Ullawas Bihari Mandi, Shop No 04, Baharampur Naya, Sector 61, Ghamroj, Gurugram, Haryana 122098, India | M35: Map
A36: 32 | B36: IMWOW - Head Office | C36: Other | D36: Office Boy, Housekeeping, Security, Helper | E36: 9958180436 | F36: 4.8 | G36: 990 | H36: Level 3 and Level 4, BPTP Centra One, Golf Course Ext Rd, Baharampur Naya, Sector 61, Gurugram, Haryana 122098, India | M36: Map
A37: 33 | B37: TENNIS VIDYALAYA | C37: Other | D37: Trainer, Housekeeping, Front Desk | E37: 9811605353 | F37: 4.9 | G37: 466 | H37: Ullawas, CRPF Rd, Baharampur Naya, Sector 61, Gurugram, Haryana 122098, India | M37: Map
A38: 34 | B38: Hair Patch Centre | C38: Other | D38: Ward Boy, Housekeeping, Attendant, Security | E38: 8920199846 | F38: 5 | G38: 109 | H38: Shop No.16, 1st floor, Ram ji Market, near Pioneer Park Drive, Ulawas, Sector 61, Gurugram, Haryana 122098, India | M38: Map

Sheet Sector 62
A1: SWITCH · SECTOR 62 · MOBILE CALL SHEET
A2: Owner/manager mobiles · shifts 1–12 hrs, pay after worker reports · instant replacement | 88 leads · 80 in priority industries (top)
A3: LEADS | B3: =COUNTA(B5:B92) | C3: CONTACTED | D3: =COUNTA(I5:I92) | E3: INTERESTED | F3: =COUNTIF(I5:I92,"Yes") | G3: ORDERS | H3: =COUNTIF(K5:K92,"Yes") | I3: HOURS BOOKED | J3: =SUM(J5:J92)
A4: S.No | B4: Business Name | C4: Target Industry | D4: Suggested Roles (per shift) | E4: Manager Mobile | F4: Rating | G4: Reviews | H4: Address | I4: Interested? | J4: Hours (1-12) | K4: Order Confirmed? | L4: Remarks | M4: Map
A5: 1 | B5: Bicycle Adda - One-stop Bicycle Shop in Gurgaon | C5: Shop / Retail | D5: Store Helper, Housekeeping, Security, Sales Staff | E5: 9821213716 | F5: 4.9 | G5: 997 | H5: Shop no. 1-3, Bicycle Adda Ramji market, CRPF Rd, near Urban Akhara, Sector 62, Gurugram, Haryana 122098, India | M5: Map
A6: 2 | B6: 72 SINGH DHABA | C6: Restaurant / Food | D6: Kitchen Helper, Cook, Dishwasher, Waiter | E6: 8745900072 | F6: 4.3 | G6: 860 | H6: CRPF Rd, Sector 62, Gurugram, Haryana 122098, India | M6: Map
A7: 3 | B7: Boombastic: Amusement & Trampoline Park Gurgaon - Birthday Party Places in Gurgaon | C7: Hotel / OYO | D7: Office Boy, Housekeeping, Security, Helper | E7: 7669157766 | F7: 4.7 | G7: 856 | H7: Jmd Empire, Golf Course Ext Rd, Block C, Sector 62, Gurugram, Haryana 122102, India | M7: Map
A8: 4 | B8: Shree Ram Dhaba | C8: Restaurant / Food | D8: Kitchen Helper, Cook, Dishwasher, Waiter | E8: 7065301308 | F8: 4.2 | G8: 438 | H8: C36G+4CR, Sector 62, Nangli Umarpur, Gurugram, Haryana 122098, India | M8: Map
A9: 5 | B9: Aquarist Design Studio – Custom Luxury Aquariums | C9: Shop / Retail | D9: Store Helper, Housekeeping, Security, Sales Staff | E9: 8851397778 | F9: 4.6 | G9: 227 | H9: Unit no. 12, First Floor, Ramji market, near Bicycle Adda, Sector 62, Gurugram, Haryana 122098, India | M9: Map
A10: 6 | B10: Giftcart Ecommerce Private Limited | C10: Shop / Retail | D10: Store Helper, Housekeeping, Security, Sales Staff | E10: 9910644899 | F10: 4.8 | G10: 142 | H10: Block-D, Jmd Empire, 343-345, Golf Course Ext Rd, Sector 62, Gurugram, Haryana 122098, India | M10: Map
A11: 7 | B11: Kaiden2Kats Foundation | C11: Shop / Retail | D11: Office Boy, Housekeeping, Security, Helper | E11: 9717965519 | F11: 4.8 | G11: 129 | H11: Gali no 1, kila number 14, Nangli Umarpur Rd, Sector 62, Gurugram, Haryana 122101, India | M11: Map
A12: 8 | B12: Glam Studios | C12: Salon / Spa | D12: Beautician, Helper, Receptionist, Cleaner | E12: 7304630696 | F12: 4.8 | G12: 122 | H12: 2, Aipl Business Club, Sector 62, Gurugram, Haryana 122098, India | M12: Map
A13: 9 | B13: The flying Apron By Karishma | C13: Restaurant / Food | D13: Kitchen Helper, Cook, Dishwasher, Waiter | E13: 9953943330 | F13: 5 | G13: 95 | H13: Pioneer Araya, Sector 62, Gurugram, Haryana 122011, India | M13: Map
A14: 10 | B14: Fur Ball Story Pet Retreat | C14: Restaurant / Food | D14: Office Boy, Housekeeping, Security, Helper | E14: 9582112979 | F14: 4.5 | G14: 63 | H14: Kila No. 20, Nagli Umarpur, near Paras Trinity, Sector 62, Gurugram, Haryana 122098, India | M14: Map
A15: 11 | B15: Curriies4u | C15: Supermarket / Grocery | D15: Office Boy, Housekeeping, Security, Helper | E15: 8851430161 | F15: 5 | G15: 62 | H15: Pioneer Araya, Shaffu Foods, Golf Course Ext Rd, Sector 62, Gurugram, Haryana 122103, India | M15: Map
A16: 12 | B16: Street Studio | C16: Shop / Retail | D16: Pump Attendant, Cleaner, Security | E16: 9910113208 | F16: 4.9 | G16: 43 | H16: Golf Course Ext Rd, Sector 62, Gurugram, Haryana 122001, India | M16: Map
... A71: 67 | B71: Restaurant Cafe kitchen equipments | C71: Restaurant / Food | D71: Kitchen Helper, Cook, Dishwasher, Waiter | E71: 9896999967 | F71: 1 | G71: 1 | H71: HBR chowk, Sector 62, Gurugram, Haryana 122098, India | M71: Map
A72: 68 | B72: Agarwal Packers And Movers Gurgaon | C72: Warehouse / Logistics | D72: Loader, Packer, Picker, Warehouse Helper, Delivery | E72: 7665678702 | H72: Shop No 03, Sector 62, Gurugram, Haryana 122098, India | M72: Map
A73: 69 | B73: Apeksha Tour and Travels | C73: Warehouse / Logistics | D73: Office Boy, Housekeeping, Security, Helper | E73: 8130327347 | H73: 19/2/62, Marg, Sector 62, Gurugram, Haryana 122098, India | M73: Map
A74: 70 | B74: Arsan Air Conditioner | C74: Shop / Retail | D74: Store Helper, Housekeeping, Security, Sales Staff | E74: 9991584470 | H74: Indira Gandhi Eye Hospital, Sector 62, Gurugram, Haryana 122102, India | M74: Map
A75: 71 | B75: Asha Shop | C75: Shop / Retail | D75: Store Helper, Housekeeping, Security, Sales Staff | E75: 7428017351 | H75: Asha Shop, Sabji Mandi, Ullahawas, Baharampur Naya, Sector 62, Gurugram, Haryana 122098, India | M75: Map
A76: 72 | B76: Bowl Radha Bowl | C76: Restaurant / Food | D76: Kitchen Helper, Cook, Dishwasher, Waiter | E76: 7430030003 | H76: Shop no 103, first floor, Ram ji market, Ullawas Dhani Rd, near Zomato office, Sector 62, Gurugram, Haryana 122098, India | M76: Map
A77: 73 | B77: Breath by Nidhi | C77: Shop / Retail | D77: Store Helper, Housekeeping, Security, Sales Staff | E77: 9811664680 | H77: B 1102, Pioneer Presidia, Sector 62, Gurugram, Haryana 122098, India | M77: Map
A78: 74 | B78: Cafe Shahtoot | C78: Restaurant / Food | D78: Kitchen Helper, Cook, Dishwasher, Waiter | E78: 8368518968 | H78: Shop G01, Imperia Mindspace, Sector 62, Gurugram, Haryana 122098, India | M78: Map
A79: 75 | B79: Crazy Fashion | C79: Restaurant / Food | D79: Store Helper, Housekeeping, Security, Sales Staff | E79: 9315530818 | H79: Block-D, Pioneer Urban Square, D-102, Golf Course Ext Rd, Sector 62, Gurugram, Haryana 122098, India | M79: Map
A80: 76 | B80: Morya Home Goods Store | C80: Shop / Retail | D80: Store Helper, Housekeeping, Security, Sales Staff | E80: 7988589044 | H80: Shop No 83 Banjara Market, near Jmd Empire, Sector 62, Gurugram, Haryana 122098, India | M80: Map
A81: 77 | B81: Navin Fruits Shop | C81: Supermarket / Grocery | D81: Store Helper, Housekeeping, Security, Sales Staff | E81: 9162860865 | H81: Sabji Mandi Ullabaas, C36R+W6M Navin Fruits Shop, Sector 62, Ghamroj, Gurugram, Haryana 122098, India | M81: Map
A82: 78 | B82: Sharwan Vegetables | C82: Restaurant / Food | D82: Kitchen Helper, Cook, Dishwasher, Waiter | E82: 8376817453 | H82: Aipl Business Club Tower-A, Kadarpur Rd, near by Heritage School, Sector 62, Gurugram, Haryana 122098, India | M82: Map
A83: 79 | B83: Soharab printers | C83: Shop / Retail | D83: Store Helper, Housekeeping, Security, Sales Staff | E83: 8092243827 | H83: Swastik hospital, Sector 62, Gurugram, Haryana 122001, India | M83: Map
A84: 80 | B84: VIKRAM YOGI | C84: Restaurant / Food | D84: Store Helper, Housekeeping, Security, Sales Staff | E84: 9718907035 | H84: DLF Sec.54, Faridabad Road, Sector 62, Gurugram, Haryana 122098, India | M84: Map
A85: 81 | B85: MRF T&S - Shri Shyam Ji Tyre Hub | C85: Other | D85: Store Helper, Housekeeping, Security, Sales Staff | E85: 9899266165 | F85: 5 | G85: 1387 | H85: Shop No 1, CRPF Rd, near Renault Showroom, Ullahawas, Baharampur Naya, Sector 62, Gurugram, Haryana 122098, India | M85: Map
A86: 82 | B86: Indira Gandhi Eye Hospital: Best Eye hospital in Gurgaon, Lasik Surgery, Cataract Surgery | C86: Other | D86: Ward Boy, Housekeeping, Attendant, Security | E86: 9667620071 | F86: 4.6 | G86: 559 | H86: Sector 62, Gurugram, Haryana 122098, India | M86: Map
A87: 83 | B87: Face Off-The Football Turf | C87: Other | D87: Trainer, Housekeeping, Front Desk | E87: 9650746664 | F87: 4.8 | G87: 552 | H87: PlayAll Sports Complex, CRPF Road, opposite Heritage Xperiential School, near Golf Course Extension Road, Sector 62, Gurugram, Haryana 122098, India | M87: Map
A88: 84 | B88: 4 Wheel Appeal | C88: Other | D88: Pump Attendant, Cleaner, Security | E88: 9599619298 | F88: 5 | G88: 375 | H88: C38M+263, Golf Course Ext Rd, Sector 62, Gurugram, Haryana 122011, India | M88: Map
A89: 85 | B89: National Battery House Luminous Inverter Battery Dealer in Gurgaon | Amaron Car Battery Dealer | C89: Other | D89: Office Boy, Housekeeping, Security, Helper | E89: 8750723447 | F89: 4.9 | G89: 205 | H89: Shop no.6, opposite Hyundai Service centre, Sector 62, Gurugram, Haryana 122098, India | M89: Map
A90: 86 | B90: Dr. Sanjay Dhawan - Eye Specialist Doctor In Delhi Gurgaon | C90: Other | D90: Office Boy, Housekeeping, Security, Helper | E90: 9810009144 | F90: 4.6 | G90: 184 | H90: Indira Gandhi Eye Hospital, Golf Course Ext Rd, near Heritage School, Sector 62, Gurugram, Haryana 122098, India | M90: Map
A91: 87 | B91: Excellence Gymnastics Private limited | C91: Other | D91: Trainer, Housekeeping, Front Desk | E91: 9999454880 | F91: 4.7 | G91: 141 | H91: 15/6& 15/8, near HBR CHOWK, Sector 62, Gurugram, Haryana 122098, India | M91: Map
A92: 88 | B92: ArchitecUS | C92: Other | D92: Office Boy, Housekeeping, Security, Helper | E92: 9811964064 | F92: 4.9 | G92: 117 | H92: 2nd Floor, Block-D, Jmd Empire, 263, Golf Course Ext Rd, Sector 62, Gurugram, Haryana 122098, India | M92: Map

Sheet Sector 63
A1: SWITCH · SECTOR 63 · MOBILE CALL SHEET
A2: Owner/manager mobiles · shifts 1–12 hrs, pay after worker reports · instant replacement | 17 leads · 14 in priority industries (top)
A3: LEADS | B3: =COUNTA(B5:B21) | C3: CONTACTED | D3: =COUNTA(I5:I21) | E3: INTERESTED | F3: =COUNTIF(I5:I21,"Yes") | G3: ORDERS | H3: =COUNTIF(K5:K21,"Yes") | I3: HOURS BOOKED | J3: =SUM(J5:J21)
A4: S.No | B4: Business Name | C4: Target Industry | D4: Suggested Roles (per shift) | E4: Manager Mobile | F4: Rating | G4: Reviews | H4: Address | I4: Interested? | J4: Hours (1-12) | K4: Order Confirmed? | L4: Remarks | M4: Map
A5: 1 | B5: Aradhya Furnishing Gurgaon. Curtains shop. | C5: Shop / Retail | D5: Store Helper, Housekeeping, Security, Sales Staff | E5: 9485908525 | F5: 5 | G5: 274 | H5: Shop no. 5, Maidawas Rd, near Aipl Business Club, Sector 63, Gurugram, Haryana 122002, India | M5: Map
A6: 2 | B6: Homemade Delights By Anamika | C6: Restaurant / Food | D6: Kitchen Helper, Cook, Dishwasher, Waiter | E6: 9599009109 | F6: 5 | G6: 216 | H6: Time Residency, D-804, Sector 63, Gurugram, Haryana 122101, India | M6: Map
A7: 3 | B7: Quick & spick car spa | C7: Salon / Spa | D7: Beautician, Helper, Receptionist, Cleaner | E7: 8800616133 | F7: 4.8 | G7: 101 | H7: near DLF, opp. annpurna dhaba, Sector 63, Gurugram, Haryana 122098, India | M7: Map
A8: 4 | B8: Nail’dit Studio by Beena | C8: Salon / Spa | D8: Beautician, Helper, Receptionist, Cleaner | E8: 8433953869 | F8: 4.8 | G8: 99 | H8: 144, FF, Paras Trinity, Golf course extension, Sector 63, Gurugram, Haryana 122011, India | M8: Map
A9: 5 | B9: Blissfully Yours | C9: Restaurant / Food | D9: Kitchen Helper, Cook, Dishwasher, Waiter | E9: 9971249820 | F9: 4.9 | G9: 87 | H9: Baani City Centre, CF-15-16, Sector 63, Gurugram, Haryana 122102, India | M9: Map
A10: 6 | B10: MB ANTIQUE FURNITURE | C10: Shop / Retail | D10: Store Helper, Housekeeping, Security, Sales Staff | E10: 8178247076 | F10: 4.9 | G10: 27 | H10: Shop no 3, dada harisingh market, Maidawas Rd, near bharat petrol pump, Sector-63A, Sector 63, Gurugram, Haryana 122098, India | M10: Map
A11: 7 | B11: Blushing Couture | C11: Shop / Retail | D11: Office Boy, Housekeeping, Security, Helper | E11: 9711845015 | F11: 5 | G11: 19 | H11: 803, Paras trinity, golf course extension road, Sector 63, Gurugram, Haryana 122098, India | M11: Map
A12: 8 | B12: Farm Durga Nursery And Plantation | C12: Shop / Retail | D12: Office Boy, Housekeeping, Security, Helper | E12: 9873130322 | F12: 5 | G12: 16 | H12: 1, J159, Adani Samsara Vilasa Rd, near to trehan luxury floor, opposite to Aipl Business Club, Sector 63, Gurugram, Haryana 122098, India | M12: Map
A13: 9 | B13: Sanowar glass & aluminium | C13: Shop / Retail | D13: Store Helper, Housekeeping, Security, Sales Staff | E13: 9990580764 | F13: 5 | G13: 11 | H13: Dada hari singh market, maidawas road, park, near Aipl Business Club, Sector 63, Gurugram, Haryana 122098, India | M13: Map
A14: 10 | B14: Kitchen Craft | C14: Restaurant / Food | D14: Kitchen Helper, Cook, Dishwasher, Waiter | E14: 9355806156 | F14: 4.1 | G14: 10 | H14: Baani city center, Sector 63, Gurugram, Haryana 122098, India | M14: Map
A15: 11 | B15: Kundan glass house | C15: Shop / Retail | D15: Store Helper, Housekeeping, Security, Sales Staff | E15: 9525576560 | F15: 5 | G15: 6 | H15: Dada hari singh market, Maidawas Rd, maidawdas, Sector 63, Gurugram, Haryana 122098, India | M15: Map
A16: 12 | B16: Unique interiors | C16: Shop / Retail | D16: Office Boy, Housekeeping, Security, Helper | E16: 8545903441 | F16: 5 | G16: 6 | H16: Shop no 1, maidawas road, park, near Aipl Business Club, Sector 63, Gurugram, Haryana 122098, India | M16: Map
A17: 13 | B17: MyTripDesk | C17: Warehouse / Logistics | D17: Office Boy, Housekeeping, Security, Helper | E17: 7042404013 | F17: 4.4 | G17: 5 | H17: CF-034, First Floor, Promenade Square BAANI CITY CENTER, Road, opposite AIPL Business Club, Medawas, Sector 63, Gurugram, Haryana 122098, India | M17: Map
A18: 14 | B18: Consortium Gifts | C18: Shop / Retail | D18: Store Helper, Housekeeping, Security, Sales Staff | E18: 9650023803 | H18: A-1801, Time Residency, Sector 63, Gurugram, Haryana 122098, India | M18: Map
A19: 15 | B19: Asthma Allergy TB Chest Centre I Dr. Jasmeet Kaur Wadhwa | C19: Other | D19: Office Boy, Housekeeping, Security, Helper | E19: 8800729407 | F19: 4.7 | G19: 210 | H19: GF Adani, Samsara, J 160, Sector 63, Gurugram, Haryana 122001, India | M19: Map
A20: 16 | B20: FIRST CHOICE PHARMACY | C20: Other | D20: Ward Boy, Housekeeping, Attendant, Security | E20: 9953142647 | F20: 4.9 | G20: 30 | H20: Dhoot, Time Residency, Sector 63, Gurugram, Haryana 122098, India | M20: Map
A21: 17 | B21: Daily car wash | C21: Other | D21: Pump Attendant, Cleaner, Security | E21: 9354991793 | F21: 4.7 | G21: 28 | H21: Maidawas Rd, near dlf, Sector 63, Gurugram, Haryana 122098, India | M21: Map

Sheet Sector 64
A1: SWITCH · SECTOR 64 · MOBILE CALL SHEET
A2: Owner/manager mobiles · shifts 1–12 hrs, pay after worker reports · instant replacement | 52 leads · 47 in priority industries (top)
A3: LEADS | B3: =COUNTA(B5:B56) | C3: CONTACTED | D3: =COUNTA(I5:I56) | E3: INTERESTED | F3: =COUNTIF(I5:I56,"Yes") | G3: ORDERS | H3: =COUNTIF(K5:K56,"Yes") | I3: HOURS BOOKED | J3: =SUM(J5:J56)
A4: S.No | B4: Business Name | C4: Target Industry | D4: Suggested Roles (per shift) | E4: Manager Mobile | F4: Rating | G4: Reviews | H4: Address | I4: Interested? | J4: Hours (1-12) | K4: Order Confirmed? | L4: Remarks | M4: Map
A5: 1 | B5: Orana Conventions | C5: Hotel / OYO | D5: Office Boy, Housekeeping, Security, Helper | E5: 8588883826 | F5: 4.4 | G5: 3505 | H5: Ramgarh, Sector 64, Golf Course Extension Road, Mall, opposite M3M Urbana Premium, Sector 64, Gurugram, Haryana 122101, India | M5: Map
A6: 2 | B6: AARamgarh | C6: Restaurant / Food | D6: Office Boy, Housekeeping, Security, Helper | E6: 9650062865 | F6: 4.4 | G6: 391 | H6: Nr M3M Urbana, Unnamed Road, Sector 64, Gurugram, Haryana 122101, India | M6: Map
A7: 3 | B7: Kósmos | C7: Hotel / OYO | D7: Housekeeping, Room Boy, Kitchen Helper, Front Desk | E7: 9100920079 | F7: 4.4 | G7: 169 | H7: opposite Worldmark, Sector 64, Gurugram, Haryana 122101, India | M7: Map
A8: 4 | B8: home decor Sofa repair gurgaon | C8: Shop / Retail | D8: Store Helper, Housekeeping, Security, Sales Staff | E8: 9870872402 | F8: 4.9 | G8: 114 | H8: Prajapati Rd, Medawas, Sector 64, Gurugram, Haryana 122101, India | M8: Map
A9: 5 | B9: Being Chef | Global Vegetarian Dining | Rooted in Vasudhaiva Kutumbakam Theme | C9: Restaurant / Food | D9: Kitchen Helper, Cook, Dishwasher, Waiter | E9: 9560500345 | F9: 4.9 | G9: 93 | H9: First Floor, Dharam Tower, Medawas Road, Golf Course Ext. Road, opp. M3M Route 65, Sector 64, Gurugram, Haryana 122101, India | M9: Map
A10: 6 | B10: Real Wood Furniture pvt ltd | C10: Shop / Retail | D10: Store Helper, Housekeeping, Security, Sales Staff | E10: 9540208011 | F10: 4.8 | G10: 93 | H10: Kshatriya samrat mibir bhoj chowk, Sector 64 Near by M3M Urbana Mall L N TChowk, Badshahpur, Sector 64, Gurugram, Haryana 122101, India | M10: Map
A11: 7 | B11: Shubhvastu Interior Design Studio | C11: Shop / Retail | D11: Office Boy, Housekeeping, Security, Helper | E11: 7450049001 | F11: 4.9 | G11: 91 | H11: Gujjar chowk, Maidawas Rd, Sector 64, Gurugram, Haryana 122101, India | M11: Map
A12: 8 | B12: Cyclocraze | C12: Shop / Retail | D12: Store Helper, Housekeeping, Security, Sales Staff | E12: 9517900060 | F12: 4.9 | G12: 69 | H12: Rect 41, Killa 13, opposite WorldMark, Sector 64, Gurugram, Haryana 122018, India | M12: Map
A13: 9 | B13: Professional Sofa Repair in Gurgaon(Reclinar Sofa Repair Sofa Cover Sofa Upholstery shop Gurugram | C13: Shop / Retail | D13: Store Helper, Housekeeping, Security, Sales Staff | E13: 7983790070 | F13: 4.9 | G13: 59 | H13: Shop No 12, Prajapati Rd, Medawas, Sector 64, Gurugram, Haryana 122101, India | M13: Map
A14: 10 | B14: DIRECT CARS | Gurgaon | C14: Shop / Retail | D14: Mechanic Helper, Cleaner, Washer | E14: 8588805508 | F14: 4.2 | G14: 54 | H14: Survey No 53 9/1, opposite M3M Urbana Mall, Sector 64, Gurugram, Haryana 122101, India | M14: Map
A15: 11 | B15: Dr. Hitesh Grewal: FreeFlow Physiotherapy Clinic | C15: Salon / Spa | D15: Ward Boy, Housekeeping, Attendant, Security | E15: 8814068141 | F15: 5 | G15: 48 | H15: Dharam Towers, Main, Maidawas Rd, Sector 64, Gurugram, Haryana 122101, India | M15: Map
A16: 12 | B16: Ruuh Wellness Spa | C16: Salon / Spa | D16: Beautician, Helper, Receptionist, Cleaner | E16: 9034450226 | F16: 5 | G16: 32 | H16: Sector 64, Urbana Worldmark Mall, opposite Gujjar Chowk, Sector 64, Gurugram, Haryana 122102, India | M16: Map
... A43: 39 | B43: H.B General Store | C43: Restaurant / Food | D43: Store Helper, Housekeeping, Security, Sales Staff | E43: 8447715883 | F43: 1 | G43: 1 | H43: Maidawas, Gurugram Delhi, 93WF+6HJ, Medawas, Sector 64, Gurugram, Haryana 122101, India | M43: Map
A44: 40 | B44: Dhan Bai | C44: Restaurant / Food | D44: Kitchen Helper, Cook, Dishwasher, Waiter | E44: 8178899762 | H44: Shop No 01 Bhuyapur, Maidawas Rd, Sector 64, Gurugram, Haryana 122101, India | M44: Map
A45: 41 | B45: Digital Payment One Time | C45: Restaurant / Food | D45: Kitchen Helper, Cook, Dishwasher, Waiter | E45: 9911144761 | H45: Maidawas Rd, near Ram Mohan Mandir, Medawas, Sector 64, Bhuyapur, Gurugram, Haryana 122101, India | M45: Map
A46: 42 | B46: Express Packers And Movers | C46: Warehouse / Logistics | D46: Loader, Packer, Picker, Warehouse Helper, Delivery | E46: 8796570072 | H46: Shop No.11, Prajapati Rd, Medawas, Sector 64, Gurugram, Haryana 122101, India | M46: Map
A47: 43 | B47: Ghilotia Home Decor | C47: Shop / Retail | D47: Store Helper, Housekeeping, Security, Sales Staff | E47: 7291076080 | H47: Kadarpur Rd, near by shani mandir, Medawas, Sector 64, Gurugram, Haryana 122101, India | M47: Map
A48: 44 | B48: Jk- Amba steel | C48: Shop / Retail | D48: Store Helper, Housekeeping, Security, Sales Staff | E48: 9810867603 | H48: Medawas, Sector 64, Gurugram, Haryana 122101, India | M48: Map
A49: 45 | B49: Rajat seth sahukar group | C49: Restaurant / Food | D49: Store Helper, Housekeeping, Security, Sales Staff | E49: 9376357165 | H49: Badshahpur, Sector 64, Gurugram, Haryana 122002, India | M49: Map
A50: 46 | B50: Rk Traders | C50: Restaurant / Food | D50: Kitchen Helper, Cook, Dishwasher, Waiter | E50: 7827486786 | H50: Shop No 05, Village, Maidawas Rd, Medawas, Sector 64, Gurugram, Haryana 122101, India | M50: Map
A51: 47 | B51: Shree Shyam dairy | C51: Restaurant / Food | D51: Kitchen Helper, Cook, Dishwasher, Waiter | E51: 9992939510 | H51: Shree Shyam dairy, near Baba mohan ram mandir, Medawas, Sector 64, Gurugram, Haryana 122101, India | M51: Map
A52: 48 | B52: Deuce Sports - Badminton Arena (BWF approved surface and High quality lighting) | C52: Other | D52: Trainer, Housekeeping, Front Desk | E52: 7428682277 | F52: 4.6 | G52: 390 | H52: Sector 64, Gurugram, Haryana 122101, India | M52: Map
A53: 49 | B53: The Pitçh | C53: Other | D53: Trainer, Housekeeping, Front Desk | E53: 9898001337 | F53: 5 | G53: 286 | H53: Power Play campus, beside Power Play sports academy, near M3M Urbana Premium, Sector 64, Gurugram, Haryana 122101, India | M53: Map
A54: 50 | B54: Nischay Cricket Academy | C54: Other | D54: Office Boy, Housekeeping, Security, Helper | E54: 9953505325 | F54: 4.3 | G54: 264 | H54: Nischay cricket academy, Sector 64, Gurugram, Haryana 122101, India | M54: Map
A55: 51 | B55: IWCA (Indian Warriors Cricket Academy ) | C55: Other | D55: Trainer, Housekeeping, Front Desk | E55: 9467509870 | F55: 5 | G55: 247 | H55: Pioneer Sports Park, opposite World Mark, Sector 64, Gurugram, Haryana 122101, India | M55: Map
A56: 52 | B56: Pioneer Sports park sector 64 | C56: Other | D56: Trainer, Housekeeping, Front Desk | E56: 9711723017 | F56: 4.5 | G56: 219 | H56: Pioneer sports park, Sector 64, Gurugram, Haryana 122001, India | M56: Map

Sheet Sector 65
A1: SWITCH · SECTOR 65 · MOBILE CALL SHEET
A2: Owner/manager mobiles · shifts 1–12 hrs, pay after worker reports · instant replacement | 124 leads · 112 in priority industries (top)
A3: LEADS | B3: =COUNTA(B5:B128) | C3: CONTACTED | D3: =COUNTA(I5:I128) | E3: INTERESTED | F3: =COUNTIF(I5:I128,"Yes") | G3: ORDERS | H3: =COUNTIF(K5:K128,"Yes") | I3: HOURS BOOKED | J3: =SUM(J5:J128)
A4: S.No | B4: Business Name | C4: Target Industry | D4: Suggested Roles (per shift) | E4: Manager Mobile | F4: Rating | G4: Reviews | H4: Address | I4: Interested? | J4: Hours (1-12) | K4: Order Confirmed? | L4: Remarks | M4: Map
A5: 1 | B5: Kanjivaraam | C5: Restaurant / Food | D5: Kitchen Helper, Cook, Dishwasher, Waiter | E5: 9205293222 | F5: 4.7 | G5: 3312 | H5: First Floor - Khasra No. 18, 22/2/1/2, Main Road, Sector 65, Gurugram, Haryana 122102, India | M5: Map
A6: 2 | B6: Karigari WorldMark | C6: Restaurant / Food | D6: Kitchen Helper, Cook, Dishwasher, Waiter | E6: 9319267185 | F6: 4.4 | G6: 1917 | H6: GR-05, GF, WorldMark, Maidawas Rd, below Inox, Sector 65, Gurugram, Haryana 122101, India | M6: Map
A7: 3 | B7: CarHeroZ | Best Car Detailing in Gurgaon, Car Wash, Car Deep Clean, Car Spa, Ceramic Coating, Paint Protection Film (PPF) | C7: Salon / Spa | D7: Beautician, Helper, Receptionist, Cleaner | E7: 8376979797 | F7: 5 | G7: 1138 | H7: STORE NO.3, next to WorldMark, Sector 65, Gurugram, Haryana 122102, India | M7: Map
A8: 4 | B8: Cafe De Flora | C8: Restaurant / Food | D8: Kitchen Helper, Cook, Dishwasher, Waiter | E8: 8448441840 | F8: 4.6 | G8: 715 | H8: GF-31 - GF38, Aipl joy central, Sector 65, Gurugram, Haryana 122101, India | M8: Map
A9: 5 | B9: Kitchen of Narwal | C9: Restaurant / Food | D9: Kitchen Helper, Cook, Dishwasher, Waiter | E9: 9990660673 | F9: 4.9 | G9: 588 | H9: 1st Floor, M3M 65th Avenue, R4 115, Mall, Sector 65, Gurugram, Haryana 122101, India | M9: Map
A10: 6 | B10: Bean Brew & Beyond. | C10: Restaurant / Food | D10: Kitchen Helper, Cook, Dishwasher, Waiter | E10: 9560544166 | F10: 4.6 | G10: 574 | H10: M3M 65th Avenue, G18 R8, Sector 65, Gurugram, Haryana 122101, India | M10: Map
A11: 7 | B11: BlueStone Jewellery Joy Central, Gurugram | C11: Shop / Retail | D11: Store Helper, Housekeeping, Security, Sales Staff | E11: 8655789755 | F11: 5 | G11: 564 | H11: Ground Floor,79, 93 Ground Floor, Joy Central, Sector 65, Gurugram, Haryana 122101, India | M11: Map
A12: 8 | B12: Punjab Grill WorldMark Gurgaon | C12: Restaurant / Food | D12: Kitchen Helper, Cook, Dishwasher, Waiter | E12: 8130605399 | F12: 4.4 | G12: 563 | H12: Located in -WorldMark Gurgaon, GR-05, GF, Maidawas Rd, Sector 65, Gurugram, Haryana 122101, India | M12: Map
A13: 9 | B13: YouMee Worldmark | C13: Restaurant / Food | D13: Kitchen Helper, Cook, Dishwasher, Waiter | E13: 8130604932 | F13: 4.4 | G13: 510 | H13: Located in- WorldMark Gurgaon, Shop No GR-02, Ground Floor, Maidawas Rd, Sector 65, Gurugram, Haryana 122101, India | M13: Map
A14: 10 | B14: Toni&Guy Hairdressing , Beauty , Make-up , Nail Bar | C14: Restaurant / Food | D14: Kitchen Helper, Cook, Dishwasher, Waiter | E14: 9667050057 | F14: 4.9 | G14: 486 | H14: R7/LG 27-28, M3M 65 Avenue, Sector 65, Gurugram, Haryana 122101, India | M14: Map
A15: 11 | B15: La Vie Douce - Cafe And Bakery | C15: Restaurant / Food | D15: Kitchen Helper, Cook, Dishwasher, Waiter | E15: 9910836657 | F15: 4.6 | G15: 455 | H15: R1G28, M3M, 65th Avenue, Sector 65, Gurugram, Haryana 122101, India | M15: Map
A16: 12 | B16: Looks Salon AIPL Joy Central | C16: Salon / Spa | D16: Beautician, Helper, Receptionist, Cleaner | E16: 7669880100 | F16: 4.4 | G16: 399 | H16: Ground Floor, Shop No. 62-68, AIPL Joy Central, Sector 65, Gurugram, Haryana 122018, India | M16: Map
... A103: 99 | B103: LONDON SLUSH | C103: Restaurant / Food | D103: Kitchen Helper, Cook, Dishwasher, Waiter | E103: 7505724429 | F103: 1 | G103: 1 | H103: M3M Golf Estate, Golf Course Ext Rd, Sector 65, Gurugram, Haryana 122101, India | M103: Map
A104: 100 | B104: Abdul Rakib Sekh | C104: Restaurant / Food | D104: Kitchen Helper, Cook, Dishwasher, Waiter | E104: 9717298694 | H104: Sector 65, Gurugram, Haryana 122101, India | M104: Map
A105: 101 | B105: Al Bek Chicken Corner | C105: Restaurant / Food | D105: Kitchen Helper, Cook, Dishwasher, Waiter | E105: 8178652247 | H105: 6, Ueueeuiwwiiw, Sector 65, Gurugram, Haryana 122101, India | M105: Map
A106: 102 | B106: Kiaasa - Joy Central, Gurgaon | C106: Shop / Retail | D106: Store Helper, Housekeeping, Security, Sales Staff | E106: 9319998169 | H106: Unit No 76, Ground Floor, AIPL Joy Central, Badshahpur, Sector 65, Gurugram, Haryana 122101, India | M106: Map
A107: 103 | B107: Manish | C107: Restaurant / Food | D107: Kitchen Helper, Cook, Dishwasher, Waiter | E107: 9560240486 | H107: Magic 9999, R28, Sector 65, Gurugram, Haryana 122101, India | M107: Map
A108: 104 | B108: Md Shakil Alam T Shop | C108: Shop / Retail | D108: Store Helper, Housekeeping, Security, Sales Staff | E108: 7835874489 | H108: Emrald Hills, Jhuggi, Sector 65, Gurugram, Haryana 122101, India | M108: Map
A109: 105 | B109: Motiur Rahaman | C109: Restaurant / Food | D109: Kitchen Helper, Cook, Dishwasher, Waiter | E109: 8510987853 | H109: Sector 65, Gurugram, Haryana 122101, India | M109: Map
A110: 106 | B110: Mukesh Dhaba | C110: Restaurant / Food | D110: Kitchen Helper, Cook, Dishwasher, Waiter | E110: 7739540272 | H110: Shop 5, Sona Road, Sector 65, Gurugram, Haryana 122101, India | M110: Map
A111: 107 | B111: My Wellnesst | C111: Salon / Spa | D111: Beautician, Helper, Receptionist, Cleaner | E111: 7290992972 | H111: Tower 1 28A, M3m St. Andrews Block-2, M3m, Golf Estate Rd, Sector 65, Gurugram, Haryana 122101, India | M111: Map
A112: 108 | B112: Nihal Singh Stall | C112: Restaurant / Food | D112: Store Helper, Housekeeping, Security, Sales Staff | E112: 8954910903 | H112: near Worldmark Tower, Badshahpur, Sector 65, Gurugram, Haryana 122101, India | M112: Map
A113: 109 | B113: Radhe Hardwork | C113: Shop / Retail | D113: Store Helper, Housekeeping, Security, Sales Staff | E113: 9354236618 | H113: Sector 65, Gurugram, Haryana 122101, India | M113: Map
A114: 110 | B114: Raju Hair Cut Saloon | C114: Salon / Spa | D114: Beautician, Helper, Receptionist, Cleaner | E114: 7703919622 | H114: Golf Course Ext Rd, near Emaar Plaza, Sector 65, Gurugram, Haryana 122101, India | M114: Map
A115: 111 | B115: Ritu Telecom | C115: Restaurant / Food | D115: Kitchen Helper, Cook, Dishwasher, Waiter | E115: 9990818814 | H115: Sector 65, Gurugram, Haryana 122101, India | M115: Map
A116: 112 | B116: Saissa | C116: Shop / Retail | D116: Store Helper, Housekeeping, Security, Sales Staff | E116: 8860611446 | H116: R7LG11, M3M 65th Avenue, Nirvana Country, Sector 65, Gurugram, Haryana 122018, India | M116: Map
A117: 113 | B117: Scan4Health Diagnosis Pvt. Ltd. | C117: Other | D117: Ward Boy, Housekeeping, Attendant, Security | E117: 9773595350 | F117: 4.8 | G117: 3455 | H117: D-4, Emerald Hills Rd, Sector 65, Gurugram, Haryana 122102, India | M117: Map
A118: 114 | B118: Splendor Trade Tower | C118: Other | D118: Office Boy, Housekeeping, Security, Helper | E118: 9582795258 | F118: 4.1 | G118: 624 | H118: C36F+786, Golf Course Ext Rd, Sector 65, Gurugram, Haryana 122101, India | M118: Map
A119: 115 | B119: Sportyzo Sports Academy – Tennis, Badminton, Football, Basketball & Box Cricket in Sector 65, Gurgaon | C119: Other | D119: Trainer, Housekeeping, Front Desk | E119: 8802713066 | F119: 4.7 | G119: 349 | H119: Sportyzo Sports Academy, Inside Emaar , Emerald Hills Rd, Golf Course Ext Rd, inside Pragyanam School, opposite Ivory Block, Sector 65, Gurugram, Haryana 122018, India | M119: Map
A120: 116 | B120: Rackonnect Strings & Feathers Badminton Arena | Sporbit | C120: Other | D120: Office Boy, Housekeeping, Security, Helper | E120: 8447938928 | F120: 4.6 | G120: 329 | H120: Emerald Hills Rd, opposite ivory, inside Emaar Mgf, society, Sector 65, Gurugram, Haryana 122101, Sector 65, Gurugram, Haryana 122018, India | M120: Map
A121: 117 | B121: Anytime Fitness | C121: Other | D121: Trainer, Housekeeping, Front Desk | E121: 9216052595 | F121: 4.6 | G121: 265 | H121: 2nd floor, North Block, M3M Tee Point, Sector 65, Gurugram, Haryana 122101, India | M121: Map
A122: 118 | B122: Fitness First Sector 65 | Best gym in Sector 65, Gurugram | C122: Other | D122: Trainer, Housekeeping, Front Desk | E122: 9810370082 | F122: 4.7 | G122: 245 | H122: First Floor, M3M 65th Avenue, R6/101-122, Sector 65, Gurugram, Haryana 122101, India | M122: Map
A123: 119 | B123: Dr. Nigam’s Clinic- ENT Specialist in Gurgaon | Voice & Cochlear Implant Surgeon | C123: Other | D123: Ward Boy, Housekeeping, Attendant, Security | E123: 8800895994 | F123: 5 | G123: 217 | H123: 125 , First Floor, Splendor Trade Tower, Golf Course Ext Rd, Sector 65, Gurugram, Haryana 122101, India | M123: Map
A124: 120 | B124: Auto Nexus | C124: Other | D124: Mechanic Helper, Cleaner, Washer | E124: 9999555927 | F124: 4.9 | G124: 217 | H124: Sector 65, Gurugram, Haryana 122101, India | M124: Map
A125: 121 | B125: Caross Detailing Studio | Gurgaon | C125: Other | D125: Mechanic Helper, Cleaner, Washer | E125: 8929227077 | F125: 4.9 | G125: 159 | H125: Shop No 8 & 9, Plot No 25/1/1/1, opposite Dharam Tower, Sector 65, Gurugram, Haryana 122101, India | M125: Map
A126: 122 | B126: Everhope Cancer Centre - Sector 65 Gurugram | C126: Other | D126: Office Boy, Housekeeping, Security, Helper | E126: 7795048160 | F126: 4.9 | G126: 150 | H126: B5-EBD, Golf Course Ext Rd, Sector 65, Gurugram, Haryana 122101, India | M126: Map
A127: 123 | B127: Seven Pillars Fitness | C127: Other | D127: Trainer, Housekeeping, Front Desk | E127: 9540465009 | F127: 4.7 | G127: 146 | H127: Emaar Club Beryl, Community Centre, EMERALD HILLS, Township, Sector 65-66, Sector 65, Gurugram, Haryana 122018, India | M127: Map
A128: 124 | B128: Detailing Daddy | C128: Other | D128: Pump Attendant, Cleaner, Security | E128: 9643583905 | F128: 4.8 | G128: 136 | H128: opposite DPS International School, adjacent to Indian Oil Petrol Pump, Sector 65, Gurugram, Haryana 122101, India | M128: Map

Sheet Sector 66
A1: SWITCH · SECTOR 66 · MOBILE CALL SHEET
A2: Owner/manager mobiles · shifts 1–12 hrs, pay after worker reports · instant replacement | 90 leads · 81 in priority industries (top)
A3: LEADS | B3: =COUNTA(B5:B94) | C3: CONTACTED | D3: =COUNTA(I5:I94) | E3: INTERESTED | F3: =COUNTIF(I5:I94,"Yes") | G3: ORDERS | H3: =COUNTIF(K5:K94,"Yes") | I3: HOURS BOOKED | J3: =SUM(J5:J94)
A4: S.No | B4: Business Name | C4: Target Industry | D4: Suggested Roles (per shift) | E4: Manager Mobile | F4: Rating | G4: Reviews | H4: Address | I4: Interested? | J4: Hours (1-12) | K4: Order Confirmed? | L4: Remarks | M4: Map
A5: 1 | B5: CaratLane Jewellery AIPL, Gurugram | C5: Shop / Retail | D5: Store Helper, Housekeeping, Security, Sales Staff | E5: 8069251485 | F5: 5 | G5: 1535 | H5: Shop 116, Ground Floor, AIPL JOY STREET, 117, Gujjar Rd, Badshahpur, Sector 66, Gurugram, Haryana 122101, India | M5: Map
A6: 2 | B6: Dtdc Courier Booking | C6: Warehouse / Logistics | D6: Loader, Packer, Picker, Warehouse Helper, Delivery | E6: 7428493146 | F6: 4.9 | G6: 779 | H6: Shop No -5, Vatica Business Park Vatica Chowk, Sohna - Gurgaon Rd, Badshahpur, Sector 66, Gurugram, Haryana 122018, India | M6: Map
A7: 3 | B7: Tattoo Studio Gurgaon - Inkcredible Art | C7: Shop / Retail | D7: Office Boy, Housekeeping, Security, Helper | E7: 7982101090 | F7: 4.9 | G7: 564 | H7: Shop No. R2 132, M3M Cosmopolitan Mall, Golf Course Ext Rd, Badshahpur, Sector 66, Gurugram, Haryana 122102, India | M7: Map
A8: 4 | B8: EMORI | C8: Shop / Retail | D8: Store Helper, Housekeeping, Security, Sales Staff | E8: 9667217998 | F8: 4.8 | G8: 535 | H8: Mall, Ground floor, AIPL JOY STREET, Shop 128-129, Badshahpur, Sector 66, Gurugram, Haryana 122101, India | M8: Map
A9: 5 | B9: BlueStone Jewellery Aipl Joy Street, Gurugram | C9: Shop / Retail | D9: Store Helper, Housekeeping, Security, Sales Staff | E9: 8097287760 | F9: 5 | G9: 520 | H9: GF, 53 & 54, B, AIPL JOY STREET, Badshahpur, Sector 66, Gurugram, Haryana 122101, India | M9: Map
A10: 6 | B10: GIVA Silver & Gold Jewellery | AIPL Joy Street | Lab Grown Diamonds | C10: Shop / Retail | D10: Store Helper, Housekeeping, Security, Sales Staff | E10: 9108962608 | F10: 4.9 | G10: 437 | H10: Unit no. GF 118, AIPL JOY STREET, 119, Sector 66U, Badshahpur, Sector 66, Gurugram, Haryana 122101, India | M10: Map
A11: 7 | B11: Glamdale Salon & Academy | C11: Salon / Spa | D11: Beautician, Helper, Receptionist, Cleaner | E11: 7982826132 | F11: 4.8 | G11: 357 | H11: M3M Cosmopolitan Sec 66 Shop No R2/14 Ground Floor Straight from OmSweets, near the lift, Badshahpur, Sector 66, Gurugram, Haryana 122101, India | M11: Map
A12: 8 | B12: Zigly - Pet Hospital, Pet Grooming & Pet Products | AIPL, Sector-66, Gurgaon | C12: Salon / Spa | D12: Ward Boy, Housekeeping, Attendant, Security | E12: 8071912468 | F12: 4.7 | G12: 345 | H12: Unit no 113, Ground Floor, AIPL JOY STREET, Badshahpur, Sector 66, Gurugram, Haryana 122018, India | M12: Map
A13: 9 | B13: SPORTS BOX 2.0 (Box Cricket Pickleball Corporate Events Birthday Parties Football) | C13: Restaurant / Food | D13: Trainer, Housekeeping, Front Desk | E13: 7428816477 | F13: 4.9 | G13: 191 | H13: Pratap Singh Tyagi Farm, next to Ireo Uptown, Badshahpur, Sector 66, Gurugram, Haryana 122001, India | M13: Map
A14: 10 | B14: Utsav FYB Health Cafe | C14: Restaurant / Food | D14: Kitchen Helper, Cook, Dishwasher, Waiter | E14: 9354517607 | F14: 4.9 | G14: 189 | H14: Cosmopolitan Mall, Golf Estate Rd, Badshahpur, Sector 66, Gurugram, Haryana 122101, India | M14: Map
A15: 11 | B15: Blue Tokai Coffee Roasters | AIPL Joy Street | C15: Restaurant / Food | D15: Kitchen Helper, Cook, Dishwasher, Waiter | E15: 9289744469 | F15: 4.4 | G15: 177 | H15: Shop No, Ground Floor, AIPL JOY STREET, 97 & 98, Gujjar Rd, Badshahpur, Sector 66, Gurugram, Haryana 122101, India | M15: Map
A16: 12 | B16: D'Decor Store Gurgaon / Decor India Furnishings | C16: Shop / Retail | D16: Store Helper, Housekeeping, Security, Sales Staff | E16: 9911723130 | F16: 4.7 | G16: 164 | H16: Hub 66, Main, Prajapati Rd, opp. Ansal Esencia C Block Road, Badshahpur, Sector 66, Gurugram, Haryana 122018, India | M16: Map
... A71: 67 | B71: Sumit Da Dhaba | C71: Restaurant / Food | D71: Kitchen Helper, Cook, Dishwasher, Waiter | E71: 9810227968 | F71: 5 | G71: 1 | H71: 8, Abc, Badshahpur, Sector 66, Gurugram, Haryana 122101, India | M71: Map
A72: 68 | B72: Aim Fast Food | C72: Restaurant / Food | D72: Kitchen Helper, Cook, Dishwasher, Waiter | E72: 9816053740 | H72: Main Bazar, near Sardana Sweet, Badshahpur, Sector 66, Gurugram, Haryana 122101, India | M72: Map
A73: 69 | B73: ARYAN AUTO SPARE PARTS | C73: Salon / Spa | D73: Store Helper, Housekeeping, Security, Sales Staff | E73: 9257379199 | H73: 144, nearby Marbella Villas, Badshahpur, Sector 66, Gurugram, Haryana 122101, India | M73: Map
A74: 70 | B74: Baba Alam Chand General Store | C74: Shop / Retail | D74: Store Helper, Housekeeping, Security, Sales Staff | E74: 7734841579 | H74: 01, Palm Dr, behind Badshahpur Main Road, Badshahpur, Sector 66, Gurugram, Haryana 122101, India | M74: Map
A75: 71 | B75: Giriraj Gernal Store | C75: Restaurant / Food | D75: Store Helper, Housekeeping, Security, Sales Staff | E75: 9873613938 | H75: Giriraj Gernal Store, near Sani Dev Mandir, Badshahpur, Sector 66, Gurugram, Haryana 122101, India | M75: Map
A76: 72 | B76: Gnome | C76: Shop / Retail | D76: Store Helper, Housekeeping, Security, Sales Staff | E76: 9811409275 | H76: 67, Belinda, Emaar, Marbella Villas, Badshahpur, Sector 66, Gurugram, Haryana 122101, India | M76: Map
A77: 73 | B77: MD ADIL | C77: Restaurant / Food | D77: Store Helper, Housekeeping, Security, Sales Staff | E77: 8097710953 | H77: 2, Badshahpur, Sector 66, Gurugram, Haryana 122101, India | M77: Map
A78: 74 | B78: Mohammad Arefin | C78: Warehouse / Logistics | D78: Office Boy, Housekeeping, Security, Helper | E78: 8075606044 | H78: Goga Colony, Badshahpur, Sector 66, Gurugram, Haryana 122101, India | M78: Map
A79: 75 | B79: Mohammad meet shop | C79: Restaurant / Food | D79: Kitchen Helper, Cook, Dishwasher, Waiter | E79: 9711778398 | H79: Guga Colony, Badshahpur, Sector 66, Gurugram, Haryana 122101, India | M79: Map
A80: 76 | B80: P-Y garments Badshahpur | C80: Shop / Retail | D80: Store Helper, Housekeeping, Security, Sales Staff | E80: 8447650875 | H80: near Bharat jewellers, opposite Ram mandir, Badshahpur, Sector 66, Gurugram, Haryana 122101, India | M80: Map
A81: 77 | B81: Rareism, Sector 66 | C81: Shop / Retail | D81: Store Helper, Housekeeping, Security, Sales Staff | E81: 8066085236 | H81: Shoppers Stop, Capital Cityscape Bhondsi, Golf Course Ext Rd, Badshahpur, Sector 66, Gurugram, Haryana 122101, India | M81: Map
A82: 78 | B82: RV Stationery Mart | C82: Supermarket / Grocery | D82: Store Helper, Housekeeping, Security, Sales Staff | E82: 9870133263 | H82: Om Plaza, B-3, Prajapati Rd, near Bala Ji Communicatioon, Badshahpur, Sector 66, Gurugram, Haryana 122101, India | M82: Map
A83: 79 | B83: Shiv Kumar Bartan Stores | C83: Supermarket / Grocery | D83: Kitchen Helper, Cook, Dishwasher, Waiter | E83: 7082854763 | H83: Sani Mandir, Badshahpur, Sector 66, Gurugram, Haryana 122101, India | M83: Map
... A85: 81 | B85: Tent wala | C85: Shop / Retail | D85: Store Helper, Housekeeping, Security, Sales Staff | E85: 9899456622 | H85: Ramgarh Rd, Badshahpur, Sector 66, Gurugram, Haryana 122101, India | M85: Map
A86: 82 | B86: Edoofa | C86: Other | D86: Office Boy, Housekeeping, Security, Helper | E86: 7292066328 | F86: 4.6 | G86: 744 | H86: 901 - Edoofa, Emaar Colonnade, Badshahpur, Sector 66, Gurugram, Haryana 122101, India | M86: Map
A87: 83 | B87: CollegeDekho | C87: Other | D87: Peon, Housekeeping, Security, Attendant | E87: 8044187303 | F87: 4.1 | G87: 711 | H87: CollegeDekho, 6th and 7th Floor, Capital The Cityscape, Badshahpur, Sector 66, Gurugram, Haryana 122101, India | M87: Map
A88: 84 | B88: Motoring 65 | C88: Other | D88: Mechanic Helper, Cleaner, Washer | E88: 7449000065 | F88: 4.6 | G88: 327 | H88: Khushal Sadh Baba Marg, behind IFC Social, opp. Shani Mandir, Badshahpur, Sector 66, Gurugram, Haryana 122101, India | M88: Map
A89: 85 | B89: Dr Geetanjali Dambalkar | C89: Other | D89: Office Boy, Housekeeping, Security, Helper | E89: 9818219160 | F89: 4.9 | G89: 175 | H89: Gurgaon Child & Vaccination Clinic, 810, 8th Floor, M3M Cosmopolitan, Badshahpur, Sector 66, Gurugram, Haryana 122101, India | M89: Map
A90: 86 | B90: Centre for Digestive Care Gastroenterologist in Gurgaon | Endoscopy Centre | Liver Specialist | Best Gastro Doctor | C90: Other | D90: Office Boy, Housekeeping, Security, Helper | E90: 8851843906 | F90: 4.8 | G90: 163 | H90: First Floor, RSC Tower, Badshahpur Sohna Rd, Badshahpur, Sector 66, Gurugram, Haryana 122018, India | M90: Map
A91: 87 | B91: Legalite Corporate Solutions | Accounting | Taxation | CA Firm in Gurgaon | C91: Other | D91: Office Boy, Housekeeping, Security, Helper | E91: 7428764445 | F91: 4.7 | G91: 86 | H91: EMAAR COLLONADE 904, Golf Course Ext Rd, Badshahpur, Sector 66, Gurugram, Haryana 122018, India | M91: Map
A92: 88 | B92: Boxlab Workout | C92: Other | D92: Trainer, Housekeeping, Front Desk | E92: 8800904630 | F92: 4.4 | G92: 83 | H92: 204, Second Floor, M3M Cosmopolitan R2, Golf Course Ext Rd, Badshahpur, Sector 66, Gurugram, Haryana 122101, India | M92: Map
A93: 89 | B93: SFMC Pvt. Ltd. | C93: Other | D93: Machine Operator, Helper, Loader, Packer | E93: 9312272766 | F93: 4.9 | G93: 74 | H93: 417, 4th Floor, Emaar Colonnade, Golf Course Ext Rd, Badshahpur, Sector 66, Gurugram, Haryana 122101, India | M93: Map
A94: 90 | B94: Doctors Test Path Lab -Best Pathology Lab in Gurgaon/Blood test Near me/ Pathology Lab in Gurugram. | C94: Other | D94: Office Boy, Housekeeping, Security, Helper | E94: 9821030905 | F94: 4.9 | G94: 61 | H94: R2/130, M3M Cosmopolitan, Golf Course Ext Rd, Badshahpur, Sector 66, Gurugram, Haryana 122101, India | M94: Map

Sheet Sector 67
A1: SWITCH · SECTOR 67 · MOBILE CALL SHEET
A2: Owner/manager mobiles · shifts 1–12 hrs, pay after worker reports · instant replacement | 62 leads · 56 in priority industries (top)
A3: LEADS | B3: =COUNTA(B5:B66) | C3: CONTACTED | D3: =COUNTA(I5:I66) | E3: INTERESTED | F3: =COUNTIF(I5:I66,"Yes") | G3: ORDERS | H3: =COUNTIF(K5:K66,"Yes") | I3: HOURS BOOKED | J3: =SUM(J5:J66)
A4: S.No | B4: Business Name | C4: Target Industry | D4: Suggested Roles (per shift) | E4: Manager Mobile | F4: Rating | G4: Reviews | H4: Address | I4: Interested? | J4: Hours (1-12) | K4: Order Confirmed? | L4: Remarks | M4: Map
A5: 1 | B5: Cars24 - Buy, Sell, Finance Used Cars in M3M Urbana, Gurgaon | C5: Shop / Retail | D5: Mechanic Helper, Cleaner, Washer | E5: 8929759586 | F5: 4.8 | G5: 1711 | H5: Shop No. 14, M3M URBANA, beside Head Master Salon Premium, Sector 67, Gurugram, Haryana 122002, India | M5: Map
A6: 2 | B6: Rajsi Poshak - Designer Women's Clothing & Accessories in Gurgaon | C6: Shop / Retail | D6: Store Helper, Housekeeping, Security, Sales Staff | E6: 9999970790 | F6: 4.5 | G6: 286 | H6: Ansal Esencia, Golden Arcade, Mall, Sector 67, Gurugram, Haryana 122101, India | M6: Map
A7: 3 | B7: DHABA HR 26 | C7: Restaurant / Food | D7: Kitchen Helper, Cook, Dishwasher, Waiter | E7: 7290012626 | F7: 4.1 | G7: 105 | H7: M3M Urbana Premium, near Hanuman Mandir, Sector 67, Gurugram, Haryana 122101, India | M7: Map
A8: 4 | B8: Lifelong Creations | C8: Shop / Retail | D8: Store Helper, Housekeeping, Security, Sales Staff | E8: 9643609319 | F8: 4.9 | G8: 60 | H8: House Number 1531-A, D Block, 3rd Floor Ansal Esencia, Ramgarh, Sector 67, Gurugram, Haryana 122101, India | M8: Map
A9: 5 | B9: KAILASH GLASS AND ALUMINIUM WORKS | C9: Shop / Retail | D9: Office Boy, Housekeeping, Security, Helper | E9: 8851464775 | F9: 4.9 | G9: 57 | H9: Anasal, Glass shop, Sector 67, Ghamroj, Gurugram, Haryana 122102, India | M9: Map
A10: 6 | B10: The soulyard farmstay | C10: Hotel / OYO | D10: Office Boy, Housekeeping, Security, Helper | E10: 8700472833 | F10: 4.8 | G10: 47 | H10: The soulyard farmstay, Sector 67, Gurugram, Haryana 122101, India | M10: Map
A11: 7 | B11: C.H PRINTERS | C11: Shop / Retail | D11: Machine Operator, Helper, Loader, Packer | E11: 9811020034 | F11: 4.7 | G11: 44 | H11: 93Q8+59G, N Ramgarh Rd, near by M3M Urbana Premium, Ramgarh, Sector 67, Gurugram, Haryana 122101, India | M11: Map
A12: 8 | B12: The Glutton Cafe | C12: Restaurant / Food | D12: Kitchen Helper, Cook, Dishwasher, Waiter | E12: 9319932119 | F12: 4.7 | G12: 44 | H12: Shop no. 19,20, Ground Floor, M3M Urbana Premium, Premium, Badshahpur, Sector 67, Gurugram, Haryana 122101, India | M12: Map
A13: 9 | B13: The Bakers Zone | C13: Restaurant / Food | D13: Kitchen Helper, Cook, Dishwasher, Waiter | E13: 9073363058 | F13: 5 | G13: 40 | H13: 17, IREO CORRIDORS, Sector 67A, Gurugram, Haryana 122101, India | M13: Map
A14: 10 | B14: Nihira Jewels | C14: Shop / Retail | D14: Store Helper, Housekeeping, Security, Sales Staff | E14: 9582407181 | F14: 4.8 | G14: 33 | H14: 4056, 2nd floor, Aaradhya homes, Sector 67A, Gurugram, Haryana 122101, India | M14: Map
A15: 11 | B15: Brown curry | C15: Restaurant / Food | D15: Kitchen Helper, Cook, Dishwasher, Waiter | E15: 9650407922 | F15: 4.8 | G15: 32 | H15: Shop no 3, Ramgarh, Sector 67, Gurugram, Haryana 122101, India | M15: Map
A16: 12 | B16: Sunrise 🌅 beauty salon | C16: Salon / Spa | D16: Beautician, Helper, Receptionist, Cleaner | E16: 9971645675 | F16: 5 | G16: 31 | H16: Golden Arcade, ansal ensesia, Sector 67, Gurugram, Haryana 122101, India | M16: Map
... A51: 47 | B51: Majed Ali Enterprises | C51: Shop / Retail | D51: Office Boy, Housekeeping, Security, Helper | E51: 8670490056 | F51: 4 | G51: 1 | H51: near Shiv Mandir Ramgarh DVR, Ramgarh, Sector 67, Gurugram, Haryana 122101, India | M51: Map
A52: 48 | B52: Ashwani Kumar | C52: Restaurant / Food | D52: Kitchen Helper, Cook, Dishwasher, Waiter | E52: 9643608878 | H52: Badshapur Badshapur, Sector 67, Gurugram, Haryana 122101, India | M52: Map
A53: 49 | B53: Black and brown brownies | C53: Restaurant / Food | D53: Kitchen Helper, Cook, Dishwasher, Waiter | E53: 7042456422 | H53: BESTECH PARK VIEW SPA NEXT, shop, Street No. 2, Sector 67, Gurugram, Haryana 122101, India | M53: Map
A54: 50 | B54: Darshan Kumar | C54: Restaurant / Food | D54: Kitchen Helper, Cook, Dishwasher, Waiter | E54: 7240755070 | H54: Shop No 87, Sector 67, Gurugram, Haryana 122101, India | M54: Map
A55: 51 | B55: Deals Ka Pitara | C55: Shop / Retail | D55: Store Helper, Housekeeping, Security, Sales Staff | E55: 9160781115 | H55: Ansal Esencia, B3, Sector 67, Gurugram, Haryana 122101, India | M55: Map
A56: 52 | B56: Fresh Morning | C56: Restaurant / Food | D56: Office Boy, Housekeeping, Security, Helper | E56: 8851743498 | H56: near Ireo The Corridors, Gate, Sector 67A, Gurugram, Haryana 122102, India | M56: Map
A57: 53 | B57: Ghanghal Kirana store | C57: Supermarket / Grocery | D57: Store Helper, Housekeeping, Security, Sales Staff | E57: 8529090937 | H57: S Ramgarh Rd, Ramgarh, Sector 67, Gurugram, Haryana 122101, India | M57: Map
A58: 54 | B58: Levi's Exclusive Store | C58: Shop / Retail | D58: Store Helper, Housekeeping, Security, Sales Staff | E58: 9211348091 | H58: Ki Dhani, No 162, Birbal Colony Darbaripur, near M3M Company, Ramgarh, Sector 67, Gurugram, Haryana 122101, India | M58: Map
A59: 55 | B59: Najirul | C59: Shop / Retail | D59: Office Boy, Housekeeping, Security, Helper | E59: 7679075481 | H59: Ireo, VICTORY VALLEY, Sector 67, Ireo, Gurugram, Haryana 122101, India | M59: Map
A60: 56 | B60: Pearl | C60: Salon / Spa | D60: Beautician, Helper, Receptionist, Cleaner | E60: 9873680504 | H60: 06, Ansal Esencia, SHREE VARDHMAN MANTRA, Ramgarh, Sector 67, Gurugram, Haryana 122101, India | M60: Map
A61: 57 | B61: Studio A2Z ( Interior | Renovation | Turnkey | Construction ) | C61: Other | D61: Office Boy, Housekeeping, Security, Helper | E61: 9667717714 | F61: 4.5 | G61: 179 | H61: First Floor, Entry 2, M3M Urbana Premium, 018, Golf Course Extension Road, Sector 67, Gurugram, Haryana 122102, India | M61: Map
A62: 58 | B62: Delhi Public School Gurugram Sector 67A | C62: Other | D62: Peon, Housekeeping, Security, Attendant | E62: 9289125601 | F62: 4.7 | G62: 131 | H62: Plot no, HS - 2, Sector 67A, Ansal Esencia C Block Rd, Gurugram, Haryana 122101, India | M62: Map
A63: 59 | B63: Asta realty | C63: Other | D63: Office Boy, Housekeeping, Security, Helper | E63: 9999315656 | F63: 4.7 | G63: 121 | H63: Unnamed Road, Ramgarh, Sector 67, Gurugram, Haryana 122101, India | M63: Map
A64: 60 | B64: SOLUTION SPECIALISTS | C64: Other | D64: Office Boy, Housekeeping, Security, Helper | E64: 8130775389 | F64: 4.9 | G64: 116 | H64: 415, Fourth Floor, Block C M3M Urbana, Sector 67, Gurugram, Haryana 122101, India | M64: Map
A65: 61 | B65: Rehab Hub Physio Center, Physiotherapy Clinic Sector 67, Physiotherapist in Gurgaon | C65: Other | D65: Ward Boy, Housekeeping, Attendant, Security | E65: 9217195269 | F65: 4.9 | G65: 109 | H65: GF, Golden Arcade, Ansal Essentia, B -9, Sector 67, Gurugram, Haryana 122102, India | M65: Map
A66: 62 | B66: Nirmal Integrated Consultancy (Team-NIC) | C66: Other | D66: Office Boy, Housekeeping, Security, Helper | E66: 9990838376 | F66: 4.9 | G66: 92 | H66: Ansal Versalia, Sector 67, Gurugram, Haryana 122101, India | M66: Map

Sheet GCR — Other
A1: SWITCH · GCR — OTHER · MOBILE CALL SHEET
A2: Owner/manager mobiles · shifts 1–12 hrs, pay after worker reports · instant replacement | 18 leads · 15 in priority industries (top)
A3: LEADS | B3: =COUNTA(B5:B22) | C3: CONTACTED | D3: =COUNTA(I5:I22) | E3: INTERESTED | F3: =COUNTIF(I5:I22,"Yes") | G3: ORDERS | H3: =COUNTIF(K5:K22,"Yes") | I3: HOURS BOOKED | J3: =SUM(J5:J22)
A4: S.No | B4: Business Name | C4: Target Industry | D4: Suggested Roles (per shift) | E4: Manager Mobile | F4: Rating | G4: Reviews | H4: Address | I4: Interested? | J4: Hours (1-12) | K4: Order Confirmed? | L4: Remarks | M4: Map
A5: 1 | B5: Rainbow Toys | C5: Shop / Retail | D5: Store Helper, Housekeeping, Security, Sales Staff | E5: 9818628918 | F5: 4.9 | G5: 2733 | H5: A14/1, Golf Course Rd, DLF Phase 1, Gurugram, Haryana 122002, India | M5: Map
A6: 2 | B6: The Sleep Company Experience Store -Golf Course Road | C6: Shop / Retail | D6: Store Helper, Housekeeping, Security, Sales Staff | E6: 7304417550 | F6: 4.9 | G6: 2043 | H6: Ground Floor, A14/15, Golf Course Rd, DLF Phase 1, Gurugram, Haryana 122002, India | M6: Map
